Workbook

Sheet Campaigns
A1: Campaign ID | B1: Campaign Name | C1: Date of Campaign Launch | D1: Strategic Framework (Full GET/TO/BY) | E1: Hypothesis (IF/THEN) | F1: Learning | G1: Highlights | H1: Lowlights | I1: Next Steps & Implications | J1: Product | K1: Channels Included | L1: Campaign Success Status | M1: Business Impact | N1: Wrap Report Link | O1: Primary Experiment Metric 1 | P1: ITC - 1 | Q1: Primary Experiment Metric 2 | R1: ITC - 2 | S1: Primary Experiment Metric 3 | T1: ITC - 3 | U1: Table Data | V1: Misc | W1: Slide Number(s) | X1: Slide Deck Name | Y1: Source Match | Z1: Strategic Framework - GET | AA1: Strategic Framework - TO | AB1: Strategic Framework - BY
A2: ELM-3877 | B2: Q3 Data in Context Campaign: Inflation | D2: GET: QBO Subscribers TO: acknowledge QBO as a key partner in running their business BY: letting they know how they stand across the QB community in the context of the economic challenges. | E2: IF: If we leverage customer's aggregate data to highlight QuickBooks as a solution to an issue facing SMBs THEN: We will see an increase in retention. | F2: • Customers that were eligible for the Data in Context since FY'22 Q3 (ELM-3877) were kept on the same treatment and control groups to see the cumulative impact of these campaigns . • There is not a significant difference in long-term retention between the customers that receive the series of 4 DiC campaigns and those that did not. | J2: QBO | L2: Positive | M2: We have not detected a stat sig impact improvement in 01-year retention. | U2: [["KPIs", "TEST", "CON.", "Δ (%pts)", "ITC"], ["Sample Size", "1,532,350", "269,630", "", ""], ["04m Churn", "6.39%", "6.40%", "-0.01%", "99.84"], ["06m Churn", "8.54%", "8.62%", "-0.08%", "99.07"], ["09m Churn", "11.31%", "11.37%", "-0.06%", "99.47"], ["01y Churn", "14.38%", "14.49%", "-0.11", "99.24"]] | V2: ⚠️ Not found in ELM Roadmap or Results Report | W2: 96 | X2: Copy of Copy of CRM Analytics 2023 AC.pptx | Y2: ⚠️ ELM Roadmap | ⚠️ Results Report | Z2: QBO Subscribers | AA2: acknowledge QBO as a key partner in running their business | AB2: letting they know how they stand across the QB community in the context of the economic challenges.
A3: ELM-3922 | B3: Personalize QBO FTU with GTKM - UBF | C3: 01-05-2023 | D3: GET: QuickBooks Online NTTF customers TO: deliver 2,208 units in FY'24 & ~$1.2M in annual revenue from those units. BY: the campaign at 100.3 ITC | E3: IF: If we personalize the QBO FTU based on their intent to use QBO THEN: We will increase 31D and 92D retention, and increase the amount of customers that reach QBO POP | F3: • 92d retention for Buy Now was positively impacted by the campaign at 100.3 ITC The experiment showed a flat impact on 92d retention for CCR . 45d conversion was positively impacted by the campaign at 104.4 ITC. • Both emails (new ELM-3922 and current ELM-2933) have a similar reach at ~80% Open Rate is higher in the treatment group (102 ITC) as well as CTR (106 ITC). • The unsub rate have increased (115 ITC), which 280 more customers per month that unsubscribe. • Buy Now and CCR customers in the TREATMENT group have received 2 more emails compared to the CONTROL group (9 vs. 7 emails) The number of emails received by non-CCR customers has stayed the same (9 emails) ELM-3922 have helped increase overall IPD reach from ~58% to ~68% (~10% of new Customers have only seen ELM-3922) and increased overall IPD CTR from ~18% to ~22% Buy Now and non-CCR customers have shown an increase in product feature adoption metrics. CCR Trialers have lower engagement with the QBO features compared to Buy Now and non-CCR customers. | G3: Retesting of flat experiment with improved targeting and placements resulted in higher UBF PoP rates. Early reads to inform iterations resulted in higher engagement and UBF PoP rates. • NEXT STEPS & IMPLICATIONS | H3: Batch attributes allowing us to reach only 60% of the audience. Better coordination between functions ( CS, PM, Marketing) | J3: QBO | K3: IPD; Email | L3: Not found (Inferred for review) | M3: The campaign delivered ~230 incremental units by significantly improving 3-month retention for Buy Now retention (+0.2% & 170 units) and Trial Conversion (+1.3% & 59 units) for the duration of the campaign. Roll-out is estimated to deliver 2,208 units in FY'24 & ~$1.2M in annual revenue from those units. | U3: [["KPIs", "TEST", "CON.", "ITC"], ["Sample Size", "79,488", "79,133", ""], ["92d Retention (BN)", "83.4%", "83.2%", "100.3"], ["92d Retention (Trial CCR)", "31.6%", "32.3%", "97.8"], ["45d Conversion (Trial non-CCR)", "30.9%", "29.6%", "104.4"], ["Cohort", "Email", "", "", "", "", "", "", "", "", "", "", "", "", "IPD", "", ""], ["", "Sent", "Opens", "%", "Δ", "ITC", "Clicks", "CTR", "Δ", "ITC", "Unsub", "%", "Δ", "ITC", "Imp.", "Clicks", "CTR"], ["CONTROL", "105,773", "68,629", "64.9%", "", "", "17,203", "16.3%", "", "", "2,786", "2.6%", "", "", "", "", ""], ["TREATMENT", "106,183", "70,534", "66.4%", "1.5%", "102", "18,410", "17.3%", "1%", "106", "3,182", "3.0%", "0.4%", "115", "45,718", "6,087", "13.3%"], ["ELM Channel Reach", "", "", "", ""], ["KPIs", "TEST", "CON.", "Δ", "ITC"], ["Sample Size", "75,928", "75,617", "", ""], ["QBO FTU Email Reach", "81.3%", "81.0%", "0.3%", "100.4"], ["QBO FTU IPD Reach", "68.4%", "57.9%", "10.5%", "118.2"], ["QBO FTU IPD CTR", "21.8%", "18.3%", "3.6%", "119.5"], ["Signup Type", "Size", "", "31d Bank Connected", "", "", "31d Txn Added\n(At least 1 txn added while having connected a bank)", "", "", "31d UBF POP", "", "", "92d Retention (BN & CCR)\n45d Conversion (non-CCR)", "", ""], ["", "TREATMENT", "CONTROL", "TREATMENT", "CONTROL", "ITC", "TREATMENT", "CONTROL", "ITC", "TREATMENT", "CONTROL", "ITC", "TREATMENT", "CONTROL", "ITC"], ["Buy Now", "69,671", "69,502", "70.3%", "70.1%", "100.3", "69.2%", "69.1%", "100.2", "15.2%", "15.1%", "100.7", "83.4%", "83.2%", "100.3"], ["CCR", "5,288", "5,133", "44.6%", "45.1%", "99.0", "43.6%", "43.9%", "99.3", "7.3%", "7.7%", "94.1", "31.6%", "32.3%", "97.8"], ["non-CCR", "4,528", "4,495", "49.8%", "47.7%", "104.3", "48.7%", "46.7%", "104.1", "9.8%", "9.9%", "99.3", "30.9%", "29.6%", "104.4"], ["KPIs", "TEST", "CON.", "ITC"], ["Sample Size", "79,488", "79,133", ""], ["92d Retention (BN)", "83.4%", "83.2%", "100.3"], ["92d Retention (Trial CCR)", "31.6%", "32.3%", "97.8"], ["45d Conversion (Trial non-CCR)", "30.9%", "29.6%", "104.4"], ["Cohort", "Email", "", "", "", "", "", "", "", "", "", "", "", "", "IPD", "", ""], ["", "Sent", "Opens", "%", "Δ", "ITC", "Clicks", "CTR", "Δ", "ITC", "Unsub", "%", "Δ", "ITC", "Imp.", "Clicks", "CTR"], ["CONTROL", "105,773", "68,629", "64.9%", "", "", "17,203", "16.3%", "", "", "2,786", "2.6%", "", "", "", "", ""], ["TREATMENT", "106,183", "70,534", "66.4%", "1.5%", "102", "18,410", "17.3%", "1%", "106", "3,182", "3.0%", "0.4%", "115", "45,718", "6,087", "13.3%"], ["ELM Channel Reach", "", "", "", ""], ["KPIs", "TEST", "CON.", "Δ", "ITC"], ["Sample Size", "75,928", "75,617", "", ""], ["QBO FTU Email Reach", "81.3%", "81.0%", "0.3%", "100.4"], ["QBO FTU IPD Reach", "68.4%", "57.9%", "10.5%", "118.2"], ["QBO FTU IPD CTR", "21.8%", "18.3%", "3.6%", "119.5"], ["Signup Type", "Size", "", "31d Bank Connected", "", "", "31d Txn Added\n(At least 1 txn added while having connected a bank)", "", "", "31d UBF POP", "", "", "92d Retention (BN & CCR)\n45d Conversion (non-CCR)", "", ""], ["", "TREATMENT", "CONTROL", "TREATMENT", "CONTROL", "ITC", "TREATMENT", "CONTROL", "ITC", "TREATMENT", "CONTROL", "ITC", "TREATMENT", "CONTROL", "ITC"], ["Buy Now", "69,671", "69,502", "70.3%", "70.1%", "100.3", "69.2%", "69.1%", "100.2", "15.2%", "15.1%", "100.7", "83.4%", "83.2%", "100.3"], ["CCR", "5,288", "5,133", "44.6%", "45.1%", "99.0", "43.6%", "43.9%", "99.3", "7.3%", "7.7%", "94.1", "31.6%", "32.3%", "97.8"], ["non-CCR", "4,528", "4,495", "49.8%", "47.7%", "104.3", "48.7%", "46.7%", "104.1", "9.8%", "9.9%", "99.3", "30.9%", "29.6%", "104.4"], ["HIGHLIGHTS", "", "LOWLIGHTS"], ["Retesting of flat experiment with improved targeting and placements resulted in higher UBF PoP rates.\nEarly reads to inform iterations resulted in higher engagement and UBF PoP rates.", "", "Batch attributes allowing us to reach only 60% of the audience.\nBetter coordination between functions ( CS, PM, Marketing)"], ["NEXT STEPS & IMPLICATIONS", "", ""]] | V3: Alt Name (slide 14): ● | Alt Date (slide 14): 08/10/2023 | Alt Product (slide 14): QuickBooks Online | Alt Name (slide 15): and current ELM-2933) have a similar reach at ~80% | Alt TO (slide 15): mers per month that unsubscribe. | Alt BY (slide 15): non-CCR customers has stayed the same (9 emails) | Alt TO (slide 16): mers have shown an increase in product feature adoption metrics. | Alt Name (slide 41): ● | Alt Date (slide 41): 08/10/2023 | Alt Product (slide 41): QuickBooks Online | Alt Name (slide 42): and current ELM-2933) have a similar reach at ~80% | Alt TO (slide 42): mers per month that unsubscribe. | Alt BY (slide 42): non-CCR customers has stayed the same (9 emails) | Alt TO (slide 43): mers have shown an increase in product feature adoption metrics. | Alt Product (slide 323): Payments | Alt GET (slide 323): ing and placements resulted in higher UBF PoP rates. | Alt TO (slide 323): inform iterations resulted in higher engagement and UBF PoP rates. | Batch attri | Date: CSV-Current | W3: 13-323 | X3: Copy of Copy of CRM Analytics 2023 AC.pptx | Y3: ✅ ELM Roadmap | ⚠️ Results Report | Z3: QuickBooks Online NTTF customers | AA3: deliver 2,208 units in FY'24 & ~$1.2M in annual revenue from those units. | AB3: the campaign at 100.3 ITC
A4: ELM-3938 | B4: Proactive Intervention | C4: 08-17-2022 | D4: GET: QBO Buy Now and Trialers who have not connected a bank by day 3 or categorized < 60% transactions from day 3 to 31 of sign up TO: the digital assistant, we can enable customers to connect to support. BY: day 3 or categorized < 60% transactions from day 3 to 31 of sign up | E4: IF: If we implement human assisted intervention IPDs for NTTF Trailers + Buy Now customers THEN: We will increase the number of customers who reach the UBF payoff event for QBO. (Inferred for review) | F4: • Overall the self serve content is highly engaging and helpful for users to connect bank and categorize transactions. CTR is quite high because of two CTA's. • Opportunity to improve Human Assisted experience further and add additional placements to improve reach and engagement. • Users who engage with Human Assisted content prefer both options call me back and schedule a call back. 70% of those who engage with Human Assisted offers schedule a call and ~ 96% of those calls are handled by agents. • Overall campaign is performing better for buy now customers as against to the trialers for UBF EPOP. • Buy now customers prefer self serve content more while connecting with the bank but need human assistance while categorizing bank transactions. • Trial customers need human assistance more for both connecting bank and categorizing transactions but QBO POP rate is trending lower compared to the control bucket. • No harm metrics such as 31d retention rate is flat at 100 ITC. | J4: QBO | K4: IPD | L4: Not found (Inferred for review) | M4: This campaign something business impact COHORT | SIZE | % | Bank Connection | Categorize 60% Txn | UBF POP % | Δ | ITC | % | Δ | ITC | % | Δ | ITC Human Assisted | 21.6K | 33% | 23.2% | -0.2 | 99.4 | 18.9% | +0.2 | 101 | 7.7% | +0.1 | 101 Self Serve | 21.7K | 33% | 23.8% | +0.4 | 102 | 19.2% | +0.5 | 103 | 8.1% | +0.5 | 106 Control | 21.8K | 33% | 23.4% | 18.7% | 7.6% This campaign something business impact COHORT | IPD Reach | Unique Clicks | CTR Human Assisted | 14.1K | 325 | 2.3% Self Serve | 14.4K | 1756 | 12.7% | U4: [["HYPO\n-THESIS", "If we implement human assisted intervention IPDs for NTTF Trailers + Buy Now customers, we will increase the number of customers who reach the UBF payoff event for QBO.", "", "", "", ""], ["14d baked data - Early read", "", "", "", "", "", ""], ["KPIs", "", "CONTROL", "HA", "SS", "ITC HA", "ITC SS"], ["UBF POP", "", "7.7%", "7.8%", "8.1%", "101", "106"], ["Retention Rate", "", "94.6%", "94.7%", "94.8%", "100", "100"], ["EPOP", "", "21.9%", "22.3%", "22.7%", "102", "104"], ["BUSINESS IMPACT", "", "", "", "", "", "", "", "", "", "", ""], ["This campaign something something something business impact", "", "", "", "", "", "", "", "", "", "", ""], ["COHORT", "SIZE", "%", "Bank Connection", "", "", "Categorize 60% Txn", "", "", "UBF POP", "", ""], ["", "", "", "%", "Δ", "ITC", "%", "Δ", "ITC", "%", "Δ", "ITC"], ["Human Assisted", "21.6K", "33%", "23.2%", "-0.2", "99.4", "18.9%", "+0.2", "101", "7.7%", "+0.1", "101"], ["Self Serve", "21.7K", "33%", "23.8%", "+0.4", "102", "19.2%", "+0.5", "103", "8.1%", "+0.5", "106"], ["Control", "21.8K", "33%", "23.4%", "", "", "18.7%", "", "", "7.6%", "", ""], ["CHANNEL ENGAGEMENT", "", "", ""], ["This campaign something something something business impact", "", "", ""], ["COHORT", "IPD", "", ""], ["", "Reach", "Unique Clicks", "CTR"], ["Human Assisted", "14.1K", "325", "2.3%"], ["Self Serve", "14.4K", "1756", "12.7%"], ["HYPO\n-THESIS", "If we implement human assisted intervention IPDs for NTTF Trailers + Buy Now customers, we will increase the number of customers who reach the UBF payoff event for QBO.", "", "", "", ""], ["14d baked data - Early read", "", "", "", "", "", ""], ["KPIs", "", "CONTROL", "HA", "SS", "ITC HA", "ITC SS"], ["UBF POP", "", "7.83%", "7.84%", "8.25%", "100", "105"], ["Retention Rate", "", "94.6%", "94.7%", "94.8%", "100", "100"], ["EPOP", "", "22.3%", "22.5%", "22.9%", "101", "103"], ["14d baked data - Early read", "", "", "", "", "", ""], ["Buy Now Customers", "", "", "", "", "", ""], ["KPIs", "", "CONTROL", "HA", "SS", "ITC HA", "ITC SS"], ["Connected Bank", "", "13%", "13.2%", "14%", "101", "107"], ["Categorized 60% Txn", "", "3.95%", "4.14%", "4.06%", "105", "103"], ["UBF EPOP", "", "3.73%", "3.8%", "4.0%", "102", "108"], ["Retention Rate", "", "96.49%", "96.86%", "96.82%", "100", "100"], ["14d baked data - Early read", "", "", "", "", "", ""], ["Trial Customers", "", "", "", "", "", ""], ["KPIs", "", "CONTROL", "HA", "SS", "ITC HA", "ITC SS"], ["Connected Bank", "", "12.6%", "13.7%", "12.1%", "109", "96"], ["Categorized 60% Txn", "", "3.34%", "3.80%", "3.82%", "114", "114"], ["UBF EPOP", "", "2.9%", "2.7%", "2.65%", "93", "92"], ["Retention Rate", "", "98.33%", "98.81%", "97.92%", "100", "100"]] | V4: Alt Date (slide 321): 07-27-2022 | Alt TO (slide 322): connect bank and categorize transactions. CTR is quite high because of two CTA's | Alt BY (slide 322): agents. | Alt Date (slide 338): 07-27-2022 | Date: CSV-Current | W4: 320-340 | X4: Copy of Copy of CRM Analytics 2023 AC.pptx | Y4: ✅ ELM Roadmap | ⚠️ Results Report | Z4: QBO Buy Now and Trialers who have not connected a bank by day 3 or categorized < 60% transactions from day 3 to 31 of sign up | AA4: the digital assistant, we can enable customers to connect to support. | AB4: day 3 or categorized < 60% transactions from day 3 to 31 of sign up
A5: ELM-4240 | B5: Awareness and adoption of new QB Commerce features | C5: 09-29-2022 | D5: GET: QBO customers selling on Amazon, Shopify, or eBay TO: Drive awareness and adoption of new Commerce features (Accounting in Q1 and Inventory/Order Mgmt in Q2). BY: making them feel excited to get more out of QBO by connecting it with their sales channels | E5: IF: we inform and educate e-commerce PBB customers about the Commerce benefits now available within QBO THEN: we will deliver more value to the PBB customer segment, leading to higher segment penetration, customer PRS (product recommendation score) and retention rates. | F5: • The campaign has a positive impact on QB Commerce adoption; however, the adoption rate is still below 1% Despite the increase in adoption, 31d Retention and 92d Retention were flat. 80% of the customers in the treatment group have seen at least 1 of the 8 IPDs we launched. • However, more people have dismissed the IPDs than clicked on them The Banking - Hellobox is the access point with the highest traffic. • It is performance has also been way above average. • Nonetheless, less than 50% of the customers have seen this access point Cohort | IPD Total Assignments | 12,330 | G5: The campaign have successfully increased the % of QBO customers adopting the QB Commerce feature. • NEXT STEPS & IMPLICATIONS • The campaign as it is, should not be made an evergreen campaign since it is not making an impact on retention. Use targeting attributes to make this a dynamic campaign instead of working with list pulls. Explore the use of email channel to explain more what this feature is about | H5: There was no stat sig impact on 31d /92d Retention Even though IPD have shown a stat sig increase in feature adoption, the text limitations could have prevented customers from knowing more about this feature. Working with list pulls limit the ability to increase the number of samples | I5: The campaign as it is, should not be made an evergreen campaign since it is not making an impact on retention. Use targeting attributes to make this a dynamic campaign instead of working with list pulls. Explore the use of email channel to explain more what this feature is about | J5: QBO | K5: IPD | L5: Not found (Inferred for review) | M5: Even though the campaign showed a positive impact on QB Commerce adoption, less than 1% have used this feature, and it had no impact on 31d / 92d Retention. | U5: [["KPIs", "TEST", "CON.", "Δ", "ITC"], ["Sample Size", "12,330", "12,393", "", ""], ["31d Retention", "98.7%", "98.7%", "-0.0%", "99.9"], ["92d Retention", "97.4%", "97.6%", "-0.2%", "99.8"], ["31d Commerce Conn.", "0.9%", "0.6%", "0.3%", "156.4"], ["31d Imported Txn", "0.8%", "0.5%", "0.3%", "163.8"], ["31d Added to Books", "0.2%", "0.2%", "0.1%", "160.0"], ["Cohort", "IPD", "", "", "", "", "", ""], ["", "Imp.", "% of Treatment", "Clicks", "CTR", "Bnchmrk", "Δ", "ITB"], ["Dashboard - Tips", "3,039", "24.6%", "19", "0.6%", "1.0%", "-0.37%", "63"], ["Banking - Hellobox", "5,209", "42.2%", "53", "1.0%", "0.3%", "0.72%", "339"], ["App Center - Hellobox", "552", "4.5%", "14", "2.5%", "N/A", "N/A", "N/A"], ["Income Overview - Tips", "2,155", "17.5%", "4", "0.2%", "0.4%", "-0.21%", "46"], ["Reports - Hellobox", "4,337", "35.2%", "9", "0.2%", "0.1%", "0.11%", "208"], ["Sales - Hellobox", "1,173", "9.5%", "6", "0.5%", "0.1%", "0.41%", "512"], ["Invoices - Hellobox", "4,613", "37.4%", "29", "0.6%", "1.9%", "-1.27%", "33"], ["Chart of Accounts - Hellobox", "3,468", "28.1%", "25", "0.7%", "0.2%", "0.52%", "360"], ["IPD Engagement Funnel", "", ""], ["Total Assignments", "12,330", ""], ["Viewed IPD", "9,854", "79.9%"], ["Clicked IPD", "141", "1.1%"], ["Dismissed IPD", "1,347", "10.9%"], ["HIGHLIGHTS", "", "LOWLIGHTS"], ["The campaign have successfully increased the % of QBO customers adopting the QB Commerce feature.", "", "There was no stat sig impact on 31d /92d Retention\nEven though IPD have shown a stat sig increase in feature adoption, the text limitations could have prevented customers from knowing more about this feature.\nWorking with list pulls limit the ability to increase the number of samples"], ["NEXT STEPS & IMPLICATIONS", "", ""], ["The campaign as it is, should not be made an evergreen campaign since it is not making an impact on retention.\nUse targeting attributes to make this a dynamic campaign instead of working with list pulls.\nExplore the use of email channel to explain more what this feature is about", "", ""]] | V5: Alt Date (slide 284): 09-29-22 | Alt Product (slide 285): Invoicing | Alt TO (slide 285): mers in the treatment group have seen at least 1 of the 8 IPDs we launched. Howe | Alt GET (slide 286): ing attributes to make this a dynamic campaign instead of working with list pull | Alt TO (slide 286): mers adopting the QB Commerce feature. | There was no stat sig impact on 31d /92 | TO replaced with CSV Project Description (was: table_bleed) | Date: CSV-Current | W5: 283-286 | X5: Copy of Copy of CRM Analytics 2023 AC.pptx | Y5: ✅ ELM Roadmap | ⚠️ Results Report | Z5: QBO customers selling on Amazon, Shopify, or eBay | AA5: Drive awareness and adoption of new Commerce features (Accounting in Q1 and Inventory/Order Mgmt in Q2). | AB5: making them feel excited to get more out of QBO by connecting it with their sales channels
A6: ELM-4749 | B6: Promote TangoApp to DTM QBO customers | C6: 10-17-2022 | D6: GET: non Advanced QBO DTM customers TO: non-Advance DTM QBO customers BY: Making them feel confident in their decision to migrate to QBO with an experience that is similar to what they are used to in Desktop. | E6: IF: If we promote the Tango App to DTM QBO customers through IPD, these customers will download the app and use it, which will ultimately make them feel more confident using QBO, resulting in a 1% lift in 31D and 92D retention | F6: • Tango App adoption increased for customers that were part of the DTM experience. • However, that same stat sig increase is not shown in customers that only saw the IPDs. • The impact is only directional Flat 31d Retention (33%) Promote TangoApp to non-Advance customers The IPDs reached ~74% of eligible customers Despite its low coverage, Banking - Hellobox and Customers - Hellobox , the proportion of customers engaging with these access points was much higher | G6: Promoting the Tango App through GTKM, Beanstalk, and the Setup Checklist (DTM experiment) was effective in creating Tango App adoption. • NEXT STEPS & IMPLICATIONS • Track 92d Retention. This metric should be available by March 21st Test if using Email as a channel to promote Tango App has a better impact compared to IPDs Limitation: If the customer opens the email in its mobile, the to download the tango app will not work properly. Dig into why more Importer Migrators were largely targeted by the ELM experience compared to the DTM experience. | H6: The IPDs on their own (ELM experiment) did not show an incremental benefit on Tango App adoption The increase in Tango App adoption did not resulted in an improvement of 31d Retention | I6: Track 92d Retention. This metric should be available by March 21st Test if using Email as a channel to promote Tango App has a better impact compared to IPDs Limitation: If the customer opens the email in its mobile, the to download the tango app will not work properly. Dig into why more Importer Migrators were largely targeted by the ELM experience compared to the DTM experience. | J6: QBO | K6: IPD | L6: Not found (Inferred for review) | M6: The experiments did not show a stat sig impact on 31d Retention. Nonetheless, the IPD + DTM experiment have increased adoption The IPD Only experience did not increased adoption. | U6: [["KPIs", "Control", "IPD Only", "ITC", "DTM + IPD", "ITC"], ["Sample Size", "5,202", "5,174", "", "5,198", ""], ["31d Tango Download", "2.3%", "2.6%", "112.9", "34.0%", "1,448.7"], ["31d Company Selection", "1.1%", "1.4%", "123.1", "22.0%", "1,970.5"], ["31d Opened Tango", "0.8%", "1.0%", "119.2", "17.4%", "2,101.6"], ["31d Retention", "95.3%", "95.3%", "100.0", "95.2%", "99.9"], ["CHANNEL ENGAGEMENT", "", "", "", "", "", ""], ["3 Access Points were used in this campaign", "", "", "", "", "", ""], ["Access Point", "IPD", "", "", "", "", ""], ["", "Imp.", "Clicks", "CTR", "Benchmark", "Δ", "ITB"], ["Chart of Accounts - Hellobox", "5,436", "102", "1.9%", "2.3%", "-0.4%", "83"], ["Banking - Hellobox", "3,254", "84", "2.6%", "1.9%", "0.7%", "136"], ["Customers - Hellobox", "3,035", "64", "2.1%", "1.9%", "0.2%", "113"], ["Funnel", "Customers", "% Customers"], ["Treatment", "10,372", ""], ["Impressions", "7,728", "74.5%"], ["Clicks", "239", "2.3%"], ["HIGHLIGHTS", "", "LOWLIGHTS"], ["Promoting the Tango App through GTKM, Beanstalk, and the Setup Checklist (DTM experiment) was effective in creating Tango App adoption.", "", "The IPDs on their own (ELM experiment) did not show an incremental benefit on Tango App adoption\nThe increase in Tango App adoption did not resulted in an improvement of 31d Retention"], ["NEXT STEPS & IMPLICATIONS", "", ""], ["Track 92d Retention. This metric should be available by March 21st\nTest if using Email as a channel to promote Tango App has a better impact compared to IPDs\nLimitation: If the customer opens the email in its mobile, the link to download the tango app will not work properly.\nDig into why more Importer Migrators were largely targeted by the ELM experience compared to the DTM experience.", "", ""]] | V6: Alt Date (slide 288): 10-16-2022 | Alt Product (slide 288): QuickBooks Online | Alt GET (slide 290): ed by the ELM experience compared to the DTM experience. | Alt TO (slide 290): non-Advance customers | Alt BY (slide 290): March 21st | Date: CSV-Current | W6: 287-290 | X6: Copy of Copy of CRM Analytics 2023 AC.pptx | Y6: ✅ ELM Roadmap | ⚠️ Results Report | Z6: non Advanced QBO DTM customers | AA6: non-Advance DTM QBO customers | AB6: Making them feel confident in their decision to migrate to QBO with an experience that is similar to what they are used to in Desktop.
A7: ELM-4941 | B7: QBO Upgrades Targeted Offer V2 | C7: 06-21-2023 | D7: GET: highly likely Quickbooks customers TO: Upgrades BY: offering targeted discounts based on price sensitivity | E7: IF: Offering discounts based on price sensitivity will optimize discount dollars & deliver significant incremental upgrades | F7: • SS > PLUS ESS > PLUS • SS > Plus upgrades sig. higher , factoring in discounts & | G7: Targeted discount based on price sensitivity were validated at scale for 6 cohorts and 3 price points • Retention sustained after discount promo period signalling right customers were targeted for upgrades • SS > Plus upgrades will break even in 1+ years and start delivering incremental revenue • NEXT STEPS & IMPLICATIONS • Align & rollout targeted discounts for SS > PLUS • Offer similar discount for ADV and/or call out higher $ savings in SKU selection ; Update targeting criteria to remove high ADV propensity candidates • Reevaluate discount bands for ESS > PLUS , i.e. >30% discount is lesser than monthly Essentials subscription cost • Test Trials or no cost upgrade for Essentials > PLUS | H7: Multiple iterations due to data issues , execution misses and other priorities like price increase • ESS > PLUS is ROI negative because of smaller lift , lesser Advanced upgrades and deep discounts | I7: upgrades will drive 82K lesser revenue in first 3 yrs. yrs. > PLUS POSITIVE BIZ IMPACT Detailed KPIs (SS > PLUS) KPIs TEST CON. Δ ITC Samples 84,081 84,193 Upgrades - PLUS (w/campaign) 1.4% 1.0% 357 143 Upgrades - ESS (w/campaign) 1.7% 1.8% -124 92 Upgrades - ADV (w/campaign) 0.4% 0.5% -53 86 Upgrades - ALL (ESS/PLUS/ADV) 3.5% 3.3% 180 107 Upgrades - PLUS (3 mo. retention) 88.8% 87.9% 0.8% 101 Upgrades - PLUS (post discount) 1.3% 0.9% 324 144 Upgrades - PLUS (4 mo. retention) 81.5% 82.8% -1.2% 99 Upgrades - PLUS Retained (post 4 mo.) 1.2% 0.8% 281 141 Est. incr. upgrade revenue in first year $16.4 $16.6 -$12,704 99 Est. incr. ESS upgrade revenue in first year $4.8 $5.3 -$35,531 92 Est. incr. PLUS upgrade revenue in first year $7.2 $6.4 $69,100 113 Est. incr. ADV upgrade revenue in first year $4.4 $4.9 -$46,274 89 Est. incr. upgrade rev. in first 2 yrs. $30.3 $29.3 $87,261 104 Est. incr. upgrade rev. in first 3 yrs. $40.5 $38.6 $163,377 105 PLUS Upgrades 3 mo. after campaign 0.40% 0.43% -23 94 Upgrade Retention ●B 3-month retention in PLUS plan of targeted discount cohort is comparable to group not receiving upgrade discount ●C 4-mo. retention (right measure for sizing full price impact) is trending down but upgrades sustained are significantly higher Estimated Incremental upgrade revenue ●D Plus upgrade rev. is significantly higher (+$69K) but ADV (-$46K) & ESS (-$35k) offset resulting in $12K lesser overall revenue • Payback period is relatively faster & targeted discount cohort E will generate incremental revenue after ~15 months Pull forwards ●F Upgrades after the campaign ended is directionally lower signalling discount driven pull forwardsHIGH Price Sens. MED Price Sens. LOW Price Sens. KPIs TEST CON. Δ ITC TEST CON. Δ ITC TEST CON. Δ ITC Samples 39,981 39,516 23,906 24,360 20,194 20,317 Upgrades - PLUS (w/campaign) 1.7% 1.1% 244 157 1.2% 0.8% 96 151 1.2% 1.1% 16 107 Upgrades - ESS (w/campaign) 1.6% 1.8% -104 86 1.6% 1.6% -1 100 2.0% 2.1% -20 95 Upgrades - ADV (w/campaign) 0.3% 0.4% -34 80 0.3% 0.4% -18 82 0.5% 0.5% -1 99 Upgrades - ALL (ESS/PLUS/ADV) 3.6% 3.3% 106 108 3.1% 2.8% 77 111 3.7% 3.7% -5 99 Upgrades - PLUS (4 mo. retention) 79.9% 81.8% -1.9% 98 82.0% 82.7% -0.7% 99 85.6% 84.6% 0 101 Upgrades - PLUS Retained (post 4 mo.) 1.3% 0.9% 187 153 1.0% 0.6% 77 150 1.0% 0.9% 16 109 Est. incr. upgrade rev. in first year $16.0 $16.9 -$34,758 95 $14.8 $14.1 $17,901 105 $19.1 $18.9 $3,177 101 Est. incr. ESS upgrade revenue in first year $4.5 $5.3 -$29,685 86 $4.6 $4.6 -$215 100 $5.7 $6.0 -$5,852 95 Est. incr. PLUS upgrade revenue in first year $7.5 $6.9 $24,363 109 $6.4 $5.0 $33,492 128 $7.5 $7.0 $10,47 3 107 Est. incr. ADV upgrade revenue in first year $4.0 $4.7 -$29,436 84 $3.8 $4.5 -$15,37 6 86 $5.9 $5.9 -$1,444 99 Est. incr. upgrade rev. in first 2 yrs. $29.8 $30.6 $31,517 103 $24.9 $26.9 $48,597 108 $33.5 $33.8 $5,429 101 Est. incr. upgrade rev. in first 3 yrs. $39.3 $41.3 $81,950 105 $32.8 $35.8 $71,997 109 $44.1 $44.5 $7,163 101 PLUS Upgrades 3 mo. after campaign 0.40% 0.38% 5 103 0.36% 0.44% -18 83 0.5% 0.5% -9 91 KPIs TEST CON. Δ ITC Samples 98,806 98,755 Upgrades - PLUS (w/campaign) 1.7% 1.5% 205 114 Upgrades - ADV (w/campaign) 0.5% 0.6% -46 92 Upgrades - ALL (ESS/PLUS/ADV) 2.2% 2.0% 159 108 Upgrades - PLUS (3 mo. retention) 92.6% 91.5% 1.1% 101 Upgrades - PLUS (post discount) 1.5% 1.3% 206 116 Upgrades - PLUS (4 mo. retention) 87.4% 86.9% 0.5% 101 Upgrades - PLUS Retained (post 4 mo.) 1.5% 1.3% 186 115 Est. incr. upgrade revenue in first year $10.5 $11.7 -117,580 90 Est. incr. PLUS upgrade revenue in first year $4.6 $5.3 -$72,558 86 Est. incr. ADV upgrade revenue in first year $6.0 $6.4 -$45,022 93 Est. incr. upgrade rev. in first 2 yrs. $20.9 $21.9 -$97,154 96 Est. incr. upgrade rev. in first 3 yrs. $28.7 $29.5 -$81,988 97 PLUS Upgrades 3 mo. after campaign 0.79% 0.83% -41 95 Detailed KPIs (ESS > PLUS) by Price Sensitivity ESS HIGH Price Sens. MED Price Sens. LOW Price Sens. KPIs TEST CON. Δ ITC TEST CON. Δ ITC TEST CON. Δ ITC Samples 37,043 37,039 30,742 30,577 30,970 31,190 Upgrades - PLUS (w/campaign) 1.7% 1.3% 149 131 1.3% 1.2% 38 110 1.9% 1.9% 19 103 Upgrades - PLUS (3 mo. retention) 93.5% 89.9% 3.7% 104 92.2% 90.6% 0 102 91.8% 93.3% 0 98 Upgrades - PLUS (post discount) 1.6% 1.2% 157 136 1.2% 1.1% 41 112 1.8% 1.8% 9 102 Upgrades - ADV (w/campaign) 0.5% 0.5% -1 99 0.4% 0.6% -47 73 0.7% 0.7% 2 101 Upgrades - ALL (ESS/PLUS/ADV) 2.2% 1.8% 148 122 1.7% 1.8% -9 98 2.6% 2.6% 22 103 Est. incr. upgrade revenue in year 1 $8.4 $10.2 -$63,503 83 $8.7 $10.8 -$63,08 0 81 $14.8 $14.5 $9,780 102 Est. incr. PLUS upgrade revenue in year 1 $3.0 $4.7 -$62,340 64 $3.9 $4.4 -$16,67 6 88 $7.0 $6.8 $6,941 103 Est. incr. ADV upgrade revenue in year 1 $5.4 $5.4 -$1,163 99 $4.9 $6.4 -$46,40 4 76 $7.8 $7.7 $2,839 101 Upgrades - PLUS (4 mo. retention) 86.7% 83.9% 2.9% 103 86.7% 86.3% 0.4% 100 88.5% 89.8% -1.2% 99 Upgrades - PLUS Retained (post 4 mo.) 1.5% 1.1% 143 135 1.2% 1.0% 34 111 1.7% 1.7% 10 102 Est. incr. upgrade rev. in first 2 yrs. $19.0 $18.4 -$20,061 97 $20.2 $17.2 -$93,71 6 85 $27.1 $27.7 $18,06 4 102 Est. incr. upgrade rev. in first 3 yrs. $25.5 $25.9 $12,317 101 $27.2 $23.4 -$116,6 10 86 $36.5 $37.3 $24,24 2 102 PLUS Upgrades 3 mo. after campaign 0.6% 0.6% 2 101 0.7% 0.7% -8 96 1.1% 1.2% Intuit Confi -33 dential and Pro 91 prietary RESULTS Targeted disco Align & rollout targeted discounts for SS > PLUS • Offer similar discount for ADV and/or call out higher $ savings in SKU selection ; Update targeting criteria to remove high ADV propensity candidates • Reevaluate discount bands for ESS > PLUS , i.e. >30% discount is lesser than monthly Essentials subscription cost • Test Trials or no cost upgrade for Essentials > PLUS Global Business Solution | J7: QBO | K7: IPD; Email; Sales; Landing Page | L7: Trending Positive | M7: ROI NEGATIVE lesser ADV upgrades payback is ~15 months & Targeted discounts delivered sig. higher SS > PLUS upgrades (143 ITC , + 357) & will deliver +170K revenue by end of year 3 ; Roll out estimate : incremental revenue estimate for first 3 yrs. is 170 K 900 incr. Plus Upgrades & +430K incremental revenue over 3 yrs. ESS > Plus sig. higher , discounts & lesser ADV Targeted discounts delivered sig. higher ESS > PLUS upgrades (114 ITC , + upgrades will drive 82K lesser revenue in first 3 yrs. 205) but will deliver 82K lesser revenue by end of year 3 | U7: [["Wrap Report"], ["ELM -4941"], ["", "", "", "", "", "ade -", "", "", "", "", ""], ["", "", "", "", "ESS > PLUS", "", "", "", "", "", ""], ["", "Business Impact: POSITIVE POSITIVE\nBIZ IMPACT ROI NEGATIVE\nTargeted discounts delivered sig. higher SS > PLUS u\n357) & will deliver +170K revenue by end of year 3 ;\n900 incr. Plus Upgrades & +430K incremental rev\nTargeted discounts delivered sig. higher ESS > PLUS\n205) but will deliver 82K lesser revenue by end of ye", "", "", "", "pgrades (143 ITC , +\nRoll out estimate :\nenue over 3 yrs.", "", "", "", "", ""], ["", "", "", "", "POSITIVE\nROI NEGATIVE", "", "", "", "", "", ""], ["", "", "", "", "", "upgrades (114 ITC , +\nar 3", "", "", "", "", ""], ["Objective\nGet highly likely Quickbooks customers\nTo upgrade to Quickbooks Plus\nBy offering targeted discounts based on price sensitivity\nHypothesis\nOffering discounts based on price sensitivity will optimize\ndiscount dollars & deliver significant incremental upgrades\nResults", "", "", "", "", "", ""], ["KPIs", "TEST", "", "CON.", "Δ", "", "ITC"], ["A SS > PLUS (N=88K/variant)", "", "", "", "", "", ""], ["Upgrades - PLUS (w/campaign)", "1.4%", "", "1.0%", "357", "", "143"], ["Est. incr. upgrade rev. in first 3 yrs.", "$40.5", "", "$38.6", "$163,377", "", "105"], ["B\nESS > PLUS (N=98k/variant)", "", "", "", "", "", ""], ["Upgrades - PLUS (w/campaign)", "1.7%", "", "1.5%", "205", "", "114"], ["Est. incr. upgrade rev. in first 3 yrs.", "$28.7", "", "$29.5", "-$81,988", "", "97"], ["Learnings & Implications\n●A SS > Plus upgrades sig. higher , factoring in discounts &\nlesser ADV upgrades payback is ~15 months &\nincremental revenue estimate for first 3 yrs. is 170 K\n●B ESS > Plus sig. higher , discounts & lesser ADV", "", "", "", "", "", ""], ["", "", "", "", "", "yrs.\ns G3ro4up8", ""], ["SS > PLUS"], ["POSITIVE\nBIZ IMPACT"], ["Detailed KPIs (SS > PLUS)", ""], ["KPIs", "TEST", "CON.", "Δ", "ITC"], [" Samples", "84,081", "84,193", "", ""], ["Upgrades - PLUS (w/campaign)", "1.4%", "1.0%", "357", "143"], ["Upgrades - ESS (w/campaign)", "1.7%", "1.8%", "-124", "92"], ["Upgrades - ADV (w/campaign)", "0.4%", "0.5%", "-53", "86"], ["Upgrades - ALL (ESS/PLUS/ADV)", "3.5%", "3.3%", "180", "107"], ["Upgrades - PLUS (3 mo. retention)", "88.8%", "87.9%", "0.8%", "101"], ["Upgrades - PLUS (post discount)", "1.3%", "0.9%", "324", "144"], ["Upgrades - PLUS (4 mo. retention)", "81.5%", "82.8%", "-1.2%", "99"], ["Upgrades - PLUS Retained (post 4 mo.)", "1.2%", "0.8%", "281", "141"], ["Est. incr. upgrade revenue in first year", "$16.4", "$16.6", "-$12,704", "99"], ["Est. incr. ESS upgrade revenue in first year", "$4.8", "$5.3", "-$35,531", "92"], ["Est. incr. PLUS upgrade revenue in first year", "$7.2", "$6.4", "$69,100", "113"], ["Est. incr. ADV upgrade revenue in first year", "$4.4", "$4.9", "-$46,274", "89"], ["Est. incr. upgrade rev. in first 2 yrs.", "$30.3", "$29.3", "$87,261", "104"], ["Est. incr. upgrade rev. in first 3 yrs.", "$40.5", "$38.6", "$163,377", "105"], ["PLUS Upgrades 3 mo. after campaign", "0.40%", "0.43%", "-23", "94"], ["Upgrade Retention\n●B 3-month retention in PLUS plan of targeted discount cohort is\ncomparable to group not receiving upgrade discount\n●C 4-mo. retention (right measure for sizing full price impact) is trending\ndown but upgrades sustained are significantly higher"], ["Estimated Incremental upgrade revenue\n●D Plus upgrade rev. is significantly higher (+$69K) but ADV (-$46K)\n& ESS (-$35k) offset resulting in $12K lesser overall revenue\n● Payback period is relatively faster & targeted discount cohort\nE will generate incremental revenue after ~15 months"], ["Pull forwards\n●F Upgrades after the campaign ended is directionally lower\nsignalling discount driven pull forwards\n"], ["", "HIGH Price Sens.", "", "", "", "MED Price Sens.", "", "", "", "LOW Price Sens.", "", "", ""], ["KPIs", "TEST", "CON.", "Δ", "ITC", "TEST", "CON.", "Δ", "ITC", "TEST", "CON.", "Δ", "ITC"], [" Samples", "39,981", "39,516", "", "", "23,906", "24,360", "", "", "20,194", "20,317", "", ""], ["Upgrades - PLUS (w/campaign)", "1.7%", "1.1%", "244", "157", "1.2%", "0.8%", "96", "151", "1.2%", "1.1%", "16", "107"], ["Upgrades - ESS (w/campaign)", "1.6%", "1.8%", "-104", "86", "1.6%", "1.6%", "-1", "100", "2.0%", "2.1%", "-20", "95"], ["Upgrades - ADV (w/campaign)", "0.3%", "0.4%", "-34", "80", "0.3%", "0.4%", "-18", "82", "0.5%", "0.5%", "-1", "99"], ["Upgrades - ALL (ESS/PLUS/ADV)", "3.6%", "3.3%", "106", "108", "3.1%", "2.8%", "77", "111", "3.7%", "3.7%", "-5", "99"], ["Upgrades - PLUS (4 mo. retention)", "79.9%", "81.8%", "-1.9%", "98", "82.0%", "82.7%", "-0.7%", "99", "85.6%", "84.6%", "0", "101"], ["Upgrades - PLUS Retained (post 4 mo.)", "1.3%", "0.9%", "187", "153", "1.0%", "0.6%", "77", "150", "1.0%", "0.9%", "16", "109"], ["Est. incr. upgrade rev. in first year", "$16.0", "$16.9", "-$34,758", "95", "$14.8", "$14.1", "$17,901", "105", "$19.1", "$18.9", "$3,177", "101"], ["Est. incr. ESS upgrade revenue in first year", "$4.5", "$5.3", "-$29,685", "86", "$4.6", "$4.6", "-$215", "100", "$5.7", "$6.0", "-$5,852", "95"], ["Est. incr. PLUS upgrade revenue in first year", "$7.5", "$6.9", "$24,363", "109", "$6.4", "$5.0", "$33,492", "128", "$7.5", "$7.0", "$10,47\n3", "107"], ["Est. incr. ADV upgrade revenue in first year", "$4.0", "$4.7", "-$29,436", "84", "$3.8", "$4.5", "-$15,37\n6", "86", "$5.9", "$5.9", "-$1,444", "99"], ["Est. incr. upgrade rev. in first 2 yrs.", "$29.8", "$30.6", "$31,517", "103", "$24.9", "$26.9", "$48,597", "108", "$33.5", "$33.8", "$5,429", "101"], ["Est. incr. upgrade rev. in first 3 yrs.", "$39.3", "$41.3", "$81,950", "105", "$32.8", "$35.8", "$71,997", "109", "$44.1", "$44.5", "$7,163", "101"], ["PLUS Upgrades 3 mo. after campaign", "0.40%", "0.38%", "5", "103", "0.36%", "0.44%", "-18", "83", "0.5%", "0.5%", "-9", "91"], ["KPIs", "TEST", "CON.", "Δ", "ITC"], [" Samples", "98,806", "98,755", "", ""], ["Upgrades - PLUS (w/campaign)", "1.7%", "1.5%", "205", "114"], ["Upgrades - ADV (w/campaign)", "0.5%", "0.6%", "-46", "92"], ["Upgrades - ALL (ESS/PLUS/ADV)", "2.2%", "2.0%", "159", "108"], ["Upgrades - PLUS (3 mo. retention)", "92.6%", "91.5%", "1.1%", "101"], ["Upgrades - PLUS (post discount)", "1.5%", "1.3%", "206", "116"], ["Upgrades - PLUS (4 mo. retention)", "87.4%", "86.9%", "0.5%", "101"], ["Upgrades - PLUS Retained (post 4 mo.)", "1.5%", "1.3%", "186", "115"], ["Est. incr. upgrade revenue in first year", "$10.5", "$11.7", "-117,580", "90"], ["Est. incr. PLUS upgrade revenue in first year", "$4.6", "$5.3", "-$72,558", "86"], ["Est. incr. ADV upgrade revenue in first year", "$6.0", "$6.4", "-$45,022", "93"], ["Est. incr. upgrade rev. in first 2 yrs.", "$20.9", "$21.9", "-$97,154", "96"], ["Est. incr. upgrade rev. in first 3 yrs.", "$28.7", "$29.5", "-$81,988", "97"], ["PLUS Upgrades 3 mo. after campaign", "0.79%", "0.83%", "-41", "95"], ["Detailed KPIs (ESS > PLUS) by Price Sensitivity", "", "", "", "", "", "", "", "", "", "", "", "", "", ""], ["ESS", "HIGH Price Sens.", "", "", "", "MED Price Sens.", "", "", "", "LOW Price Sens.", "", "", "", "", ""], ["KPIs", "TEST", "CON.", "Δ", "ITC", "TEST", "CON.", "Δ", "ITC", "TEST", "CON.", "", "Δ", "ITC", ""], [" Samples", "37,043", "37,039", "", "", "30,742", "30,577", "", "", "30,970", "31,190", "", "", "", ""], ["Upgrades - PLUS (w/campaign)", "1.7%", "1.3%", "149", "131", "1.3%", "1.2%", "38", "110", "1.9%", "1.9%", "", "19", "103", ""], ["Upgrades - PLUS (3 mo. retention)", "93.5%", "89.9%", "3.7%", "104", "92.2%", "90.6%", "0", "102", "91.8%", "93.3%", "", "0", "98", ""], ["Upgrades - PLUS (post discount)", "1.6%", "1.2%", "157", "136", "1.2%", "1.1%", "41", "112", "1.8%", "1.8%", "", "9", "102", ""], ["Upgrades - ADV (w/campaign)", "0.5%", "0.5%", "-1", "99", "0.4%", "0.6%", "-47", "73", "0.7%", "0.7%", "", "2", "101", ""], ["Upgrades - ALL (ESS/PLUS/ADV)", "2.2%", "1.8%", "148", "122", "1.7%", "1.8%", "-9", "98", "2.6%", "2.6%", "", "22", "103", ""], ["Est. incr. upgrade revenue in year 1", "$8.4", "$10.2", "-$63,503", "83", "$8.7", "$10.8", "-$63,08\n0", "81", "$14.8", "$14.5", "", "$9,780", "102", ""], ["Est. incr. PLUS upgrade revenue in year 1", "$3.0", "$4.7", "-$62,340", "64", "$3.9", "$4.4", "-$16,67\n6", "88", "$7.0", "$6.8", "", "$6,941", "103", ""], ["Est. incr. ADV upgrade revenue in year 1", "$5.4", "$5.4", "-$1,163", "99", "$4.9", "$6.4", "-$46,40\n4", "76", "$7.8", "$7.7", "", "$2,839", "101", ""], ["Upgrades - PLUS (4 mo. retention)", "86.7%", "83.9%", "2.9%", "103", "86.7%", "86.3%", "0.4%", "100", "88.5%", "89.8%", "", "-1.2%", "99", ""], ["Upgrades - PLUS Retained (post 4 mo.)", "1.5%", "1.1%", "143", "135", "1.2%", "1.0%", "34", "111", "1.7%", "1.7%", "", "10", "102", ""], ["Est. incr. upgrade rev. in first 2 yrs.", "$19.0", "$18.4", "-$20,061", "97", "$20.2", "$17.2", "-$93,71\n6", "85", "$27.1", "$27.7", "", "$18,06\n4", "102", ""], ["Est. incr. upgrade rev. in first 3 yrs.", "$25.5", "$25.9", "$12,317", "101", "$27.2", "$23.4", "-$116,6\n10", "86", "$36.5", "$37.3", "", "$24,24\n2", "102", ""], ["PLUS Upgrades 3 mo. after campaign", "0.6%", "0.6%", "2", "101", "0.7%", "0.7%", "-8", "96", "1.1%", "", "1.2%\nIntuit Confi", "-33\ndential and Pro", "91\nprietary", ""], ["RESULTS\nTargeted disco"], ["HIGHLIGHTS", "", "LOWLIGHTS"], ["● Targeted discount based on price sensitivity were\nvalidated at scale for 6 cohorts and 3 price points\n● Retention sustained after discount promo period\nsignalling right customers were targeted for\nupgrades\n● SS > Plus upgrades will break even in 1+ years and\nstart delivering incremental revenue", "", "● Multiple iterations due to data issues , execution misses\nand other priorities like price increase\n● ESS > PLUS is ROI negative because of smaller lift , lesser\nAdvanced upgrades and deep discounts"], ["NEXT STEPS & IMPLICATIONS", "", ""], ["● Align & rollout targeted discounts for SS > PLUS\n● Offer similar discount for ADV and/or call out higher $ savings in SKU selection ; Update targeting criteria to remove high\nADV propensity candidates\n● Reevaluate discount bands for ESS > PLUS , i.e. >30% discount is lesser than monthly Essentials subscription cost\n● Test Trials or no cost upgrade for Essentials > PLUS", "", ""]] | V7: Alt Product (slide 348): QuickBooks | Alt TO (slide 348): mers | Alt GET (slide 349): ed discount cohort is | Alt TO (slide 349): group not receiving upgrade discount | Alt BY (slide 349): incremental PLUS (357) & offset by Essentials (-124) / Advanced | Alt BY (slide 350): Price Sensitivity | Alt GET (slide 351): ed discount cohort is | Alt TO (slide 351): group not receiving upgrade discount | Alt BY (slide 351): Upgrades - PLUS (w/campaign) 1.7% 1.5% 205 114 A | Alt BY (slide 352): Price Sensitivity | Alt GET (slide 353): ed discounts for SS > Plus delivered positive | Alt TO (slide 353): data issues , execution misses | Date source: CSV - Current Target Launch Date | Name source: CSV | W7: 347-353 | X7: Copy of FY'25_ CRM Analytics Monthly Experiment_Notebook_AC.pdf | Y7: ✅ ELM Roadmap | ⚠️ Results Report | Z7: highly likely Quickbooks customers | AA7: Upgrades | AB7: offering targeted discounts based on price sensitivity
A8: ELM-5379 | B8: Tax Biz Partnership email with CG | C8: 02-06-2023 | D8: GET: ing QBO customers (S Corp, Multi-Member LLC, Partnerships) with an email to introduce Turbox Tax Live full service and DIY product to drive Business TT take rate. BY: sending an email introducing TurboTax features | E8: IF: THEN: We will see a positive take rate in treatment group with a discernable pattern of attributes with interested customers. (Inferred for review) | F8: • | Turbo Tax take rate (Full Service + Assisted) is directionally higher in treatment than control However, the lift units are pretty small due to that TaxBiz is a new product which just has just been launched since the end of January of 2023 Email Open rate is well above benchmark at 134 ITB Email Click rate is well above benchmark at 112 ITB Email Unsub is a little bit higher than benchmark might because we did not target high TT propensity users Even though our email content was only created for Biz products, it might also have a eco effect for the awareness of personal products. • Email shows higher take rate in treatment group than control. • The take rates for treatment and control group were flat for past 4 years (without ELM email) but directional positive for this year (with ELM email). | G8: Treatment group shows higher take rate than control Email engagement is pretty well • NEXT STEPS & IMPLICATIONS • Personalize emails and target TT high propensity users with promo QBLive + TT Biz bundle (i.e buy QBLive FS, get a 10% off discount for TTBiz FS etc) to improve both QBL and TTB GNS • KPIs TEST CON. • Assignments 86,787 22,003 • Turbo Tax Take rate (2018) 2.84% 2.93% • Turbo Tax Take rate (2019) 3.00% 3.13% • Turbo Tax Take rate (2020) 3.19% 3.35% • Turbo Tax Take rate (2021) 3.51% 3.59% • Turbo Tax Take rate (2022) 0.91% 0.89% | H8: Take rate in treatment group is not stat. Sig QBO audience is not able to expand more (Business Entity) • Δ ITC ELM Incentive • (80:20) • -114 97 NO • -155 96 NO • -182 95 NO • -115 98 NO • 7 102 Email | I8: Personalize emails and target TT high propensity users with promo QBLive + TT Biz bundle (i.e buy QBLive FS, get a 10% off discount for TTBiz FS etc) to improve both QBL and TTB GNS KPIs TEST CON. Δ ITC ELM Incentive Assignments 86,787 22,003 (80:20) Turbo Tax Take rate (2018) 2.84% 2.93% -114 97 NO Turbo Tax Take rate (2019) 3.00% 3.13% -155 96 NO Turbo Tax Take rate (2020) 3.19% 3.35% -182 95 NO Turbo Tax Take rate (2021) 3.51% 3.59% -115 98 NO Turbo Tax Take rate (2022) 0.91% 0.89% 7 102 Email | J8: QBO | K8: Email | L8: Not found (Inferred for review) | U8: [["HYPO\n-THESIS", "We will see a positive take rate in treatment group with a discernable pattern of attributes with interested customers.", "", "", "", ""], ["KPIs", "TEST", "CON.", "Δ", "ITC"], ["Assignments", "86,787", "22,003", "(80:20)", ""], ["Turbo Biz (FS +Assisted)", "15", "2", "7 (Scaled)*", ""], ["Turbo Biz (FS +Assisted)", "0.02%", "0.01%", "0.01%", "190"], ["Email ENGAGEMENT", "", "", "", "", "", "", "", "", ""], ["Cohort", "Email", "", "", "", "", "", "", "", ""], ["", "Unique Sends*", "Unique Opens", "Open rate %", "ITB", "Unique Clicks", "CTR", "ITB", "Unsub %", "ITB"], ["Treatment", "75.5K", "26.8K", "35.5%", "134", "422.6", "0.56%", "112", "0.18%", "165"], ["Control", "No comms", "", "", "", "", "", "", "", ""], ["Email XSell Benchmark*", "", "", "27%", "", "", "0.5%", "", "0.11%", ""], ["HIGHLIGHTS", "LOWLIGHTS"], ["Treatment group shows higher take rate than control\nEmail engagement is pretty well", "Take rate in treatment group is not stat. Sig\nQBO audience is not able to expand more (Business Entity)"], ["NEXT STEPS & IMPLICATIONS", ""], ["Personalize emails and target TT high propensity users with promo\nQBLive + TT Biz bundle (i.e buy QBLive FS, get a 10% off discount for TTBiz FS etc) to improve both QBL and TTB GNS", ""], ["KPIs", "TEST", "CON.", "Δ", "ITC", "ELM Incentive"], ["Assignments", "86,787", "22,003", "(80:20)", "", ""], ["Turbo Tax Take rate (2018)", "2.84%", "2.93%", "-114", "97", "NO"], ["Turbo Tax Take rate (2019)", "3.00%", "3.13%", "-155", "96", "NO"], ["Turbo Tax Take rate (2020)", "3.19%", "3.35%", "-182", "95", "NO"], ["Turbo Tax Take rate (2021)", "3.51%", "3.59%", "-115", "98", "NO"], ["Turbo Tax Take rate (2022)", "0.91%", "0.89%", "7", "102", "Email"]] | V8: Alt GET (slide 221): high TT propensity users | Alt GET (slide 222): TT high propensity users with promo | Alt TO (slide 222): expand more (Business Entity) | TO repaired: truncated 'customers' prefix restored | Date: CSV-Current | W8: 219-223 | X8: Copy of Copy of CRM Analytics 2023 AC.pptx | Y8: ✅ ELM Roadmap | ⚠️ Results Report | Z8: ing QBO customers (S Corp, Multi-Member LLC, Partnerships) with an email to introduce Turbox Tax Live full service and DIY product to drive Business TT take rate. | AA8: Customers (S Corp, Multi-Member LLC, Partnerships) with an email to introduce Turbox Tax Live full service and DIY product to drive Business TT take rate. | AB8: sending an email introducing TurboTax features
A9: ELM-5835 | B9: Increase Take Rate of Annual Plan post sign up | C9: 01-31-2024 | D9: GET: QuickBooks Online and Advanced subscribers with with a high TO: Customers BY: Making them aware that they save 10% by switching to an annual plan. | E9: IF: we surface the discounted annual plan to customers with 90-1Y tenure, with a high propensity to churn THEN: we will increase annual plan take | F9: • Monthly to QBO Annual Plan switches increased significantly (~3X & +1k switches). • The annual plan take rate was higher in QBO Core compared to QBO Advanced The campaign was more effective on NTTF customers compare to DTM; however, both groups were positively affected by the campaign• Banking Hellobox and QBO Bottom Drawer were the IPDs with the best performance. • Dashboard Tips had low reach and Invoice Hellobox had a poor CTR compared to Emails had a Open Rate above benchmark but a poor CTR. • Unsub Rate also performed C above benchmark Low Email Reach. | G9: 31d Annual Plan Take Rate had a 316.7 ITC increase as a consequence of the campaign • 92d Retention had a 100.3 ITC improvement due to more customers in the Annual Plan • 12-month Ecosystem Revenue is projected to be better by $160k as a consequence of the campaign • NEXT STEPS & IMPLICATIONS • Recommendation: Rollout the campaign to everyone ➤ Before rollout, align with GTM Ops how to identify customers that are currently on a discount • Track 12-month retention and 12-month Ecosystem revenue to compare against projections • Explore testing bundle annual plan to customers • Explore expanding experiment to >12M customers with high propensity to churn | H9: Email Reach below 50% • Dashboard Tips had low reach • Invoice Hellobox had a poor CTR compared to Benchmark • FISCAL WEEK 05 | I9: Business Impact: POSITIVE BIZ IMPACT Monthly to annual switches of high churn risk customers incre ITC & +1K switches) resulting in significantly higher 92D Q ITC & +344 saves) ; Experiment & evergreen rollout is esti incremental 1.7K saves & $600K ecosystem revenue. ased significantly (317 BO retention (100.3 mated to deliver KPIs TEST CON. Δ ITC Add. Units Sample Size 122,322 122,778 31d QBO Annual Plan Take Rate 1.2% 0.4% 0.9% 316.7 1,045 31d Payroll Annual Plan Take Rate 0.07% 0.02% 0.05% 321.2 55 92d QBO Retention 90.2% 89.9% 0.28% 100.3 344 12-month Eco. Rev per Customers $865.2 $864.1 $1.1 100.1 $129,853 BIZ IMPACT PO BI Detailed performance summary QBO Core KPIs TEST CON. Δ ITC Sample Size 115,129 115,703 A 31d QBO Annual Plan Take Rate 1.3% 0.4% 0.9% 321.2 92d QBO Retention 90.2% 89.9% 0.2% 100.3 QB Advanced KPIs TEST CON. Δ ITC Sample Size 7,133 7,009 31d QBO Annual Plan Take Rate 0.7% 0.3% 0.4% 219.9 92d QBO Retention 90.6% 89.8% 0.8% 100.9 NTTF KPIs TEST CON. Δ ITC Sample Size 101,945 102,418 B 31d QBO Annual Plan Take Rate 1.2% 0.3% 0.9% 389.5 92d QBO Retention 90.3% 90.0% 0.3% 100.3 DTM KPIs TEST CON. Δ ITC Sample Size 20,377 20,360 31d QBO Annual Plan Take Rate 1.5% 0.8% 0.7% 179.6 92d QBO Retention 89.7% 89.4% 0.3% 100.3 : POSITIVE NEGATIVE BIZ IMPACT BIZ IMPACT LAT & ROLL OUT POSITIVE BIZ IMPACT Access Point Offer Name IPD Imp. Clicks CTR Benchmark Δ ITB Banking - Hellobox ELM5835-IPD-HelloBank-US-QBO_QBOAV-NA-NA-RET-PROMO-NA-CM-AnnualPlanUpsellQBOandQBOAVQ2FY24 13,875 174 1.25% 0.19% 1.06% 660 Dashboard - Tips ELM5835-IPD-TipsDash-US-QBO_QBOAV-NA-NA-RET-PROMO-NA-CM-AnnualPlanUpsellQBOandQBOAVQ2FY24 1,197 3 0.25% 0.14% 0.11% 179 Invoices - Hellobox ELM5835-IPD-HelloInvoice-US-QBO_QBOAV-NA-NA-RET-PROMO-NA-CM-AnnualPlanUpsellQBOandQBOAVQ2FY24 29,334 195 0.66% 1.11% -0.45% 60 QBO Dashboard - Bottom Drawer ELM5835-IPD-QBODashBottom-US-QBO_QBOAV-NA-NA-RET-PROMO-NA-CM-AnnualPlanUpsellQBOandQBOAVQ2FY24 59,201 1,366 2.31% 1.76% 0.55% 131 Asset Name Email Sent Opens % ITB Clicks CTR ITB Unsub % ITB ELM5835-OM-US-QBO_QBOAV-NA-NA-RET-PROMO-NA-EQ-AnnualPlanUpsellQBOandQBOAVQ2FY24_TRT209725_001 46,130 20,294 44% 126 637 1.4% 55 49 0.11% 29 ELM5835-OM-US-QBO_QBOAV-NA-NA-RET-PROMO-NA-EQ-AnnualPlanUpsellQBOandQBOAVQ2FY24_TRT209725_002 45,325 18,925 42% 119 385 0.8% 34 60 0.13% 36 Email Benchmark* 35.0% 2.5% 0.37% : POSITIVE NEGATIVE BIZ IMPACT BIZ IMPACT LAT & ROLL OUT POSITIVE BIZ IMPACT PO BI Annual Plan Campaign Yielded Positive Impact WEEK 05 | J9: QBO | K9: IPD; Email | L9: Positive (Inferred for review) | Results: 5.1 MEASURE: Complete | M9: 92d Retention improved significantly (+344 saves) driven by the BIZ IMPACT uptick in switches to annual billing by high churn risk customers Monthly to annual switches of high churn risk customers increased significantly (317 ITC & +1K switches) resulting in significantly higher 92D QBO retention (100.3 • Additional saves is estimated to deliver ~$130k incremental ITC & +344 saves) ; Experiment & evergreen rollout is estimated to deliver revenue over next 12 months incremental 1.7K saves & $600K ecosystem revenue. 341 | N9: https://docs.google.com/presentation/d/1QPs2C-0hiSKhh9-uFIr-J0uWv_Sk8PYzJO5u9q2mwGE/edit#slide=id.g1d9b8a0b231_0_2704 | O9: Retention Rate | P9: 100.3 | Q9: Annual Take Rate | R9: 316.7 | S9: Annual Take Rate | T9: 316.7 | U9: [["", "Template v4.1 Updated Jan. FY'23"], ["Source of Truth"], ["Link", ""], ["", "Link"], ["", "Link"], ["", "", "", "", "", "Objective\nGet QuickBooks Online and Advanced subscribers with with a high\npropensity to churn and >90 day tenure -12 months that are currently on a\nmonthly plan.\nTo Switch to an annual plan.\nBy Making them aware that they save 10% by switching to an annual plan.\nHypothesis\nIf we surface the discounted annual plan to customers with 90-1Y tenure,\nwith a high propensity to churn, then we will increase annual plan take\nrate and retention amongst those customers.\nResults"], ["", "Annual Pla", "", "", "st\nwards surfacing\ngets customer\nity to churn..", ""], ["", "", "", "", "", "Learnings & Implications\n●A Monthly to QBO Annual Plan switches increased significantly (~3X\n& +1k switches).\n●B 92d Retention improved significantly (+344 saves) driven by the\nuptick in switches to annual billing by high churn risk customers\n●C Additional saves is estimated to deliver ~$130k incremental\nrevenue over next 12 months"], ["Business Impact: POSITIVE\nBIZ IMPACT\nMonthly to annual switches of high churn risk customers incre\nITC & +1K switches) resulting in significantly higher 92D Q\nITC & +344 saves) ; Experiment & evergreen rollout is esti\nincremental 1.7K saves & $600K ecosystem revenue.", "", "", "", "ased significantly (317\nBO retention (100.3\nmated to deliver", ""], ["KPIs", "TEST", "CON.", "Δ", "ITC", "Add. Units", ""], ["Sample Size", "122,322", "122,778", "", "", "", ""], ["31d QBO Annual Plan Take Rate", "1.2%", "0.4%", "0.9%", "316.7", "1,045", ""], ["31d Payroll Annual Plan Take Rate", "0.07%", "0.02%", "0.05%", "321.2", "55", ""], ["92d QBO Retention", "90.2%", "89.9%", "0.28%", "100.3", "344", ""], ["12-month Eco. Rev per Customers", "$865.2", "$864.1", "$1.1", "100.1", "$129,853", ""], ["", "Use this google"], ["template for KPIs", ""], ["POSITIVE BIZ IMPACT PO\nBI\nDetailed performance summary"], ["QBO Core", "", "", "", ""], ["KPIs", "TEST", "CON.", "Δ", "ITC"], ["Sample Size", "115,129", "115,703", "", "A"], ["31d QBO Annual Plan Take Rate", "1.3%", "0.4%", "0.9%", "321.2"], ["92d QBO Retention", "90.2%", "89.9%", "0.2%", "100.3"], ["QB Advanced", "", "", "", ""], ["KPIs", "TEST", "CON.", "Δ", "ITC"], ["Sample Size", "7,133", "7,009", "", ""], ["31d QBO Annual Plan Take Rate", "0.7%", "0.3%", "0.4%", "219.9"], ["92d QBO Retention", "90.6%", "89.8%", "0.8%", "100.9"], ["NTTF", "", "", "", ""], ["KPIs", "TEST", "CON.", "Δ", "ITC"], ["Sample Size", "101,945", "102,418", "", "B"], ["31d QBO Annual Plan Take Rate", "1.2%", "0.3%", "0.9%", "389.5"], ["92d QBO Retention", "90.3%", "90.0%", "0.3%", "100.3"], ["DTM", "", "", "", ""], ["KPIs", "TEST", "CON.", "Δ", "ITC"], ["Sample Size", "20,377", "20,360", "", ""], ["31d QBO Annual Plan Take Rate", "1.5%", "0.8%", "0.7%", "179.6"], ["92d QBO Retention", "89.7%", "89.4%", "0.3%", "100.3"], ["Results: POSITIVE NEGATIVE\nBIZ IMPACT BIZ IMPACT", "", ""], ["", "FLAT &\nROLL OUT", ""], ["POSITIVE BIZ IMPACT"], ["Access Point", "Offer Name", "IPD", "", "", "", "", ""], ["", "", "Imp.", "Clicks", "CTR", "Benchmark", "Δ", "ITB"], ["Banking - Hellobox", "ELM5835-IPD-HelloBank-US-QBO_QBOAV-NA-NA-RET-PROMO-NA-CM-AnnualPlanUpsellQBOandQBOAVQ2FY24", "13,875", "174", "1.25%", "0.19%", "1.06%", "660"], ["Dashboard - Tips", "ELM5835-IPD-TipsDash-US-QBO_QBOAV-NA-NA-RET-PROMO-NA-CM-AnnualPlanUpsellQBOandQBOAVQ2FY24", "1,197", "3", "0.25%", "0.14%", "0.11%", "179"], ["Invoices - Hellobox", "ELM5835-IPD-HelloInvoice-US-QBO_QBOAV-NA-NA-RET-PROMO-NA-CM-AnnualPlanUpsellQBOandQBOAVQ2FY24", "29,334", "195", "0.66%", "1.11%", "-0.45%", "60"], ["QBO Dashboard - Bottom Drawer", "ELM5835-IPD-QBODashBottom-US-QBO_QBOAV-NA-NA-RET-PROMO-NA-CM-AnnualPlanUpsellQBOandQBOAVQ2FY24", "59,201", "1,366", "2.31%", "1.76%", "0.55%", "131"], ["Asset Name", "Email", "", "", "", "", "", "", "", "", ""], ["", "Sent", "Opens", "%", "ITB", "Clicks", "CTR", "ITB", "Unsub", "%", "ITB"], ["ELM5835-OM-US-QBO_QBOAV-NA-NA-RET-PROMO-NA-EQ-AnnualPlanUpsellQBOandQBOAVQ2FY24_TRT209725_001", "46,130", "20,294", "44%", "126", "637", "1.4%", "55", "49", "0.11%", "29"], ["ELM5835-OM-US-QBO_QBOAV-NA-NA-RET-PROMO-NA-EQ-AnnualPlanUpsellQBOandQBOAVQ2FY24_TRT209725_002", "45,325", "18,925", "42%", "119", "385", "0.8%", "34", "60", "0.13%", "36"], ["Email Benchmark*", "", "", "35.0%", "", "", "2.5%", "", "", "0.37%", ""], ["Results: POSITIVE NEGATIVE\nBIZ IMPACT BIZ IMPACT", "", ""], ["", "FLAT &\nROLL OUT", ""], ["POSITIVE BIZ IMPACT PO\nBI\nAnnual Plan Campaign Yielded Positive Impact"], ["HIGHLIGHTS", "", "LOWLIGHTS"], ["● 31d Annual Plan Take Rate had a 316.7 ITC\nincrease as a consequence of the campaign\n● 92d Retention had a 100.3 ITC improvement due\nto more customers in the Annual Plan\n● 12-month Ecosystem Revenue is projected to be\nbetter by $160k as a consequence of the\ncampaign", "", "● Email Reach below 50%\n● Dashboard Tips had low reach\n● Invoice Hellobox had a poor CTR compared to\nBenchmark"], ["NEXT STEPS & IMPLICATIONS", "", ""], ["● Recommendation: Rollout the campaign to everyone\n➤ Before rollout, align with GTM Ops how to identify customers that are currently on a discount\n● Track 12-month retention and 12-month Ecosystem revenue to compare against projections\n● Explore testing bundle annual plan to customers\n● Explore expanding experiment to >12M customers with high propensity to churn", "", ""], ["FISCAL WEEK 05"]] | V9: Alt Date (slide 341): 01-31-24 | Alt TO (slide 341): churn and >90 day tenure -12 months that are currently on a | Alt Product (slide 342): QBO | Alt TO (slide 342): r Type | Alt BY (slide 342): QBO SKU | Alt status (slide 342): Trending Positive | Alt Campaign Name (slide 343): IPD-HelloBank-US-QBO_QBOAV-NA-NA-RET-PROMO-NA-CM-AnnualPlanUpsellQBOandQBOAVQ2FY24 13,875 174 1.25% 0.19% 1.06% 660 | Alt Product (slide 343): Invoicing | Alt TO (slide 343): m Drawer ELM5835-IPD-QBODashBottom-US-QBO_QBOAV-NA-NA-RET-PROMO-NA-CM-AnnualPlanUpsellQBOandQBOAVQ2FY24 59,201 1,366 2.31% 1.76% 0.55% 131 | Alt status (slide 343): Trending Positive | Alt Product (slide 344): Invoicing | Alt GET (slide 344): to manually send the wrap report email | Alt TO (slide 344): be | Alt BY (slide 344): $160k as a consequence of the | Date source: CSV - Current Target Launch Date | Name source: CSV | Business Impact updated from Results Report | Status enriched from Results Report | TO repaired: truncated 'customers' prefix restored | W9: 340-345 | X9: Copy of FY'25_ CRM Analytics Monthly Experiment_Notebook_AC.pdf | Y9: ✅ ELM Roadmap | ✅ Results Report | Z9: QuickBooks Online and Advanced subscribers with with a high | AA9: Customers | AB9: Making them aware that they save 10% by switching to an annual plan.
A10: ELM-6548 | B10: Annual plan targeted offer for early tenured customers | C10: 06-04-2024 | D10: GET: QuickBooks Online and Advanced high propensity to churn TO: Surfacing annual pricing with a special targeted offer of 16% for customer 30-90 days in tenure currently on 50% off for 3 months plan. (Inferred for review) BY: Making giving them a TO with a special 16% discount to | E10: IF: Here If we surface a special 16% discount to early tenured customers on day 1-90 that are currently on 50% off for 3 months offer , we | F10: • Increased awareness & savings significantly increased (1424 ITC) switches from monthly to Annual plan for high churn risk new QBO subscribers but • Billing frequency switches from Monthly to Annual this did not translate into customer saves. 92 D retention is flat and we increased significantly (1424 ITC & +435 switches). recommend not to roll out this experiment. 3-month retention is flat , customers who switched would have have retained nevertheless • The annual plan take rate was higher in QBO Core compared to QBO Advanced 92 D retention for Advanced is better (+19 units) in spite of relatively lower switches to annual offer (+4 units) , hence retention improvement is not completely driven by annual plan and highly likely to be small sample noise. | G10: Annual Plan Take Rate had a 1424 ITC increase as a consequence of the campaign • NEXT STEPS & IMPLICATIONS • Identify pocket rollout opportunities (i.e.churn decile) & validate same plan retention benefits for premium SKUs (ADV/PLUS) • Refine targeting criteria by updating the respective churn models • Consider testing differential discounts based on price sensitivity | H10: Annual plan switches increase did not translate to customer saves and 92d Retention is flat (100 ITC). • | I10: Core KPIs TEST CON. Δ ITC Sample Size 28,864 28,964 Annual Plan Take Rate 1.6% 0.1% 1.5% 1,549 92 d Retention 84.4% 84.6% -0.2% 99.7 QBO Advanced KPIs TEST CON. Δ ITC Sample Size 1,273 1,282 Annual Plan Take Rate 0.5% 0.2% 0.3% 235 92 d Retention 75.6% 74.2% 1.5% 102.0 : POSITIVE NEGATIVE BIZ IMPACT BIZ IMPACT LAT & ROLL OUT Email Channel Engagement EMAIL Asset Name Sends Open % CTR CTR ITB Unsub %U nsub % IT Open % ITB ELM6548-EM-US-QBO_QBOAV-NA-NA-RET-PROMO-NA-EQ-AnnualPlanTOearlyTenure_001 16,877 37.90% 126 1.49% 186 0.09% 111 ELM6548-EM-US-QBO_QBOAV-NA-NA-RET-PROMO-NA-EQ-AnnualPlanTOearlyTenure_001a 16,175 36.60% 122 1.24% 155 0.12% 83 ELM6548-EM-US-QBO_QBOAV-NA-NA-RET-PROMO-NA-EQ-AnnualPlanTOearlyTenure_002 3,065 36.20% 121 1.31% 164 0.10% 100 ELM6548-EM-US-QBO_QBOAV-NA-NA-RET-PROMO-NA-EQ-AnnualPlanTOearlyTenure_002a 2,953 33.80% 113 1.42% 178 0.03% 333 ELM6548-EM-US-QBO_QBOAV-NA-NA-RET-PROMO-NA-EQ-AnnualPlanTOearlyTenure_003 4,086 36.90% 123 1.49% 186 0.02% 500 ELM6548-EM-US-QBO_QBOAV-NA-NA-RET-PROMO-NA-EQ-AnnualPlanTOearlyTenure_003a 3,941 34.90% 116 1.50% 188 0.05% 200 ELM6548-EM-US-QBO_QBOAV-NA-NA-RET-PROMO-NA-EQ-AnnualPlanTOearlyTenure_004 702 31.90% 106 0.85% 106 0.14% 71 ELM6548-EM-US-QBO_QBOAV-NA-NA-RET-PROMO-NA-EQ-AnnualPlanTOearlyTenure_004a 670 32.10% 107 A 1.64% A 205 0.00% 0 Email Benchmark *** 30.00% 0.80% 0.10% A Email Open Rate and CTRs are high compared to benchmarks B• ELM6548_*__001a and ELM6548_*__004 asset name has a higher unsubscribe rate compared to the benchmark IPD Access Point Offer ID Offer Name Imp. Clicks CTR Δ ITB Advanced Shell - Banner c33bf8e0-1945-11ef-af6b-bde26c825903 20053191 - ELM6548-IPD-AdvShellBan-US-QBOAV-NA-NA-RET-PROMO-NA-CM-AnnualPl anTOearlyTenure 1,897 63 3.32% 2.75% 583 QBO Dashboard - Bottom Drawer 48d955f0-1947-11ef-8d06-f7ceec2fd2cd 20053192 - ELM6548-IPD-QBODashBottom-US-QBO-PLUS-NA-RET-PROMO-NA-CM-Ann ualPlanTOearlyTenure 2,585 136 5.26% 5.26% 923 642d4bf0-1946-11ef-ae71-5ffb59e590f1 20053193 - ELM6548-IPD-QBODashBottom-US-QBO-SS-NA-RET-PROMO-NA-CM-Annual PlanTOearlyTenure 7,502 451 6.01% 5.44% 1,055 bbf8bae0-1946-11ef-8d06-f7ceec2fd2cd 20053190 - ELM6548-IPD-QBODashBottom-US-QBO-ES-NA-RET-PROMO-NA-CM-Annual PlanTOearlyTenure 1,721 79 4.59% 4.59% 805 c0b1e0b0-1947-11ef-ae71-5ffb59e590f1 20053191 - ELM6548-IPD-QBODashBottom-US-QBOAV-NA-NA-RET-PROMO-NA-CM-Ann ualPlanTOearlyTenure 608 29 4.77% 4.20% 837 Shell - Banner 62602280-1945-11ef-ae71-5ffb59e590f1 20053192 - ELM6548-IPD-ShellBan-US-QBO-PLUS-NA-RET-PROMO-NA-CM-AnnualPlanT OearlyTenure 8,688 221 2.54% 2.54% 446 75fe3800-1944-11ef-ae71-5ffb59e590f1 20053193 - ELM6548-IPD-ShellBan-US-QBO-SS-NA-RET-PROMO-NA-CM-AnnualPlanTOe arlyTenure 28,798 795 2.76% 2.19% 484 fbfa7360-1944-11ef-ae71-5ffb59e590f1 20053190 - ELM6548-IPD-ShellBan-US-QBO-ES-NA-RET-PROMO-NA-CM-AnnualPlanTOe arlyTenure 6,160 164 2.66% 2.66% 467 IPD Benchmark *** 0.57% Annual Plan Campaign for <90D: Identify pocket rollout opportunities (i.e.churn decile) & validate same plan retention benefits for premium SKUs (ADV/PLUS) • Refine targeting criteria by updating the respective churn models • Consider testing differential discounts based on price sensitivity Global Business Solution | J10: QBO | K10: IPD; Email | L10: Positive (Inferred for review) | Results: 5.1 MEASURE: Complete | M10: 100 ITC-1 | 1424 ITC-2 | 1424 ITC-3 [Results Report] ITC-1: 100 | ITC-2: 1424 | ITC-3: 1424 | N10: https://docs.google.com/presentation/d/1lOhbprbtXVSOePMLgijcha4JrpmRHWujHlxrAJyM7KM/edit#slide=id.g1d9b8a0b231_0_2704 | O10: Retention Rate | P10: 100 | Q10: Annual Take Rate | R10: 1424 | S10: Annual Take Rate | T10: 1424 | U10: [["TOPIC", "", "TIME"], ["01.Proactive Saves - Annual offer (New customers < 90 days , ELM 6548)\nKarthik", "", "10 Min"], ["02.Passive Cancel Winbacks (ELM 6478)\nAndre", "", "10 Min"], ["03.Live Landing Page (ELM 6557)\nAneesh", "", "10 Min"], ["04.Bottom Drawer V1 (ELM 6616)\nNaveen", "", "10 Min"], ["05.Optimizing Payroll Landing Page (ELM 3152)\nManasa", "", "10 Min"], ["Wrap Report"], ["ELM -6548\nAnnual Plan TO for Early Tenured"], ["RESULTS\nAnnual Plan Te\nThis is phase 2 of a 2-phase project working toward\nannual plan discount. This phase will focus on highli\nannual discount to high propensity to churn early te\nday 1-90 that are currently on the 50% for 3 months\nProject Name\nHere\nDescribe the what of the project and\nexperience a little bit here, what\nchannels were useIdnc alundde a pnryotjehcint gvi suals here\nunique about the targeting.", "", "", "RESULTS", "", "", "", "", "", "st\ns surfacing the the\nghting a special 16%\nnured customers on\noffer.", "", ""], ["", "", "", "", "", "", "", "", "", "st\ns surfacing the the\nghting a special 16%\nnured customers on\noffer.", "", ""], ["", "", "", "", "Project Name\nHere\nDescribe the what of the project and\nexperience a little bit here, what\nchannels were useIdnc alundde a pnryotjehcint gvi suals he\nunique about the targeting.", "", "ect Name\nthe what of the project and", "", "", "", "", ""], ["", "", "", "", "", "rien\nnels\nue a", "ce a little bit here, what\nwere useIdnc alundde a pnryotjehcint gvi suals he\nbout the targeting.", "", "re", "", "", ""], ["", "", "Business Impact: FLAT\nIncreased awareness & savings significantly increase\nfrom monthly to Annual plan for high churn risk new\nthis did not translate into customer saves. 92 D retenti\nrecommend not to roll out this experiment.", "", "", "", "", "", "", "d (1424 ITC) switches\nQBO subscribers but\non is flat and we", "", ""], ["Objective\nGet QuickBooks Online and Advanced high propensity to churn\ncustomers in days 1-90 in tenure currently on 50% off for 3\nmonths\nTo Switch to an annual plan.\nBy Making giving them a TO with a special 16% discount to\nencourage them to switch to an annual plan.\nHypothesis\nIf we surface a special 16% discount to early tenured customers\non day 1-90 that are currently on 50% off for 3 months offer , we\nwill increase annual plan take rate and retention amongst those\ncustomers.\nResults\nKPIs TEST CON. Δ ITC"], ["KPIs", "TEST", "CON.", "Δ", "ITC", ""], ["Sample Size", "30,105", "30,222", "A", "", ""], ["Annual Plan Take Rate", "1.6%", "0.1%", "1.4%", "1,424", ""], ["31d Retention", "91.5%", "91.9%", "-0.3%", "100", ""], ["92 d Retention", "84.1%", "84.2%", "B\n-0.1%", "100", ""], ["QBO Core", "", "", "", ""], ["KPIs", "TEST", "CON.", "Δ", "ITC"], ["Sample Size", "28,864", "28,964", "", ""], ["Annual Plan Take Rate", "1.6%", "0.1%", "1.5%", "1,549"], ["92 d Retention", "84.4%", "84.6%", "-0.2%", "99.7"], ["QBO Advanced", "", "", "", ""], ["KPIs", "TEST", "CON.", "Δ", "ITC"], ["Sample Size", "1,273", "1,282", "", ""], ["Annual Plan Take Rate", "0.5%", "0.2%", "0.3%", "235"], ["92 d Retention", "75.6%", "74.2%", "1.5%", "102.0"], ["Results: POSITIVE NEGATIVE\nBIZ IMPACT BIZ IMPACT", "", ""], ["", "FLAT &\nROLL OUT", ""], ["Email Channel Engagement", "", "", "", "", "", "", "", "", ""], ["EMAIL", "", "", "", "", "", "", "", "", ""], ["Asset Name", "Sends", "Open %", "", "", "CTR", "CTR ITB", "Unsub %U", "", "nsub % IT"], ["", "", "", "", "Open % ITB", "", "", "", "", ""], ["ELM6548-EM-US-QBO_QBOAV-NA-NA-RET-PROMO-NA-EQ-AnnualPlanTOearlyTenure_001", "16,877", "37.90%", "", "126", "1.49%", "186", "0.09%", "", "111"], ["ELM6548-EM-US-QBO_QBOAV-NA-NA-RET-PROMO-NA-EQ-AnnualPlanTOearlyTenure_001a", "16,175", "36.60%", "", "122", "1.24%", "155", "0.12%", "", "83"], ["ELM6548-EM-US-QBO_QBOAV-NA-NA-RET-PROMO-NA-EQ-AnnualPlanTOearlyTenure_002", "3,065", "36.20%", "", "121", "1.31%", "164", "0.10%", "", ""], ["ELM6548-EM-US-QBO_QBOAV-NA-NA-RET-PROMO-NA-EQ-AnnualPlanTOearlyTenure_002a", "2,953", "33.80%", "", "113", "1.42%", "178", "0.03%", "", "333"], ["ELM6548-EM-US-QBO_QBOAV-NA-NA-RET-PROMO-NA-EQ-AnnualPlanTOearlyTenure_003", "4,086", "36.90%", "", "123", "1.49%", "186", "0.02%", "", "500"], ["ELM6548-EM-US-QBO_QBOAV-NA-NA-RET-PROMO-NA-EQ-AnnualPlanTOearlyTenure_003a", "3,941", "34.90%", "", "116", "1.50%", "188", "0.05%", "", ""], ["ELM6548-EM-US-QBO_QBOAV-NA-NA-RET-PROMO-NA-EQ-AnnualPlanTOearlyTenure_004", "702", "31.90%", "", "106", "0.85%", "106", "0.14%", "", "71"], ["ELM6548-EM-US-QBO_QBOAV-NA-NA-RET-PROMO-NA-EQ-AnnualPlanTOearlyTenure_004a", "670", "32.10%", "", "107", "A\n1.64%", "A\n205", "0.00%", "", ""], ["Email Benchmark ***", "", "30.00%", "", "", "0.80%", "", "0.10%", "", ""], ["● A Email Open Rate and CTRs are high compared to benchmarks\nB● ELM6548_*__001a and ELM6548_*__004 asset name has a higher unsubscribe rate compared to the benchmark", "", "", "", "", "", "", "", "", ""], ["IPD", "", "", "", "", "", "", "", "", ""], ["Access Point", "Offer ID", "Offer Name", "Imp.", "Clicks", "CTR", "Δ", "", "ITB", ""], ["Advanced Shell - Banner", "c33bf8e0-1945-11ef-af6b-bde26c825903", "20053191 -\nELM6548-IPD-AdvShellBan-US-QBOAV-NA-NA-RET-PROMO-NA-CM-AnnualPl\nanTOearlyTenure", "1,897", "63", "3.32%", "2.75%", "", "", ""], ["QBO Dashboard - Bottom Drawer", "48d955f0-1947-11ef-8d06-f7ceec2fd2cd", "20053192 -\nELM6548-IPD-QBODashBottom-US-QBO-PLUS-NA-RET-PROMO-NA-CM-Ann\nualPlanTOearlyTenure", "2,585", "136", "5.26%", "5.26%", "", "923", ""], ["", "642d4bf0-1946-11ef-ae71-5ffb59e590f1", "20053193 -\nELM6548-IPD-QBODashBottom-US-QBO-SS-NA-RET-PROMO-NA-CM-Annual\nPlanTOearlyTenure", "7,502", "451", "6.01%", "5.44%", "", "1,055", ""], ["", "bbf8bae0-1946-11ef-8d06-f7ceec2fd2cd", "20053190 -\nELM6548-IPD-QBODashBottom-US-QBO-ES-NA-RET-PROMO-NA-CM-Annual\nPlanTOearlyTenure", "1,721", "79", "4.59%", "4.59%", "", "805", ""], ["", "c0b1e0b0-1947-11ef-ae71-5ffb59e590f1", "20053191 -\nELM6548-IPD-QBODashBottom-US-QBOAV-NA-NA-RET-PROMO-NA-CM-Ann\nualPlanTOearlyTenure", "608", "29", "4.77%", "4.20%", "", "837", ""], ["Shell - Banner", "62602280-1945-11ef-ae71-5ffb59e590f1", "20053192 -\nELM6548-IPD-ShellBan-US-QBO-PLUS-NA-RET-PROMO-NA-CM-AnnualPlanT\nOearlyTenure", "8,688", "221", "2.54%", "2.54%", "", "446", ""], ["", "75fe3800-1944-11ef-ae71-5ffb59e590f1", "20053193 -\nELM6548-IPD-ShellBan-US-QBO-SS-NA-RET-PROMO-NA-CM-AnnualPlanTOe\narlyTenure", "28,798", "795", "2.76%", "2.19%", "", "484", ""], ["", "fbfa7360-1944-11ef-ae71-5ffb59e590f1", "20053190 -\nELM6548-IPD-ShellBan-US-QBO-ES-NA-RET-PROMO-NA-CM-AnnualPlanTOe\narlyTenure", "6,160", "164", "2.66%", "2.66%", "", "467", ""], ["IPD Benchmark ***", "", "", "", "", "0.57%", "", "", "", ""], ["Annual Plan Campaign for <90D:"], ["HIGHLIGHTS", "", "LOWLIGHTS"], ["● Annual Plan Take Rate had a 1424 ITC increase as\na consequence of the campaign", "", "● Annual plan switches increase did not translate to\ncustomer saves and 92d Retention is flat (100 ITC)."], ["NEXT STEPS & IMPLICATIONS", "", ""], ["● Identify pocket rollout opportunities (i.e.churn decile) & validate same plan retention benefits for premium SKUs (ADV/PLUS)\n● Refine targeting criteria by updating the respective churn models\n● Consider testing differential discounts based on price sensitivity", "", ""], ["●"], ["●"], ["●"]] | V10: Alt TO (slide 298): for Early Tenured | Alt Product (slide 299): QuickBooks Online | Alt TO (slide 299): churn | Alt Product (slide 300): QBO | Alt TO (slide 300): QBO Advanced | Alt BY (slide 300): QBO SKU | Alt status (slide 300): Trending Positive | Alt Campaign Name (slide 301): EM-US-QBO_QBOAV-NA-NA-RET-PROMO-NA-EQ-AnnualPlanTOearlyTenure_001 16,877 37.90% 126 1.49% 186 0.09% 111 | Alt Product (slide 301): QBO | Alt TO (slide 301): earlyTenure_001 16,877 37.90% 126 1.49% 186 0.09% 111 | Alt Campaign Name (slide 302): IPD-AdvShellBan-US-QBOAV-NA-NA-RET-PROMO-NA-CM-AnnualPl | Alt Product (slide 302): QBO | Alt TO (slide 302): earlyTenure 3.32% 2.75% 583 | Alt GET (slide 303): ing criteria by updating the respective churn models | Alt TO (slide 303): a consequence of the campaign customer saves and 92d Retention is flat (100 ITC). | Alt BY (slide 303): updating the respective churn models | Date source: CSV - Current Target Launch Date | Name source: CSV | Business Impact updated from Results Report | Status enriched from Results Report | TO replaced with CSV Project Description (was: placeholder) | W10: 297-303 | X10: Copy of FY'25_ CRM Analytics Monthly Experiment_Notebook_AC.pdf | Y10: ✅ ELM Roadmap | ✅ Results Report | Z10: QuickBooks Online and Advanced high propensity to churn | AA10: Surfacing annual pricing with a special targeted offer of 16% for customer 30-90 days in tenure currently on 50% off for 3 months plan. (Inferred for review) | AB10: Making giving them a TO with a special 16% discount to
A11: ELM-4766 | B11: Targeted Offers - Advanced Upgrade | C11: 10-18-2022 | D11: GET: Existing QBO customers with high Advanced propensity (Inferred for review) TO: Customers with high Adv. propensity BY: offering a compelling discount in multiple channels and highlighting value proposition | E11: IF: Offering compelling discounts in multiple channels will drive incremental Advanced upgrades (Inferred for review) | F11: • | Advanced upgrades is significantly higher for the treatment group Retention post upgrade is trending in the right direction Payroll GNS during the campaign was similar (1) IPD - shell banner In-app landing page (OICMS) /app/learn-more/accounting-upgrade Billing & Subscriptions page | G11: • NEXT STEPS & IMPLICATIONS • Calling out discounts prominently & a shortened funnel might be other contributors , we should prioritize experimenting similar experiences with evergreen offers across the ecosystem Make a roll out decision based on 3+ month retention • CHANNEL ENGAGEMENT • CTR < ADV Upsell benchmark but it is a function of impression volume • COHORT IPD • Imp. Clicks • Targeted offer 5,656,716 52,605 • IPD Benchmark ** • BUSINESS IMPACT • Campaign delivered incremental advanced upgrades • COHORT SIZE % ADV Upgrades till date • Total Δ ITC • Targeted offer 70,171 49.8% 1.3% 0.46% 153 • Control 70,645 50.2% 0.9% | H11: • CTR Δ ITB • 0.93% -0.22% 81 • 1.15% • Retention till date Payroll GNS • % Δ ITC % Δ ITC • 95.5% 0.26% 100 0.49% -0.01% 98 • 95.2% 0.50% | I11: Calling out discounts prominently & a shortened funnel might be other contributors , we should prioritize experimenting similar experiences with evergreen offers across the ecosystem Make a roll out decision based on 3+ month retention CTR < ADV Upsell benchmark but it is a function of impression volume COHORT IPD Imp. Clicks CTR Δ ITB Targeted offer 5,656,716 52,605 0.93% -0.22% 81 IPD Benchmark ** 1.15% BUSINESS IMPACT Campaign delivered incremental advanced upgrades COHORT SIZE % ADV Upgrades till date Retention till date Payroll GNS Total Δ ITC % Δ ITC % Δ ITC Targeted offer 70,171 49.8% 1.3% 0.46% 153 95.5% 0.26% 100 0.49% -0.01% 98 Control 70,645 50.2% 0.9% 95.2% 0.50% | J11: QBO Advanced | K11: Email | L11: Not found (Inferred for review) | M11: Campaign delivered incremental advanced upgrades COHORT | SIZE | % | ADV Upgrades till date | Retention till date | Payroll GNS Total | Δ | ITC | % | Δ | ITC | % | Δ | ITC Targeted offer | 70,171 | 49.8% | 1.3% | 0.46% | 153 | 95.5% | 0.26% | 100 | 0.49% | -0.01% | 98 Control | 70,645 | 50.2% | 0.9% | 95.2% | 0.50% | U11: [["HYPO\n-THESIS", "Offering compelling discounts in multiple channels will drive incremental Advanced upgrades", "", "", "", ""], ["LEARNINGS", "Advanced upgrades is significantly higher for the treatment group\nRetention post upgrade is trending in the right direction\nPayroll GNS during the campaign was similar", "", "", "", ""], ["KPIs", "TEST", "CON.", "Δ", "ITC"], ["Samples", "70.2K", "70.6K", "", ""], ["ADV Upgrades till date", "1.3%", "0.9%", "0.46%", "153"], ["Retention till date", "95.5%", "95.2%", "0.26%", "100"], ["Payroll GNS", "0.49%", "0.50%", "-0.01%", "98"], ["HIGHLIGHTS", "", "LOWLIGHTS"], ["NEXT STEPS & IMPLICATIONS", "", ""], ["Calling out discounts prominently & a shortened funnel might be other contributors , we should prioritize experimenting similar experiences with evergreen offers across the ecosystem\nMake a roll out decision based on 3+ month retention", "", ""], ["CHANNEL ENGAGEMENT", "", "", "", "", ""], ["CTR < ADV Upsell benchmark but it is a function of impression volume", "", "", "", "", ""], ["COHORT", "IPD", "", "", "", ""], ["", "Imp.", "Clicks", "CTR", "Δ", "ITB"], ["Targeted offer", "5,656,716", "52,605", "0.93%", "-0.22%", "81"], ["", "IPD Benchmark **", "", "1.15%", "", ""], ["BUSINESS IMPACT", "", "", "", "", "", "", "", "", "", "", ""], ["Campaign delivered incremental advanced upgrades", "", "", "", "", "", "", "", "", "", "", ""], ["COHORT", "SIZE", "%", "ADV Upgrades till date", "", "", "Retention till date", "", "", "Payroll GNS", "", ""], ["", "", "", "Total", "Δ", "ITC", "%", "Δ", "ITC", "%", "Δ", "ITC"], ["Targeted offer", "70,171", "49.8%", "1.3%", "0.46%", "153", "95.5%", "0.26%", "100", "0.49%", "-0.01%", "98"], ["Control", "70,645", "50.2%", "0.9%", "", "", "95.2%", "", "", "0.50%", "", ""]] | V11: Alt Name (slide 347): ● | Alt Date (slide 347): 10-17-22 | Alt GET (slide 347): existing QB customers with high Adv. propensity | Alt Date (slide 348): 10-17-22 | Alt GET (slide 348): ed discounts communicated through IPDs | Alt TO (slide 348): EXPERIMENT DESIGN | Alt GET (slide 349): specific customers with discounts | Alt TO (slide 349): make a rollout decision | Alt GET (slide 350): ed offer | 5,656,716 | 52,605 | 0.93% | -0.22% | 81 | Alt TO (slide 350): tal | Δ | ITC | % | Δ | ITC | % | Δ | ITC | TO repaired: truncated 'customers' prefix restored | Date: CSV-Current | W11: 346-350 | X11: Copy of Copy of CRM Analytics 2023 AC.pptx | Y11: ✅ ELM Roadmap | ⚠️ Results Report | Z11: Existing QBO customers with high Advanced propensity (Inferred for review) | AA11: Customers with high Adv. propensity | AB11: offering a compelling discount in multiple channels and highlighting value proposition
A12: ELM-8533 | B12: BI November Release QBO Advanced | C12: 11-18-2025 | D12: GET: high propensity for QBO Adv clients TO: high-propensity QBO customers drove positive lift in overall upgrade (102 ITC). Advance upgrades is flat (101 ITC) and Plus is positive (108 ITC); Plus→Advance upgrade shows a statistically significant positive lift (ITC 108) (~600 annual plus to advance upgrades) BY: Promoting the new reporting functionality from BI November release | E12: IF: If customers are made aware of the new BI functionality page with new features / product releases, it will increase feature adoption & awareness about other offerings thereby increase | F12: • BI reporting drove positive lift in overall upgrade rate BI drove significantly positive lift in Plus upgrade rate whereas advance and essential upgrade are flat. • Promote the benefits of the new reporting functionality from BI Nov release to high propensity QuickBooks customers to drive upgrades to QBO Adv Plus customers are the primary drivers of Advance upgrades when exposed to the BI Reporting feature. • The experiment shows a statistically strong lift in Plus → Advance upgrades Essential customers did not drive any upgrade unites. • Essential→Advance is negative while Essentials→Plus is Flat indicating opportunity to retarget essentials customers with more value driven messaging along with BI Simple Start customers drove significant lift in Plus upgrade with 126 ITC.however SS→Advance and SS→Essentials show no improvement and trend negative (ITC 93 and 96 respectively). BI Reporting and AURA Report Discovery reinforce each other. • When both treatments are shown, upgrade rate increases from 0.13% to 0.16% (ITC ~122) IPD CTR is 1.24% with 148 ITB mostly driven by Modal interrupters with 2% CTR Email open rate is 27% and click rate is 0.27% along with BI for Essential and SS customers. • Leverage more prominent access points like Bottom Drawer along with others to capture high intent customers Revalidate targeting attribute used to target high propensity customers Do not forget to manually send the wrap report email summary to everyone who was interested in this project. • Email template here. • Delete this when you have sent the email. | G12: Strong engagement with BI Reporting surfaces: IPD drove high engagement with an overall CTR of 1.24%, including 1.48 ITB CTR and ~2% CTR on the modal interrupter, indicating strong interest in reporting-related value. Plus customers exposed to BI Reporting showed a significant uplift in Advance upgrades (ITC ~107), validating BI Reporting as an effective upgrade lever for this segment. BI Reporting exposure led to a meaningful lift in Simple Start → Plus upgrades • NEXT STEPS & IMPLICATIONS • Roll out BI Reporting upgrade messaging broadly to all Plus customers. Use move value driven messaging and insights along with BI for Essential and SS customers. Leverage more prominent access points like Bottom Drawer along with others to capture high intent customers Revalidate targeting attribute used to target high propensity customers | H12: Despite strong CTRs, overall Advance upgrade conversion remained low, particularly among non-Plus segments. Both Essential → Advance and Essential → Plus upgrades trended flat to negative, indicating BI Reporting alone does not sufficiently motivate Essentials customers to upgrade. Simple Start → Advance and Simple Start → Essential upgrades showed no positive movement, reinforcing that BI Reporting may be too advanced for direct conversion at this stage. ~75% of the targeted audience was Essential and Simple Start, while only 25% were Plus, limiting overall Advance lift despite strong Plus performance | I12: Roll out BI Reporting upgrade messaging broadly to all Plus customers. Use move value driven messaging and insights along with BI for Essential and SS customers. Leverage more prominent access points like Bottom Drawer along with others to capture high intent customers Revalidate targeting attribute used to target high propensity customers | J12: QBO Advanced | K12: IPD; Email; Landing Page | L12: Not found (Inferred for review) | Results: 5.1 MEASURE: Complete | M12: Overall positive impact : Promoting BI features to high-propensity QBO customers drove positive lift in overall upgrade (102 ITC). Advance upgrades is flat (101 ITC) and Plus is positive (108 ITC); Plus→Advance upgrade shows a statistically significant positive lift (ITC 108) (~600 annual plus to advance upgrades) [Results Report] | ITC-1: 108 | N12: https://docs.google.com/presentation/d/1TcHV9k3-wqU36nvojnvqzyXvp_5ZDkBbaJbdQJigGEU/edit?usp=sharing | O12: Upgrades | P12: 108 | U12: [["KPIs", "TEST", "CON.", "ITC", "P(T>C)"], [" Assignments", "456,626", "456,989", "", ""], ["Overall upgrade 31D", "0.45%", "0.44%", "102.44", "78%"], ["Advance upgrade 31D", "0.13%", "0.13%", "100.60", "54%"], ["Plus upgrade 31D", "0.20%", "0.18%", "107.99", "94%"], ["Essentials upgrade 31D", "0.11%", "0.11%", "96.17", "53%"], ["KPIs", "TEST", "CON.", "ITC", "P(T>C)"], [" Assignments", "105,100", "104,903", "", ""], ["Advance upgrade 31D", "0.32%", "0.30%", "108.05", "84%"], ["KPIs", "TEST", "CON.", "ITC", "P(T>C)"], [" Assignments", "167,859", "167,425", "", ""], ["Advance upgrade 31D", "0.09%", "0.10%", "90.13", "18%"], ["Plus upgrade 31D", "0.34%", "0.34%", "99.04", "44%"], ["KPIs", "TEST", "CON.", "ITC", "P(T>C)"], [" Assignments", "183,663", "184,658", "", ""], ["Advance upgrade 31D", "0.05%", "0.05%", "93.05", "31%"], ["Plus upgrade 31D", "0.17%", "0.14%", "125.58", "99%"], ["Essential upgrade 31D", "0.26%", "0.27%", "96.76", "31%"], ["", "AURA test", "", ""], ["BI test", "control", "treatment", "ITC"], ["control", "0.13%", "0.14%", ""], ["treatment", "0.13%", "0.16%", "122.34"], ["access point name", "offer_viewed", "offer_clicked", "ctr"], ["QBO - Modal Interrupters", "210640", "4230", "2.01%"], ["Discovery Hub - Hellobox", "385625", "573", "0.15%"], ["SBSEG QBO Hellobox AppStandardreports", "42944", "105", "0.24%"], ["Dashboard - Tips", "16980", "48", "0.28%"], ["Sales - Hellobox", "27512", "42", "0.15%"], ["Chart of Accounts - Hellobox", "55357", "35", "0.06%"], ["Email", "Sends", "Open", "Clicks", "Open rate", "Click rate"], ["ELM8533-OM-US-QBOAV-NA-MULTAV-USLL-PROMO-NA-EQ-BINovemberReportsUpdateQBOAdv_001", "257243", "70069", "704", "27.24%", "0.27%"], ["IPD", "Offer Viewed", "Offer Clicked", "CTR", "Benchmark", "ITB"], ["ELM8533", "360257", "4484", "1.24%", "0.84%", "148"], ["HIGHLIGHTS", "", "LOWLIGHTS"], ["Strong engagement with BI Reporting surfaces: IPD drove high engagement with an overall CTR of 1.24%, including 1.48 ITB CTR and ~2% CTR on the modal interrupter, indicating strong interest in reporting-related value.\nPlus customers exposed to BI Reporting showed a significant uplift in Advance upgrades (ITC ~107), validating BI Reporting as an effective upgrade lever for this segment.\nBI Reporting exposure led to a meaningful lift in Simple Start → Plus upgrades", "", "Despite strong CTRs, overall Advance upgrade conversion remained low, particularly among non-Plus segments.\nBoth Essential → Advance and Essential → Plus upgrades trended flat to negative, indicating BI Reporting alone does not sufficiently motivate Essentials customers to upgrade. \nSimple Start → Advance and Simple Start → Essential upgrades showed no positive movement, reinforcing that BI Reporting may be too advanced for direct conversion at this stage.\n~75% of the targeted audience was Essential and Simple Start, while only 25% were Plus, limiting overall Advance lift despite strong Plus performance"], ["NEXT STEPS & IMPLICATIONS", "", ""], ["Roll out BI Reporting upgrade messaging broadly to all Plus customers.\nUse move value driven messaging and insights along with BI for Essential and SS customers.\nLeverage more prominent access points like Bottom Drawer along with others to capture high intent customers \nRevalidate targeting attribute used to target high propensity customers", "", ""]] | V12: Alt Date (slide 22): 11/17/25 | Alt Product (slide 22): QuickBooks | Alt GET (slide 23): essentials customers with more value driven messaging along with BI | Alt TO (slide 23): mers are the primary drivers of Advance upgrades when exposed to the BI Reportin | Alt TO (slide 24): 0.16% (ITC ~122) | Alt Name (slide 25): OM-US-QBOAV-NA-MULTAV-USLL-PROMO-NA-EQ-BINovemberReportsUpdateQBOAdv_001 | 25724 | Alt BY (slide 25): Modal interrupters with 2% CTR | Alt GET (slide 26): ed audience was Essential and Simple Start, while only 25% were Plus, limiting o | Alt TO (slide 26): mers exposed to BI Reporting showed a significant uplift in Advance upgrades (IT | Date: CSV-Current | W12: 21-26 | X12: Copy of FY'26_ CRM Analytics Monthly Experiment Review AC.pptx | Y12: ✅ ELM Roadmap | ✅ Results Report | Z12: high propensity for QBO Adv clients | AA12: high-propensity QBO customers drove positive lift in overall upgrade (102 ITC). Advance upgrades is flat (101 ITC) and Plus is positive (108 ITC); Plus→Advance upgrade shows a statistically significant positive lift (ITC 108) (~600 annual plus to advance upgrades) | AB12: Promoting the new reporting functionality from BI November release
A13: ELM-4276 | B13: Peak Season Campaign to align with Q2 tax season | C13: 12-21-2022 | D13: GET: QBO customers TO: customers through email and IPD channels and testing the impact of emotional vs. questions vs. generic subject line in a 3 email sequence. BY: delivering compelling messagings to make them feel confident about purchasing QBL to deliver accurate books. | E13: IF: Sending Question/Emotional Messages could better echo customers' need and thus improve email engagement and QBL conversion rate. (Inferred for review) | F13: • | We reached 260k customers to QBL prospects thru 2023 peak season campaign, and email series touched 795 GNS units Question messages have the highest engagement as well as conversion rate First email was sent out right before Christmas and thus had the lowest CTR Overall, subject line with tax season messages generates the higher engagement data More direct messaging "Take a deep breath and let us do your books for you" have the highest 1.79% CTR Shell Notification is the access point that has the highest engagement data Because of its retargeting nature, the third IPD has the highest engagement data | J13: QBO Live | K13: IPD; Email | L13: Positive | M13: in an easy to understand sentence. All projects should be one of the colored pill options below, and align to this logic. | U13: [["HYPO\n-THESIS", "Sending Question/Emotional Messages could better echo customers' need and thus improve email engagement and QBL conversion rate.", "", "", "", ""], ["LEARNINGS", "We reached 260k customers to QBL prospects thru 2023 peak season campaign, and email series touched 795 GNS units \nQuestion messages have the highest engagement as well as conversion rate", "", "", "", ""], ["KPIs", "Generic (Control)", "Question", "Emotional", "ITC/delta (Question)", "ITC/delta (Control)"], ["Email Send Count", "87289", "88017", "87965", "", ""], ["Email Open Rate (Aggregate)", "51.18%", "51.91%", "52.00%", "101%", "102%"], ["Email CTR (Aggregate)", "2.57%", "2.74%", "3.19%", "107%", "124%"], ["QBL GNS (email touched)", "252", "289", "254", "37", "2"], ["QBL GNS (email touched)", "0.29%", "0.33%", "0.29%", "114%", "100%"], ["Sequence", "Assignment", "Subject Line", "Send", "Open", "Click", "Open Rate", "Click Rate"], ["first", "generic", "Leave your books to a QuickBooks Live Bookkeeper", "87331", "29912", "586", "34.25%", "0.67%"], ["second", "generic", "Tax time stressing you out? We can help with that.", "86310", "29680", "963", "34.39%", "1.12%"], ["third", "generic", "Take the stress out of tax season with Live Bookkeeping", "85871", "28308", "882", "32.97%", "1.03%"], ["first", "question", "Want someone to take bookkeeping off your plate?", "85731", "29948", "773", "34.93%", "0.90%"], ["second", "question", "Not sure you are ready for tax time? Not to worry.", "84809", "30247", "1034", "35.66%", "1.22%"], ["third", "question", "Do the words \"tax time\" make you uncomfortable?", "84362", "27864", "720", "33.03%", "0.85%"], ["first", "emotional", "Feel reassured your books are done right", "86659", "29902", "538", "34.51%", "0.62%"], ["second", "emotional", "Take a deep breath and let us do your books for you", "85761", "30425", "1536", "35.48%", "1.79%"], ["third", "emotional", "Imagine what is possible with a Live Bookkeeper in your corner", "85313", "28143", "912", "32.99%", "1.07%"], ["CHANNEL ENGAGEMENT", "", "", "", "", "", "", "", "", ""], ["Three Email Sequence", "", "", "", "", "", "", "", "", ""], ["COHORT", "First Email", "", "", "Second Email", "", "", "Third Email", "", ""], ["", "Sent", "Open Rate", "Click Rate", "Sent", "Open Rate", "Click Rate", "Sent", "Open Rate", "Click Rate"], ["generic", "86659", "34.25%", "0.67%", "85761", "34.39%", "1.12%", "85313", "32.97%", "1.03%"], ["question", "87331", "34.93%", "0.90%", "86310", "35.66%", "1.22%", "85871", "33.03%", "0.85%"], ["emotional", "85731", "34.51%", "0.62%", "84809", "35.48%", "1.79%", "84362", "32.99%", "1.07%"], ["CHANNEL ENGAGEMENT", "", "", "", "", "", "", "", "", ""], ["IPD Sequence", "", "", "", "", "", "", "", "", ""], ["COHORT", "First IPD", "", "", "Second IPD", "", "", "Third IPD", "", ""], ["", "View", "Click", "CTR", "View", "Click", "CTR", "View", "Click", "CTR"], ["Banking - Hellobox", "95241", "781", "0.82%", "70550", "615", "0.87%", "1428", "54", "3.78%"], ["Payments Deposit - Hellobox", "36745", "233", "0.63%", "17703", "78", "0.44%", "226", "7", "3.10%"], ["Shell - Notification", "54745", "905", "1.65%", "28904", "215", "0.74%", "795", "49", "6.16%"], ["HIGHLIGHTS", "", "LOWLIGHTS"], [""Question" messages have the highest engagement as well as conversion rate. 114 ITC\nSubject lines including 'tax' keywords have overall higher engagement data", "", "First emails was sent out right before Christmas due to delayed content creation"], ["", "", ""], ["NEXT STEPS & IMPLICATIONS", "", ""], ["'Tax Season' keywords should be included in future tax season campaigns\nLower ITPY in terms of QBL GNS mainly contributed to cleanup price changes \nCombining Question & Emotional messaging to next campaigns \nNext step", "", ""]] | V13: Alt Product (slide 254): QuickBooks | Alt TO (slide 254): a QuickBooks Live Bookkeeper | 87331 | 29912 | 586 | 34.25% | 0.67% | Alt Product (slide 255): Payments | Alt GET (slide 255): ing nature, the third IPD has the highest engagement data | Alt TO (slide 256): understand sentence. All projects should be one of the colored pill options bel | Alt Date (slide 257): 11/22/2022 | Date: CSV-Current | W13: 253-257 | X13: Copy of Copy of CRM Analytics 2023 AC.pptx | Y13: ✅ ELM Roadmap | ⚠️ Results Report | Z13: QBO customers | AA13: customers through email and IPD channels and testing the impact of emotional vs. questions vs. generic subject line in a 3 email sequence. | AB13: delivering compelling messagings to make them feel confident about purchasing QBL to deliver accurate books.
A14: ELM-5691 | B14: Update to IPDs for QBLive Free Guided Setup -- QBO Dashboard | C14: 06-26-2023 | D14: GET: QuickBooks Buy Now NTTF Customers TO: Customers BY: making them feel supported with expert guidance to get started in QuickBooks Online | E14: IF: If we show an easily discoverable access point (feature card which is embedded in the setup checklist) to 100% of eligible QBO customers THEN: We will be able to driven 30D guided setup appointment completion rates compared to the current/control experience, where we have both setup checklist and bottom drawer access points. | F14: • Both GSU scheduling and completing rate is performing worse in the treatment group than the control group QBL GSU Feature Card Test GSU has been stable with ~8.5% scheduling rate which is soft to the targeted scheduling rate at 15%. GTM Team wants to test if scheduling rate would go higher if we could remind them about this offer at the top of setup checklist, so every new customers would know about the offering. GSU scheduling & completing rate all trending negative ITCs Feature card has a slight higher CTR, 4.9% vs 4.2% for setup checklist However, we see a lower schedule rate once the customers land on the scheduling page from feature card 60% vs 76% from setup checklist, indicating lower intent clicks from feature card Setup checklist + bottom drawer perform better than feature card alone with 76 ITC Even tho only half of the customers see bottom drawer IPD due to many competing offers from the same access points, it is still proven to be high performing Signups originating from both accountant and IPD related pages seem to be trending lower than control Breaking overall cohort into existing and new customers who viewed the LP post experiment launch, both cohorts were underperforming to control with similar ITC's | G14: It proves that the current ELM strategy is working well, and additional impressions may not proportionally translates to more schedulings • NEXT STEPS & IMPLICATIONS • Next Step for this experiment Rolled back to 100% control experience - done Recommendation for GSU Optimize placement where we market GSU based on new customers' traffic Optimize placement to where GSU could provide value, based on research Update content to contextually relevant messaging • Current Top Performing AP June Scheduling • QBO Dashboard - Bottom Drawer 467 • Banking - Hellobox 127 • SBSEG QBO FC AppHomepage 37 • Customers - Hellobox 21 • Shell - Notification 8 • Expenses - Hellobox 8 • Payments Deposit - Hellobox 8 • Vendors - Hellobox 5 • KPIs (5/24 - 7/22) TEST • Assignments 24.5K • Payroll Signup Rate 9.0% • Payroll Trial Signup Rate 1.6% • Payroll Buy Now Signup Rate 7.3% • Payroll GNS Rate 7.5% • Page Load Time 1.8K µsec • Both Payroll signup and GNS rates are trending stat sig negative in treatment cell and below our estimated threshold of 95 ITC Although samples for Trial signups are low, softness seems to be stemming from Buy Now signup flow with Trial signups at 100 ITC Operational metrics seem to be performing at par with control cell • Overall • COHORT SIZE % Payroll Signups • % ITC • Test 24.5K 50 9.0 93 • Control 24.3K 50 9.6 • Test 8.7K 50 9.4 94 • Control 8.6K 50 9.9 • Test 15.7K 50 8.8 93 • Control 15.7K 50 9.4 • Hypothesis • Test accounts not excluded from test reads • Of the customers generated in the abandoners list, control cell is converting them at a higher rate vs treatment • Leads from chat being unavailable in treatment cell is leading to lower conversions • Just a particular segment of customers underperformance is causing our signup trends to look soft • Treatment cell was probably showing incorrect pricing to some customers during promo period • RECOMMENDATIONS & IMPLICATIONS | H14: Overall treatment experience performs worse than the control experience at 76 ITC • Buy Now Customer Top Traffic AP 30d total Traffic • QBO Dashboard - Bottom Drawer • Banking - Hellobox • Reports - Hellobox • Customers - Hellobox • QBO - Modal Interrupters • Discovery Hub - Hellobox 90265 • SBSEG QBO FC AppHomepage 73613 • Invoice - Text Image 62595 • Expenses - Hellobox 50482 • Hypothesis • Migrating hard coded IPDs to Campaign Manager will improve conversion rate in long run due to better targeting and messaging achieved through Campaign Manager • CON. Δ ITC • 24.3 - • 9.6% (0.7%) pts 93 • 1.6% - 100 • 7.9% (0.6%) pts 92 • 8.1% (0.6%) pts- 92 • 2.3K µsec 500 µsec - • Payroll IPD Signups Payroll Accountant Signups Payroll GNS • % ITC % ITC % ITC • 5.7 91 2.6 95 7.5 92 • 6.3 2.8 8.1 • 6.6 92 2.2 95 7.0 91 • 7.1 2.3 7.7 • 5.3 90 2.9 94 7.8 93 • 5.9 3.0 8.4 • Proven/Disproven Supporting data points so far • No test accounts were found to be part of the test reads • Although control cell had higher number of converts vs treatment cell abandoners, the difference was marginal at ~0.1% pts • Leads from chat have been close to 0 since beginning of May as chat was discontinued across both control/treatment cell • Payroll Buy Now signups seem to be underperforming control • TBD Signup ITC trends started to improve once July 4th promo ended on 7/10 | I14: Current Top Performing AP June Scheduling Buy Now Customer Top Traffic AP 30d total Traffic QBO Dashboard - Bottom Drawer 467 QBO Dashboard - Bottom Drawer Banking - Hellobox 127 Banking - Hellobox SBSEG QBO FC AppHomepage 37 Reports - Hellobox Customers - Hellobox 21 Customers - Hellobox Shell - Notification 8 QBO - Modal Interrupters Expenses - Hellobox 8 Discovery Hub - Hellobox 90265 Payments Deposit - Hellobox 8 SBSEG QBO FC AppHomepage 73613 Vendors - Hellobox 5 Invoice - Text Image 62595 Expenses - Hellobox 50482 Hypothesis Migrating hard coded IPDs to Campaign Manager will improve conversion rate in long run due to better targeting and messaging achieved through Campaign Manager KPIs (5/24 - 7/22) TEST CON. Δ ITC Assignments 24.5K 24.3 - Payroll Signup Rate 9.0% 9.6% (0.7%) pts 93 Payroll Trial Signup Rate 1.6% 1.6% - 100 Payroll Buy Now Signup Rate 7.3% 7.9% (0.6%) pts 92 Payroll GNS Rate 7.5% 8.1% (0.6%) pts- 92 Page Load Time 1.8K µsec 2.3K µsec 500 µsec - Both Payroll signup and GNS rates are trending stat sig negative in treatment cell and below our estimated threshold of 95 ITC Although samples for Trial signups are low, softness seems to be stemming from Buy Now signup flow with Trial signups at 100 ITC Operational metrics seem to be performing at par with control cell Overall COHORT SIZE % Payroll Signups Payroll IPD Signups Payroll Accountant Signups Payroll GNS % ITC % ITC % ITC % ITC Test 24.5K 50 9.0 93 5.7 91 2.6 95 7.5 92 Control 24.3K 50 9.6 6.3 2.8 8.1 COHORT SIZE % Payroll Signups Payroll IPD Signups Payroll Accountant Signups Payroll GNS % ITC % ITC % ITC % ITC Test 8.7K 50 9.4 94 6.6 92 2.2 95 7.0 91 Control 8.6K 50 9.9 7.1 2.3 7.7 COHORT SIZE % Payroll Signups Payroll IPD Signups Payroll Accountant Signups Payroll GNS % ITC % ITC % ITC % ITC Test 15.7K 50 8.8 93 5.3 90 2.9 94 7.8 93 Control 15.7K 50 9.4 5.9 3.0 8.4 Hypothesis Proven/Disproven Supporting data points so far Test accounts not excluded from test reads No test accounts were found to be part of the test reads Of the customers generated in the abandoners list, control cell is converting them at a higher rate vs treatment Although control cell had higher number of converts vs treatment cell abandoners, the difference was marginal at ~0.1% pts Leads from chat being unavailable in treatment cell is leading to lower conversions Leads from chat have been close to 0 since beginning of May as chat was discontinued across both control/treatment cell Just a particular segment of customers underperformance is causing our signup trends to look soft Payroll Buy Now signups seem to be underperforming control Treatment cell was probably showing incorrect pricing to some customers during promo period TBD Signup ITC trends started to improve once July 4th promo ended on 7/10 | J14: QBO Live | K14: IPD | L14: Not found (Inferred for review) | M14: Primary metric on GSU scheduling rate is trending 76 ITC, resulting in stats sig negative result. • Metrics | Control | Treatment | Delta | ITC Assignment | 9537 | 9534 GSU Appt Scheduling | 674 | 515 | -159 GSU Appt Scheduling Rate | 7.07% | 5.40% | 76 GSU Appt Complete | 517 | 388 | -129 GSU Appt Complete | 5.42% | 4.07% | 75 in an easy to understand sentence. All projects should be one of the colored pill options below, and align to this logic. | U14: [["KPIs", "Control", "TEST", "ITC"], ["Assignment", "9537", "9534", ""], ["GSU scheduling rate", "7.07%", "5.40%", "76"], ["GSU completion rate", "5.42%", "4.07%", "75"], ["Business Impact", "", "", "", ""], ["Metrics", "Control", "Treatment", "Delta", "ITC"], ["Assignment", "9537", "9534", "", ""], ["GSU Appt Scheduling", "674", "515", "-159", ""], ["GSU Appt Scheduling Rate", "7.07%", "5.40%", "", "76"], ["GSU Appt Complete", "517", "388", "-129", ""], ["GSU Appt Complete", "5.42%", "4.07%", "", "75"], ["Channel Engagement", "", ""], ["Access Points", "Control", "Treatment"], ["Feature Card Imp", "", "8826"], ["Feature Card CTR", "", "4.90%"], ["GSU in Setup Checklist", "8877", ""], ["Setup Checklist CTR", "4.20%", ""], ["Bottom Drawer Imp", "4959", ""], ["Bottom Drawer CTR", "4.70%", ""], ["HIGHLIGHTS", "", "LOWLIGHTS"], ["It proves that the current ELM strategy is working well, and additional impressions may not proportionally translates to more schedulings", "", "Overall treatment experience performs worse than the control experience at 76 ITC"], ["NEXT STEPS & IMPLICATIONS", "", ""], ["Next Step for this experiment \nRolled back to 100% control experience - done\nRecommendation for GSU \nOptimize placement where we market GSU based on new customers' traffic\nOptimize placement to where GSU could provide value, based on research\nUpdate content to contextually relevant messaging", "", ""], ["Current Top Performing AP", "June Scheduling", "", "Buy Now Customer Top Traffic AP", "30d total Traffic"], ["QBO Dashboard - Bottom Drawer", "467", "", "QBO Dashboard - Bottom Drawer", "211948"], ["Banking - Hellobox", "127", "", "Banking - Hellobox", "145294"], ["SBSEG QBO FC AppHomepage", "37", "", "Reports - Hellobox", "138221"], ["Customers - Hellobox", "21", "", "Customers - Hellobox", "132139"], ["Shell - Notification", "8", "", "QBO - Modal Interrupters", "101801"], ["Expenses - Hellobox", "8", "", "Discovery Hub - Hellobox", "90265"], ["Payments Deposit - Hellobox", "8", "", "SBSEG QBO FC AppHomepage", "73613"], ["Vendors - Hellobox", "5", "", "Invoice - Text Link Image", "62595"], ["", "", "", "Expenses - Hellobox", "50482"], ["Hypothesis"], ["Migrating hard coded IPDs to Campaign Manager will improve conversion rate in long run due to better targeting and messaging achieved through Campaign Manager"], ["KPIs\n(5/24 - 7/22)", "TEST", "CON.", "Δ", "ITC"], ["Assignments", "24.5K", "24.3", "-", ""], ["Payroll Signup Rate", "9.0%", "9.6%", "(0.7%) pts", "93"], ["Payroll Trial Signup Rate", "1.6%", "1.6%", "-", "100"], ["Payroll Buy Now Signup Rate", "7.3%", "7.9%", "(0.6%) pts", "92"], ["Payroll GNS Rate", "7.5%", "8.1%", "(0.6%) pts-", "92"], ["Page Load Time", "1.8K µsec", "2.3K µsec", "500 µsec", "-"], ["Both Payroll signup and GNS rates are trending stat sig negative in treatment cell and below our estimated threshold of 95 ITC\nAlthough samples for Trial signups are low, softness seems to be stemming from Buy Now signup flow with Trial signups at 100 ITC\nOperational metrics seem to be performing at par with control cell", "", "", "", ""], ["Overall", "", "", "", "", "", "", "", "", "", ""], ["COHORT", "SIZE", "%", "Payroll Signups", "", "Payroll IPD Signups", "", "Payroll Accountant Signups", "", "Payroll GNS", ""], ["", "", "", "%", "ITC", "%", "ITC", "%", "ITC", "%", "ITC"], ["Test", "24.5K", "50", "9.0", "93", "5.7", "91", "2.6", "95", "7.5", "92"], ["Control", "24.3K", "50", "9.6", "", "6.3", "", "2.8", "", "8.1", ""], ["COHORT", "SIZE", "%", "Payroll Signups", "", "Payroll IPD Signups", "", "Payroll Accountant Signups", "", "Payroll GNS", ""], ["", "", "", "%", "ITC", "%", "ITC", "%", "ITC", "%", "ITC"], ["Test", "8.7K", "50", "9.4", "94", "6.6", "92", "2.2", "95", "7.0", "91"], ["Control", "8.6K", "50", "9.9", "", "7.1", "", "2.3", "", "7.7", ""], ["COHORT", "SIZE", "%", "Payroll Signups", "", "Payroll IPD Signups", "", "Payroll Accountant Signups", "", "Payroll GNS", ""], ["", "", "", "%", "ITC", "%", "ITC", "%", "ITC", "%", "ITC"], ["Test", "15.7K", "50", "8.8", "93", "5.3", "90", "2.9", "94", "7.8", "93"], ["Control", "15.7K", "50", "9.4", "", "5.9", "", "3.0", "", "8.4", ""], ["Hypothesis", "Proven/Disproven", "Supporting data points so far"], ["Test accounts not excluded from test reads", "", "No test accounts were found to be part of the test reads"], ["Of the customers generated in the abandoners list, control cell is converting them at a higher rate vs treatment", "", "Although control cell had higher number of converts vs treatment cell abandoners, the difference was marginal at ~0.1% pts"], ["Leads from chat being unavailable in treatment cell is leading to lower conversions", "", "Leads from chat have been close to 0 since beginning of May as chat was discontinued across both control/treatment cell"], ["Just a particular segment of customers underperformance is causing our signup trends to look soft", "", "Payroll Buy Now signups seem to be underperforming control"], ["Treatment cell was probably showing incorrect pricing to some customers during promo period", "TBD", "Signup ITC trends started to improve once July 4th promo ended on 7/10"], ["RECOMMENDATIONS & IMPLICATIONS", "", ""]] | V14: Alt Date (slide 46): 07-18-23 | Alt Product (slide 46): QuickBooks Online | Alt TO (slide 47): m Drawer IPDs thru customer lifecycle | Alt TO (slide 48): mers land on the scheduling page from feature card 60% vs 76% from setup checkli | Alt Name (slide 49): has negative result | Alt GET (slide 49): to manually send the wrap report email summary to everyone who was interested in | Alt TO (slide 49): more schedulings | Overall treatment experience performs worse than the control | Alt Product (slide 50): Payments | Alt TO (slide 50): p Performing AP | June Scheduling | Buy Now Customer Top Traffic AP | 30d total | Alt Name (slide 51): for the bottom drawers | Alt GET (slide 51): ed placements for GSU to improve engagement | Alt TO (slide 51): contextual messaging | Alt TO (slide 52): Free Guided Setup | Alt Product (slide 53): Payroll | Alt Hypothesis (slide 54): Migrating hard coded IPDs to Campaign Manager will improve conversion rate in l | Alt Product (slide 54): Payroll | Alt GET (slide 54): ing and messaging achieved through Campaign Manager | Alt TO (slide 54): Campaign Manager will improve conversion rate in long run due to better targetin | Alt Product (slide 55): Payroll | Alt TO (slide 55): be trending lower than control | Alt Hypothesis (slide 56): on performance Hypothesis | Proven/Disproven | Supporting data points so far Tes | Alt Product (slide 56): Payroll | Alt GET (slide 56): ting generated in treatment cell | Customers from both test and control cell wer | Alt TO (slide 56): be part of the test reads | Alt Hypothesis (slide 58): about low performance due to promo season with PD to rule it out. Implement trac | Alt Product (slide 58): Payroll | Alt TO (slide 58): hypothesis about low performance due to promo season with PD to rule it out. Imp | TO repaired: truncated 'customers' prefix restored | Date: CSV-Current | W14: 45-58 | X14: Copy of Copy of CRM Analytics 2023 AC.pptx | Y14: ✅ ELM Roadmap | ⚠️ Results Report | Z14: QuickBooks Buy Now NTTF Customers | AA14: Customers | AB14: making them feel supported with expert guidance to get started in QuickBooks Online
A15: ELM-5896 | B15: [SCU] Standalone Cleanup SKU Launch | C15: 11-20-2024 | D15: GET: QBO customers TO: We want to expand the customers we serve and grow QBL revenue by creating a standalone Cleanup Bookkeeping offer. The new standalone Cleanup offer will be available as an a la carte option for any eligible QBO subscriber or may be purchased as an optional add-on to DIFM, DIWM, or Biz Tax. (Inferred for review) BY: Presenting cleanup as an add-on through journey from QBO customer. | E15: IF: we alert customers to the SCU product through marketing and on the zero state pages THEN: total live attach will increase -- Increasing annualized | F15: • Aggressive placement of DIFM, DIWM & SCU on top resulted in a drop in DIWM signups, with Trial to GNS at 59% for the agg. group compared to 70% for passive group for 25% of baked units. | G15: • NEXT STEPS & IMPLICATIONS | I15: DIWM signups, with Trial to GNS at 59% for the agg. group compared to 70% for passive group for 25% of baked units. B• The goodness observed in SCU & DIFM was not enough to have lift in 1yr estimated QBL revenue Business Impact: STILL BAKING Results are still baking ELM- Deck KPIs Aggressive Passive Δ ITC Assignments 30753 30486 31D DIWM SU 2122 2534 -412 84 31D DIWM GNS (est.) 1,619 1,933 -314 84 31D DIFM GNS 82 56 26 146 31D SCU GNS 131 91 40 144 1 Yr QBL Rev (est.) 766k 817k - 52 K 94 B INCONCLUSIVE TRENDING POSITIVE RESULTS Results: POSITIVE NEGATIVE BIZ IMPACT BIZ IMPACT LAT & ROLL OUT RESULTS | J15: QBO Live | K15: IPD; Email; Landing Page | L15: Trending Positive | Results: 5.1 MEASURE: Complete | M15: The goodness observed in SCU & DIFM was not enough to have lift in 1yr estimated QBL revenue [Results Report] ITC-1: 99 | N15: https://docs.google.com/presentation/d/1r54YHWljGw7TiyIvxfXXzFFuvxpZ1lkeQ8qipaBHKAU/edit#slide=id.g2efff53d832_0_813 | O15: GNS/GNA | P15: 99 | U15: [["WRAP REPORT", "", ""], ["Link", ""], ["", "Link"], ["", "Link"], ["", "Template v5.0 Updated Aug 2024\nGLOBAL BGUlSoIbNaEl SBSus SinOeLsUs SToIOluNtioSn Gs RGOroUuPp", "", ""], ["", "", "GLOBAL BGUlSoIbNaEl SBSus SinOeLsUs SToIOluNtioSn Gs RGOroUuPp", ""], ["", "", "EXPERIMENT RESULTS", "", "", "", ""], ["", "", "", "", "", "", "Learnings & Implications\nA● Aggressive placement of DIFM, DIWM & SCU on top resulted in a drop in\nDIWM signups, with Trial to GNS at 59% for the agg. group compared to 70%\nfor passive group for 25% of baked units.\nB● The goodness observed in SCU & DIFM was not enough to have lift in 1yr\nestimated QBL revenue"], ["", "", "", "", "", "", "DIWM signups, with Trial to GNS at 59% for the agg. group compared to 70%\nfor passive group for 25% of baked units.\nB● The goodness observed in SCU & DIFM was not enough to have lift in 1yr\nestimated QBL revenue"], ["", "Business Impact: STILL BAKING\nResults are still baking", "", "", "", "", ""], ["ELM-", "", "Deck"], ["", "KPIs", "Aggressive", "Passive", "", "Δ", "ITC"], ["", "Assignments", "30753", "30486", "", "", ""], ["", "31D DIWM SU", "2122", "2534", "", "-412", "84"], ["", "31D DIWM GNS (est.)", "1,619", "1,933", "", "-314", "84"], ["", "31D DIFM GNS", "82", "56", "", "26", "146"], ["", "31D SCU GNS", "131", "91", "", "40", "144"], ["", "1 Yr QBL Rev (est.)", "766k", "817k", "", "- 52 K", "94 B"], ["INCONCLUSIVE\nTRENDING POSITIVE"], ["RESULTS"], ["Results: POSITIVE NEGATIVE\nBIZ IMPACT BIZ IMPACT", "", ""], ["", "FLAT &\nROLL OUT", ""], ["RESULTS"], ["HIGHLIGHTS", "", "LOWLIGHTS"], ["NEXT STEPS & IMPLICATIONS", "", ""]] | V15: Campaign re-appears on slide 244 (gap from slide 239) | Alt Date (slide 244): 24-11-20 | Alt TO (slide 244): 25-01-21 | Alt Campaign Name (slide 246): SCU | Alt GET (slide 246): to manually send the wrap | Alt TO (slide 246): have flat impact on 1yr projected revenue. But the | Date source: CSV - Current Target Launch Date | Name source: CSV | Business Impact updated from Results Report | Status enriched from Results Report | TO replaced with CSV Project Description (was: garbled_text) | W15: 239-246 | X15: Copy of FY'25_ CRM Analytics Monthly Experiment_Notebook_AC.pdf | Y15: ✅ ELM Roadmap | ✅ Results Report | Z15: QBO customers | AA15: We want to expand the customers we serve and grow QBL revenue by creating a standalone Cleanup Bookkeeping offer. The new standalone Cleanup offer will be available as an a la carte option for any eligible QBO subscriber or may be purchased as an optional add-on to DIFM, DIWM, or Biz Tax. (Inferred for review) | AB15: Presenting cleanup as an add-on through journey from QBO customer.
A16: ELM-6336 | B16: FY'24 FEB GAP CLOSER: Replace DIFM with DIWM - [DIWM] 30+ Existing Customers Promotion | C16: 05-16-2024 | D16: GET: 30d+ QuickBooks customers TO: Customers BY: Messaging the benefits of DIWM paired with a CCR pricing offer or CCR | E16: IF: If we communicate the benefits of DIWM BK in combination with a "50% off for 3 months" promotion or "1 month free trial" THEN: We will increase DIWM attach | F16: • Trial group exceeds discount offer with +75 GNS units. • Free trial LP 50% off LP Despite having a 96 ITC 120D retention rate for discount Vs trial groups, Imp. • Clicks CTR Δ ITB • IPDs with offers have higher CTR Vs control mainly due to 67,273 368 0.55% high visibility access points Treatment - Discount A offer 230,956 9,531 4.13% 132 • The trial to GNS conversion is observed to be ~69% on Treatment - Free trial 230,601 9,378 4.07% 130 par with assumptions based on early data that facilitated IPD Benchmark ** 3.12% roll out treatment_group Channel & Price diwm_signups diwm_gns Control Sales Channel - 50% off of 3 Months 350 350 Control In Product - $50 / Month 130 130 Control Others 15 11 Treatment - Discount offer Sales Channel - 50% off of 3 Months 320 319 Treatment - Discount offer In Product -50% off of 3 Months 192 192 Treatment - Discount offer Others 18 17 Treatment - Free trial In Product - 1 Month Free Trial 381 261 B Treatment - Free trial Sales Channel - 50% off of 3 Months 317 315 Treatment - Free trial Others 33 27 treatment_group accesspointname ipd_viewed ipd_clicked CTR Insights Control Chart of Accounts - Hellobox 28,934 30 0.10% Control Shell - Notification 21,128 199 0.94% • High CTR is primarily due to use of Shell Banner; other Control Banking - Hellobox 16,083 37 0.23% access points are consistent with Control group for Control Expenses - Hellobox 10,820 19 0.18% Control Income Overview - Tips 9,238 84 0.91% both treatments Control Shell - Banner 31 0 0.00% Control Vendors - Hellobox 4 0 0.00% Control Payments Deposit - Hellobox 1 0 0.00% Treatment - Discount offer Shell - Banner 220,311 9,299 A 4.22% Treatment - Discount offer Chart of Accounts - Hellobox 36,549 19 0.05% Treatment - Discount offer Banking - Hellobox 29,097 48 0.16% Treatment - Discount offer Vendors - Hellobox 27,096 21 0.08% Treatment - Discount offer Shell - Notification 22,606 165 0.73% Treatment - Discount offer Expenses - Hellobox 12,940 6 0.05% Treatment - Discount offer Payments Deposit - Hellobox 5,642 3 0.05% Treatment - Discount offer Income Overview - Tips 218 2 0.92% Treatment - Free trial Shell - Banner 219,935 9,132 A 4.15% Treatment - Free trial Chart of Accounts - Hellobox 37,124 17 0.05% Treatment - Free trial Banking - Hellobox 29,297 45 0.15% Treatment - Free trial Vendors - Hellobox 27,012 11 0.04% Treatment - Free trial Shell - Notification 22,737 182 0.80% Treatment - Free trial Expenses - Hellobox 13,194 9 0.07% Treatment - Free trial Payments Deposit - Hellobox 5,733 2 0.03% Treatment - Free trial Income Overview - Tips 209 2 0.96% | J16: QBO Live | K16: IPD | L16: Trending Positive | Results: 5.1 MEASURE: Complete | M16: revenue is still expected to increase due to pricing and incremental units. Trial offer delivered sig. higher DIWM GNS Units (123 ITC , + 112 Units); Trial group has seen slightly higher activation Vs Control at 102 ITC and Roll out estimate : + 900 incremental DIWM GNS higher than treatment group at 107 ITC [Results Report] | ITC-1: 111 | N16: https://docs.google.com/presentation/d/1aCL7o46DdJstbL_MPzTFz2dkWq5n_buLUc5Zr9h4T94/ | O16: GNS/GNA | P16: 111 | U16: [["EXPERIMENT RESULTS\n30+D QBO Customers\nPromotion / Free Trial\nFree\nFree trial LP 50% off LP\nBusiness Impact: POSITIVE\nBIZ IMPACT\nTrial offer delivered sig. higher DIWM GNS Units (12\nRoll out estimate : + 900 incremental DIWM GNS", "", "EXPERIMENT RESULTS", "", "", "", "", "", "", "", "", "", "", "", "", "", "", "", "", "", ""], ["", "", "", "", "", "", "", "", "", "", "", "", "Objective\nGet 30d+ QuickBooks customers\nTo Attach Live Assisted Bookkeeping\nBy Messaging the benefits of DIWM paired with a CCR pricing offer or CCR\nfree trial for 1 month\nHypothesis\nIf we communicate the benefits of DIWM BK in combination with a "50% off\nfor 3 months" promotion or "1 month free trial", we will increase DIWM attach\nResults", "", "", "", "", "", "", "", ""], ["", "", "", "", "", "", "", "", "", "", "offer\nTrial IPDs", "", "", "", "", "", "", "", "", "", ""], ["", "", "", "", "", "", "", "", "", "", "Trial IPDs", "", "", "", "", "", "", "", "", "", ""], ["", "", "", "", "", "", "", "", "Free", "Free", "Trial IPDs", "", "", "", "", "", "", "", "", "", ""], ["", "", "", "", "", "", "", "", "", "", "", "", "", "", "", "", "", "", "", "", ""], ["", "", "", "", "", "", "", "", "", "", "", "", "", "", "", "", "", "", "", "", ""], ["", "", "", "", "", "", "", "", "", "", "", "", "", "", "", "", "", "", "", "", ""], ["", "", "", "", "", "", "", "", "", "", "", "", "", "", "", "", "", "", "", "", ""], ["", "", "", "", "", "", "", "", "", "", "", "", "", "treatment_group", "", "Control", "50% offer", "Free trial", "Con Vs\nTrial", "50% Vs\nTrial", "ITC"], ["", "", "", "", "", "", "", "", "", "", "", "", "", "Assignments", "", "256,225", "255,882", "255,215", "", "", ""], ["", "", "", "", "", "", "", "", "", "", "", "", "", "", "", "", "", "", "", "", ""], ["", "", "", "", "", "", "", "", "", "", "", "", "", "Signups", "", "495", "530", "731 A", "", "", ""], ["", "", "", "", "", "", "", "", "", "", "", "", "", "", "", "", "", "", "", "A", ""], ["", "", "", "", "", "", "", "", "", "", "", "", "", "31d GNS", "", "491", "528", "603", "+ 112", "+ 75", "123"], ["", "", "", "", "", "", "", "", "", "", "", "", "", "7d Activation", "", "44%", "42%", "45%", "102 C", "107", ""], ["", "", "", "", "", "", "", "", "", "", "", "", "", "120 D Ret. (baked)", "", "69%", "76%", "72%", "B\n105", "96 B", ""], ["", "", "", "", "50% off LP", "", "", "", "", "", "", "", "", "", "● Despite having a 96 ITC 120D retention rate for discount Vs trial groups,\nB\nrevenue is still expected to increase due to pricing and incremental units.\n●C Trial group has seen slightly higher activation Vs Control at 102 ITC and", "", "", "", "", "", ""], ["", "Business Impact: POSITIVE\nBIZ IMPACT\nTrial offer delivered sig. higher DIWM GNS Units (12\nRoll out estimate : + 900 incremental DIWM GNS", "", "", "", "", "", "", "", "", "3 ITC , + 112 Un", "its);", "", "", "", "", "", "", "", "", ""], ["", "", "", "", "", "", "", "", "", "", "", "", "", "", "", "", "", "", "", "", ""], ["", "", "", "", "", "", "", "", "", "", "", "", "", "", "", "", "", "", "", "", ""], ["", "", "", "", "", "", "", "", "", "", "", "", "", "", "", "", "", "", "", "", ""], ["", ""], ["FLAT &\nROLL OUT", ""], ["", ""], [""], ["INSIGHTS"], ["Cohort", "IPD", "", "", "", ""], ["", "Imp.", "Clicks", "CTR", "Δ", "ITB"], ["Control", "67,273", "368", "0.55%", "", ""], ["Treatment - Discount\noffer", "230,956", "9,531", "4.13%", "A", "132"], ["Treatment - Free trial", "230,601", "9,378", "4.07%", "", "130"], ["", "", "", "", "", ""], ["", "IPD Benchmark **", "", "", "3.12%", ""], ["treatment_group", "Channel & Price", "diwm_signups", "", "diwm_gns", ""], ["Control", "Sales Channel - 50% off of 3 Months", "350", "", "350", ""], ["Control", "Others", "15", "", "11", ""], ["Treatment - Discount offer", "Sales Channel - 50% off of 3 Months", "320", "", "319", ""], ["Treatment - Discount offer", "Others", "18", "", "17", ""], ["Treatment - Free trial", "Sales Channel - 50% off of 3 Months", "317", "", "315", ""], ["Treatment - Free trial", "Others", "33", "", "27", ""], ["", "337"], ["Results: POSITIVE NEGATIVE\nBIZ IMPACT BIZ IMPACT", "", "", ""], ["", "", "FLAT &\nROLL OUT", ""], ["", "", "", ""], ["", "FLAT\nROI NEGATIVE", "", ""], [""], ["INSIGHTS"], ["treatment_group", "accesspointname", "ipd_viewed", "ipd_clicked", "", "CTR"], ["Control", "Chart of Accounts - Hellobox", "28,934", "30", "", "0.10%"], ["Control", "Shell - Notification", "21,128", "199", "", "0.94%"], ["Control", "Banking - Hellobox", "16,083", "37", "", "0.23%"], ["Control", "Expenses - Hellobox", "10,820", "19", "", "0.18%"], ["Control", "Income Overview - Tips", "9,238", "84", "", "0.91%"], ["Control", "Shell - Banner", "31", "0", "", "0.00%"], ["Control", "Vendors - Hellobox", "4", "0", "", "0.00%"], ["Control", "Payments Deposit - Hellobox", "1", "0", "", "0.00%"], ["Treatment - Discount offer", "Shell - Banner", "220,311", "9,299", "A", "4.22%"], ["Treatment - Discount offer", "Chart of Accounts - Hellobox", "36,549", "19", "", "0.05%"], ["Treatment - Discount offer", "Banking - Hellobox", "29,097", "48", "", "0.16%"], ["Treatment - Discount offer", "Vendors - Hellobox", "27,096", "21", "", "0.08%"], ["Treatment - Discount offer", "Shell - Notification", "22,606", "165", "", "0.73%"], ["Treatment - Discount offer", "Expenses - Hellobox", "12,940", "6", "", "0.05%"], ["Treatment - Discount offer", "Payments Deposit - Hellobox", "5,642", "3", "", "0.05%"], ["Treatment - Discount offer", "Income Overview - Tips", "218", "2", "", "0.92%"], ["Treatment - Free trial", "Shell - Banner", "219,935", "9,132", "A", "4.15%"], ["Treatment - Free trial", "Chart of Accounts - Hellobox", "37,124", "17", "", "0.05%"], ["Treatment - Free trial", "Banking - Hellobox", "29,297", "45", "", "0.15%"], ["Treatment - Free trial", "Vendors - Hellobox", "27,012", "11", "", "0.04%"], ["Treatment - Free trial", "Shell - Notification", "22,737", "182", "", "0.80%"], ["Treatment - Free trial", "Expenses - Hellobox", "13,194", "9", "", "0.07%"], ["Treatment - Free trial", "Payments Deposit - Hellobox", "5,733", "2", "", "0.03%"], ["Treatment - Free trial", "Income Overview - Tips", "209", "2", "", "0.96%"], ["", "338"], ["Results: POSITIVE NEGATIVE\nBIZ IMPACT BIZ IMPACT", "", ""], ["", "FLAT &\nROLL OUT", ""], ["", "", ""], [""], ["The campaign improved 31d QBO GNS, stays within estimated Trial to GNS Conversion rate range reported. Also\nhas goodness on ecosystem via QBO Saves."], ["HIGHLIGHTS", "", "LOWLIGHTS"], ["● High visibility IPDs combined with pricing offer / Trial\nCTAs have recorded 130 ITB CTR.\n● Observed Trial to GNS Conversion (69%) is within range\nestimated when Trial offer roll out", "", "● 120D Retention is expected to be flat between Trial Offer &\nDiscount offer its at 96 ITC.\n● For IPDs, other than Shell Banner the reach is lower for other\nIPDs"], ["", "", ""], ["NEXT STEPS & IMPLICATIONS", "", ""], ["● Audience: Expand free trial offerings to Accountant attached customers\n● IPD Setup: Reduce reliance on Shell banner and explore ideas to improve reach through other access points\n● Personalisation: Personalize messaging based on QBO journey using Insight Repository/Spokesmodel and segment targeting by QBO\ntenure.\n● Ecosystem Impact : Explore opportunities to increase QBO retention through DIWM Free Trial offer.\n● Retention:Consider implementing Annual pricing plan to improve 120-day DIWM retention\n● Retention: Monitor 120-day retention rate for Trial offer users and devise retention improvement strategies", "", ""], ["", "339"], ["Results: POSITIVE NEGATIVE\nBIZ IMPACT BIZ IMPACT", "", ""], ["", "FLAT &\nROLL OUT", ""], ["", "", ""]] | V16: Alt TO (slide 337): Control | Alt Product (slide 338): Payments | Alt TO (slide 338): use of Shell Banner; other | Alt Product (slide 339): QBO | Alt GET (slide 339): ing by QBO | Alt TO (slide 339): GNS Conversion rate range reported. Also | Alt BY (slide 339): QBO | Date source: CSV - Current Target Launch Date | Name source: CSV | Business Impact updated from Results Report | Status enriched from Results Report | TO repaired: truncated 'customers' prefix restored | W16: 336-339 | X16: Copy of FY'25_ CRM Analytics Monthly Experiment_Notebook_AC.pdf | Y16: ✅ ELM Roadmap | ✅ Results Report | Z16: 30d+ QuickBooks customers | AA16: Customers | AB16: Messaging the benefits of DIWM paired with a CCR pricing offer or CCR
A17: ELM-6557 | B17: findings from the QBL BK Landing page experiment, but differing from Turbotax learnings, indicating varying customer | C17: 08-16-2024 | D17: GET: to manually send the wrap TO: tals Total BY: Defaulting customers to the DIWM tab on the Zero State Page | E17: IF: Separating DIWM and DIFM into two tabs vs having them side By first showing DIWM by itself to customers THEN: We will increase interest by side reduces the cognitive load on the customer. in the SKU compared to DIFM while increasing net revenue. | F17: • , indicating varying customer behavior between QBO and TT. for other business types. • Personalisation - Identify opportunities to personalize the landing page for QBL Tax. • Email Creative - Improve breakthrough/relevancy of content to address discrepancy between high open rates vs. low CTR Access Points - Omit the few IPDs that performed poorly for peak season and incorporate urgency and personalisation.& Implications Organic traffic from Left Nav and prod access point was split evenly We need to continue to test and optimize merchandising our between the control and test experience. • The test ran from 8/16 to QBL offerings to maximize revenue throughout the year. 10/5. • Elevating DIWM drove incremental sign ups without major impact to DIFM units vs. control. • Despite the decreased visibility of DIFM in the second tab, we Get QBO customers looking for help with their bookkeeping only lost 3 DIFM units vs control - indicating that the two To Sign up for QB Live Expert Assisted Bookkeeping products are complementary not cannibalistic. • Related, By Defaulting customers to the DIWM tab on the Zero State Page opportunity to further refine audience targeting for campaigns. • Hypothesis • Separating DIWM and DIFM into two tabs vs having them side By first showing DIWM by itself to customers, we will increase interest by side reduces the cognitive load on the customer. in the SKU compared to DIFM while increasing net revenue. | G17: DIWM trial starts increased 27% during the course of the test • The redesign has resulted in an estimated 1400 units of incremental GNS per year and $450k in incremental revenue per year • ~71% conversion rate of customers who signed up for the free trial and converted to a GNS • NEXT STEPS & IMPLICATIONS • Roll out - Roll out the Treatment 1 for Sole proprietor companies, iterate based on learnings for other business types. • Personalisation - Identify opportunities to personalize the landing page for QBL Tax. • Email Creative - Improve breakthrough/relevancy of content to address discrepancy between high open rates vs. low CTR • Access Points - Omit the few IPDs that performed poorly for peak season and incorporate urgency and personalisation. • CUSTOMER EXPERIENCE Prioritizing DIWM on Zero State LP - Previous Experience [ELM 6557] • Results: POSITIVE NEGATIVE BIZ IMPACT BIZ IMPACT Introducing SCU on Zero State Page - Passive Experience • DIFM Tab Introducing SCU on Zero State Page - Aggressive Experience • DIWM Tab SCU details page & ELM comms • SCU Details page • FLAT & • WRAP REPORT • ELM - 6557 Zero State Page Prioritize • • Template v5.0 Updated Aug 2024 GLOBAL BGUlSoIbNaEl SBSus SinOeLsUs SToIOluNtioSn Gs RGOroUuPp • Prioritize DIWM o tate Page over for DIFM • Background • revenue. • KPIs TEST • IXP Assignments 47,827 • 30D DIWM Signups 967 • 30D DIFM GNS 60 • DIWM on Zero State Page - Prior Experience Prioritize DIWM on Zero State Page - Treatment Experience • RESULTS • NEXT STEPS | H17: DIFM Signups were impacted at 95 ITC (3 units). • Added additional complexity for future iterations of the page, including the addition of SCU. • CUSTOMER EXPERIENCE • DIWM Tab • DIFM Tab • FLAT & • IPD & Email comms • DIWM • • GLOBAL BGUlSoIbNaEl SBSus SinOeLsUs SToIOluNtioSn Gs RGOroUuPp • CON. Δ ITC • 47,348 • 760 207 127 • 63 -3 95 • on3• Control • DIWM and DIFM presented on the same page • Customer's path to page • Treatment - DIWM Tab • DIWM and DIFM presented on separate tabs • Treatment - DIFM Tab • POSITIVE | I17: Roll out - Roll out the Treatment 1 for Sole proprietor companies, iterate based on learnings for other business types. • Personalisation - Identify opportunities to personalize the landing page for QBL Tax. • Email Creative - Improve breakthrough/relevancy of content to address discrepancy between high open rates vs. low CTR • Access Points - Omit the few IPDs that performed poorly for peak season and incorporate urgency and personalisation. EXPERIENCE CUSTOMER EXPERIENCE Prioritizing DIWM on Zero State LP - Previous Experience [ELM 6557] CUSTOMER EXPERIENCE DIWM Tab DIFM Tab up 240 Results: POSITIVE NEGATIVE BIZ IMPACT BIZ IMPACT LAT & ROLL OUT CUSTOMER EXPERIENCE CUSTOMER EXPERIENCE Introducing SCU on Zero State Page - Passive Experience CUSTOMER EXPERIENCE DIWM Tab up 242 Results: POSITIVE NEGATIVE BIZ IMPACT BIZ IMPACT LAT & ROLL OUT CUSTOMER EXPERIENCE CUSTOMER EXPERIENCE SCU details page & ELM comms CUSTOMER EXPERIENCE SCU Details page IPD & Email comms up 243 LAT & ROLL OUT WRAP REPORT ELM - 6557 Zero State Page Prioritize DIWM Template v5.0 Updated Aug 2024 GLOBAL BGUlSoIbNaEl SBSus SinOeLsUs SToIOluNtioSn Gs RGOroUuPp 3 GLOBAL BGUlSoIbNaEl SBSus SinOeLsUs SToIOluNtioSn Gs RGOroUuPp Prioritize DIWM o tate Page over for DIFM Background opportunity to further refine audience targeting for campaigns • Separating DIWM and DIFM into two tabs vs having them side by side reduces the cognitive load on the customer. revenue. KPIs TEST CON. Δ ITC IXP Assignments 47,827 47,348 30D DIWM Signups 967 760 207 127 30D DIFM GNS 60 63 -3 95 on3EXPERIENCE CUSTOMER EXPERIENCE Prioritize DIWM on Zero State Page - Prior Experience CUSTOMER EXPERIENCE Control DIWM and DIFM presented on the same page Customer's path to page up 311 Results: POSITIVE NEGATIVE BIZ IMPACT BIZ IMPACT LAT & ROLL OUT CUSTOMER EXPERIENCE CUSTOMER EXPERIENCE Prioritize DIWM on Zero State Page - Treatment Experience CUSTOMER EXPERIENCE Treatment - DIWM Tab DIWM and DIFM presented on separate tabs up 312 Results: POSITIVE NEGATIVE BIZ IMPACT BIZ IMPACT LAT & ROLL OUT CUSTOMER EXPERIENCE Treatment - DIWM Tab DIWM and DIFM presented on separate tabs up 313 Results: POSITIVE NEGATIVE BIZ IMPACT BIZ IMPACT LAT & ROLL OUT RESULTS POSITIVE BIZ IMPACT Organic traffic from Left Nav and prod access point was split evenly We need to continue to test and optimize merchandising our between the control and test experience. The test ran from 8/16 to QBL offerings to maximize revenue throughout the year. 10/5. Elevating DIWM drove incremental sign ups without major impact to DIFM units vs. control. Objective Despite the decreased visibility of DIFM in the second tab, we Get QBO customers looking for help with their bookkeeping only lost 3 DIFM units vs control - indicating that the two To Sign up for QB Live Expert Assisted Bookkeeping products are complementary not cannibalistic. Related, By Defaulting customers to the DIWM tab on the Zero State Page opportunity to further refine audience targeting for campaigns. Hypothesis • Separating DIWM and DIFM into two tabs vs having them side By first showing DIWM by itself to customers, we will increase interest by side reduces the cognitive load on the customer. in the SKU compared to DIFM while increasing net revenue. | J17: QBO Live | K17: Landing Page | L17: Trending Positive (Inferred for review) | Results: 5.1 MEASURE: Complete | M17: | 121 ITC-1 [Results Report] | ITC-1: 121 | N17: https://docs.google.com/presentation/d/16njmsVvxnAIbueDBmkuI7790p8G8Oe2aR3CCaXge5QQ/edit?usp=sharing | O17: GNS/GNA | P17: 121 | U17: [["RESULTS"], ["Control", "DIWM, Inc", "40", "", "322", "66", "428", ""], ["", "", "", "", "", "", "", "1,282"], ["", "DIFM, Inc", "4", "", "34", "11", "49", ""], ["", "DIWM, Un Inc", "", "588", "A\n53", "164", "805", ""], ["Treatment-1", "DIWM, Inc", "36", "", "180", "58", "274", ""], ["", "", "", "", "", "", "", "1,304"], ["", "DIFM, Inc", "6", "", "53", "16", "75", ""], ["", "DIWM, Un Inc", "", "720", "A\n54", "181", "955", ""], ["Treatment-2", "DIWM, Inc", "28", "", "268", "63", "359", ""], ["", "", "", "", "", "", "", "1,074"], ["", "DIFM, Inc", "5", "", "26", "6", "37", ""], ["", "DIWM, Un Inc", "489", "", "53", "136", "678", ""], ["Note: Non colored ITCs are not measured towards stat sig."], ["RESULTS"], ["Landing page test resulted in stat sig impact on starts for the sole prop companies at a 120 ITC and estimated to drive 2000\nincremental signups when rolled out for TY 24 peak season.\nHIGHLIGHTS LOWLIGHTS", "", "", "", ""], ["", "HIGHLIGHTS", "", "LOWLIGHTS", ""], ["", "NEXT STEPS & IMPLICATIONS", "", "", ""], ["", "● Roll out - Roll out the Treatment 1 for Sole proprietor companies, iterate based on learnings for other business types.\n● Personalisation - Identify opportunities to personalize the landing page for QBL Tax.\n● Email Creative - Improve breakthrough/relevancy of content to address discrepancy between high open rates vs. low CTR\n● Access Points - Omit the few IPDs that performed poorly for peak season and incorporate urgency and personalisation.", "", "", ""], ["", "CUSTOMER EXPERIENCE"], ["CUSTOMER EXPERIENCE\nPrioritizing DIWM on Zero State LP - Previous Experience [ELM 6557]", "CUSTOMER EXPERIENCE"], ["", "DIWM Tab", ""], ["", "A\nA B\nC\nC\nD", ""], ["", "", "A\nA B\nC\nC\nD"], ["DIFM Tab"], ["B\nC\nD"], ["B\nC\nD"], ["Results: POSITIVE NEGATIVE\nBIZ IMPACT BIZ IMPACT", "", ""], ["", "FLAT &\nROLL OUT", ""], ["", "CUSTOMER EXPERIENCE"], ["CUSTOMER EXPERIENCE\nIntroducing SCU on Zero State Page - Passive Experience", "CUSTOMER EXPERIENCE"], ["", "DIWM Tab", ""], ["", "A\nB", ""], ["", "A", ""], ["", "", "B"], ["DIFM Tab", ""], ["C\nD", ""], ["C", ""], ["Results: POSITIVE NEGATIVE\nBIZ IMPACT BIZ IMPACT", "", ""], ["", "FLAT &\nROLL OUT", ""], ["", "CUSTOMER EXPERIENCE"], ["CUSTOMER EXPERIENCE\nIntroducing SCU on Zero State Page - Aggressive Experience", "CUSTOMER EXPERIENCE"], ["DIWM Tab", ""], ["A\nB", ""], ["A", ""], ["", "B"], ["DIFM Tab", ""], ["C\nD\nD", ""], ["C", ""], ["Results: POSITIVE NEGATIVE\nBIZ IMPACT BIZ IMPACT", "", ""], ["", "FLAT &\nROLL OUT", ""], ["", "CUSTOMER EXPERIENCE"], ["CUSTOMER EXPERIENCE\nSCU details page & ELM comms", "CUSTOMER EXPERIENCE"], ["SCU Details page", ""], ["IPD & Email comms"], ["FLAT &\nROLL OUT", ""], ["WRAP REPORT", "", ""], ["ELM - 6557\nZero State Page Prioritize", "DIWM", ""], ["Link", ""], ["", "Link"], ["", "Link"], ["", "Template v5.0 Updated Aug 2024\nGLOBAL BGUlSoIbNaEl SBSus SinOeLsUs SToIOluNtioSn Gs RGOroUuPp", "", ""], ["", "", "GLOBAL BGUlSoIbNaEl SBSus SinOeLsUs SToIOluNtioSn Gs RGOroUuPp", ""], ["", "Prioritize DIWM o", "", "tate Page\nover for DIFM", "", "", "", "", "", "", ""], ["", "Background", "", "", "", "", "", "", "", "", ""], ["", "", "", "revenue.", "", "", "", "", "", "", ""], ["KPIs", "TEST", "CON.", "Δ", "ITC"], ["IXP Assignments", "47,827", "47,348", "", ""], ["30D DIWM Signups", "967", "760", "207", "127"], ["30D DIFM GNS", "60", "63", "-3", "95"], ["on3s G1ro0up"], ["Global Business Soluti", "on3s G1ro0up"], ["", "CUSTOMER EXPERIENCE"], ["CUSTOMER EXPERIENCE\nPrioritize DIWM on Zero State Page - Prior Experience", "CUSTOMER EXPERIENCE"], ["Control"], ["DIWM and DIFM presented on the same\npage"], ["Customer's path to page"], ["Results: POSITIVE NEGATIVE\nBIZ IMPACT BIZ IMPACT", "", ""], ["", "FLAT &\nROLL OUT", ""], ["", "CUSTOMER EXPERIENCE"], ["CUSTOMER EXPERIENCE\nPrioritize DIWM on Zero State Page - Treatment Experience", "CUSTOMER EXPERIENCE"], ["", "Treatment - DIWM Tab", ""], ["", "DIWM and DIFM presented on separate tabs\nA\nA B\nC\nC\nD", ""], ["", "", "A\nA B\nC\nC\nD"], ["Treatment - DIFM Tab"], ["DIWM and DIFM presented on separate tabs\nB\nC\nD"], ["B\nC\nD"], ["Results: POSITIVE NEGATIVE\nBIZ IMPACT BIZ IMPACT", "", ""], ["", "FLAT &\nROLL OUT", ""], ["CUSTOMER EXPERIENCE"], ["Treatment - DIWM Tab"], ["DIWM and DIFM presented on separate tabs\nA\nA\nA\nA B\nB\nC\nCC"], ["Treatment - DIFM Tab"], ["DIWM and DIFM presented on separate tabs\nA\nA\nB\nB\nC\nC"], ["Results: POSITIVE NEGATIVE\nBIZ IMPACT BIZ IMPACT", "", ""], ["", "FLAT &\nROLL OUT", ""], ["", "RESULTS", "POSITIVE\nBIZ IMPACT", "", ""], ["HIGHLIGHTS", "", "LOWLIGHTS"], ["● DIWM trial starts increased 27% during the\ncourse of the test\n● The redesign has resulted in an estimated 1400\nunits of incremental GNS per year and $450k in\nincremental revenue per year\n● ~71% conversion rate of customers who signed\nup for the free trial and converted to a GNS", "", "● DIFM Signups were impacted at 95 ITC (3 units).\n● Added additional complexity for future iterations of the\npage, including the addition of SCU."], ["NEXT STEPS", "", ""], ["Results: POSITIVE NEGATIVE\nBIZ IMPACT BIZ IMPACT", "", ""], ["", "FLAT &\nROLL OUT", ""]] | V17: Alt TO (slide 238): drive 2000 | Campaign re-appears on slide 240 (gap from slide 238) | Alt TO (slide 240): MER EXPERIENCE | Alt TO (slide 241): MER EXPERIENCE | Alt TO (slide 242): MER EXPERIENCE | Alt TO (slide 243): MER EXPERIENCE | Campaign re-appears on slide 309 (gap from slide 243) | Alt TO (slide 309): IOluNtioSn Gs RGOroUuPp 309 | Alt Campaign Name (slide 310): ● | Alt Date (slide 310): 8-16-24 | Alt GET (slide 310): QBO customers looking for help with their bookkeeping | Alt TO (slide 310): tab over for DIFM results with an estimated DIWM Signups (127 ITC, +207) while | Alt status (slide 310): Positive | Alt TO (slide 311): MER EXPERIENCE | Alt TO (slide 312): MER EXPERIENCE | Alt GET (slide 313): s to the | Alt TO (slide 313): MER EXPERIENCE | Alt Product (slide 314): Payroll | Alt TO (slide 314): mers who signed | Date source: CSV - Current Target Launch Date | Business Impact updated from Results Report | Status enriched from Results Report | W17: 237-314 | X17: Copy of FY'25_ CRM Analytics Monthly Experiment_Notebook_AC.pdf | Y17: ✅ ELM Roadmap | ✅ Results Report | Z17: to manually send the wrap | AA17: tals Total | AB17: Defaulting customers to the DIWM tab on the Zero State Page
A18: ELM-6769 | B18: [TAX] Tax Extension 3rd Peak Campaign Wave 1 Non-Schedule C | C18: 08-15-2024 | D18: GET: QBO customers with a known business entity that must TO: Campaign to remind extension customers that it is time to clean up their books and/or file taxes (Inferred for review) BY: Using better targeting and messaging than 6513 | E18: IF: Better results w/ urgent/benefit message and 'younger' target | F18: • repository - Attach Naveen / Manasa / Aneesh 02.Cancel Flow Deep Discount and Single/Multi Screen 03.ELM 6769 Biz. • Tax Urgency message has shown stat sig results in younger Benefits message is consistent in performance at 160+ ITB in both audience groups & consistent across weeks Younger QBO Audience tend to open emails around Tax communication at ~112 ITB but 2+ QBO tenure audience, open at 95 ITB CTR is consistently at 11 to 40 ITB, performing lower than benchmark - indicating lesser interest around the second peak tax filing | G18: Urgency messaging have shown Stat sig results in Younger QBO companies at 157 ITC, Positive result in 2+ yr old companies at 180 ITC • Benefits message have shown consistent better IPD performance at 160 ITB performance at 160 ITB • Smaller target audience, combined at ~200k. Campaign only focused on customers with known S-Corp/Partnership.* • Emails had lower CTR in the ranges of 11 - 40 ITB, indicating need to review the email strategy for the audience • NEXT STEPS & IMPLICATIONS • *Expand urgency message to both known S-Corp/Partnership (200k) and Sole Proprietors (350k) during the March/April Peak 1 & 2 tax deadlines. These two audiences have different tax deadlines (3/15, 4/15). • In the same period field Urgent messages to customers with 60% of customers with unknown entity types (650k); these may be compromised as we do not know the specific deadline these customers must file by. • Consider opportunities for Urgency messaging for QBL DIWM in addition to QBL Tax in key periods • Results: POSITIVE NEGATIVE BIZ IMPACT BIZ IMPACT | H18: Smaller target audience, combined at ~200k. Campaign only focused on customers with known S-Corp/Partnership.* • Emails had lower CTR in the ranges of 11 - 40 ITB, indicating need to review the email strategy for the audience • FLAT & | I18: *Expand urgency message to both known S-Corp/Partnership (200k) and Sole Proprietors (350k) during the March/April Peak 1 & 2 tax deadlines. These two audiences have different tax deadlines (3/15, 4/15). • In the same period field Urgent messages to customers with 60% of customers with unknown entity types (650k); these may be compromised as we do not know the specific deadline these customers must file by. • Consider opportunities for Urgency messaging for QBL DIWM in addition to QBL Tax in key periods Results: POSITIVE NEGATIVE BIZ IMPACT BIZ IMPACT LAT & ROLL OUT Urgency message has shown stat sig results in younger Benefits message is consistent in performance at 160+ ITB in both audience groups & consistent across weeks Younger QBO Audience tend to open emails around Tax communication at ~112 ITB but 2+ QBO tenure audience, open at 95 ITB CTR is consistently at 11 to 40 ITB, performing lower than benchmark - indicating lesser interest around the second peak tax filing | J18: QBO Live | K18: IPD; Email | L18: Trending Positive | Results: 5.1 MEASURE: Complete | M18: INCONCLUSIVE audience & directional pos. results for 2+ yr old audience. BIZ IMPACT TRENDING POSITIVE Urgency message has shown positive impact for Audience 1 - Younger Benefits message drove directional neg results for younger QBO customers, has shown directional positive results for Audience 2 - 2+ audience & positive results for 2+yr QGBlobOal Bcusuinsestso Somlutieonrss G.roup 276 yr QBO customers [Results Report] | ITC-1: 120 | N18: https://docs.google.com/presentation/d/1UY14dSgFQNuyMk9W7ENVVhn92TSLxMPDm8OwMIna45U/edit?usp=sharing | O18: GNS/GNA | P18: 120 | U18: [["TOPIC", "", "TIME"], ["01.Insights repository - Attach\nNaveen / Manasa / Aneesh", "", "30 Min"], ["02.Cancel Flow Deep Discount and Single/Multi Screen\nAndre", "", "15 Min"], ["03.ELM 6769 Biz. Tax\nAneesh", "", "15 Min"], ["", "WRAP REPORT", "", ""], ["ELM -6769\nQBL Tax Extension 3rd", "", "Peak", ""], ["Link", ""], ["", "Link"], ["", "Link"], ["Template v5.0 Updated Aug 2024\nGLOBAL BGUlSoIbNaEl SBSus SinOeLsUs SToIOluNtioSn Gs RGOroUuPp", "", ""], ["", "GLOBAL BGUlSoIbNaEl SBSus SinOeLsUs SToIOluNtioSn Gs RGOroUuPp", ""], ["", "", "", "", "", "", "", "", "", "Objective\nGet QBO customers with a known business entity that must\nfile Non-Schedule C tax forms\nTo Attach to QBL DIFM/DIWM QBL Tax before 9/16 deadline\nBy Using better targeting and messaging than 6513\nHypothesis\nBetter results w/ urgent/benefit message and 'younger' target\nResults", "", "", "", "", "", "", ""], ["", "", "", "", "", "", "L Tax starts\ned target.", "", "", "", "", "", "", "", "", "", ""], ["", "Business Impact: POSITIVE INCONCLUSIVE\nBIZ IMPACT TRENDING POSITIVE\nUrgency message has shown positive impact for A\nQBO customers, has shown directional positive resu\nyr QBO customers", "", "", "", "", "", "", "", "", "", "", "", "", "", "", ""], ["", "", "", "", "", "", "", "", "audience & directional pos. results for 2+ yr old audience.\nB● Benefits message drove directional neg results for younger\naudience & positive results for 2+yr QGBlobOal Bcusuinsestso Somlutieonrss G.roup 276", "", "", "", "", "", "", "", ""], ["", "", "", "", "", "", "udience 1 - Youn\nlts for Audience", "ger\n2 - 2+", "", "", "", "", "", "", "", "", ""], ["", "", "", "", "", "", "", "G", "", "", "", "", "", "", "", "", ""], ["", "", "", "FLAT &\nROLL OUT", "", "", "", "", "", "", "", "", "", "", "", "", ""], ["Audience 0-2yr QBO Tenure", "", "", "", "", "", "", ""], ["KPIs", "Control", "Treatment -\nUrgent", "Δ", "ITC", "Treatment -\nBenefits", "Δ", "ITC"], ["Assignments", "43,269", "43,250", "", "", "43,101", "", ""], ["14d Signups", "63", "99", "36", "157", "A\n60", "-3", "B\n95"], ["Audience 2yr+ QBO Tenure", "", "", "", "", "", "", ""], ["KPIs", "Control", "Treatment -\nUrgent", "Δ", "ITC", "Treatment -\nBenefits", "Δ", "ITC"], ["Assignments", "14,678", "14,894", "", "A", "14,550", "", ""], ["14d Signups", "15", "27", "12", "180", "18", "3", "B\n120"], ["2+yr QGBlobOal Bcusuinsestso Somlutieo", "nrss G.roup", "276"], ["RESULTS"], ["Audience 0-2yr QBO Tenure"], ["Audience 0-2yr QBO Tenure", "", "", "", "", ""], ["Cohort", "IPD", "", "", "", ""], ["", "Imp.", "Clicks", "CTR", "Δ", "ITB"], ["Control", "281", "14", "", "", ""], ["Treatment 1", "37594", "1712", "4.55%", "1.43%", "146"], ["Treatment 2", "37556", "1921", "5.12%", "2.00%", "164 A"], ["IPD Benchmark **", "", "", "3.12%", "", ""], ["Audience 2yr+ QBO Tenure", "", "", "", "", ""], ["Cohort", "IPD", "", "", "", ""], ["", "Imp.", "Clicks", "CTR", "Δ", "ITB"], ["Control", "252", "5", "", "", ""], ["Treatment 1", "12669", "523", "4.13%", "1.01%", "132"], ["Treatment 2", "12394", "675", "5.45%", "2.33%", "175\nA"], ["IPD Benchmark **", "", "", "3.12%", "", ""], ["Audience 2yr+ QBO Tenure"], ["Results: POSITIVE NEGATIVE\nBIZ IMPACT BIZ IMPACT", "", ""], ["", "FLAT &\nROLL OUT", ""], ["RESULTS"], ["Cohort", "Email", "", "", "", "", "", "", "", "", ""], ["", "Sent", "Opens", "%", "Δ", "ITB", "Clicks", "CTR", "Δ", "ITB", "Unsub"], ["Audience 0-2yr QBO Tenure", "", "", "", "", "", "", "", "", "", ""], ["ELM6769-EM-US-QBL-NA-NA-XSLL-PROMO-NA-EQ-BizTaxGapClosure_002a", "44,552", "12,507", "28.07%", "3.07%", "A\n112", "78", "0.18%", "-0.82%", "B\n18", "0"], ["ELM6769-EM-US-QBL-QBLT-NA-XSLL-PROMO-NA-EQ-BizTaxGapClosure_001a", "44,812", "12,577", "28.07%", "3.07%", "112", "171", "0.38%", "-0.62%", "38", "0"], ["Audience 2yr+ QBO Tenure", "", "", "", "", "", "", "", "", "", ""], ["ELM6769-EM-US-QBL-NA-NA-XSLL-PROMO-NA-EQ-BizTaxGapClosure_002b", "12,660", "2,993", "23.64%", "-1.36%", "A\n95", "14", "0.11%", "-0.89%", "B 11", "0"], ["ELM6769-EM-US-QBL-QBLT-NA-XSLL-PROMO-NA-EQ-BizTaxGapClosure_001b", "12,837", "3,010", "23.45%", "-1.55%", "94", "30", "0.23%", "-0.77%", "23", "0"], ["Email Benchmark*", "", "", "25%", "", "", "", "1%", "", "", ""], ["Results: POSITIVE NEGATIVE\nBIZ IMPACT BIZ IMPACT", "", ""], ["", "FLAT &\nROLL OUT", ""], ["Urgency IPD CTRs did translate into an increase in signup rate, but had varying performance in QBO accounts with\ndifferent tenures. Potential factors are introduced below."], ["HIGHLIGHTS", "", "LOWLIGHTS", "", "", ""], ["● Urgency messaging have shown Stat sig results in\nYounger QBO companies at 157 ITC, Positive result\nin 2+ yr old companies at 180 ITC\n● Benefits message have shown consistent better IPD\nperformance at 160 ITB", "", "● Smaller target audience, combined at ~200k. Campaign\nonly focused on customers with known\nS-Corp/Partnership.*\n● Emails had lower CTR in the ranges of 11 - 40 ITB,\nindicating need to review the email strategy for the\naudience", "", "", ""], ["NEXT STEPS & IMPLICATIONS", "", "", "", "", ""], ["● *Expand urgency message to both known S-Corp/Partnership (200k) and Sole Proprietors (350k) during the March/April\nPeak 1 & 2 tax deadlines. These two audiences have different tax deadlines (3/15, 4/15).\n● In the same period field Urgent messages to customers with 60% of customers with unknown entity types (650k); these may\nbe compromised as we do not know the specific deadline these customers must file by.\n● Consider opportunities for Urgency messaging for QBL DIWM in addition to QBL Tax in key periods", "", "", "", "", ""], ["Results: POSITIVE NEGATIVE\nBIZ IMPACT BIZ IMPACT", "", ""], ["", "FLAT &\nROLL OUT", ""]] | V18: Alt TO (slide 275): IOluNtioSn Gs RGOroUuPp 275 | Alt TO (slide 276): mers with a known business entity that must | Alt Campaign Name (slide 278): EM-US-QBL-NA-NA-XSLL-PROMO-NA-EQ-BizTaxGapClosure_002a 44,552 12,507 28.07% 3.07% 112 78 0.18% -0.82% 18 0 | Alt TO (slide 278): open emails around Tax communication at ~112 ITB but 2+ QBO tenure audience, open at 95 ITB | Alt GET (slide 279): audience, combined at ~200k. Campaign | Alt TO (slide 279): an increase in signup rate, but had varying performance in QBO accounts with | Alt BY (slide 279): . | Name source: CSV | Business Impact updated from Results Report | Status enriched from Results Report | TO replaced with CSV Project Description (was: placeholder) | W18: 274-279 | X18: Copy of FY'25_ CRM Analytics Monthly Experiment_Notebook_AC.pdf | Y18: ✅ ELM Roadmap | ✅ Results Report | Z18: QBO customers with a known business entity that must | AA18: Campaign to remind extension customers that it is time to clean up their books and/or file taxes (Inferred for review) | AB18: Using better targeting and messaging than 6513
A19: ELM-6837 | B19: FY24 FEB GAP CLOSER: Shift GSU brand into unified -first call with BK- experience DIWM - QBL Trial Conversion Phase II | C19: 03-29-2024 | D19: GET: Post GSU to DIWM migration work to enable us to heavy up on trial conversion, in IPD and promote the 50% off discount for 3 months to NTTF QBO subscribers who become eligible for a DIWM - QBL 1-month trial. This is to help offset the softness monetization will see since they will not be able to target QBO NTTF Subs in the first 30D. (Inferred for review) TO: A | E19: IF: Post GSU to DIWM migration work to enable us to heavy up on trial conversion, in IPD and promote the 50% off discount for 3 months to NTTF QBO subscribers who become eligible for a DIWM - QBL 1-month trial. This is to help offset the softness monetization will see since they will not be able to target QBO NTTF Subs in the first 30D. | F19: • The coverage for IPDs have been improved due to Loss expanding the day range filters from ELM 6837 The choice of not using Multimodal IPD access point and using bottom drawers didnt result in better CTR, 15.4k 14.2k 512 76 resulting in control being the better performing cohort A B Treatment 1 • Though the IPD Clicked to 45D GNS is slightly better 8% 96% 85% C for treatment 1 (14.8% vs 14.2%) it wasnt enough to offset the loss due to overall cohort performance Treatment 2 QBO Dashboard - Bottom Drawer 6,753 81 1.20% | J19: QBO Live | K19: IPD | L19: Trending Positive | U19: [["RESULTS"], ["15.4k 10.5k 555 79\nControl\nA B C\n32% 95% 86%\nLoss Loss Loss"], ["15.4k 14.2k 512 76\nA B Treatment 1\nC\n8% 96% 85%\nLoss Loss Loss"], ["Results: POSITIVE NEGATIVE\nBIZ IMPACT BIZ IMPACT", "", ""], ["", "FLAT &\nROLL OUT", ""], ["RESULTS"], ["Cohort", "IPD", "", "", "", "", "", "", ""], ["", "Assigns", "Coverage", "", "Clicks", "CTR", "Δ", "ITB", ""], ["Control", "15,430", "", "A\n68%", "556", "5.30%", "-0.10%", "", "A\n98"], ["Treatment 1", "15,378", "", "92%", "509", "3.60%", "-1.80%", "", "67"], ["Treatment 2", "15,252", "", "93%", "465", "3.28%", "-2.12%", "", "61"], ["", "IPD Benchmark **", "", "", "5.40%", "", "", "", ""], ["Cohort", "Access point", "Unq Views", "Unq Clicks", "Unq CTR"], ["Control", "Shell - Banner", "10,173", "367 B", "3.61%"], ["", "QBO - Logout Modal", "2,487", "187", "7.52%"], ["", "Advanced Shell - Banner", "297", "12", "4.04%"], ["", "Reports - Hellobox", "197", "2", "1.02%"], ["", "QBO - Modal Interrupters", "24", "4", "16.67%"], ["Treatment 1", "Shell - Banner", "13,885", "423 B", "3.05%"], ["", "QBO Dashboard - Bottom Drawer", "6,753", "81", "1.20%"], ["", "Banking - Hellobox", "3,734", "11", "0.29%"], ["", "Invoices - Hellobox", "2,208", "2", "0.09%"], ["", "Chart of Accounts - Hellobox", "215", "0", "0.00%"], ["", "Reports - Hellobox", "157", "0", "0.00%"], ["", "Advanced Shell - Banner", "152", "10", "6.58%"], ["Treatment 2", "Shell - Banner", "13,863", "B\n400", "2.89%"], ["", "QBO Dashboard - Bottom Drawer", "6,609", "53", "0.80%"], ["", "Banking - Hellobox", "3,688", "5", "0.14%"], ["", "Invoices - Hellobox", "2,213", "1", "0.05%"], ["", "Advanced Shell - Banner", "292", "10", "3.42%"], ["", "Chart of Accounts - Hellobox", "229", "0", "0.00%"], ["", "", "", "", "0.00%"], ["", "Reports - Hellobox", "152", "0", ""], ["Results: POSITIVE NEGATIVE\nBIZ IMPACT BIZ IMPACT", "", ""], ["", "FLAT &\nROLL OUT", ""]] | V19: Alt TO (slide 123): m Drawer 6,753 81 1.20% | Date source: CSV - Current Target Launch Date | Name source: CSV | Hypothesis filled from CSV Project Description CSV (Inferred for review) | Strategic Framework - GET filled from CSV Project Description (Inferred for review) | Strategic Framework - BY filled from CSV Project Description (Inferred for review) | W19: 122-123 | X19: Copy of FY'25_ CRM Analytics Monthly Experiment_Notebook_AC.pdf | Y19: ✅ ELM Roadmap | ⚠️ Results Report | Z19: Post GSU to DIWM migration work to enable us to heavy up on trial conversion, in IPD and promote the 50% off discount for 3 months to NTTF QBO subscribers who become eligible for a DIWM - QBL 1-month trial. This is to help offset the softness monetization will see since they will not be able to target QBO NTTF Subs in the first 30D. (Inferred for review) | AB19: Post GSU to DIWM migration work to enable us to heavy up on trial conversion, in IPD and promote the 50% off discount for 3 months to NTTF QBO subscribers who become eligible for a DIWM - QBL 1-month trial. This is to help offset the softness monetization will see since they will not be able to target QBO NTTF Subs in the first 30D. (Inferred for review)
A20: ELM-7013 | B20: QB Live DIWM Trial Active Use Personalization TEST - Spokesmodel | C20: 09-30-2024 | D20: GET: to manually send the wrap TO: be <70 ITB for both treatment BY: Providing them a personalized in-product experience (via IPDs) during | E20: IF: Delivering DIWM trialers personalized content (IPDs) based on how they manage | F20: • Treatment has driven +61 calls over a month, showing the impact Control IPDs of personalised messaging & Increased coverage in treatment. • Personalised messaging has driven more calls rate and 31D GNS units delivering +41 incremental GNS Vs Control. • The increased coverage caused a drop in CTR across most Treatment Segment Unique views Unq CTR access points, creating path for further optimisation. • Control Control IPDs 6286 6.1% Treat - Seg 1 - Get Started 7547 4.1% A Treat - Seg 1 - Spreadsheet 1418 4.3% Treat - Seg 1 - Others 1292 4.7% Treat - Seg 2 - Established 841 5.5% The coverage for IPDs have been improved due to Treatment expanding the rules of targeting. A B C D Loss • The spokesmodel IPDs have been effective in 14d Scheduling rate even with the challenge of expanded 10 0% k 1 86 k 8 0 6 ~1% The personalised IPDs, triggered based on how customers managed their finances, have been effective in driving scheduling to completion rates - showing the increased intent of audience with S2C at 72% vs 79% with 109 ITC A B C • D Apart from observed higher coverage, contextual & 50% 93% 29% 91% personalized messaging also had an impact here with IPD viewed to GNS ratio at 0.46% in control vs 0.80% in treatment at 173 ITC 29 assigns ~0.2% | I20: Treatment has driven +61 calls over a month, showing the impact Control IPDs of personalised messaging & Increased coverage in treatment. Personalised messaging has driven more calls rate and 31D GNS units delivering +41 incremental GNS Vs Control. Customer Segment Wise The increased coverage caused a drop in CTR across most Treatment Segment Unique views Unq CTR access points, creating path for further optimisation. Control Control IPDs 6286 6.1% Treat - Seg 1 - Get Started 7547 4.1% A Treat - Seg 1 - Spreadsheet 1418 4.3% Treatment Treat - Seg 1 - Others 1292 4.7% Treat - Seg 2 - Established 841 5.5% The coverage for IPDs have been improved due to Treatment expanding the rules of targeting. A B C D 14% 92% 22% 87% Loss • The spokesmodel IPDs have been effective in 14d Scheduling rate even with the challenge of expanded coverage 1 10 2 0% k 1 86 1 % k 8 7 3 % 0 6 5 5 % 1 ~1% 8 6 ss igns The personalised IPDs, triggered based on how assigns customers managed their finances, have been effective in driving scheduling to completion rates - showing the increased intent of audience with S2C at 72% vs 79% with 109 ITC Control A B C • D Apart from observed higher coverage, contextual & 50% 93% 29% 91% personalized messaging also had an impact here with Loss IPD viewed to GNS ratio at 0.46% in control vs 0.80% in treatment at 173 ITC 12k 6.3k 457 326 29 100% 50% 4% 3% assigns ~0.2% assigns | J20: QBO Live | K20: IPD | L20: Trending Positive | Results: 5.1 MEASURE: Complete | M20: Though the coverage in treatment is higher, 31D Ecosystem BIZ IMPACT Revenue is flat Treatment delivered significantly higher DIWM GNS Units (114 ITC , + 41 Units); Annual estimate : 480 incremental units [Results Report] | ITC-1: 114 | N20: https://docs.google.com/presentation/d/1bHQ4NS9OG4W_CiwBSXIsEkvJROy2HnRmlxZ8e-Ld_ag/edit?usp=sharing | O20: Trial Conversion Rate | P20: 114 | U20: [[""], ["Control Outperformed Treatments: A combination of different messaging and access point strategy resulted in the control group\noutperforming the treatments."], ["HIGHLIGHTS", "", "LOWLIGHTS"], ["● Expanding day ranges has resulted in improved\nIPD Coverage (135+ ITC) across both treatment\ngroups.\n● 31D Eco rev. observed to be trending positive at\n103 ITC", "", "● IPD CTR was observed to be <70 ITB for both treatment\ngroups while control remained flat at 97 ITB\n● DIWM Conversion rate is observed to be 97 ITC and 87\nITC for both treatments"], ["", "", ""], ["NEXT STEPS & IMPLICATIONS", "", ""], ["● Consider utilising Multimodal access point mixed with spokesmodel messaging same as ELM 7013.\n● Utilise the personalisation attributes observed to be successful in build habits campaign for this cohort", "", ""], ["", "124"], ["Results: POSITIVE NEGATIVE\nBIZ IMPACT BIZ IMPACT", "", ""], ["", "FLAT &\nROLL OUT", ""], ["", "", ""], [""], ["TOPIC", "", "TIME"], ["01.Bill Pay Propensity\nManasa", "", "10 Min"], ["02.Bill Pay Retargeting\nManasa", "", "10 Min"], ["03.Payments Left Nav\nNaveen", "", "20 Min"], ["04.QBO Upgrade Funnel optimization\nKarthik", "", "10 Min"], ["05.Build Habits\nAneesh", "", "10 Min"], ["06.DIWM FTU Trial Optimization\nAneesh", "", "10 Min"], ["", "125"], ["", "", "", ""], ["", "", "", "Template v4.3 Updated Jan FY'24"], ["WRAP REPORT", ""], [""], ["04-15-2024"], ["", "", "", "", "", "", "", "kesmodel\nustomers with a Live Expert\ne in getting them to\nthe current non-contextual", "", "", "", "", ""], ["", "", "", "", "", "", "", "", "", "", "", "", ""], ["Emerging: Just getting started, help getting setup", "", "", "", "", "", "", "Treatment IPDs", "", "", "", "", ""], ["Emerging/Established: Other, chart of accounts", "", "", "", "", "", "", "", "", "", "", "", ""], ["", "Emerging/Established: Other, chart of accounts", "", "", "", "", "", "", "", "", "", "", ""], ["", "", "", "", "", "", "", "", "", "", "", "", ""], ["", "", "Emerging: Spreadsheets, reports", "", "", "", "", "", "", "", "", "", ""], ["", "", "Established: account reconciliatio", "", "", "", "", "", "", "", "", "", ""], ["", "", "", "Established: account reconciliatio", "", "", "", "n", "", "", "", "", ""], ["", "", "", "", "", "", "", "", "", "", "", "", ""], ["", "", "", "", "", "", "", "", "", "", "", "", "Learnings & Implications\n●A Treatment has driven +61 calls over a month, showing the impact\nof personalised messaging & Increased coverage in treatment.\n●B Personalised messaging has driven more calls rate and 31D gns\nunits delivering +41 incremental GNS Vs Control.\n●C Though the coverage in treatment is higher, 31D Ecosystem\nRevenue is flat"], ["", "", "", "", "", "", "", "", "", "", "", "", ""], ["", "", "", "", "", "", "", "", "", "", "", "", ""], ["", "", "", "", "", "", "", "", "", "", "", "", "of personalised messaging & Increased coverage in treatment.\n●B Personalised messaging has driven more calls rate and 31D gns\nunits delivering +41 incremental GNS Vs Control.\n●C Though the coverage in treatment is higher, 31D Ecosystem\nRevenue is flat"], ["", "", "", "", "", "", "", "", "", "", "", "", ""], ["", "", "", "", "", "", "", "", "", "", "", "", ""], ["Business Impact:\nPOSITIVE\nBIZ IMPACT\nTreatment delivered significantly higher DIWM GNS Units (1\nAnnual estimate : 480 incremental units", "", "", "", "", "", "", "", "", "", "", "", ""], ["", "", "", "", "", "", "", "14 ITC , + 41 Units", "", ");", "", "", ""], ["KPIs", "TEST", "CON.", "Δ", "ITC"], ["Assignments", "12,593", "12,472", "", ""], ["14D Activation", "6.1%", "5.6%", "+61", "108"], ["45D DIWM GNS", "2.4%", "2.1%", "+41 B", "114"], ["31D Avg. Eco Rev", "43.44", "43.97", "0", "99"], ["", "", ""], ["", "228"], ["", ""], ["FLAT &\nROLL OUT", ""], ["", ""], [""], ["RESULTS"], ["Overall IPDs", "", "", "", "", "", ""], ["Cohort", "IPD", "", "", "", "", ""], ["", "Imp.", "Clicks", "CTR", "Δ", "ITB", ""], ["Control", "6,286", "383", "6.1%", "6.1%", "113", ""], ["Treatment", "10,786", "500", "4.6%", "4.6%", "86", ""], ["IPD Benchmark **", "", "", "5.4%", "", "", ""], ["Customer Segment Wise", "", "", ""], ["Treatment", "Segment", "Unique views", "Unq CTR"], ["Control", "Control IPDs", "6286", "6.1%"], ["Treatment", "Treat - Seg 1 - Get Started", "7547", "4.1%"], ["", "Treat - Seg 1 - Spreadsheet", "1418", "4.3%"], ["", "Treat - Seg 1 - Others", "1292", "4.7%"], ["", "Treat - Seg 2 - Established", "841", "5.5%"], ["", "229"], ["Results: POSITIVE NEGATIVE\nBIZ IMPACT BIZ IMPACT", "", ""], ["", "FLAT &\nROLL OUT", ""], ["", "", ""], ["RESULTS"], [""], ["In\nTreatment\nA B C D\n14% 92% 22% 87%\nLoss Loss Loss Loss\n12k 11k 830 651 86\n100% 86% 7% 5%", ""], ["", "In"], ["Control\nA B C D\n50% 93% 29% 91%\nLoss Loss Loss Loss\n12k 6.3k 457 326\n29", ""], ["12k"], ["100%"], ["6.3k"], ["50%"], ["457"], ["4%"], ["326"], ["3%"], ["29"], ["~0.2%"], ["", "230"], ["Results: POSITIVE NEGATIVE\nBIZ IMPACT BIZ IMPACT", "", ""], ["", "FLAT &\nROLL OUT", ""], ["", "", ""], ["RESULTS"], ["", "", ""], ["HIGHLIGHTS", "", "LOWLIGHTS"], ["", "", ""], ["NEXT STEPS & IMPLICATIONS", "", ""], ["● Test concluded with POSITIVE results. ELM rolled out the test as the new DIWM trial evergreen on 1/21/25.\n● Consider a CTA test "Talk to an expert" vs. "Schedule my setup" to learn if which one will improve CTR.", "", ""], [""]] | V20: Alt GET (slide 125): ing | Alt TO (slide 125): PIC TIME | Campaign re-appears on slide 227 (gap from slide 125) | Alt Campaign Name (slide 228): ● | Alt Date (slide 228): 01-11-2024 | Alt Product (slide 228): QBO | Alt GET (slide 228): All QBO-NTTF, buy-now with (DIWM) 30-day trial | Alt TO (slide 228): 01-12-2025 | Alt GET (slide 229): Started 7547 4.1% A | Alt TO (slide 229): mer Segment Wise | Alt GET (slide 230): ing. | Alt TO (slide 230): Treatment expanding the rules of targeting. | Alt Campaign Name (slide 231): DIWM hyper-personalization test delivered stat sig. positive results of 114 ITC | Alt Date (slide 231): 1/21/25 | Alt TO (slide 231): DIWM trialers drove more customers to schedule their 1st call with an expert within the first 14D (108 ITC) and | Alt BY (slide 231): an additional 4 wks (vs. planned 4wks) | Date source: CSV - Current Target Launch Date | Name source: CSV | Business Impact updated from Results Report | Status enriched from Results Report | W20: 124-231 | X20: Copy of FY'25_ CRM Analytics Monthly Experiment_Notebook_AC.pdf | Y20: ✅ ELM Roadmap | ✅ Results Report | Z20: to manually send the wrap | AA20: be <70 ITB for both treatment | AB20: Providing them a personalized in-product experience (via IPDs) during
A21: ELM-7084 | B21: TAX Redesign Zero State LP | C21: 01-24-2025 | D21: GET: QBO/QBSP Customers who have not signed-up for 2024 tax year TO: [Not extractable - garbled_text] (Inferred for review) BY: communicating benefits on By making them feel secure and Start QBL Tax for 2024 tax season | E21: IF: If the TOF is redesigned, for each +1.0 increase in the view-to-start rate* will increase QBL Tax Starts By 10,000 * | F21: • Overall tax starts are at 102 ITC for T1, but the merchandising | J21: QBO Live | K21: IPD; Email; Landing Page | L21: Trending Positive | Results: 5.1 MEASURE: Complete | M21: BIZ IMPACT BIZ IMPACT performance is mixed Redesigned QBL Tax LP has delivered sig. higher starts for Sole prop (DIWM Un Inc) customers (120 ITC , + 150) & will deliver +2100 starts by end of peak season. • DIWM Un Inc customers account for ~70% of starts, T1 has shown a 120 ITC. Redesigned QBL Tax LP has delivered negative performance across other biz entity type customers, we recommend roll back to control group design. • The goodness observed in DIFM - Inc group for T1 is not enough to compensate for the drop in DIWM - Inc gGrloobuapl B ucsuinsestso Smoluetirosn. [Results Report] | ITC-1: 120 | N21: https://docs.google.com/presentation/d/1DZ46Q5JkxjkSYMQpgnr5bjD-PMn4pnpNAlaZNQ2C35E/edit?usp=sharing | O21: GNS/GNA | P21: 120 | Q21: Ecosystem Revenue | S21: Ecosystem Revenue | U21: [["WRAP REPORT", ""], ["ELM -8355\n[TAX] TY24 Zero State\nPage Optimization \\", ""], ["R5", "5KKYsymog/edit\nGLOBAL BGUlSoIbNaEl SBSus SinOeLsUs SToIOluNtioSn Gs RGOroUuPp", "", ""], ["", "", "", "1"], ["", "", "GLOBAL BGUlSoIbNaEl SBSus SinOeLsUs SToIOluNtioSn Gs RGOroUuPp", ""], ["", "", "", ""], ["WRAP REPORT", "", ""], ["ELM -7084\n[TAX] Zero State Page R", "edesign", ""], ["", "Template v5.0 Updated Aug 2024\nGLOBAL BGUlSoIbNaEl SBSus SinOeLsUs SToIOluNtioSn Gs RGOroUuPp", "", ""], ["", "", "", "2"], ["", "", "GLOBAL BGUlSoIbNaEl SBSus SinOeLsUs SToIOluNtioSn Gs RGOroUuPp", ""], ["", "", "", ""], [""], [""], [""], ["Business type", "", "DIWM Tax", "DIFM Tax", "Deadline"], ["Inc - In scope", "S Corp", "$489.00", "$1,169.00", "March 17"], ["", "Partnership", "$489.00", "$1,169.00", "March 17"], ["Sole prop", "Sole proprietor", "$169.00", "NA", "April 15"], ["inc (out of scope)", "corporation", "NA", "NA", "NA"], ["", "233"], [""], ["STRATEGY & APPROACH"], [""], ["CONTROL "Legacy""], [""], ["TREATMENT A - "Price Compare""], [""], ["TREATMENT B - "DIWM focus"", "TREATMENT B - "DIWM focus""], ["", ""], ["", ""], ["", ""], ["", "234"], [""], ["STRATEGY & APPROACH"], ["CONTROL "Legacy""], [""], ["TREATMENT A - "Price Compare""], [""], ["TREATMENT B - "DIWM focus"", ""], ["", ""], ["", "235"], ["", "", "QBL Tax Zero Stat", "", "", "", "Redesign\nof QBO customers\nmunicating benefits on", "", "", "", "", "", "", "", ""], ["", "", "", "", "", "", "", "", "", "", "", "", "", "", ""], ["", "", "", "", "", "", "", "", "", "", "", "", "", "", ""], ["", "", "", "", "", "", "", "", "", "", "", "", "", "", ""], ["", "", "", "", "", "", "", "", "", "", "", "", "", "", ""], ["", "", "", "", "", "", "", "", "", "Learnings & Implications\n● Overall tax starts are at 102 ITC for T1, but the merchandising\nA\nperformance is mixed\nB ● DIWM Un Inc customers account for ~70% of starts, T1 has shown a\n120 ITC.\nC● The goodness observed in DIFM - Inc group for T1 is not enough to\ncompensate for the drop in DIWM - Inc gGrloobuapl B ucsuinsestso Smoluetirosn.s Group 236", "", "", "", "", ""], ["", "Business Impact: POSITIVE NEGATIVE\nBIZ IMPACT BIZ IMPACT\nRedesigned QBL Tax LP has delivered sig. higher starts for\nInc) customers (120 ITC , + 150) & will deliver +2100 start\nRedesigned QBL Tax LP has delivered negative performanc\ntype customers, we recommend roll back to control group", "", "", "", "", "Sole prop (DIWM Un\ns by end of peak season.\ne across other biz entity", "", "", "", "", "", "", "", ""], ["", "", "", "", "", "", "", "Un\nason.\nentity", "", "", "", "", "", "", ""], ["", "", "", "", "", "", "Sole prop (DIWM", "Un", "", "", "", "", "", "", ""], ["", "", "", "", "", "", "s by end of peak se\ne across other biz", "", "", "", "", "", "", "", ""], ["", "", "", "", "", "", "design.", "", "", "", "", "", "", "", ""], ["", "", "", "", "", "", "", "", "", "", "", "", "", "", ""], ["", "", "", "", "", "", "", "", "", "", "", "", "", "", ""], ["", "", "", "FLAT &\nROLL OUT", "", "", "", "", "", "", "", "", "", "", ""], ["", "", "", "", "", "", "", "", "", "", "", "", "Use this google\ntemplate for KPIs", "", ""], ["", "", "", "", "", "", "", "", "", "", "", "", "", "", ""], [""], [""], ["", "T1", "T2", "Con.", "Δ T1", "Δ T2", "ITC - T1", "ITC - T2"], ["Assignments", "19,731", "20,148", "20,113", "", "", "", ""], ["Total Starts", "1,304", "1,074", "1,283", "21", "-209", "102 A", "84"], ["DIWM, Inc", "274", "359", "429", "-155", "-70", "64", "84"], ["DIFM, Inc", "75", "37", "49", "26", "-12", "C\n153", "76"], ["DIWM, Un Inc", "955", "678", "805", "150", "-127", "119", "84 B"], ["M - Inc gGrloobuapl B ucsuinsestso Smoluetiro", "sn.s Group", "236"], ["Use this google"], ["emplate for KPIs"]] | V21: Campaign re-appears on slide 232 (gap from slide 13) | Alt TO (slide 232): IOluNtioSn Gs RGOroUuPp 232 | Alt TO (slide 233): mers - ~1Mn traffic for TY 23 - 25k Starts for TY 23 | Alt TO (slide 235): rship | Alt Date (slide 236): 24-12-16 | Alt TO (slide 236): 25-01-15 | Date source: CSV - Current Target Launch Date | Name source: CSV | Business Impact updated from Results Report | Status enriched from Results Report | TO could not be extracted (garbled_text) | W21: 13-236 | X21: Copy of FY'25_ CRM Analytics Monthly Experiment_Notebook_AC.pdf | Copy of FY'26_ CRM Analytics Monthly Experiment Review AC.pptx | Y21: ✅ ELM Roadmap | ✅ Results Report | Z21: QBO/QBSP Customers who have not signed-up for 2024 tax year | AA21: [Not extractable - garbled_text] (Inferred for review) | AB21: communicating benefits on By making them feel secure and Start QBL Tax for 2024 tax season
A22: ELM-7172 | B22: QB Live DIWM Build Habits | C22: 01-30-2025 | D22: GET: Existing DIWM Customers that have completed their first call TO: Drive DIWM engagement among attached customers (30+ days) in their business journey to continue to utilize the service and connect with an expert through contextualized messages, especially during those critical moments of need and changes in their business. Leverage personalization to KPIs centered around increasing DIWM 92-day retention. (Inferred for review) BY: reminding them To To schedule their second+ call | E22: IF: we drive customers to schedule their second/third call THEN: we will | F22: • Treatment has driven +44 units over a month, showing the impact of personalised messaging in driving diwm calls and retention The communications had stat sig impact on 31D QBO Ret, driving Cohort Assigns Coverage Clicks CTR Δ ITB • Overall Unq CTR is observed Control 33,868 0 0 NA TBD TBD to be performing at 168 ITB, IPD Benchmark ** 2.75% efforts from IPDs The IPDs are observed to treatment_name accesspointname ipd_viewed ipd_clicked CTR benchmark ITB QBO Dashboard - benchmarks across Chart of Accounts - Treatment Banking - Hellobox 13,860 119 0.86% 0.43% 198 Reports - Hellobox 322 1 0.31% 0.12% 265 Personalised message based Bottom Drawers encouraging customers to get help for Reconciliation, clear Uncategorised Transactions, Invoicing and generic call schedule messaging had >1% Unq CTR Personalised emails had performed better than benchmarks across open rate and mainly at CTR, driven mostly due to personalised messaging | G22: Personalized message increased call rate vs. control at 101.3 ITC • IPD ads with personalised message had performed at 168 ITB • Emails had higher open rates (>150 ITB) and CTR (>100 ITB) driven due to personalisation • NEXT STEPS & IMPLICATIONS • Test concluded with POSITIVE results. ELM rolled out the test as the new DIWM evergreen on 4/23/25. • Consider testing the personalisation over FTU & XSLL goals to have higher impact and unit growth. • Results: POSITIVE NEGATIVE BIZ IMPACT BIZ IMPACT | H22: Multiple Attributes had to be built from ground due to non availability of data in CM • Dashboard tips IPD is the only IPD with 19 ITB. • FLAT & | I22: Business Impact: POSITIVE BIZ IMPACT Treatment delivered significantly higher DIWM GNS 44 Units) & QBO saved Units (100.12 ITC , + 41 U Annual estimate : 260 - incremental DIWM & 220 Q Units (100.15 ITC , + nits) BO saved units Deck Objective Get Existing DIWM Customers that have completed their first call To To schedule their second+ call By Reminding them of how the DIWM service can help them during their moments of need, and driving them to schedule a call Hypothesis If we drive customers to schedule their second/third call , Then we will increase 92D Retention -- Increasing 92D Retention By 101 ITC Results - expected 01/31 - 03/24 KPIs TEST CON. Δ ITC Assignments 34,135 33,868 31D DIWM Ret. 95.08% 94.95% 44 100.15 81% 31D QBO Ret 98.15% 98.03% 41 100.12 86% 31D Activation 41.06% 40.60% 157 C101.13 31D Eco Rev $233.88 $234.31 -$0.43 100 LAT & ROLL OUT RESULTS RESULTS Detailed performance summary - IPD Insights A• Overall Unq CTR is observed to be performing at 168 ITB, due to strong personalization efforts from IPDs B• The IPDs are observed to perform better than benchmarks across accesspoints except Dashboard Tips IPDs Cohort IPD Assigns Coverage Clicks CTR Δ ITB Control 33,868 0 0 NA TBD TBD Treatment 34,135 84% 1325 4.62% 4.62% 168 A IPD Benchmark ** 2.75% treatment_name accesspointname ipd_viewed ipd_clicked CTR benchmark ITB Treatment QBO Dashboard - Bottom Drawer 25,414 1,117 4.40% 2.41% B 183 183 Chart of Accounts - Hellobox 15,653 98 0.63% 0.15% 405 Banking - Hellobox 13,860 119 0.86% 0.43% 198 Dashboard - Tips 2,179 9 0.41% 2.16% 19 Items - Hellobox 423 2 0.47% 0.35% 137 Reports - Hellobox 322 1 0.31% 0.12% 265 Results: POSITIVE NEGATIVE BIZ IMPACT BIZ IMPACT LAT & ROLL OUT RESULTS offerid Message ipd viewed unq unq_ctr 3da49190-ca04-11ef-9bda-7faf0370dd41 Reconcilation 12,255 1.62% A 235d9dd0-c94c-11ef-91f9-e39c6a79a902 Uncat Trx 14,381 1.11% f507b060-cc70-11ef-91f9-e39c6a79a902 Invoicing 7,531 1.08% a113a240-d1e1-11ef-a537-738f6e90746e Sch call 2 18,098 1.02% 3f4c2e70-ca01-11ef-91f9-e39c6a79a902 Chart of accounts 1,622 0.92% 106ef0c0-d1d5-11ef-b3db-89eef14459e0 grow biz - sch call 1 18,157 0.90% e6e32f70-d1e1-11ef-a537-738f6e90746e grow biz - sch call 3 18,095 0.87% 0e9ce6c0-cc6d-11ef-91f9-e39c6a79a902 Custom reports 12,169 0.80% b450c390-c9ff-11ef-91f9-e39c6a79a902 Connect bank 5,928 0.62% 2e724ed0-c94e-11ef-91ea-59bb3731ce09 P & L report run 16,183 0.61% f8310e70-cc71-11ef-91ea-59bb3731ce09 Bills 18,232 0.54% Results: POSITIVE NEGATIVE BIZ IMPACT BIZ IMPACT LAT & ROLL OUT RESULTS RESULTS Detailed performance summary - Email ASSET_NAME sent_count open_count open rate ITB click_count CTR ITB unsub rate Results: POSITIVE NEGATIVE BIZ IMPACT BIZ IMPACT LAT & ROLL OUT RESULTS Test concluded with POSITIVE results. ELM rolled out the test as the new DIWM evergreen on 4/23/25. • Consider testing the personalisation over FTU & XSLL goals to have higher impact and unit growth. | J22: QBO Live | K22: IPD; Email | L22: Trending Positive | Results: 5.1 MEASURE: Complete | M22: BIZ IMPACT +41 units over a month. Treatment delivered significantly higher DIWM GNS Units (100.15 ITC , + 44 Units) & QBO saved Units (100.12 ITC , + 41 Units) • Personalised messaging drove +157 more calls, instrumental in driving GNS saves. Annual estimate : 260 - incremental DIWM & 220 QBO saved units [Results Report] | ITC-1: 100.17 | N22: https://docs.google.com/presentation/d/1WHrx-bvV-N9RpttWwVuYgQxd1vpZXFm7lAvFuGYH4Eg/edit?usp=sharing | O22: Retention Rate | P22: 100.17 | U22: [["WRAP REPORT", "", ""], ["ELM - 7172\nQB Live DIWM Bui", "ld Habits", ""], ["Link", ""], ["", "Link"], ["", "Link"], ["", "Template v5.0 Updated Aug 2024\nGLOBAL BGUlSoIbNaEl SBSus SinOeLsUs SToIOluNtioSn Gs RGOroUuPp", "", ""], ["", "", "GLOBAL BGUlSoIbNaEl SBSus SinOeLsUs SToIOluNtioSn Gs RGOroUuPp", ""], ["", "", "EXPERIMENT RESULTS", "", "", "", "", "", ""], ["", "", "QB Live DIWM", "", "", "Habits\nld the habit of\nreminding them\nge post-purchase\ng to better", "", "", ""], ["", "Business Impact: POSITIVE\nBIZ IMPACT\nTreatment delivered significantly higher DIWM GNS\n44 Units) & QBO saved Units (100.12 ITC , + 41 U\nAnnual estimate : 260 - incremental DIWM & 220 Q", "", "", "", "", "", "", ""], ["", "", "", "", "", "Units (100.15 ITC , +\nnits)\nBO saved units", "", "", ""], ["Deck"], ["Objective\nGet Existing DIWM Customers that have completed their first call\nTo To schedule their second+ call\nBy Reminding them of how the DIWM service can help them during their\nmoments of need, and driving them to schedule a call\nHypothesis\nIf we drive customers to schedule their second/third call , Then we will\nincrease 92D Retention -- Increasing 92D Retention By 101 ITC\nResults - expected 01/31 - 03/24", "", "", "", "", "", "", ""], ["KPIs", "TEST", "CON.", "Δ", "ITC", "", "", ""], ["Assignments", "34,135", "33,868", "", "", "", "", ""], ["31D DIWM Ret.", "95.08%", "94.95%", "44", "100.15", "", "81%", ""], ["31D QBO Ret", "98.15%", "98.03%", "41", "100.12", "", "86%", ""], ["31D Activation", "41.06%", "40.60%", "157", "C101.13", "", "", ""], ["31D Eco Rev", "$233.88", "$234.31", "-$0.43", "100", "", "", ""], ["", "115"], ["FLAT &\nROLL OUT", ""], ["RESULTS"], ["RESULTS\nDetailed performance summary - IPD", ""], ["", "Insights\nA● Overall Unq CTR is observed\nto be performing at 168 ITB,\ndue to strong personalization\nefforts from IPDs\nB● The IPDs are observed to\nperform better than\nbenchmarks across\naccesspoints except\nDashboard Tips IPDs"], ["Cohort", "IPD", "", "", "", "", ""], ["", "Assigns", "Coverage", "Clicks", "CTR", "Δ", "ITB"], ["Control", "33,868", "0", "0", "NA", "TBD", "TBD"], ["Treatment", "34,135", "84%", "1325", "4.62%", "4.62%", "168 A"], ["", "IPD Benchmark **", "", "2.75%", "", "", ""], ["treatment_name", "accesspointname", "ipd_viewed", "ipd_clicked", "CTR", "benchmark", "ITB", "", ""], ["Treatment", "QBO Dashboard -\nBottom Drawer", "25,414", "1,117", "4.40%", "2.41%", "B\n183", "", ""], ["", "Chart of Accounts -\nHellobox", "15,653", "98", "0.63%", "0.15%", "", "405", ""], ["", "Banking - Hellobox", "13,860", "119", "0.86%", "0.43%", "", "198", ""], ["", "Dashboard - Tips", "2,179", "9", "0.41%", "2.16%", "", "19", ""], ["", "Items - Hellobox", "423", "2", "0.47%", "0.35%", "", "137", ""], ["", "Reports - Hellobox", "322", "1", "0.31%", "0.12%", "", "265", ""], ["Results: POSITIVE NEGATIVE\nBIZ IMPACT BIZ IMPACT", "", ""], ["", "FLAT &\nROLL OUT", ""], ["RESULTS"], ["offerid", "Message", "ipd viewed unq", "unq_ctr", "", ""], ["3da49190-ca04-11ef-9bda-7faf0370dd41", "Reconcilation", "12,255", "", "1.62%", "A"], ["235d9dd0-c94c-11ef-91f9-e39c6a79a902", "Uncat Trx", "14,381", "", "1.11%", ""], ["f507b060-cc70-11ef-91f9-e39c6a79a902", "Invoicing", "7,531", "", "1.08%", ""], ["a113a240-d1e1-11ef-a537-738f6e90746e", "Sch call 2", "18,098", "", "1.02%", ""], ["3f4c2e70-ca01-11ef-91f9-e39c6a79a902", "Chart of accounts", "1,622", "0.92%", "", ""], ["106ef0c0-d1d5-11ef-b3db-89eef14459e0", "grow biz - sch call 1", "18,157", "0.90%", "", ""], ["e6e32f70-d1e1-11ef-a537-738f6e90746e", "grow biz - sch call 3", "18,095", "0.87%", "", ""], ["0e9ce6c0-cc6d-11ef-91f9-e39c6a79a902", "Custom reports", "12,169", "0.80%", "", ""], ["b450c390-c9ff-11ef-91f9-e39c6a79a902", "Connect bank", "5,928", "0.62%", "", ""], ["2e724ed0-c94e-11ef-91ea-59bb3731ce09", "P & L report run", "16,183", "0.61%", "", ""], ["f8310e70-cc71-11ef-91ea-59bb3731ce09", "Bills", "18,232", "0.54%", "", ""], ["Results: POSITIVE NEGATIVE\nBIZ IMPACT BIZ IMPACT", "", ""], ["", "FLAT &\nROLL OUT", ""], ["RESULTS"], ["RESULTS\nDetailed performance summary - Email", "", "", "", "", "", "", "", "", "", "", "", ""], ["", "ASSET_NAME", "sent_count", "open_count", "open rate", "ITB", "click_count", "", "CTR", "ITB", "", "unsub rate", ""], ["Results: POSITIVE NEGATIVE\nBIZ IMPACT BIZ IMPACT", "", ""], ["", "FLAT &\nROLL OUT", ""], ["RESULTS"], ["HIGHLIGHTS", "", "LOWLIGHTS"], ["● Personalized message increased call rate vs. control\nat 101.3 ITC\n● IPD ads with personalised message had performed\nat 168 ITB\n● Emails had higher open rates (>150 ITB) and CTR\n(>100 ITB) driven due to personalisation", "", "● Multiple Attributes had to be built from ground due to non\navailability of data in CM\n● Dashboard tips IPD is the only IPD with 19 ITB."], ["NEXT STEPS & IMPLICATIONS", "", ""], ["● Test concluded with POSITIVE results. ELM rolled out the test as the new DIWM evergreen on 4/23/25.\n● Consider testing the personalisation over FTU & XSLL goals to have higher impact and unit growth.", "", ""], ["Results: POSITIVE NEGATIVE\nBIZ IMPACT BIZ IMPACT", "", ""], ["", "FLAT &\nROLL OUT", ""]] | V22: Alt TO (slide 115): 04/26/25 | Alt TO (slide 116): be performing at 168 ITB, | Alt Product (slide 117): Invoicing | Alt GET (slide 117): help for Reconciliation, clear Uncategorised Transactions, | Alt TO (slide 117): m Drawer | Alt Campaign Name (slide 118): EM-US-QBL-QBLAST-DOMEQL-RET-PROD-NA-EQ-QBLDIWMBuildHabits_TRT336318_002 68,860 28,659 41.62% 166 A 1,245 1.81% 181 A 0.00% | Alt TO (slide 118): personalised messaging | Alt Campaign Name (slide 119): DIWM personalization test delivered stat sig. positive results of 100.17 ITC | Alt Date (slide 119): 4/23/25 | Alt GET (slide 119): to manually send the wrap | Alt TO (slide 119): DIWM Customers drove more customers to schedule their beyond first calls with an expert within the first 31D | Date source: CSV - Current Target Launch Date | Name source: CSV | Business Impact updated from Results Report | Status enriched from Results Report | TO replaced with CSV Project Description (was: garbled_text) | W22: 114-119 | X22: Copy of FY'25_ CRM Analytics Monthly Experiment_Notebook_AC.pdf | Y22: ✅ ELM Roadmap | ✅ Results Report | Z22: Existing DIWM Customers that have completed their first call | AA22: Drive DIWM engagement among attached customers (30+ days) in their business journey to continue to utilize the service and connect with an expert through contextualized messages, especially during those critical moments of need and changes in their business. Leverage personalization to KPIs centered around increasing DIWM 92-day retention. (Inferred for review) | AB22: reminding them To To schedule their second+ call
A23: ELM-7266 | B23: QB Live DIWM Winback | C23: 01-28-2025 | D23: GET: Lapsed and Cancelled DIWM/DIFM Customers TO: [NEW] Repurposing this to be a winback campaign for lapsed and cancelled DIWM Trial/DIFM Cancels to get them to resubscribe. [OLD] Customers who have not used DIWM ever or who have not engaged recently are good candidates for activation campaigns focused on benefits to drive first call/activation. (Inferred for review) | E23: IF: [NEW] Repurposing this to be a winback campaign for lapsed and cancelled DIWM Trial/DIFM Cancels to get them to resubscribe. [OLD] Customers who have not used DIWM ever or who haven't engaged recently are good candidates for activation campaigns focused on benefits to drive first call/activation (Inferred for review) THEN: Not found (Inferred for review) | F23: • Treatment drove ~88 incremental units in ~3.5 weeks IPDs drove >120 ITC incremental resub units when sent within 150 days of first signup (i.e., <120 days post-trial) PDs drove just >105 ITC incremental resub units for customers beyond 150 days of first signup (i.e., >120 days IPD Viewed → Clicked has seen highest drop of 98%, though flat with benchmark there is room for IPD Clicked → GNS number can be improved via LP Personalisation and targetted product or pricing offers Coverage at 97% is driven by effective usage of high traffic access points like Shell Banner, BD. etc The Unq CTR is at 96 ITB, showcasing room for improvement. • Personalisation of IPDs further is an opportunity. **Benchmark is calculated for XSLL campaigns in same time frame as experiment | G23: Driving communications to DIWM trial lapsed customers have shown incremental unit impact with no harm on ecosystem • 3 attributes were onboarded which were used for multiple campaigns , leveraging the Insights Repository • NEXT STEPS & IMPLICATIONS • Results: POSITIVE NEGATIVE BIZ IMPACT BIZ IMPACT • WRAP REPORT • Reimagined P Cancel Flow • Template v5.1 Updated Oct. 2024 GLOBAL BGUlSoIbNaEl SBSus SinOeLsUs SToIOluNtioSn Gs RGOroUuPp | H23: Daily report table is not available • Had to build attributes that were used to target customers for contextual IPDs • FLAT & • ayroll • GLOBAL BGUlSoIbNaEl SBSus SinOeLsUs SToIOluNtioSn Gs RGOroUuPp | I23: Results: POSITIVE NEGATIVE BIZ IMPACT BIZ IMPACT LAT & ROLL OUT WRAP REPORT Reimagined P Cancel Flow ayroll Template v5.1 Updated Oct. 2024 GLOBAL BGUlSoIbNaEl SBSus SinOeLsUs SToIOluNtioSn Gs RGOroUuPp 1 GLOBAL BGUlSoIbNaEl SBSus SinOeLsUs SToIOluNtioSn Gs RGOroUuPp IPDs drove >120 ITC incremental resub units when sent within 150 days of first signup (i.e., <120 days post-trial) PDs drove just >105 ITC incremental resub units for customers beyond 150 days of first signup (i.e., >120 days & Implications IPD Viewed → Clicked has seen highest drop of 98%, though flat with benchmark there is room for improvement here IPD Clicked → GNS number can be improved via LP Personalisation and targetted product or pricing offers Coverage at 97% is driven by effective usage of high traffic access points like Shell Banner, BD. etc The Unq CTR is at 96 ITB, showcasing room for improvement. Personalisation of IPDs further is an opportunity. **Benchmark is calculated for XSLL campaigns in same time frame as experiment Improve Funnel : Consider personalization of landing pages for next iteration. Personalised Targeted Offers: Consider testing pricing offer for low to high price sensitivity customers for incremental revenue impact Expanding product targeting: For customers who are beyond 150 Days from DIWM signup, recommendation is to push this cohort to cross sell efforts. | J23: QBO Live | K23: IPD; Email | L23: Trending Positive (Inferred for review) | Results: 5.1 MEASURE: Complete | M23: BIZ IMPACT • Flat Impact on Ecosystem across products and 31D Treatment delivered significantly higher DIWM GNS Units (113 ITC , + 88 QBO revenue Units); Annual estimate : 750 incremental units [Results Report] | ITC-1: 113 | ITC-2: 101 | N23: https://docs.google.com/presentation/d/1TZoTolSstpqBXxc_FwJiP4Lh4KGQctgpNOzymzZSTg8/edit?usp=sharing | O23: GNS/GNA | P23: 113 | Q23: Ecosystem Revenue | R23: 101 | S23: Ecosystem Revenue | U23: [["WRAP REPORT", "", ""], ["ELM - 7266\nQBL DIWM Winbac", "k", ""], ["Link", ""], ["", "Link"], ["", "Link"], ["", "Template v5.0 Updated Aug 2024\nGLOBAL BGUlSoIbNaEl SBSus SinOeLsUs SToIOluNtioSn Gs RGOroUuPp", "", ""], ["", "", "GLOBAL BGUlSoIbNaEl SBSus SinOeLsUs SToIOluNtioSn Gs RGOroUuPp", ""], ["", "", "EXPERIENCE", "", "", "", ""], ["", "", "", "", "Treatment", "", ""], ["", "", "", "", "A", "", ""], ["A", ""], ["FLAT &\nROLL OUT", ""], ["Intuit Confidential and Pr", "oprietary", "178"], ["", "Business Impact: POSITIVE\nBIZ IMPACT\nTreatment delivered significantly higher DIWM GNS\nUnits); Annual estimate : 750 incremental units", "", "", "", "", "", "", "Units (113 ITC ,", "", "+ 88", "", ""], ["KPIs", "TEST", "CON.", "Δ", "ITC", "Prob. (T>C)", "", ""], ["Assignments", "67,351", "67,113", "", "", "", "", ""], ["31D DIWM GNS", "757", "669", "88", "113", "96%", "", ""], ["31D Eco Rev", "$115.11", "$114.37", "$0.73", "101", "B", "", ""], ["31D QBO Rev", "$77.82", "$77.40", "$0.42", "101", "", "", ""], ["31D Payments Rev", "$16.49", "$16.51", "-$0.01", "100", "", "", ""], ["FLAT &\nROLL OUT", ""], ["treatment_name", "age_segment", "assigns", "diwm_gns", "cr"], ["Control-ELM7266", "150+", "35,337", "298", "0.84"], ["Control-ELM7266", "45-150", "31,291", "372", "A 1.19"], ["Treatment-ELM7266", "150+", "35,409", "303", "0.86"], ["Treatment-ELM7266", "45-150", "31,441", "450", "A 1.43"], ["Intuit Confidential and Pr", "oprietary", "180"], ["3%", "98% A", "91% B"], ["Loss", "Loss", "Loss"], ["Intuit Confidential and Pr", "oprietary", "181"], ["CHANNEL WISE PERFORMANCE"], ["Cohort", "IPD", "", "", "", "", ""], ["", "Coverage", "Imp.", "Clicks", "CTR", "Δ", "ITB"], ["TEST", "97% A", "65,188", "1,557", "2.39%", "2.39%", "96 B"], ["CONTROL", "0%", "0", "0.0%", "0.00%", "0.00%", "TBD"], ["IPD Benchmark **", "", "", "2.50%", "", "", ""], ["Results: POSITIVE NEGATIVE\nBIZ IMPACT BIZ IMPACT", "", ""], ["", "FLAT &\nROLL OUT", ""], ["Delivering personalized and contextualized IPDs to DIWM lapsed trailers, DIWM cancelled customers and DIFM\ncancelled customers drove more customers to purchase DIWM (113 ITC, +88 incremental units) over the control\nexperience. Roll out estimated to deliver: 750 incremental units.", "", ""], ["HIGHLIGHTS", "", "LOWLIGHTS"], ["● Driving communications to DIWM trial lapsed\ncustomers have shown incremental unit impact with\nno harm on ecosystem\n● 3 attributes were onboarded which were used for\nmultiple campaigns , leveraging the Insights\nRepository", "", "● Daily report table is not available\n● Had to build attributes that were used to target customers\nfor contextual IPDs"], ["NEXT STEPS & IMPLICATIONS", "", ""], ["Results: POSITIVE NEGATIVE\nBIZ IMPACT BIZ IMPACT", "", ""], ["", "FLAT &\nROLL OUT", ""], ["WRAP REPORT", "", ""], ["Reimagined P\nCancel Flow", "ayroll", ""], ["", "Template v5.1 Updated Oct. 2024\nGLOBAL BGUlSoIbNaEl SBSus SinOeLsUs SToIOluNtioSn Gs RGOroUuPp", "", ""], ["", "", "GLOBAL BGUlSoIbNaEl SBSus SinOeLsUs SToIOluNtioSn Gs RGOroUuPp", ""]] | V23: Alt Product (slide 179): Payments | Alt TO (slide 179): 02-22-25 | Alt Campaign Name (slide 180): 150+ 35,337 298 0.84 | Alt TO (slide 180): mers beyond 150 days of first signup (i.e., >120 days | Alt GET (slide 181): ted product or pricing offers | Alt status (slide 181): Flat | Alt BY (slide 182): effective usage of high traffic access points like Shell Banner, BD. etc | Alt GET (slide 183): customers | Alt TO (slide 183): DIWM lapsed trailers, DIWM cancelled customers and DIFM | Alt Product (slide 184): Payroll | Alt TO (slide 184): IOluNtioSn Gs RGOroUuPp 184 | Date source: CSV - Current Target Launch Date | Name source: CSV | Business Impact updated from Results Report | Status enriched from Results Report | TO replaced with CSV Project Description (was: garbled_text) | W23: 176-184 | X23: Copy of FY'25_ CRM Analytics Monthly Experiment_Notebook_AC.pdf | Y23: ✅ ELM Roadmap | ✅ Results Report | Z23: Lapsed and Cancelled DIWM/DIFM Customers | AA23: [NEW] Repurposing this to be a winback campaign for lapsed and cancelled DIWM Trial/DIFM Cancels to get them to resubscribe. [OLD] Customers who have not used DIWM ever or who have not engaged recently are good candidates for activation campaigns focused on benefits to drive first call/activation. (Inferred for review) | AB23: Get Lapsed and Cancelled DIWM/DIFM Customers
A24: ELM-7268 | B24: DIWM QB Live DIWM Trial Conversion Optimization TEST | C24: 01-30-2025 | D24: GET: QBO Buy Now subscribers currently on DIWM Trial TO: FY'25 Funnel Optimization initiative. Create a unified shopping experience for QBO NTTF, FTU customers whose subscription includes a QB Live Expert Assisted 30-day trial that optimizes the value of the service from the point of purchase thru onboarding. (Inferred for review) BY: making them feel X, by having them think Y and doing Z. | E24: IF: we create a new and optimized experience to help drive FTU customers who are eligible for the DIWM 1-month free trial to convert into paid subscribers by offering them a 50% off promo for their first 3 months. THEN: we will increase DIWM trial conversion by 0.3 pts. | F24: • The benefits message to NTTF DIWM Trialers resulted in 97 ITC and Tax urgency message yielded 87 ITC delivering units loss Treatment 2 The revenue is trending positive, but since the units loss is observed | I24: Rollback to control experience [Results Report] | ITC-1: 97 | ITC-2: 103 | ITC-3: 103 | J24: QBO Live | K24: IPD; Email | L24: Trending Positive | Results: 5.1 MEASURE: Complete | M24: we recommend rollback to control Changing the messaging to benefits based or tax based urgency message has resulted in 97 ITC and 87 ITC. Recommendation: Rollback to control experience [Results Report] | ITC-1: 97 | ITC-2: 103 | ITC-3: 103 | N24: https://docs.google.com/presentation/d/1DSuh5UzrZ22IkfjBL8zjlW5ImWwMxGmpOVNsyH6UhxY/edit#slide=id.g2efff53d832_0_813 | O24: Trial Conversion Rate | P24: 97 | Q24: Ecosystem Revenue | R24: 103 | S24: Ecosystem Revenue | T24: 103 | U24: [["WRAP REPORT", "", ""], ["ELM - 7268\nDIWM Trial Conver\noptimization test", "sion", ""], ["Link", ""], ["", "Link"], ["", "Template v5.0 Updated Aug 2024\nGLOBAL BGUlSoIbNaEl SBSus SinOeLsUs SToIOluNtioSn Gs RGOroUuPp", "", ""], ["", "", "GLOBAL BGUlSoIbNaEl SBSus SinOeLsUs SToIOluNtioSn Gs RGOroUuPp", ""], ["EXPERIMENT RESULTS\nDIWM Trial Conversion opt\nWe are testing a new optimized and experie\nFTU customers who are eligible for the DIW\ntrial to convert into paid subscribers by offer\noff promo for their first 3 months.\nBusiness Impact: INCONCLUSIVE\nTRENDING NEGATIVE\nChanging the messaging to benefits based or tax based u\nresulted in 97 ITC and 87 ITC. Recommendation: Rollbac", "", "EXPERIMENT RESULTS", "", "", "", "imization\nnce to help drive\nM 1-month free\ning them a 50%\nControl\nTreatment 1\nTreatment 2", "", "", "", "", ""], ["", "", "DIWM Trial Conver", "", "", "", "imization\nnce to help drive\nM 1-month free\ning them a 50%", "", "", "", "", ""], ["", "", "", "", "", "", "Treatment 2", "", "", "", "", ""], ["", "", "", "", "", "", "", "", "", "", "", "Learnings & Implications\nA● The benefits message to NTTF DIWM Trialers resulted in 97 ITC and\nTax urgency message yielded 87 ITC delivering units loss\nB● The revenue is trending positive, but since the units loss is observed\nwe recommend rollback to control"], ["", "", "", "", "", "", "", "Treat", "ment 2", "", "", "Tax urgency message yielded 87 ITC delivering units loss\nB● The revenue is trending positive, but since the units loss is observed\nwe recommend rollback to control"], ["", "Business Impact: INCONCLUSIVE\nTRENDING NEGATIVE\nChanging the messaging to benefits based or tax based u\nresulted in 97 ITC and 87 ITC. Recommendation: Rollbac", "", "", "", "", "rgency message h", "", "as", "", "", ""], ["", "", "", "", "", "", "k to control experie", "", "nce", "", "", ""], ["Control", ""], ["KPIs", "Treat. 1", "Treat. 2", "Con.", "Δ vs T1", "ITC vs T1", "Δ vs T2", "ITC vs T2"], ["Assignments", "15,378", "15,252", "15,430", "", "A", "", "A"], ["31D DIWM Conv.", "2.46%", "2.19%", "2.53%", "-11", "97", "-52", "87"], ["31D Eco Rev.", "$53.50", "$53.79", "$52.17", "$1.34", "103 B", "$1.62", "103 B"], ["ELM Coverage", "92%", "93%", "68%", "", "135", "", "137"], ["Treatment 1", ""], ["FLAT &\nROLL OUT", ""]] | V24: Alt TO (slide 121): 04/26/25 | Date source: CSV - Current Target Launch Date | Name source: CSV | Business Impact updated from Results Report | Status enriched from Results Report | TO replaced with CSV Project Description (was: garbled_text) | W24: 120-121 | X24: Copy of FY'25_ CRM Analytics Monthly Experiment_Notebook_AC.pdf | Y24: ✅ ELM Roadmap | ✅ Results Report | Z24: QBO Buy Now subscribers currently on DIWM Trial | AA24: FY'25 Funnel Optimization initiative. Create a unified shopping experience for QBO NTTF, FTU customers whose subscription includes a QB Live Expert Assisted 30-day trial that optimizes the value of the service from the point of purchase thru onboarding. (Inferred for review) | AB24: making them feel X, by having them think Y and doing Z.
