Workbook

Sheet Campaigns
A1: Campaign ID | B1: Campaign Name | C1: Date of Campaign Launch | D1: Strategic Framework - GET | E1: Strategic Framework - TO | F1: Strategic Framework - BY | G1: Strategic Framework (Full GET/TO/BY) | H1: Hypothesis (IF/THEN) | I1: Learning | J1: Product | K1: Channels Included | L1: Campaign Success Status | M1: Business Impact | N1: Wrap Report Link | O1: Primary Experiment Metric 1 | P1: ITC - 1 | Q1: Primary Experiment Metric 2 | R1: ITC - 2 | S1: Primary Experiment Metric 3 | T1: ITC - 3 | U1: Table Data | V1: Misc | W1: Slide Number(s) | X1: Slide Deck Name
A2: ELM-8343 | B2: [DIWM] Test 2-Click Conversion on IPDs | C2: 09-15-2025 | D2: Existing QBO customer | E2: PIC TIME | F2: Reducing the cognitive load on customers by taking them directly to the | G2: GET: Existing QBO customer | TO: PIC TIME | BY: Reducing the cognitive load on customers by taking them directly to the | H2: If we send customers straight to the billing page, Then we reduce the | I2: Repository Upgrade - ELM 6651 12 Min Manasa / Sowmya Global Business Solutions Group 6 & Implications 0d-90d assigns 4,373 4,162 ●A +8.3% lift in DIWM SU for Accountant Attached 31D DIWM SU 0.57% 0.65% 113 NA (366d+) users (ITC = 108, 94% confidence) 91d-365d assigns 25,412 25,493 Accountant ●B +5% lift for Non-Accountant Attached (366d+) Attached 31D DIWM SU 0.31% 0.30% 96 NA users (ITC = 105) 366d+ assigns 411,510 413,420 A 31D DIWM SU 0.21% 0.23% 108 94% 0d-90d assigns 5,271 5,269 31D DIWM SU 2.28% 2.16% 95 Non 91d-365d assigns 19,488 19,448 Accountant 31D DIWM SU 0.79% 0.78% 98 B Attached 366d+ assigns 216,138 215,723 31D DIWM SU 0.30% 0.31% 105 71% This, Indicates “fewer steps to purchase” or simplified messaging resonates most with mature, embedded QBO users who are already familiar with workflows., Minimal or negative movement in <1 year cohorts suggests need for differentiated onboarding or guidance messaging for newer users. Global Business Solutions Group 9 Segment qbo_age treatment Imp. Clicks CTR Δ ITC ● Accountant Attached: All cohorts (0–90d, 91–365d, 0d-90d Control 2,681 22 0.82% A A 366d+) show lower CTR and ITC, indicating weaker 0d-90d Treatment 2,581 14 0.54% -0.28% 66 response to treatment. Accountant 366d+ Control 244,169 1,180 0.48% Attached 366d+ Treatment 245,789 989 0.40% -0.08% 83 B● Non-Accountant Attached: 91–365d and 366d+ 91d-365d Control 16,457 60 0.36% cohorts see small CTR and ITC gains, showing positive 91d-365d Treatment 16,614 50 0.30% -0.06% 83 treatment lift. 0d-90d Control 4,916 424 8.62% B 0d-90d Treatment 4,918 377 7.67% -0.96% 89 C● Overall: Treatment underperforms for Accountant Non Accountant 366d+ Control 200,472 15,319 7.64% Attached users but delivers modest uplift for Attached 366d+ Treatment 201,407 15,512 7.70% 0.06% 101 Non-Accountant Attached users. 91d-365d Control 17,951 1,214 6.76% 91d-365d Treatment 17,949 1,234 6.88% 0.11% 102 IPD Segment Cohort Imp. Clicks CTR Δ ITC Accountant Control 244,169 1,180 0.48% Attached Treatment 245,789 989 0.40% -0.08% 83 C Non Accountant Control 200,472 15,319 7.64% Attached Treatment 201,407 15,512 7.70% 0.06% 101 Global Business Solutions Group 11 into “Streamline Purchase” pillar of FODE experiments to guide future activation tests. ● Monitor eco-revenue & trial to gns conversion to validate long-term monetization impact post trial. Global Business Solutions Group 12 | J2: QBO | K2: IPD | L2: Positive | Results: 5.1 MEASURE: Complete | M2: Positive Biz Impact | 107 ITC-1 | N2: https://docs.google.com/presentation/d/1eCpJUw73_gHKVsWXHbX-LjM0QESG_Df0_YDTzfesHS4/edit?usp=sharing | O2: GNS/GNA | P2: 107 | U2: [[""], ["AGENDA"], ["TOPIC", "", "TIME"], ["1.Live - 2 Click Conversion - ELM 8343\nAneesh", "", "12 Min"], ["2.Tax - Zero State Page Optimization - ELM-8355\nAneesh", "", "12 Min"], ["3.TCO Dry Tests - ELM-8764, ELM-8929, ELM-8777\nAndre", "", "20 Min"], ["4.Insights Repository Upgrade - ELM 6651\nManasa / Sowmya", "", "12 Min"], ["Global Business Solutio", "ns Group", "6"], ["WRAP REPORT", "", ""], ["ELM - 8343- [FODE / DIW\nTest 2-Click", "M]", ""], ["Link", ""], ["", "Link"], ["", "Link"], ["", "Template v6.0 Updated Sept 2025\nGLOBAL BGUlSoIbNaEl SBSus SinOeLsUs SToIOluNtioSn Gs RGOroUuPp", "", ""], ["", "", "", "7"], ["", "", "GLOBAL BGUlSoIbNaEl SBSus SinOeLsUs SToIOluNtioSn Gs RGOroUuPp", ""], ["", "", "", ""], ["ELM EXPERIMENT RESULTS\n2-Click Conversion for IPDs\nTesting a new CTA directing DIWM free trial IPDs straight to\nthe billing flow to streamline activation. Run across digital\nchannels with simplified targeting to reduce friction and boost\ntrial starts.\nControl Experience\nIPD Clicked Landing Page Billing Page\nIPD Clicked Billing Page\nTreatment Experience\nBusiness Impact: POSITIVE\nIMPACT\n● Removing Landing Page visit after IPD Click has delivered stat sig results\nfor 366d+ QBO Customers across Non Accnt Attached and Accnt\nAttached with an estimated DIWM Signups (107 ITC, +70).\n● Roll out estimate: ~775 incremental DIWM GNS annually (assuming\n67% Conversion from trial) with +$300K incremental annual revenue.", "", "", "PRODUCTS: QBLive ● DRIVER: Name ● QB: ELM-8343 ● SOT: Deck ● DATES: ##-##-## to ##-##-##", "", "", "", "", "", "", "", "", ""], ["", "", "", "", "Objective\nGet Existing QBO customer\nTo Sign up for the consent up front DIWM free trial\nBy Reducing the cognitive load on customers by taking them directly to the\nfree trial billing page.\nHypothesis\nIf we send customers straight to the billing page, Then we reduce the\nnumber of steps to start their trial-- Increasing Trial Starts By 10%\nResults - 09/15/2025 - 09/30/2025", "", "", "", "", "", "", "", ""], ["", "", "", "", "Segment", "KPIs", "TEST", "", "CON.", "Δ", "ITC", "Prob. (T>C)", ""], ["", "", "", "", "", "", "", "", "", "", "", "", ""], ["", "", "", "", "Accountant\nAttached", "Assigns", "456,471", "", "454,727", "", "", "", ""], ["", "", "", "", "", "31D DIWM SU", "0.24%", "", "0.22%", "70", "107", "85%", ""], ["", "", "", "", "", "31D Eco rev", "$166", "", "$166", "$0.0", "100", "", ""], ["", "", "", "", "Non\nAccountant\nAttached", "Assigns", "249,208", "", "249,786", "", "", "", ""], ["", "", "", "", "", "31D DIWM SU", "0.39%", "0.39%", "0.39%", "8", "101", "", ""], ["", "", "", "", "", "", "", "", "", "", "", "", ""], ["", "", "", "", "", "31D Eco rev", "$149", "", "$149", "$0.0", "100", "", ""], ["", "", "", "", "", "", "", "", "", "", "", "", ""], ["", "", "", "", "Learnings & Implications\nA ● Overall DIWM SU: +7% lift vs. control ( Prob =\n85%).Revenue flat indicated improved activation not yet\ntranslating into higher monetization.\nB● DIWM SU: +8 Unit improvement (ITC = 101) —\nstatistically flat. Eco Rev ($149) unchanged.\nGlobal Business Solutions Group 8", "", "", "", "", "", "", "", ""], ["", "Business Impact: POSITIVE\nIMPACT\n● Removing Landing Page visit after IPD Click has delivered stat sig results\nfor 366d+ QBO Customers across Non Accnt Attached and Accnt\nAttached with an estimated DIWM Signups (107 ITC, +70).\n● Roll out estimate: ~775 incremental DIWM GNS annually (assuming\n67% Conversion from trial) with +$300K incremental annual revenue.", "", "", "", "", "", "", "", "", "", "", ""], ["", "", "t\ning\nue.", "", "", "", "", "", "", "", "", "", ""], ["", "", "", "", "", "", "", "", "", "", "", "", ""], ["ELM EXPERIMENT RESULTS"], ["2-Click Conve"], ["", "Control Experience"], ["IPD Clicked Landing Page Billing Page", ""], ["IPD Clicked", "Landing Page", "Billing Page"], ["IPD Clicked Billing Page", ""], ["", "Treatment Experience"], ["IPD Clicked", "Billing Page"], ["Global Business Solutio", "ns Group", "8"], ["", "Call Outs: A D G"], ["FLAT\nIMPACT", ""], [""], ["ELM EXPERIMENT RESULTS"], ["cohort", "QBO Age", "KPIs", "Control", "Treatment", "ITC", "Prob. (T>C)"], ["Accountant\nAttached", "0d-90d", "assigns", "4,373", "4,162", "", ""], ["", "", "31D DIWM SU", "0.57%", "0.65%", "113", "NA"], ["", "91d-365d", "assigns", "25,412", "25,493", "", ""], ["", "", "31D DIWM SU", "0.31%", "0.30%", "96", "NA"], ["", "366d+", "", "", "", "", ""], ["", "", "assigns", "411,510", "413,420", "", "A"], ["", "", "", "", "", "", ""], ["", "", "31D DIWM SU", "0.21%", "0.23%", "108", "94%"], ["Non\nAccountant\nAttached", "0d-90d", "assigns", "5,271", "5,269", "", ""], ["", "", "31D DIWM SU", "2.28%", "2.16%", "95", ""], ["", "91d-365d", "assigns", "19,488", "19,448", "", ""], ["", "", "31D DIWM SU", "0.79%", "0.78%", "98", "B"], ["", "", "", "", "", "", ""], ["", "366d+", "", "", "", "", ""], ["", "", "assigns", "216,138", "215,723", "", ""], ["", "", "31D DIWM SU", "0.30%", "0.31%", "105", "71%"], ["Global Business Solutio", "ns Group", "9"], ["Results: POSITIVE DIR. POSITIVE\nIMPACT IMPACT", "", "Call Outs: A D G"], ["", "FLAT\nIMPACT", ""], [""], ["ELM EXPERIMENT RESULTS"], ["", "Accountant Attached\nnel\n41%\nloss", "", "", "Non Accountant Attached\n7%\nloss", "Non Accountant Attached", ""], ["Control Fun", "nel", "", "", "", "", ""], ["", "", "", "", "", "", ""], ["", "", "", "", "B", "", ""], ["Test Funn", "el", "", "", "+7.2% +29%\n7%\nloss", "", ""], ["", "", "+69%", "", "", "", "+29%"], ["", "A ● Accountant Attached users, with +13% uplift in “V", "", "", "Signup” and a +69% uplift in “Clicked to 3ID Signup,” indica", "", ""], ["Global Business Solutio", "ns Group", "10"], ["Results: POSITIVE DIR. POSITIVE\nIMPACT IMPACT", "FLAT\nIMPACT", "Call Outs: A D G"], [""], ["ELM EXPERIMENT RESULTS"], ["Segment", "qbo_age", "treatment", "IPD", "", "", "", ""], ["", "", "", "Imp.", "Clicks", "CTR", "Δ", "ITC"], ["Accountant\nAttached", "0d-90d", "Control", "2,681", "22", "0.82%", "", ""], ["", "", "", "", "", "", "", ""], ["", "0d-90d", "Treatment", "2,581", "14", "0.54%", "-0.28%", "66"], ["", "366d+", "Control", "244,169", "1,180", "0.48%", "", ""], ["", "366d+", "Treatment", "245,789", "989", "0.40%", "-0.08%", "83"], ["", "91d-365d", "Control", "16,457", "60", "0.36%", "", ""], ["", "91d-365d", "Treatment", "16,614", "50", "0.30%", "-0.06%", "83"], ["Non Accountant\nAttached", "0d-90d", "Control", "4,916", "424", "8.62%", "", ""], ["", "", "", "", "", "", "", ""], ["", "0d-90d", "Treatment", "4,918", "377", "7.67%", "-0.96%", "89"], ["", "366d+", "Control", "200,472", "15,319", "7.64%", "", ""], ["", "366d+", "Treatment", "201,407", "15,512", "7.70%", "0.06%", "101"], ["", "91d-365d", "Control", "17,951", "1,214", "6.76%", "", ""], ["", "91d-365d", "Treatment", "17,949", "1,234", "6.88%", "0.11%", "102"], ["Segment", "Cohort", "IPD", "", "", "", ""], ["", "", "Imp.", "Clicks", "CTR", "Δ", "ITC"], ["Accountant\nAttached", "Control", "244,169", "1,180", "0.48%", "", ""], ["", "Treatment", "245,789", "989", "0.40%", "-0.08%", "83"], ["Non Accountant\nAttached", "Control", "200,472", "15,319", "7.64%", "", "C"], ["", "Treatment", "201,407", "15,512", "7.70%", "0.06%", "101"], ["Global Business Solutio", "ns Group", "11"], ["Results: POSITIVE DIR. POSITIVE\nIMPACT IMPACT", "", "Call Outs: A D G"], ["", "FLAT\nIMPACT", ""], [""], ["ELM EXPERIMENT RESULTS"], [""], ["The 2-Click IPD experience delivered measurable lift in trial conversion for established QBO customers, validating\nsimplified activation as a lever for future purchase flows."], ["HIGHLIGHTS", "", "LOWLIGHTS"], ["● 2-Click IPD flow delivered +7 % overall DIWM sign-ups vs\ncontrol (ITC 107 / Prob 85 %) — stat sig for 366 d+ cohorts\nacross both Accountant & Non-Accountant segments.\n● Accountant Attached (366 d+) +8.3 % lift (ITC 108) and\nNon-Accountant Attached (366 d+) +5 % lift (ITC 105),\nconfirming friction reduction improves trial activation\n● Funnel data shows strong last-step uplift (+69 % Accountant\nAttached, +29 % Non-Accountant) → simplified flow drives\nmore completions", "", "● Accountant-Attached CTR dropped (<90 ITC) across all age bands\n(0–90 d → 366 d+) indicating weaker top-of-funnel response.\n● Revenue outcomes flat so far — activation improved, but monetization\nimpact not yet realized.\n● Newer (< 1 year) QBO users showed minimal or negative response,\nsignaling need for differentiated onboarding messaging."], ["", "", ""], ["NEXT STEPS & IMPLICATIONS", "", ""], ["● Introduce 2-Click IPD across relevant journeys to further boost tax trial starts.\n● Expand to other products for tenured (366 d+) customers where flow simplification has proven effective.\n● Feed learning into “Streamline Purchase” pillar of FODE experiments to guide future activation tests.\n● Monitor eco-revenue & trial to gns conversion to validate long-term monetization impact post trial.", "", ""], ["", "", ""], ["Global Business Solutio", "ns Group", "12"], ["Results: POSITIVE DIR. POSITIVE\nIMPACT IMPACT", "", "Call Outs: A D G"], ["", "FLAT\nIMPACT", ""]] | V2: Alt TO (slide 7): IOluNtioSn Gs RGOroUuPp 7 | Alt Date (slide 8): 09/15/2025 | Alt TO (slide 8): ##-##-## | Alt TO (slide 9): purchase” or simplified messaging resonates most with mature, embedded QBO users who are already familiar with | Alt TO (slide 10): 31D Signup” and a +69% uplift in “Clicked to 3ID Signup,” indicating that the | Alt TO (slide 11): treatment. | Alt GET (slide 12): to manually send the wrap | Alt TO (slide 12): mers, validating | Date source: CSV – Current Target Launch Date | Name source: CSV | Business Impact updated from Results Report | Status enriched from Results Report | W2: 6–12 | X2: Copy of FY'25_ CRM Analytics Monthly Experiment_Notebook_AC.pdf
A3: ELM-7084 | B3: TAX Redesign Zero State LP | C3: 01-24-2025 | D3: QBO/QBSP Customers who have not signed-up for 2024 tax year | E3: IOluNtioSn Gs RGOroUuPp 13 | F3: communicating benefits on By making them feel secure and Start QBL Tax for 2024 tax season | G3: GET: QBO/QBSP Customers who have not signed-up for 2024 tax year | TO: IOluNtioSn Gs RGOroUuPp 13 | BY: communicating benefits on By making them feel secure and Start QBL Tax for 2024 tax season | H3: If the TOF is redesigned, for each +1.0 increase in the view-to-start rate* will increase QBL Tax Starts By 10,000 * Results - 24-12-16 to 25-01-15 T1 T2 Con. Δ T1 Δ T2 ITC - T1 ITC - T2 Assignments 19,731 20,148 20,113 Total Starts 1,304 1,074 1,283 21 -209 102 A 84 DIWM, Inc 274 359 429 -155 -70 64 84 C DIFM, Inc 75 37 49 26 -12 153 76 DIWM, Un Inc 955 678 805 150 -127 119 84 B Learnings & Implications ● Overall tax starts are at 102 ITC for T1, but the merchandising | I3: & Implications ● Overall tax starts are at 102 ITC for T1, but the merchandising | J3: QBO | K3: IPD; Email; Landing Page | L3: Trending Positive | Results: 5.1 MEASURE: Complete | M3: Positive Biz Impact | 120 ITC-1 | N3: https://docs.google.com/presentation/d/1DZ46Q5JkxjkSYMQpgnr5bjD-PMn4pnpNAlaZNQ2C35E/edit?usp=sharing | O3: GNS/GNA | P3: 120 | Q3: Ecosystem Revenue | S3: Ecosystem Revenue | U3: [["WRAP REPORT", ""], ["ELM -8355\n[TAX] TY24 Zero State\nPage Optimization \\", ""], ["R5", "5KKYsymog/edit\nGLOBAL BGUlSoIbNaEl SBSus SinOeLsUs SToIOluNtioSn Gs RGOroUuPp", "", ""], ["", "", "", "1"], ["", "", "GLOBAL BGUlSoIbNaEl SBSus SinOeLsUs SToIOluNtioSn Gs RGOroUuPp", ""], ["", "", "", ""], ["WRAP REPORT", "", ""], ["ELM -7084\n[TAX] Zero State Page R", "edesign", ""], ["", "Template v5.0 Updated Aug 2024\nGLOBAL BGUlSoIbNaEl SBSus SinOeLsUs SToIOluNtioSn Gs RGOroUuPp", "", ""], ["", "", "", "2"], ["", "", "GLOBAL BGUlSoIbNaEl SBSus SinOeLsUs SToIOluNtioSn Gs RGOroUuPp", ""], ["", "", "", ""], [""], ["QBL TAX - INTRODUCTION"], [""], [""], ["Business type", "", "DIWM Tax", "DIFM Tax", "Deadline"], ["Inc - In scope", "S Corp", "$489.00", "$1,169.00", "March 17"], ["", "Partnership", "$489.00", "$1,169.00", "March 17"], ["Sole prop", "Sole proprietor", "$169.00", "NA", "April 15"], ["inc (out of scope)", "corporation", "NA", "NA", "NA"], ["Global Business Solutio", "ns Group", "233"], [""], ["STRATEGY & APPROACH"], [""], ["CONTROL “Legacy”"], [""], ["TREATMENT A - “Price Compare”"], [""], ["TREATMENT B - “DIWM focus”", "TREATMENT B - “DIWM focus”"], ["", ""], ["", ""], ["", ""], ["Global Business Solutio", "ns Group", "234"], [""], ["STRATEGY & APPROACH"], ["CONTROL “Legacy”"], [""], ["TREATMENT A - “Price Compare”"], [""], ["TREATMENT B - “DIWM focus”", ""], ["", ""], ["Global Business Solutio", "ns Group", "235"], ["EXPERIMENT RESULTS\nQBL Tax Zero State Page\nWe are looking to increase the traffic-to-start (T2S) rate*\nwho come to QBL Tax Zero State Landing Page, by com\nthe QBL Tax LP, by using IPDs/emails to drive LP traffic.\nBusiness Impact: POSITIVE NEGATIVE\nBIZ IMPACT BIZ IMPACT\nRedesigned QBL Tax LP has delivered sig. higher starts for\nInc) customers (120 ITC , + 150) & will deliver +2100 start\nRedesigned QBL Tax LP has delivered negative performanc\ntype customers, we recommend roll back to control group", "", "EXPERIMENT RESULTS", "", "", "", "Redesign\nof QBO customers\nmunicating benefits on", "", "PRODUCTS: QBLive ● DRIVER: Bryan W. ● QB: ELM 7084 ● SOT:", "", "", "", "", "Deck", "● DATES: 24-12-16 to 25-01-15"], ["", "", "QBL Tax Zero Stat", "", "", "", "Redesign\nof QBO customers\nmunicating benefits on", "", "", "", "", "", "", "", ""], ["", "", "", "", "", "", "", "", "", "", "", "", "", "", ""], ["", "", "", "", "", "", "", "", "", "", "", "", "", "", ""], ["", "", "", "", "", "", "", "", "", "", "", "", "", "", ""], ["", "", "", "", "", "", "", "", "", "", "", "", "", "", ""], ["", "", "", "", "", "", "", "", "", "Learnings & Implications\n● Overall tax starts are at 102 ITC for T1, but the merchandising\nA\nperformance is mixed\nB ● DIWM Un Inc customers account for ~70% of starts, T1 has shown a\n120 ITC.\nC● The goodness observed in DIFM - Inc group for T1 isn't enough to\ncompensate for the drop in DIWM - Inc gGrloobuapl B ucsuinsestso Smoluetirosn.s Group 236", "", "", "", "", ""], ["", "Business Impact: POSITIVE NEGATIVE\nBIZ IMPACT BIZ IMPACT\nRedesigned QBL Tax LP has delivered sig. higher starts for\nInc) customers (120 ITC , + 150) & will deliver +2100 start\nRedesigned QBL Tax LP has delivered negative performanc\ntype customers, we recommend roll back to control group", "", "", "", "", "Sole prop (DIWM Un\ns by end of peak season.\ne across other biz entity", "", "", "", "", "", "", "", ""], ["", "", "", "", "", "", "", "Un\nason.\nentity", "", "", "", "", "", "", ""], ["", "", "", "", "", "", "Sole prop (DIWM", "Un", "", "", "", "", "", "", ""], ["", "", "", "", "", "", "s by end of peak se\ne across other biz", "", "", "", "", "", "", "", ""], ["", "", "", "", "", "", "design.", "", "", "", "", "", "", "", ""], ["", "", "", "", "", "", "", "", "", "", "", "", "", "", ""], ["", "", "", "", "", "Call Outs: A D G", "", "", "", "", "", "", "", "", ""], ["", "", "", "FLAT &\nROLL OUT", "", "", "", "", "", "", "", "", "", "", ""], ["", "", "", "", "", "", "", "", "", "", "", "", "Use this google\ntemplate for KPIs", "", ""], ["", "", "", "", "", "", "", "", "", "", "", "", "", "", ""], [""], [""], ["", "T1", "T2", "Con.", "Δ T1", "Δ T2", "ITC - T1", "ITC - T2"], ["Assignments", "19,731", "20,148", "20,113", "", "", "", ""], ["Total Starts", "1,304", "1,074", "1,283", "21", "-209", "102 A", "84"], ["DIWM, Inc", "274", "359", "429", "-155", "-70", "64", "84"], ["DIFM, Inc", "75", "37", "49", "26", "-12", "C\n153", "76"], ["DIWM, Un Inc", "955", "678", "805", "150", "-127", "119", "84 B"], ["M - Inc gGrloobuapl B ucsuinsestso Smoluetiro", "sn.s Group", "236"], ["Use this google"], ["emplate for KPIs"]] | V3: Campaign re-appears on slide 232 (gap from slide 13) | Alt TO (slide 232): IOluNtioSn Gs RGOroUuPp 232 | Alt TO (slide 233): mers - ~1Mn traffic for TY 23 - 25k Starts for TY 23 | Alt TO (slide 235): rship | Alt Date (slide 236): 24-12-16 | Alt TO (slide 236): 25-01-15 | Date source: CSV – Current Target Launch Date | Name source: CSV | Business Impact updated from Results Report | Status enriched from Results Report | W3: 13–236 | X3: Copy of FY'25_ CRM Analytics Monthly Experiment_Notebook_AC.pdf
A4: ELM-8355 | B4: [TAX] TY24 Zero State Page Optimization Test | C4: 08-27-2025 | D4: Existing QBO/SP customers Sole Prop, Partnership, S-Corp | E4: 25-09-15 | F4: By making QBO customers confident that filing taxes directly in | G4: GET: Existing QBO/SP customers Sole Prop, Partnership, S-Corp | TO: 25-09-15 | BY: By making QBO customers confident that filing taxes directly in | H4: If the TOF is redesigned, for each +1.0 increase in the view-to-start rate will increase QBL Tax Starts By 5,000 Results Treatment Control Δ ITC Assignments 10,827 10,827 Total Starts 577 528 49 109 A Learnings & Implications ● Overall tax starts are at 109 ITC for Treatment, but the merchandising A performance is mixed | I4: & Implications ● Overall tax starts are at 109 ITC for Treatment, but the merchandising A performance is mixed & Implications ● Overall tax starts are at 223 ITC with 149 Incr starts for Treatment, A this is in line with unknown entity type starts | J4: QBO | K4: Landing Page | L4: Trending Positive | Results: 5.1 MEASURE: Complete | M4: Positive Biz Impact | 109 ITC-1 | 223 ITC-2 | N4: https://docs.google.com/presentation/d/1NRL_Alxvw2IabKQdV0SCRADbZZk1GYQYaKGGNy4pLV0/edit?usp=sharing | O4: Retention Rate | P4: 109 | Q4: Retention Rate | R4: 223 | U4: [["EXPERIMENT RESULTS\nQBL Tax Zero State Page\nIncrease the traffic-to-start (T2S) rate among QBO custo\nTax Zero State Landing Page by clearly communicating\nthrough targeted cobranding with TurboTax for Sole Pro\nS Corps and Partnerships\nBusiness Impact: POSITIVE\nBIZ IMPACT\nRedesigned QBL Tax LP with TT Co branding has delivered\nprop (DIWM Un Inc) customers (109 ITC , + 49) & will deli\nof peak season TY 25.", "", "EXPERIMENT RESULTS", "", "Redesign\nmers visiting the QBL\nproduct benefits\nprietors & DIWM for", "", "PRODUCTS: QBLive ● DRIVER: Bryan W. ● QB: ELM 8355 ● SOT: Deck ● DATES: 25-08-16 to 25-09-15\nObjective\nGet Existing QBO/SP customers Sole Prop, Partnership, S-Corp\nTo Sign up for QBL Tax\nBy By making QBO customers confident that filing taxes directly in\nQBO by showing them the tax preparation credentials of TurboTax\nHypothesis\nIf the TOF is redesigned, for each +1.0 increase in the view-to-start rate\nwill increase QBL Tax Starts By 5,000\nResults\nTreatment Control Δ ITC\nAssignments 10,827 10,827\nTotal Starts 577 528 49 109\nA\nLearnings & Implications\n● Overall tax starts are at 109 ITC for Treatment, but the merchandising\nA\nperformance is mixed\n14\nGlobal Business Solutions Group", "", ""], ["", "", "QBL Tax Zero Stat", "", "Redesign\nmers visiting the QBL\nproduct benefits\nprietors & DIWM for", "", "", "", ""], ["", "", "", "", "", "", "", "", ""], ["", "", "", "", "", "", "", "Learnings & Implications\n● Overall tax starts are at 109 ITC for Treatment, but the merchandising\nA\nperformance is mixed", ""], ["", "", "", "", "", "", "performance is mixed", "performance is mixed", ""], ["", "Business Impact: POSITIVE\nBIZ IMPACT\nRedesigned QBL Tax LP with TT Co branding has delivered\nprop (DIWM Un Inc) customers (109 ITC , + 49) & will deli\nof peak season TY 25.", "", "", "sig. higher starts fo\nver +2000 starts b", "r Sole\ny end", "", "", ""], ["", "", "", "", "", "", "", "", ""], ["", "", "", "", "", "", "", "", "14"], ["Deck", "● DATES: 25-08-16 to 25-09-15"], ["", "Treatment", "Control", "Δ", "ITC"], ["Assignments", "10,827", "10,827", "", ""], ["Total Starts", "577", "528", "49", "109\nA"], ["", "Call Outs: A D G"], ["FLAT &\nROLL OUT", ""], ["", ""], ["Use this google"], ["emplate for KPIs"], ["EXPERIMENT RESULTS\nQBL Tax Zero State Page\nIncrease the traffic-to-start (T2S) rate among QBO custo\nTax Zero State Landing Page by clearly communicating\nthrough showing only DIWM for S Corps and Partnershi\nBusiness Impact: POSITIVE\nBIZ IMPACT\nRedesigned QBL Tax LP with TT Co branding has delivered\nprop (DIWM Un Inc) customers (223 ITC , + 149) & will de\nof peak season TY 25.", "", "EXPERIMENT RESULTS", "", "", "Redesign\nmers visiting the QBL\nproduct benefits\nps", "", "PRODUCTS: QBLive ● DRIVER: Bryan W. ● QB: ELM 8355 ● SOT: Deck ● DATES: 25-08-16 to 25-09-15\nObjective\nGet Existing QBO/SP customers Sole Prop, Partnership, S-Corp\nTo Sign up for QBL Tax\nBy By making QBO customers confident that filing taxes directly in\nQBO by showing them only DIWM product\nHypothesis\nIf the TOF is redesigned, for each +1.0 increase in the view-to-start rate\nwill increase QBL Tax Starts By 5,000\nResults\nTreatment Control Δ ITC\nAssignments 4,065 4,232\nTotal Starts 270 121 149 223 A\nLearnings & Implications\n● Overall tax starts are at 223 ITC with 149 Incr starts for Treatment,\nA\nthis is in line with unknown entity type starts\n15\nGlobal Business Solutions Group", "", ""], ["", "", "QBL Tax Zero Stat", "", "", "Redesign\nmers visiting the QBL\nproduct benefits\nps", "", "", "", ""], ["", "", "", "", "", "", "", "", "", ""], ["", "", "", "", "", "", "", "", "Learnings & Implications\n● Overall tax starts are at 223 ITC with 149 Incr starts for Treatment,\nA\nthis is in line with unknown entity type starts", ""], ["", "", "", "", "", "", "", "this is in line with unknown entity type starts", "this is in line with unknown entity type starts", ""], ["", "Business Impact: POSITIVE\nBIZ IMPACT\nRedesigned QBL Tax LP with TT Co branding has delivered\nprop (DIWM Un Inc) customers (223 ITC , + 149) & will de\nof peak season TY 25.", "", "", "", "sig. higher starts fo\nliver +4000 starts", "r Sole\nby end", "", "", ""], ["", "", "", "", "", "", "", "", "", ""], ["", "", "", "", "", "", "", "", "", "15"], ["Deck", "● DATES: 25-08-16 to 25-09-15"], ["", "Treatment", "Control", "Δ", "ITC"], ["Assignments", "4,065", "4,232", "", ""], ["Total Starts", "270", "121", "149", "223 A"], ["", "Call Outs: A D G"], ["FLAT &\nROLL OUT", ""], ["", ""]] | V4: Alt Hypothesis (slide 15): If the TOF is redesigned, for each +1.0 increase in the view-to-start rate will increase QBL Tax Starts By 5,000 Results Treatment Control Δ ITC Assignments 4,065 4,232 Total Starts 270 121 149 223 A Learnings & Implications ● Overall tax starts are at 223 ITC with 149 Incr starts for Treatment, A this is in line with unknown entity type starts | Date source: CSV – Current Target Launch Date | Name source: CSV | Business Impact updated from Results Report | Status enriched from Results Report | W4: 14–15 | X4: Copy of FY'25_ CRM Analytics Monthly Experiment_Notebook_AC.pdf
A5: ELM-8764 | B5: TCO Learning Plan: Test 2: SKU Price Increase and Upgrade to Suite giving Customers Choice Dry Test | C5: 09-30-2025 | D5: her capabilities | E5: IOluNtioSn Gs RGOroUuPp 16 | G5: GET: her capabilities | TO: IOluNtioSn Gs RGOroUuPp 16 | H5: Dry Test: Existing Customers SKU Price Increase > Upgrade to Suite giving Customers Choice | I5: Plan: Test 2: SKU > Suite Migration giving Customers Choice & Current H/L & No Change Pricing Options Dry Test SWAG Effort Size When given the option, customers ●A High intention to “Downgrade to Suite” was a result of features offered on a Suite showed a best value for adopt Suites through downgrades | J5: Bill Pay | K5: IPD; Landing Page | L5: Positive | U5: [["WRAP REPORT", "", ""], ["TCO Dry Tests\n● ELM-8764 (Dry Test 2)\n● ELM-8929 (Dry Test 4)\n● ELM-8777 (Dry Test 3)", "", ""], ["", "Template v6.0 Updated Sept 2025\nGLOBAL BGUlSoIbNaEl SBSus SinOeLsUs SToIOluNtioSn Gs RGOroUuPp", "", ""], ["", "", "", "1"], ["", "", "GLOBAL BGUlSoIbNaEl SBSus SinOeLsUs SToIOluNtioSn Gs RGOroUuPp", ""], ["", "", "", ""], ["Global Business Solutio", "ns Group", "17"], ["TCO Dry Test Customer Experience"], [""], ["What’s a dry test?\nA dry test is a method used to gauge the potential success of a product or campaign before fully launching it.\nIt involves creating a simulated version of the product or campaign and presenting it to a select group of consumers to\ngather their feedback and measure their interest.\nCustomer Experience\nThank You Modal\nNon-Dismissible IPD - Dry Test LP Survey /Form Gift card\nPop up of modal with\nBottom Drawer each CTA", ""], ["", ""], ["", "Customer will\nbe emailed a\nGift card for\nparticipation"], ["Thank You Modal\nPop up of modal with\neach CTA"], [""], [""], [""], [""], [""], ["Global Business Solut", "ions Group", "18"], ["SOURCE OF TRUTH\nELM - 8764\nTCO Learning Plan: Test 2: SKU > Suite\nMigration giving Customers Choice &\nCurrent H/L & No Change Pricing Options\nDry Test\nELM Driver: Dan Eliab\nCRM Analytics: Andre Remy\nELM Workstream: SMB\nDate: 09-11-25\nELM Quickbase Record: ELM-8764\nWorkbook: Link\nBusiness Brief: N/A\nSlack Channel: Link", "SWAG Effort Size\nMega\nGlobal Business Solutions Group\nTemplate v6.0 Updated Jan.. 2025", ""], ["SOURCE OF TRUTH", ""], ["", ""], ["ELM - 8764\nTCO Learning Plan: Test 2: SKU > Suite\nMigration giving Customers Choice &\nCurrent H/L & No Change Pricing Options\nDry Test", ""], ["Mega"], [""], ["", "", "", "", ""], ["Context\nDry Test 2 Price Structure\nCurrent Pricing\nSKU Current SKU Price\nSS $38\nESS $75\nPL $115\nADV $275\nCurrent SKU Price + Suite Price = SKU Price + $10\nSKU New SKU Price Suite Price\nESS $75 $85\nPL $115 $125\nADV $275 $285\nLow Price Increase in SKU (except SS) + Low Suite Price\nSKU New SKU Price Suite Price\nSS $38 $40\nESS $80 $85\nPL $135 $140\nADV $295 $305\nHigh Price Increase in SKU (except SS) + High Suite Price\nSKU New SKU Price Suite Price\nSS $38 $45\nESS $85 $95\nPL $140 $155\nADV $315 $340\nCreatives: [Link to Figma]", "", "", "", ""], ["", "", "", "Creative for PLUS: Current SKU Price + Suite Price = SKU Price + $10", ""], ["", "Context\nDry Test 2 Price Structure", "Context", "", ""], ["", "", "", "", ""], ["Current Pricing", ""], ["SKU", "Current SKU Price"], ["SS", "$38"], ["ESS", "$75"], ["PL", "$115"], ["ADV", "$275"], ["Current SKU Price + Suite Price = SKU Price + $10", "", ""], ["SKU", "New SKU Price", "Suite Price"], ["ESS", "$75", "$85"], ["PL", "$115", "$125"], ["ADV", "$275", "$285"], ["Low Price Increase in SKU (except SS) + Low Suite Price", "", ""], ["SKU", "New SKU Price", "Suite Price"], ["SS", "$38", "$40"], ["ESS", "$80", "$85"], ["PL", "$135", "$140"], ["ADV", "$295", "$305"], ["High Price Increase in SKU (except SS) + High Suite Price", "", ""], ["SKU", "New SKU Price", "Suite Price"], ["SS", "$38", "$45"], ["ESS", "$85", "$95"], ["PL", "$140", "$155"], ["ADV", "$315", "$340"], ["", "IntGuliot Cbaoln Bfiudseinnetisasl aSnodlu Ptiro", "onpsr iGertaoruyp", "20"], ["", "", "Call Outs: A D G"], ["", "FLAT\nIMPACT", ""], ["STILL BAKING", "", ""], ["Dry Test 02 Results\nWhen given the option, customers\nadopt Suites through downgrades\nTreatment 1 - SKU at Current Price | Suite Price at an additional $10 with downgrade option\nSKU Keep SKU * Downgrade to Suite Switch to Suite Cancel Revenue Impact\nSS N/A N/A N/A N/A N/A\nESS 83.2% 16.8% 0.0% 0.0% -$68.1 M\nPL 87.9% 10.5% 1.3% 0.3% -$49.9 M\nADV 88.4% 9.4% 2.2% 0.0% -$50.1 M\nTOTAL 86.5% 12.3% A 1.1% 0.1% -$168.1 M\nTreatment 2 - SKUs (except SS) at New Low price | Suite at New Low price with downgrade option\nSKU Keep SKU * Downgrade to Suite Switch to Suite Cancel Revenue Impact\nSS 94% N/A 5% 1% -$3.7 M\nESS 83.6% 14.2% 1.6% 0.6% -$16.6 M\nPL 83.2% 15.2% 1.4% 0.3% $181.4 M D\nADV 85.0% 12.0% 2.2% 0.7% -$2.0 M\nTOTAL 86.4% 10.5% 2.5% 0.6% $159.1 M\nTreatment 3 - SKUs (except SS) at New Hish price | Suite at New High price with downgrade option\nSKU Keep SKU * Downgrade to Suite Switch to Suite Cancel Revenue Impact\nSS 98% 0% 2% 0% $4.1 M\nESS 83% 16% 1% 1% $44.0 M\nPL 85% 16% 1% 0% $270.6 M\nADV 85% 13% 1% 1% $62.3 M\nTOTAL 87.0% 11.2% 1.5% 0.4% $380.9 M\n* Assumes that the 43% of customers that didn’t answer will remain in their current SKU", "", "", "", "", "", "", "", "Insights\n●A High intention to “Downgrade to Suite” was a result of\nfeatures offered on a Suite showed a best value for\nmoney:\n○ Creatives didn’t show features trade-off at\ndowngrade\n○ For a lower price, downgrades to a Suite gave\ncustomers more free ACH and included Payroll\n●B Downgrades are the main driver for Revenue loss\nwhile the Price increase is driving the goodness in\nRevenue\n●C ~90% of Suite adoption would happen through\nDowngrades\n●D The price structure of PLUS allows this SKU to yield a\npositive revenue (see next slide)\n-13%\n-43%\nGlobal Business Solutions Group 21", ""], ["", "Dry Test 02 Results\nWhen given the option, customers\nadopt Suites through downgrades", "Dry Test 02 Results", "", "", "", "", "", "", ""], ["", "Treatment 1 - SKU at Current Price | Suite Price at an additional $10 with downgrade option", "", "", "", "", "", "", "", ""], ["", "SKU", "", "Keep SKU *", "Downgrade to Suite", "Switch to Suite", "Cancel", "Revenue Impact", "", ""], ["", "SS", "", "N/A", "N/A", "N/A", "N/A", "N/A", "", ""], ["", "ESS", "", "83.2%", "16.8%", "0.0%", "0.0%", "-$68.1 M", "", ""], ["", "PL", "", "87.9%", "10.5%", "1.3%", "0.3%", "-$49.9 M", "", ""], ["", "ADV", "", "88.4%", "9.4%", "2.2%", "0.0%", "-$50.1 M", "", ""], ["", "TOTAL", "", "86.5%", "12.3% A", "1.1%", "0.1%", "-$168.1 M", "", ""], ["Treatment 2 - SKUs (except SS) at New Low price | Suite at New Low price with downgrade option", "", "", "", "", ""], ["SKU", "Keep SKU *", "Downgrade to Suite", "Switch to Suite", "Cancel", "Revenue Impact"], ["SS", "94%", "N/A", "5%", "1%", "-$3.7 M"], ["ESS", "83.6%", "14.2%", "1.6%", "0.6%", "-$16.6 M"], ["PL", "83.2%", "15.2%", "1.4%", "0.3%", "$181.4 M D"], ["ADV", "85.0%", "12.0%", "2.2%", "0.7%", "-$2.0 M"], ["TOTAL", "86.4%", "10.5%", "2.5%", "0.6%", "$159.1 M"], ["Treatment 3 - SKUs (except SS) at New Hish price | Suite at New High price with downgrade option", "", "", "", "", ""], ["SKU", "Keep SKU *", "Downgrade to Suite", "Switch to Suite", "Cancel", "Revenue Impact"], ["SS", "98%", "0%", "2%", "0%", "$4.1 M"], ["ESS", "83%", "16%", "1%", "1%", "$44.0 M"], ["PL", "85%", "16%", "1%", "0%", "$270.6 M"], ["ADV", "85%", "13%", "1%", "1%", "$62.3 M"], ["TOTAL", "87.0%", "11.2%", "1.5%", "0.4%", "$380.9 M"], ["Global Business Solutio", "ns Group", "21"]] | V5: Alt Campaign Name (slide 17): TCO Dry Test 2 - Introduce Suites with options to upgrade/downgrade to a Suite, Keep plan, or | Alt TO (slide 17): mers | Alt TO (slide 18): mer Experience | Alt Date (slide 19): 09-11-25 | Alt TO (slide 19): mers Choice & | Alt TO (slide 20): Figma] | Alt Product (slide 21): Payroll | Alt TO (slide 21): mers | Date source: CSV – Current Target Launch Date | Name source: CSV | Hypothesis filled from CSV Project Description CSV (Inferred for review) | W5: 16–21 | X5: Copy of FY'25_ CRM Analytics Monthly Experiment_Notebook_AC.pdf
A6: ELM-8929 | B6: TCO Learning Plan: Test 4 Upgrade to Suite, New Pricing and NO Downgrade | C6: 10-07-2025 | E6: Suite, New Pricing and NO Downgrade | G6: TO: Suite, New Pricing and NO Downgrade | H6: Fast follow of Dry Test 2 ELM 8764. Test 4 will give customer options to upgrade to Suite with new pricing and NO downgrade option. | I6: Plan: Test 4: Upgrade to Suite, New Pricing and NO Downgrade SWAG Effort Size | K6: IPD; Landing Page | L6: Not found (Inferred for review) | U6: [["SOURCE OF TRUTH\nELM - 8929\nTCO Learning Plan: Test 4: Upgrade to\nSuite, New Pricing and NO Downgrade\nELM Driver: Dan Eliab\nCRM Analytics: Andre Remy\nELM Workstream: SMB\nDate: 10-3-25\nELM Quickbase Record: ELM-8929\nWorkbook: Link (Same workbook was used for ELM-8764 and ELM-8929)\nBusiness Brief: N/A\nSlack Channel: Link (Same slack channel was used for ELM-8764 and ELM-8929)", "SWAG Effort Size\nSmall\nGlobal Business Solutions Group\nTemplate v6.0 Updated Jan.. 2025", ""], ["SOURCE OF TRUTH", ""], ["", ""], ["ELM - 8929\nTCO Learning Plan: Test 4: Upgrade to\nSuite, New Pricing and NO Downgrade", ""], ["Small"], [""]] | V6: Date source: CSV – Current Target Launch Date | Name source: CSV | Hypothesis filled from CSV Project Description CSV (Inferred for review) | W6: 22 | X6: Copy of FY'25_ CRM Analytics Monthly Experiment_Notebook_AC.pdf
A7: ELM-8047 | B7: FY25 MAR GAP CLOSER: TEST 4 - S2: Price in Agents: Existing Customer Dry Test | C7: 04-02-2025 | E7: mers ● Gov’t officials | F7: effort and Stop: Relying on price or discounts alone to drive adoption. | G7: TO: mers ● Gov’t officials | BY: effort and Stop: Relying on price or discounts alone to drive adoption. | H7: Test 3 Price points: 4 SKU lineup - If we add agentic experiences across the lineup and clearly communicate the value, we can minimize the churn/downgrade impact of increased prices with existing customers. Estimated assets needed: landing pages (versioned for different price levels and SKUs) and bottom drawer IPD. May be able to leverage parts of ACQ price line up. https://docs.google.com/spreadsheets/d/1b4XDWwIw_ZW8L_iAkcvrHsESJHbh06ftKentnFD6KZE/edit?gid=0#gid=0&fvid=2130047774 | I7: 18% of Customers would upgrade A● 18% of customers would switch to a Suite when there’s no price increase. That intention drops up to to a Suite 2% when the Suite is offered at a higher price compared to SKU B● The intention to switch to a Suite is higher at higher SKU at Current Price | Suite Price = SKU Price SKUs. Customers in highers SKU could need SKU Keep SKU * Switch to Suite Cancel Revenue Impact additional features to run their businesses. SS 87.8% 12.2% 0.0% $0.0 M ESS 83.2% 16.5% 0.3% -$3.0 M C● ~1% of customers showed an intent to cancel their PL 76.7% 23.1% 0.3% -$4.6 M subscription when there’s a price increase; which is ADV 77.1% 21.7% 1.3% -$12.6 M very close to the observed behavior during July’s TOTAL 81.6% 18.0% A 0.4% -$20.1 M price increase. SKUs at New Low price | Suite at New Low price SKU Keep SKU* Switch to Suite Cancel Revenue Impact SS 94.3% 5.1% 0.6% -$3.7 M ESS 97.4% 1.6% 1.1% $63.5 M B PL 96.8% 2.7% 0.5% $292.2 M ADV 93.5% 4.5% 1.9% $53.0 M TOTAL 95.7% 3.3% 1.0% $405.0 M -15% SKUs at New High price | Suite at New High price SKU Keep SKU * Switch to Suite Cancel Revenue Impact -40% SS 97.8% 2.2% 0.0% $4.1 M ESS 97.2% 2.0% 0.8% $143.3 M PL 96.7% 2.0% 1.3% $353.2 M ADV 96.2% 2.2% 1.6% $128.1 M TOTAL 97.0% 2.1% 0.9% C $628.7 M * Assumes that the 40% of customers that didn’t answer will remain in their current SKU Global Business Solutions Group 24 and implications? LEARNING / INSIGHTS HOW WE KNOW THIS IMPLICATION Equal Price Does Not Equal When AIO Suites are offered at current SKU prices, only 18% Start: Test and learn into consumption strategy that drive active use Appeal (Low Adoption From SKU switched, showing resistance is driven by effort and Stop: Relying on price or discounts alone to drive adoption. to Suite Even at Price Parity). uncertainty, not cost Continue: Use real-customer proof and transition stories to demonstrate ease and Increased price ($5-10) Suite adoption drops to 3.3% when offered at a price benefit. significantly reduced adoption difference of $5-$10 and 2.1% when offered at a price difference of $10-$25 (Source: AIO Dry Test - Test 04) Higher SKU customers are more Customers showed a higher intent to switch to a Suite when Start: Build SKU-specific strategies for Suites by making higher level suites more likely to switch to a Suite. they are on higher SKUs. On average, 10% Adv customers compelling as they have a higher chance of adoption. The ICP’s for plus and MM/higher SKU likely more open switch to a suite compared to 9% in Plus, 7% in Essentials, and advanced will need to be revisited in conjunction with conjoint inputs. to learn about AIO. 7% in Simple Start. (Source: AIO Dry Test - Test 04) Risk of SKU-to-Suite Downgrades Initial dry test showed significant 18-22% downgrade rates Start: Clearly differentiate feature/value prop across SKUs and highlight what and Revenue Impact (varies by SKU and price point) driven by side-by-side customer is going to lose with downgrade path. Restrict organic discovery of SKU placement of downgrade suite options. downgrade paths. If PLUS is removed, most customers A● Even though all projections show a negative revenue impact, Scenario 1 (SKU at Current Price | Suite Price would downgrade hurting revenue at SKU Price + $10) is the one with less negative impact due to the higher adoption of ADV Suite. ○ To breakeven in Scenario 1, ADV Suite Repository Upgrade SWAG Effort Size | J7: Payments | K7: IPD; Landing Page | L7: Negative | U7: [["", "", "", ""], ["Context\nDry Test 4 Design\nCurrent Pricing\nSKU Current SKU Price\nSS $38\nESS $75\nPL $115\nADV $275\nSKU Price = Suite Price (No Price Increase)\nSKU SKU Price Suite Price\nSS $38 $38\nESS $75 $75\nPL $115 $115\nADV $275 $275\nLow Price Increase in SKU | Low Suite Price\nSKU New SKU Price Suite Price\nESS $80 $85\nPL $135 $140\nADV $295 $305\nHigh Price Increase in SKU | High Suite Price\nSKU New SKU Price Suite Price\nESS $85 $95\nPL $140 $155\nADV $315 $340\nCreatives: [Link to Slide Deck]", "", "", "Creative for PLUS: SKU Price = Suite Price (No Price Increase)\nAUDIENCE EXCLUSIONS\n● QBO Simple Start customers ● Gov’t officials\n● Monthly subscribers ● Trialers\n● Paid ● Customers with attached products (Payroll, Payments, BillPay,\n● Tenure: Greater than 6 months since signup Live, Mailchimp)\n● Master Admin ● Accountant attached\n● Wholesale\n● Customers on a discount\n● IES\n● Part of FY’25 Agents Dry Tests: ELM-8047,ELM-8048,ELM-8077\n● Anyone part of TCO Dry Test 2 (ELM-8764) and Dry Test 3\n(ELM-8477)\n● For PLUS ONLY: Customers that used inventory and projects\nmanagement features\nGlobal Business Solutions Group 23"], ["", "Context\nDry Test 4 Design", "Context", ""], ["Creative for PLUS: SKU Price = Suite Price (No Price Increase)"], [""], ["Current Pricing", ""], ["SKU", "Current SKU Price"], ["SS", "$38"], ["ESS", "$75"], ["PL", "$115"], ["ADV", "$275"], ["SKU Price = Suite Price (No Price Increase)", "", ""], ["SKU", "SKU Price", "Suite Price"], ["SS", "$38", "$38"], ["ESS", "$75", "$75"], ["PL", "$115", "$115"], ["ADV", "$275", "$275"], ["Low Price Increase in SKU | Low Suite Price", "", ""], ["SKU", "New SKU Price", "Suite Price"], ["ESS", "$80", "$85"], ["PL", "$135", "$140"], ["ADV", "$295", "$305"], ["High Price Increase in SKU | High Suite Price", "", ""], ["SKU", "New SKU Price", "Suite Price"], ["ESS", "$85", "$95"], ["PL", "$140", "$155"], ["ADV", "$315", "$340"], ["Global Business Solutio", "ns Group", "23"], ["Dry Test 04 Results\n18% of Customers would upgrade\nto a Suite\nSKU at Current Price | Suite Price = SKU Price\nSKU Keep SKU * Switch to Suite Cancel Revenue Impact\nSS 87.8% 12.2% 0.0% $0.0 M\nESS 83.2% 16.5% 0.3% -$3.0 M\nPL 76.7% 23.1% 0.3% -$4.6 M\nADV 77.1% 21.7% 1.3% -$12.6 M\nTOTAL 81.6% 18.0% A 0.4% -$20.1 M\nSKUs at New Low price | Suite at New Low price\nSKU Keep SKU* Switch to Suite Cancel Revenue Impact\nSS 94.3% 5.1% 0.6% -$3.7 M\nESS 97.4% 1.6% 1.1% $63.5 M\nB\nPL 96.8% 2.7% 0.5% $292.2 M\nADV 93.5% 4.5% 1.9% $53.0 M\nTOTAL 95.7% 3.3% 1.0% $405.0 M\nSKUs at New High price | Suite at New High price\nSKU Keep SKU * Switch to Suite Cancel Revenue Impact\nSS 97.8% 2.2% 0.0% $4.1 M\nESS 97.2% 2.0% 0.8% $143.3 M\nPL 96.7% 2.0% 1.3% $353.2 M\nADV 96.2% 2.2% 1.6% $128.1 M\nTOTAL 97.0% 2.1% 0.9% C $628.7 M\n* Assumes that the 40% of customers that didn’t answer will remain in their current SKU", "", "", "Insights\nA● 18% of customers would switch to a Suite when\nthere’s no price increase. That intention drops up to\n2% when the Suite is offered at a higher price\ncompared to SKU\nB● The intention to switch to a Suite is higher at higher\nSKUs. Customers in highers SKU could need\nadditional features to run their businesses.\nC● ~1% of customers showed an intent to cancel their\nsubscription when there’s a price increase; which is\nvery close to the observed behavior during July’s\nprice increase.\n-15%\n-40%\nGlobal Business Solutions Group 24", ""], ["", "Dry Test 04 Results\n18% of Customers would upgrade\nto a Suite", "Dry Test 04 Results", "", ""], ["SKU at Current Price | Suite Price = SKU Price", "", "", "", "", "", ""], ["SKU", "Keep SKU *", "Switch to Suite", "", "", "Cancel", "Revenue Impact"], ["SS", "87.8%", "12.2%", "", "", "0.0%", "$0.0 M"], ["ESS", "83.2%", "16.5%", "", "", "0.3%", "-$3.0 M"], ["PL", "76.7%", "23.1%", "", "", "0.3%", "-$4.6 M"], ["ADV", "77.1%", "21.7%", "", "", "1.3%", "-$12.6 M"], ["TOTAL", "81.6%", "", "18.0% A", "", "0.4%", "-$20.1 M"], ["SKUs at New Low price | Suite at New Low price", "", "", "", "", "", ""], ["SKU", "Keep SKU*", "Switch to Suite", "", "", "Cancel", "Revenue Impact"], ["SS", "94.3%", "", "5.1%", "", "0.6%", "-$3.7 M"], ["ESS", "97.4%", "", "1.6%", "", "1.1%", "$63.5 M"], ["PL", "96.8%", "", "2.7%", "B", "0.5%", "$292.2 M"], ["ADV", "93.5%", "", "4.5%", "", "1.9%", "$53.0 M"], ["TOTAL", "95.7%", "3.3%", "", "", "1.0%", "$405.0 M"], ["SKUs at New High price | Suite at New High price", "", "", "", "", "", ""], ["SKU", "Keep SKU *", "Switch to Suite", "Cancel", "", "", "Revenue Impact"], ["SS", "97.8%", "2.2%", "0.0%", "", "", "$4.1 M"], ["ESS", "97.2%", "2.0%", "0.8%", "", "", "$143.3 M"], ["PL", "96.7%", "2.0%", "1.3%", "", "", "$353.2 M"], ["ADV", "96.2%", "2.2%", "1.6%", "", "", "$128.1 M"], ["TOTAL", "97.0%", "2.1%", "", "0.9%", "C", "$628.7 M"], ["Global Business Solutio", "ns Group", "24"], ["LEARNING / INSIGHTS", "HOW WE KNOW THIS", "IMPLICATION"], ["Equal Price Does Not Equal\nAppeal (Low Adoption From SKU\nto Suite Even at Price Parity).\nIncreased price ($5-10)\nsignificantly reduced adoption", "When AIO Suites are offered at current SKU prices, only 18%\nswitched, showing resistance is driven by effort and\nuncertainty, not cost\nSuite adoption drops to 3.3% when offered at a price\ndifference of $5-$10 and 2.1% when offered at a price\ndifference of $10-$25\n(Source: AIO Dry Test - Test 04)", "Start: Test and learn into consumption strategy that drive active use\nStop: Relying on price or discounts alone to drive adoption.\nContinue: Use real-customer proof and transition stories to demonstrate ease and\nbenefit."], ["Higher SKU customers are more\nlikely to switch to a Suite.\nMM/higher SKU likely more open\nto learn about AIO.", "Customers showed a higher intent to switch to a Suite when\nthey are on higher SKUs. On average, 10% Adv customers\nswitch to a suite compared to 9% in Plus, 7% in Essentials, and\n7% in Simple Start.\n(Source: AIO Dry Test - Test 04)", "Start: Build SKU-specific strategies for Suites by making higher level suites more\ncompelling as they have a higher chance of adoption. The ICP’s for plus and\nadvanced will need to be revisited in conjunction with conjoint inputs."], ["Risk of SKU-to-Suite Downgrades\nand Revenue Impact", "Initial dry test showed significant 18-22% downgrade rates\n(varies by SKU and price point) driven by side-by-side\nplacement of downgrade suite options.\nSecond dry test does not allow customers to downgrade.\nSimilarly, GA will also not have the downgrade option side by\nside but there is a risk of customers downgrading when they\nfind these options organically. Baseline downgrade rates are\n0.2% | 120 ITPY.\n(Source: AIO Dry Test - Test 02, Downgrade Trends)", "Start: Clearly differentiate feature/value prop across SKUs and highlight what\ncustomer is going to lose with downgrade path. Restrict organic discovery of SKU\ndowngrade paths.\nStop: Giving away lot of valuable features in lower SKU’s. Presenting lower Suites\nalongside higher SKUs without feature trade-offs.\nContinue: Iterate on SKU features and pricing"], ["Global Business Solutio", "ns Group", "25"], ["", "", "Creative for PLUS: SKUs at New High price | Suite at New High price", ""], ["", "", "", ""], ["", "Dry Test 3 Design", "", ""], ["", "", "", ""], ["", "SKU PL ESS Suite ADV Suite ADV SKU\nCurrent Price $115 $275\nScenario 1: SKU at Current\nPrice | Suite Price at SKU $85 $285 $275\nPrice + $10\nScenario 2: SKUs at New\nLow price | Suite at New $85 $305 $295\nLow price\nScenario 3: SKUs at New\nHigh price | Suite at New $95 $340 $315\nHigh price\nAUDIENCE\n● QBO PLUS\n● Monthly subscribers\n● Paid\n● 6 months or greater tenure (since customers are price protected if <6 months)\n● Master Admin\nEXCLUSIONS\n● Gov’t officials\n● Trialers\n● Wholesale\n● Accountant-attached\n● Customers on a discount\n● Customers with attached products (Payroll, Payments, BillPay, Live,\nMailchimp)\n● IES\n● Part of prior dry tests ELM-8047,ELM-8048,ELM-8477\n● Part of the other TCO dry test, ELM-8764", "", ""], ["SKU", "PL", "ESS Suite", "ADV Suite", "ADV SKU"], ["Current Price", "$115", "", "", "$275"], ["Scenario 1: SKU at Current\nPrice | Suite Price at SKU\nPrice + $10", "", "$85", "$285", "$275"], ["Scenario 2: SKUs at New\nLow price | Suite at New\nLow price", "", "$85", "$305", "$295"], ["Scenario 3: SKUs at New\nHigh price | Suite at New\nHigh price", "", "$95", "$340", "$315"], ["Global Business Solutio", "ns Group", "27"], ["Dry Test 03 Results\nIf PLUS is removed, most customers\nwould downgrade hurting revenue\nScenario 1: SKU at Current Price | Suite Price at SKU Price + $10\nSKU Downgrade to ESS Suite Upgrade to ADV Suite Upgrade to ADV SKU Cancel Revenue Impact\nPL 82.4% 10.2% 5.6% 1.9% -$9.7 M\nScenario 2: SKUs at New Low price | Suite at New Low price\nSKU Downgrade to ESS Suite Upgrade to ADV Suite Upgrade to ADV SKU Cancel Revenue Impact\nPL 89.7% 2.6% 4.3% 3.4% -$274.4 M\nScenario 3: SKUs at New High price | Suite at New High price\nSKU Downgrade to ESS Suite Upgrade to ADV Suite Upgrade to ADV SKU Cancel Revenue Impact\nPL 97.3% 0.0% 0.9% 1.8% -$295.9 M\n-5%\n-47%", "", "", "Insights\nA● Even though all projections show a negative revenue\nimpact, Scenario 1 (SKU at Current Price | Suite Price\nat SKU Price + $10) is the one with less negative\nimpact due to the higher adoption of ADV Suite.\n○ To breakeven in Scenario 1, ADV Suite\nadoption has to be at least 10.5%\n●B Similar to what was observed in Dry Test 2 and Dry\nTest 4, a high prices are likely to be a barrier to Suite\nadoption (potentially high price sensitivity)\nGlobal Business Solutions Group 28", ""], ["", "Dry Test 03 Results\nIf PLUS is removed, most customers\nwould downgrade hurting revenue", "Dry Test 03 Results", "", ""], ["Scenario 1: SKU at Current Price | Suite Price at SKU Price + $10", "", "", "", "", ""], ["SKU", "Downgrade to ESS Suite", "Upgrade to ADV Suite", "Upgrade to ADV SKU", "Cancel", "Revenue Impact"], ["PL", "82.4%", "10.2%", "5.6%", "1.9%", "-$9.7 M"], ["Scenario 2: SKUs at New Low price | Suite at New Low price", "", "", "", "", ""], ["SKU", "Downgrade to ESS Suite", "Upgrade to ADV Suite", "Upgrade to ADV SKU", "Cancel", "Revenue Impact"], ["PL", "89.7%", "2.6%", "4.3%", "3.4%", "-$274.4 M"], ["Scenario 3: SKUs at New High price | Suite at New High price", "", "", "", "", ""], ["SKU", "Downgrade to ESS Suite", "Upgrade to ADV Suite", "Upgrade to ADV SKU", "Cancel", "Revenue Impact"], ["PL", "97.3%", "0.0%", "0.9%", "1.8%", "-$295.9 M"], ["Global Business Solutio", "ns Group", "28"], ["", "", "", ""], ["WRAP REPORT\nELM - 6651\nPayroll Insights Repository\nUpgrade\nELM Driver: Jamie Peng\nCRM Analytics: Manasa Shankar, Sowmya Lingamneni\nELM Workstream: Attach & Upsell\nDate: ##-##-####\nEPLMr Qeuisckebasne Rteecorrd: ENLM-a665m1 e\nWorkbook: Link\nSlack Channel: Link", "", "", "SWAG Effort Size\nM"], ["", "", "", "29\nTemplate v5.0 Updated Aug 2024"], ["WRAP REPORT"], ["ELM - 6651\nPayroll Insights Repository"], ["ELM Driver: Jamie Peng\nCRM Analytics: Manasa Shankar, Sowmya Lingamneni", ""], ["ELM Workstream: Attach & Upsell\nDate: ##-##-####\nEPLMr Qeuisckebasne Rteecorrd: ENLM-a665m1 e\nWorkbook: Link", ""], ["Slack Channel: Link", ""], ["en\nLink", ""], ["", "Link"], [""], ["29\nv5.0 Updated Aug 20"]] | V7: Alt TO (slide 24): mers would upgrade | Alt TO (slide 25): consumption strategy that drive active use | Campaign re-appears on slide 27 (gap from slide 25) | Alt Campaign Name (slide 27): ,ELM-8048,ELM-8477 | Alt TO (slide 27): mers are price protected if <6 months) | Alt Product (slide 29): Payroll | Alt TO (slide 29): ry | Date source: CSV – Current Target Launch Date | Name source: CSV | Hypothesis filled from CSV Project Description CSV (Inferred for review) | W7: 23–29 | X7: Copy of FY'25_ CRM Analytics Monthly Experiment_Notebook_AC.pdf
A8: ELM-8477 | B8: TCO Learning Plan: Test 3 Existing Customers Remove Plus Dry Test | C8: 10-02-2025 | E8: mers Remove Plus Dry Test | G8: TO: mers Remove Plus Dry Test | H8: Dry Test for existing Plus customers - options of downgrade to ESS Suite or upgrade if Plus SKU is not an option at different prices | I8: Plan: Test 3 Existing Customers Remove Plus Dry Test SWAG Effort Size | K8: IPD; Landing Page | L8: Not found (Inferred for review) | U8: [["SOURCE OF TRUTH\nELM - 8477\nTCO Learning Plan: Test 3 Existing\nCustomers Remove Plus Dry Test\nELM Driver: Dan Eliab\nCRM Analytics: Andre Remy\nELM Workstream: SMB\nDate: 09-11-25\nELM Quickbase Record: ELM-8477\nWorkbook: Link\nBusiness Brief: N/A\nSlack Channel: Link", "SWAG Effort Size\nM\nGlobal Business Solutions Group\nTemplate v6.0 Updated Jan.. 2025", ""], ["SOURCE OF TRUTH", ""], ["SOURCE OF TRUTH", ""], ["ELM - 8477\nTCO Learning Plan: Test 3 Existing\nCustomers Remove Plus Dry Test", ""], ["SWAG Effort Size"], ["M"]] | V8: Date source: CSV – Current Target Launch Date | Name source: CSV | Hypothesis filled from CSV Project Description CSV (Inferred for review) | W8: 26 | X8: Copy of FY'25_ CRM Analytics Monthly Experiment_Notebook_AC.pdf
A9: ELM-6651 | B9: Optimize payroll upgrade messaging leveraging insights repository | C9: 10-31-2024 | D9: Payroll Core & Premium users with a high propensity to upgrade | E9: upgrade | F9: Leveraging Insights Repository & spokesmodel to generate | G9: GET: Payroll Core & Premium users with a high propensity to upgrade | TO: upgrade | BY: Leveraging Insights Repository & spokesmodel to generate | H9: If we create a personalized experience with Insights repository for Payroll upgrades, we can drive Ecosystem incremental revenue and Hypothesis upgrade rate for Payroll If we hyper-personalize Payroll upgrade messaging combining both pain Control points and insights repository while also optimizing the upgrade journey with a SKU specific landing page that lightens the cognitive load for customers, then we can expect to drive incremental upgrades | I9: & Implications ●A Although sample sizes were small, upgrade rate was stat sig positive at 225 ITC KPIs CONT. TEST Δ ITC ●A Although most of our target audience was tenured Sample Size 0.8K 0.8K payroll customers, there is directional evidence that Impressions 33.3% 66.6% customers with lower tenure are a lot more receptive to CTR 1.9% 2.7% 0.80% 142 Payroll 92D Upgrades 0.4% 1.7% 1.30% 425 A personalized content . CTR’s were trending at 142 in this Payroll Cancels post upgrade 0.1% 0.4% 0.30% 400 cohort vs 127 ITC in tenure greater than 360D Between 90 - 360D KPIs CONT. TEST Δ ITC B● Payroll 92D upgrade rate at 425 ITC for lower tenured Sample Size 0.8K 0.8K customers vs 267 ITC for tenured customers Impressions 33.3% 81.2% CTR 1.4% 2.6% 1.21% 185 Payroll 92D Upgrades 1.0% 0.8% -0.12% 88 Payroll Cancels post upgrade 0.2% 0.1% -0.12% 50 Greater than 360D KPIs CONT. TEST Δ ITC Sample Size 4.9K 4.8K Impressions 30.6% 83.1% CTR 1.1% 1.4% 0.30% 127 Payroll 92D Upgrades 0.3% 0.8% 0.50% 267 A Payroll Cancels post upgrade 0.0% 0.1% 0.10% N/A Global Business Solutions Group 31 Access Point Impressions Reach CTR Benchmark ITB ●A Majority of impression and engagement came from Banking - Hellobox 371 5.1% 0.50% 0.34% 147 highly contextual placements which had more than Expenses - Hellobox 951 13.0% 0.10% 0.11% 91 50% of all impressions and 85% of all clicks Invoices - Hellobox 1,780 24.2% 0.30% 0.22% 136 Reports - Hellobox 5 0.1% 0.00% 0.33% 0 SBSEG QBO Hellobox A ● Mid way into the experiment QRS remediation offers AppEmployees 4,234 57.7% 1.30% 0.40% 325 B were launched on the same access points across IR offers QRS offers both control/treatment of IR Access Point Impressions CTR Impressions CTR Banking - Hellobox 371 0.50% 317 0.00% ● CTR on IR offers much higher on most access points C Expenses - Hellobox 951 0.10% 140 0.70% compared to QRS offers that were running on the Invoices - Hellobox 1,780 0.30% 119 0.00% same access points Reports - Hellobox 5 0.00% 2 0.00% SBSEG QBO Hellobox AppEmployees 4,234 1.30% B 380 0.30% ● Offers that had content related to the number of D paychecks that were run did best compared to other offers Global Business Solutions Group 32 to expand on the volume of customers we could personalize content for Global Business Solutions Group 33 | J9: Payroll | K9: IPD | L9: Trending Positive | Results: 5.1 MEASURE: Complete | M9: Positive Biz Impact | N9: https://docs.google.com/presentation/d/18Pb5t7bMwK6FJPznakUoYjv34eSviMBOli_T2nmiHiA/edit#slide=id.g2efff53d832_0_813 | O9: Upgrades | U9: [["", "", "", "", "", "", "", "", "", "", "", "", "", "", "", "", "", "", "", ""], ["EXPERIMENT RESULTS\nPayroll Upgrad\nIf we create a personalized experience with Insights\nPayroll upgrades, we can drive Ecosystem incremen\nupgrade rate for Payroll\nControl\nTreatment\nBusiness Impact: POSITIVE\nBIZ IMPACT\nHyper-personalizing our recommendations with the\nan incremental annual revenue of at least ~$105K f\nPayroll Upgrades: 144 incr. units annually", "", "EXPERIMENT RESULTS", "", "", "e test\nrepository for\ntal revenue and", "", "PRODUCTS: Payroll ● DRIVER: Jamie Peng ● QB:", "", "", "", "ELM-", "6651 ● SOT:", "", "Deck", "● LAUNCH: Apr", "", "", "", ""], ["", "", "", "", "", "", "", "Objective\nGet Payroll Core & Premium users with a high propensity to upgrade\nTo Upgrade their Payroll SKU\nBy Leveraging Insights Repository & spokesmodel to generate\nhyper-personalized experiences\nHypothesis\nIf we hyper-personalize Payroll upgrade messaging combining both pain\npoints and insights repository while also optimizing the upgrade journey\nwith a SKU specific landing page that lightens the cognitive load for\ncustomers, then we can expect to drive incremental upgrades\nResults", "", "", "", "", "", "", "", "", "", "", "", ""], ["", "", "", "", "", "e test\nrepository for\ntal revenue and", "", "", "", "", "", "", "", "", "", "", "", "", "", ""], ["", "", "", "", "", "", "", "", "", "", "", "", "", "", "", "", "", "", "", ""], ["", "", "", "", "", "", "", "", "", "KPIs (4/20 - 6/7)", "TEST", "", "", "CON.", "Δ", "", "", "", "", ""], ["", "", "", "", "", "", "", "", "", "Assignments", "6.5K", "", "", "6.5K", "", "", "", "", "", ""], ["", "", "", "", "", "", "", "", "", "IPD views", "80.20%", "", "", "31.30%", "", "", "", "", "A", ""], ["", "", "", "", "", "", "", "", "", "", "", "", "", "", "", "", "", "", "", ""], ["", "", "", "", "", "", "", "", "", "CTR", "1.70%", "", "", "1.30%", "0.40", "", "", "", "", ""], ["", "", "", "", "", "", "", "", "", "Payroll 92D upgrades", "0.90%", "", "", "0.40%", "0.50", "", "", "", "225", "A"], ["", "", "", "ent", "", "", "", "", "", "Core to Prem", "0.70%", "", "", "0.30%", "0.40", "", "", "", "233", ""], ["", "", "", "", "", "", "", "", "", "Core to Elite", "0.12%", "", "", "0.10%", "0.02", "", "", "", "120", ""], ["", "", "", "", "", "", "", "", "", "Prem to Elite", "0.12%", "", "", "0.08%", "0.04", "", "", "", "150", ""], ["", "", "", "", "", "", "", "", "", "Payroll Cancels post upgrade", "0.11%", "", "", "0.08%", "0.03", "", "", "", "138", ""], ["", "", "", "", "", "", "", "", "Learnings & Implications\n●A Although sample sizes were small, upgrade rate was stat sig positive at\n225 ITC\n● Over 70% of the upgrades came from Core customers upgrading to\nB\nPremium\nGlobal Business Solutions Group 30\n●C Cancellation rates were higher too but not statistically significant", "", "", "", "", "", "", "", "", "", "", ""], ["", "", "", "", "", "", "", "", "", "", "", "", "", "", "", "", "", "", "", ""], ["", "", "", "", "", "", "", "", "", "", "", "", "", "", "", "", "", "", "", ""], ["", "Business Impact: POSITIVE\nBIZ IMPACT\nHyper-personalizing our recommendations with the\nan incremental annual revenue of at least ~$105K f\nPayroll Upgrades: 144 incr. units annually", "", "", "", "", "", "", "", "", "", "", "", "", "", "", "", "", "", ""], ["", "", "", "", "", "reasoning could drive\nor Payroll Upgrades", "", "", "", "", "", "", "", "", "", "", "", "", "", ""], ["", "", "", "", "", "", "", "", "", "", "", "", "", "", "", "", "", "", "", ""], ["", "Control", ""], ["", "", ""], ["Global Business Soluti", "ons Group", "30"], [""], ["INCONCLUSIVE\nTRENDING POSITIVE"], ["POSITIV", "", ""], ["", "POSITIV", "E"], ["RESULTS", "BIZ IMPAC", "T"], ["RESULTS\nBIZ IMPACT\nKPIs by Payroll tenure", "", "", "", ""], ["Less than 90D", "", "", "", ""], ["KPIs", "CONT.", "TEST", "Δ", "ITC"], ["Sample Size", "0.8K", "0.8K", "", ""], ["Impressions", "33.3%", "66.6%", "", ""], ["CTR", "1.9%", "2.7%", "0.80%", "142"], ["Payroll 92D Upgrades", "0.4%", "1.7%", "1.30%", "425 A"], ["Payroll Cancels post upgrade", "0.1%", "0.4%", "0.30%", "400"], [""], ["Insights\n●A Although most of our target audience was tenured\npayroll customers, there is directional evidence that\ncustomers with lower tenure are a lot more receptive to\npersonalized content . CTR’s were trending at 142 in this\ncohort vs 127 ITC in tenure greater than 360D\nB● Payroll 92D upgrade rate at 425 ITC for lower tenured\ncustomers vs 267 ITC for tenured customers"], ["Between 90 - 360D", "", "", "", ""], ["KPIs", "CONT.", "TEST", "Δ", "ITC"], ["Sample Size", "0.8K", "0.8K", "", ""], ["Impressions", "33.3%", "81.2%", "", ""], ["CTR", "1.4%", "2.6%", "1.21%", "185"], ["Payroll 92D Upgrades", "1.0%", "0.8%", "-0.12%", "88"], ["Payroll Cancels post upgrade", "0.2%", "0.1%", "-0.12%", "50"], ["Greater than 360D", "", "", "", ""], ["KPIs", "CONT.", "TEST", "Δ", "ITC"], ["Sample Size", "4.9K", "4.8K", "", ""], ["Impressions", "30.6%", "83.1%", "", ""], ["CTR", "1.1%", "1.4%", "0.30%", "127"], ["Payroll 92D Upgrades", "0.3%", "0.8%", "0.50%", "267 A"], ["Payroll Cancels post upgrade", "", "", "", ""], ["", "0.0%", "0.1%", "0.10%", "N/A"], ["Global Business Solutio", "ns Group", "31"], ["Results: POSITIVE NEGATIVE\nBIZ IMPACT BIZ IMPACT", "", "Call Outs: A D G"], ["", "FLAT &\nROLL OUT", ""], ["", "", ""], ["POSITIV", "", ""], ["", "POSITIV", "E"], ["RESULTS", "BIZ IMPACT", ""], ["Access Point", "IPD", "", "", "", ""], ["", "Impressions", "Reach", "CTR", "Benchmark", "ITB"], ["Banking - Hellobox", "371", "5.1%", "0.50%", "0.34%", "147"], ["Expenses - Hellobox", "951", "13.0%", "0.10%", "0.11%", "91"], ["Invoices - Hellobox", "1,780", "24.2%", "0.30%", "0.22%", "136"], ["Reports - Hellobox", "5", "0.1%", "0.00%", "0.33%", "0"], ["SBSEG QBO Hellobox\nAppEmployees", "4,234", "57.7%", "1.30%", "0.40%", "325"], ["Access Point", "IR offers", "", "QRS offers", ""], ["", "Impressions", "CTR", "Impressions", "CTR"], ["Banking - Hellobox", "371", "0.50%", "317", "0.00%"], ["Expenses - Hellobox", "951", "0.10%", "140", "0.70%"], ["Invoices - Hellobox", "1,780", "0.30%", "119", "0.00%"], ["Reports - Hellobox", "5", "0.00%", "2", "0.00%"], ["SBSEG QBO Hellobox AppEmployees", "4,234", "1.30%", "B 380", "0.30%"], ["Global Business Solutio", "ns Group", "32"], ["Results: POSITIVE NEGATIVE\nBIZ IMPACT BIZ IMPACT", "", "Call Outs: A D G"], ["", "FLAT &\nROLL OUT", ""], ["", "", ""], ["POSITIVE", "", ""], ["", "POSITIVE", ""], ["RESULTS", "BIZ IMPACT", ""], ["HIGHLIGHTS", "", "LOWLIGHTS"], ["● Although small sample sizes, stat sig reads on\nupgrades were achieved\n● Highly contextual access points drove majority of\nthe engagement and upgrades", "", "● More access points were chosen accidentally compared to\ncontrol which did led to lower coverage amongst control\n● Limited offers launched than planned due to operational\nissues which led to a very small sample size"], ["", "", ""], ["NEXT STEPS & IMPLICATIONS", "", ""], ["● Roll out treatment offers that were successfully tested along with offers that were shelved due to operational issues\n● Expand offers to standalone customers as well\n● Utilize lot more insights to expand on the volume of customers we could personalize content for", "", ""], ["Global Business Solutio", "ns Group", "33"], ["Results: POSITIVE NEGATIVE\nBIZ IMPACT BIZ IMPACT", "", "Call Outs: A D G"], ["", "FLAT &\nROLL OUT", ""], ["", "", ""]] | V9: Alt GET (slide 31): audience was tenured | Alt TO (slide 31): mers, there is directional evidence that | Alt BY (slide 31): Payroll tenure | Alt Product (slide 32): Invoicing | Alt TO (slide 32): the experiment QRS remediation offers | Alt GET (slide 33): to manually send the wrap | Alt TO (slide 33): incremental upgrades | Date source: CSV – Current Target Launch Date | Name source: CSV | Business Impact updated from Results Report | Status enriched from Results Report | W9: 30–33 | X9: Copy of FY'25_ CRM Analytics Monthly Experiment_Notebook_AC.pdf
A10: ELM-7175 | B10: QBO Cancel Flow - new discounts to new audiences | C10: 01-30-2025 | D10: A) FTU Subscribers <60D Tenure B) Trialers C) Ess & Plus SKU Medium and High Price | E10: PIC TIME | F10: Incentivizing them with a discount to make them feel supported as valued customers | G10: GET: A) FTU Subscribers <60D Tenure B) Trialers C) Ess & Plus SKU Medium and High Price | TO: PIC TIME | BY: Incentivizing them with a discount to make them feel supported as valued customers | H10: If we offer a discount to customer segments that have historically not been offered a discount when initiating cancel, we will increase the save rate of those segments by 105-110 ITC Results Early Tenure Discount KPIs TEST CONTROL Δ ITC Pr(T>C) Sample Size 9,000 8,961 A Save Rate 8.0% 7.8% 0.3% 103.3 64.7% Retained 92d (after save) 53.6% 49.7% 3.9% 107.8 96.0% B Learnings & Implications A● The discounts tested for Early Tenured had flat and directionally positive impact on Save Rate | I10: & Implications A● The discounts tested for Early Tenured had flat and directionally positive impact on Save Rate KPIs TEST CONTROL Δ ITC Pr(T>C) Sample Size 9,000 8,961 A● The increased Save Rate was largely driven by the new discounts Save Rate 8.0% 7.8% 0.3% 103.3 64.6% (+0.6%). Saved by CS 0.4% 0.4% -0.02% 94.6 36.5% Saved by Upgrade 0.2% 0.1% 0.1% 145.5 85.3% A ●B On top of increasing the overall Save Rate, this campaign also Saved by Downgrade 0.4% 0.4% -0.04% 91.0 31.2% managed to drop the number of Cancel Flow Abandoners, which Saved by Discount 0.6% 0.0% 0.6% explains the increase in 92d Retention Exited Cancel Flow 6.4% 6.8% -0.36% 94.6 13.2% B ●C 61% of cancel flow traffic saw the Discount IPD KPIs TEST CONTROL Δ & Implications A● The campaign manages to improve Save Rate by 104 ITC for ESS + PL w/60d+ Tenure; however, these are not coming from an increase in the discount take rate KPIs TEST CONTROL Δ ITC Pr(T>C) Sample Size 10,597 10,611 ●A The increase in Save Rate was mainly driven by an increase in Save Rate 9.7% 9.4% 0.4% 104.0 82.0% cancel flow abandoners. Saved by CS 0.5% 0.5% 0.0% 102.0 54.1% Saved by Upgrade 0.1% 0.1% 0.0% 63.7 INSUFFICIENT ● There was a noticeable drop in ‘Saved by Discount’, which is Saved by Downgrade 0.8% 0.9% -0.1% 91.8 27.9% B mainly driven by a drop in ‘Discount IPD’ reach. Saved by Discount 0.8% 1.2% -0.4% 65.9 0.2% Exited Cancel Flow 7.5% 6.7% 0.9% 113.0 99.3% & Implications A● The campaigns managed to improve Save Rate by 118.7 ITC (+27 saves) ●B 92d Retention was also improved by 113.4 ITC (+9 saves) KPIs TEST CONTROL Δ ITC Pr(T>C) Sample Size 2,000 2,041 ●A Even though there’s observed improvement on Save Rate, we don’t Save Rate 8.6% 7.2% 1.3% 118.7 92.2% see that customers are taking the discounts. In fact, the goodness is Saved by CS 0.7% 0.5% 0.2% 129.9 74.5% coming from an increase in cancel flow abandoners. Saved by Upgrade 0.1% 0.1% 0.0% 68.0 INSUFFICIENT CCR Cancellation Funnel non-CCR Cancellation Funnel A● During the experiment, only 13% of all trial signups were CCR Trialers (17k CCR vs. 112k 17k 49% 112k 23% non-CCR). A & Implications A● The discounts tested for Early Tenured customers have managed to increase Save Rate by 110.3 ITC (40 additional saves) ●B Despite a better Save Rate on Trialers and “Essentials & Plus > 60 days”, this A● The increased Save Rate was driven largely driven by the new discounts (+0.6%). There’s an observed increase in CS saves (+0.2%). ●B Despite the improvement on Save Rate, the Multi-Screen still manages to save more customers. A● There’s a directionally goodness on Save Rate; however, the percentage of customers being saved by customers has dropped (-0.1%). The increase in Save Rate is mostly coming from customers abandoning the Cancel Flow (+1.4%) A ● Even though there’s observed goodness on Save Rate, we don’t see that customers are taking the discounts. In fact, most of the goodness is coming from customers abandoning the cancel flow. B● Trialers are not abandoning the cancel flow to take the discount at a later point, as observed by the discount take rate in a 31d window since first cancel flow engagement. C ● Only CCR Trialers have to go to the cancellation flow to avoid conversion; however, only 15% of Trialers were CCR (much less than expected). Also, 43% of CCR Trialers are cancelling outside the cancellation flow (e.g. passive cancels, cancel through CS, etc.) Repository enables hyper-personalization To From QRS suggests “what” Makes Why do I to recommend - based sense!!! see these on local model ads!? QRS suggests “what” to recommend based on propensity models GTM qualitative Hyper-personalized research based ELM IPDs product value props Generic ELM IPDs IR explains “why” we Spokesmodel to GTM qualitative recommend - based generate dynamic research based product on customer activities contextual messages value props and reduce fatigue Current state Future state Global Business Solutions Group | J10: Payments | K10: IPD | L10: Trending Positive (Inferred for review) | Results: 5.0 MEASURE: Live - Waiting for Results | M10: Positive Biz Impact | 103.3 ITC-1 | 105.2 ITC-2 | N10: https://docs.google.com/presentation/d/1YY4WQ8uJM_ocDfpWIqUxH3Z7ZkPX1nsmwYIc9G2gzPU/edit?usp=sharing | O10: Cancel Rate | P10: 103.3 | Q10: Retention Rate | R10: 105.2 | U10: [[""], ["AGENDA"], ["TOPIC", "", "TIME"], ["1.QBO Cancel Flow Discounts - ELM 7175\nAndre", "", "12 Min"], ["2.Annual Plan for >12M Customers - ELM-7558\nAndre", "", "12 Min"], ["3.Payments Propensity - ELM 7510\nNaveen", "", "12 Min"], ["4.AE Customer Coverage - ELM 7665\nNaveen", "", "12 Min"], ["5.QBO What’s New - ELM 7188\nBhumika", "", "12 Min"], ["Global Business Solutio", "ns Group", "34"], ["", "", "", ""], ["SOURCE OF TRUTH\nELM - 7175\nNew Discounts to\nQBO Customers in\nCancel Flow\nELM Driver: Aditi Bhargava\nCRM Analytics: Karthik Renganathan/Andre Remy\nELM Workstream: Retention\nDate: 10-31-2024\nEPLMr Qeuisckebasne Rteecorrd: ENLM-a717m5 e\nWorkbook: Link\nBusiness Brief: Link\nSlack Channel: Link", "", "", "SWAG Effort Size\nM"], ["", "", "", "35\nTemplate v5.0 Updated Aug 2024"], ["SOURCE OF TRUTH"], ["ELM - 7175"], ["ELM Driver: Aditi Bhargava\nCRM Analytics: Karthik Renganathan/Andre Remy", ""], ["ELM Workstream: Retention\nDate: 10-31-2024\nEPLMr Qeuisckebasne Rteecorrd: ENLM-a717m5 e\nWorkbook: Link", ""], ["Business Brief: Link\nSlack Channel: Link", ""], ["", "SWAG Effort Size", "", ""], ["", "M", "", ""], ["", "", "", ""], ["", "", "35\nv5.0 Updated Aug 20", ""], ["en\nLink", ""], ["", "Link"], ["", "Link"], ["", "", "", "", "", "", "", "", "", ""], ["POSITIVE BIZ IMPACT\nNew Cancel Flow Disc\n<60d Tenure\nOffer discounts to customer segments that have historically\ndiscount (FTU Subscribers <60D Tenure)\nBusiness Impact: POSITIVE\nBIZ IMPACT\nThe campaign was able to directionally improve Save\nimproved 92d Retention. Annually, will translate into +\ncompanies | +$280k to the Ecosystem Revenue an", "", "POSITIVE BIZ IMPACT", "", "", "PRODUCTS: QBO ● DRIVER: Aditi B ● QB:", "ELM-7175", "● SOT:", "Deck", "● LAUNCH: 01-30-25"], ["", "", "", "", "", "Objective\nGet A) FTU Subscribers <60D Tenure B) Trialers C) Ess & Plus SKU Medium and High Price\nSensitive Customers\nTo Accept a discount instead of canceling their subscription\nBy Incentivizing them with a discount to make them feel supported as valued customers\nHypothesis\nIf we offer a discount to customer segments that have historically not been offered a\ndiscount when initiating cancel, we will increase the save rate of those segments by 105-110\nITC\nResults", "", "", "", ""], ["", "New Cancel Flow Disc\n<60d Tenure\nOffer discounts to customer segments that have historically\ndiscount (FTU Subscribers <60D Tenure)", "", "", "ounts\nnot been offered a", "", "", "", "", ""], ["", "", "", "", "", "", "", "", "", ""], ["", "Business Impact: POSITIVE\nBIZ IMPACT\nThe campaign was able to directionally improve Save\nimproved 92d Retention. Annually, will translate into +\ncompanies | +$280k to the Ecosystem Revenue an", "", "", "Rate and positively\n210 retained", "", "", "", "", ""], ["", "", "", "", "nually", "", "", "", "", ""], ["", "", "", "", "", "", "", "", "", ""], ["Early Tenure Discount", "", "", "", "", "", ""], ["KPIs", "TEST", "CONTROL", "Δ", "", "ITC", "Pr(T>C)"], ["Sample Size", "9,000", "8,961", "A", "", "", ""], ["Save Rate", "8.0%", "7.8%", "0.3%", "", "103.3", "64.7%"], ["Retained 92d (after save)", "53.6%", "49.7%", "3.9%", "", "107.8", "96.0%"], ["Global Business Solutio", "ns Group", "36"], ["", "Call Outs: A D G"], ["FLAT &\nROLL OUT", ""], ["", ""], [""], ["POSITIVE BIZ IMPACT"], ["Early Tenure Discount", "", "", "", "", "", ""], ["KPIs", "TEST", "CONTROL", "Δ", "ITC", "Pr(T>C)", ""], ["Sample Size", "9,000", "8,961", "", "", "", ""], ["Save Rate", "8.0%", "7.8%", "0.3%", "103.3", "64.6%", ""], ["Saved by CS", "0.4%", "0.4%", "-0.02%", "94.6", "36.5%", ""], ["Saved by Upgrade", "0.2%", "0.1%", "0.1%", "145.5", "85.3%", ""], ["Saved by Downgrade", "0.4%", "0.4%", "-0.04%", "91.0", "31.2%", ""], ["Saved by Discount", "0.6%", "0.0%", "0.6%", "", "", ""], ["Exited Cancel Flow", "6.4%", "6.8%", "-0.36%", "94.6", "13.2%", ""], ["KPIs", "TEST", "CONTROL", "Δ", ""], ["Viewed Billing IPD", "99.3%", "99.7%", "-0.4%", ""], ["Discount IPD", "61.4%", "0.0%", "61.4%", ""], ["'Keep my Plan' IPD", "37.9%", "99.7%", "-61.7%", ""], ["Global Business Solutio", "ns Group", "37"], ["Results: POSITIVE NEGATIVE\nBIZ IMPACT BIZ IMPACT", "FLAT &\nROLL OUT", "Call Outs: A D G"], ["", "BROKEN & UNMEASURABLE\nNew Cancel Flow Disc\nESS + PL w/ 60d+\nOffer discounts to customer segments that have historically\ndiscount regardless of their price sensitivity (Ess & Plus SKU", "", "BROKEN & UNMEASURABLE", "", "", "PRODUCTS: QBO ● DRIVER: Aditi B ● QB:", "ELM-7175", "● SOT:", "Deck", "● LAUNCH: 01-30-25"], ["", "", "", "", "", "", "Objective\nGet A) FTU Subscribers <60D Tenure B) Trialers C) Ess & Plus SKU Medium and High Price\nSensitive Customers\nTo Accept a discount instead of canceling their subscription\nBy Incentivizing them with a discount to make them feel supported as valued customers\nHypothesis\nIf we offer a discount to customer segments that have historically not been offered a\ndiscount when initiating cancel, we will increase the save rate of those segments by 105-110\nITC\nResults", "", "", "", ""], ["", "", "New Cancel Flow Disc\nESS + PL w/ 60d+\nOffer discounts to customer segments that have historically\ndiscount regardless of their price sensitivity (Ess & Plus SKU", "", "", "ounts\nTenure\nhave had a standard\nw/ 60d+ Tenure)", "", "", "", "", ""], ["", "", "", "", "", "", "", "", "", "", ""], ["", "Business Impact: BROKEN &\nUNMEASURABLE\nThe low Discount IPDs reach on the TEST group compa\nmade this campaign unmeasurable. Ensure Discount i\ncomparable across both groups and retest this expe", "", "", "", "red to CONTROL\nmpression is", "", "", "", "", ""], ["", "", "", "", "", "rience", "", "", "", "", ""], ["", "", "", "", "", "", "", "", "", "", ""], ["Essential & Plus > 60 days", "", "", "", "", ""], ["KPIs", "TEST", "CONTROL", "Δ", "ITC", "Pr(T>C)"], ["Sample Size", "10,597", "10,611", "", "", ""], ["Save Rate", "9.7%", "9.4%", "0.4%", "104.0", "82.0%"], ["Retained 92d (after save)", "66.5%", "66.0%", "0.4%", "100.7", "43.7%"], ["Global Business Solutio", "ns Group", "38"], ["", "Call Outs: A D G"], ["FLAT &\nROLL OUT", ""], ["", ""], [""], ["BROKEN & UNMEASURABLE"], ["Essential & Plus > 60 days", "", "", "", "", ""], ["KPIs", "TEST", "CONTROL", "Δ", "ITC", "Pr(T>C)"], ["Sample Size", "10,597", "10,611", "", "", ""], ["Save Rate", "9.7%", "9.4%", "0.4%", "104.0", "82.0%"], ["Saved by CS", "0.5%", "0.5%", "0.0%", "102.0", "54.1%"], ["Saved by Upgrade", "0.1%", "0.1%", "0.0%", "63.7", "INSUFFICIENT"], ["Saved by Downgrade", "0.8%", "0.9%", "-0.1%", "91.8", "27.9%"], ["Saved by Discount", "0.8%", "1.2%", "-0.4%", "65.9", "0.2%"], ["Exited Cancel Flow", "7.5%", "6.7%", "0.9%", "113.0", "99.3%"], ["KPIs", "TEST", "CONTROL", "Δ"], ["Viewed Billing IPD", "86.7%", "99.7%", "-12.9%"], ["Discount IPD", "40.4%", "74.6%", "-34.2%"], ["'Keep my Plan' IPD", "46.4%", "25.1%", "21.3%"], ["Global Business Solutio", "ns Group", "39"], ["Results: POSITIVE NEGATIVE\nBIZ IMPACT BIZ IMPACT", "", "Call Outs: A D G"], ["", "FLAT &\nROLL OUT", ""], ["", "", ""], ["", "", "", "", "", "", "", "", "", ""], ["POSITIVE BIZ IMPACT\nNew Cancel Flow Disc\nTrialers\nOffer discounts to customer segments that have historically\ndiscount (Trialers)\nBusiness Impact: POSITIVE\nBIZ IMPACT\nThe campaign was able to improve Save Rate for Trial\nnot enough evidence that this increase is directly com\nAnnually, this campaign would add +107 retained co\nEco. Revenue", "", "POSITIVE BIZ IMPACT", "", "", "PRODUCTS: QBO ● DRIVER: Aditi B ● QB:", "ELM-7175", "● SOT:", "Deck", "● LAUNCH: 01-30-25"], ["", "", "", "", "", "Objective\nGet A) FTU Subscribers <60D Tenure B) Trialers C) Ess & Plus SKU Medium and High Price\nSensitive Customers\nTo Accept a discount instead of canceling their subscription\nBy Incentivizing them with a discount to make them feel supported as valued customers\nHypothesis\nIf we offer a discount to customer segments that have historically not been offered a\ndiscount when initiating cancel, we will increase the save rate of those segments by 105-110\nITC\nResults", "", "", "", ""], ["", "New Cancel Flow Disc\nTrialers\nOffer discounts to customer segments that have historically\ndiscount (Trialers)", "", "", "ounts\nnot been offered a", "", "", "", "", ""], ["", "", "", "", "", "", "", "", "", ""], ["", "", "", "", "ers; however, there’s\ning from discounts.", "", "", "", "", ""], ["", "", "", "", "mpanies | +$208k", "", "", "", "", ""], ["Trialers", "", "", "", "", ""], ["KPIs", "TEST", "CONTROL", "Δ", "ITC", "Pr(T>C)"], ["Sample Size", "2,000", "2,041", "", "", ""], ["Save Rate", "8.6%", "7.2%", "1.3%", "118.7", "92.2%"], ["92d Retention (after Save)", "46.3%", "42.0%", "4.2%", "110.0", "81.8%"], ["Global Business Solutio", "ns Group", "40"], ["", "Call Outs: A D G"], ["FLAT &\nROLL OUT", ""], ["", ""], [""], ["POSITIVE BIZ IMPACT"], ["Trialers", "", "", "", "", "", ""], ["KPIs", "TEST", "CONTROL", "Δ", "ITC", "Pr(T>C)", ""], ["Sample Size", "2,000", "2,041", "", "", "", ""], ["Save Rate", "8.6%", "7.2%", "1.3%", "118.7", "92.2%", ""], ["Saved by CS", "0.7%", "0.5%", "0.2%", "129.9", "74.5%", ""], ["Saved by Upgrade", "0.1%", "0.1%", "0.0%", "68.0", "INSUFFICIENT", ""], ["Saved by Downgrade", "0.9%", "1.2%", "-0.3%", "76.5", "15.8%", ""], ["Saved by Discount", "0.0%", "0.0%", "0.0%", "", "", ""], ["Exited Cancel Flow", "6.9%", "5.3%", "1.5%", "128.3", "97.0%", ""], ["KPIs", "TEST", "CONTROL", "Δ", ""], ["Viewed Billing IPD", "99.5%", "99.5%", "-0.1%", ""], ["Discount IPD", "60.0%", "0.0%", "60.0%", "B"], ["'Keep my Plan' IPD", "39.5%", "99.5%", "-60.1%", ""], ["Clicked 'Take Discount'", "0.8%", "0.0%", "0.8%", ""], ["KPIs", "TEST", "CONTROL", "Δ", ""], ["Trialers", "2,000", "2,041", "", ""], ["Save Rate", "8.6%", "7.2%", "1.3%", ""], ["45d Returned to Cancel Flow\n(of total Trial Traffic)", "6.0%", "6.3%", "-0.3%", "C"], ["Global Business Solutio", "ns Group", "41"], ["Results: POSITIVE NEGATIVE\nBIZ IMPACT BIZ IMPACT", "", "Call Outs: A D G"], ["", "FLAT &\nROLL OUT", ""], ["", "", ""], [""], ["Insights\nA● During the experiment, only 13% of all trial\nsignups were CCR Trialers (17k CCR vs. 112k\nnon-CCR).\nB● CCR Trialers followed three main paths: (1)\nconverted – 49%, (2) let the trial expire by\nremoving their consent to be charged – 30%, or\n(3) entered the cancel flow – 21%\nC● Overall, 2% of all CCR Trialers were saved. Among\nthose saved, 40% became subscribers before their\ntrial ended, while 60% still let their trial expire.\n● Non-CCR Trialers don’t go through the cancel\nD flow. In fact, 77% of them let their trial expire,\nwhich means the cancel flow is not the right place\nto save them. Proactive saves and trial winback\ncampaigns are a better strategy for this group\nNext Step\n● Identify other path CCR customer take to cancel\n(30% that let their Trial Expire)\n● Explore campaigns for CCR Trialers that removed\ntheir auto-charge consent (or that are in the\nprocess of doing so)\n● Test proactive saves for both Trialers"], ["CCR Cancellation Funnel"], [""], ["17k"], ["A"], ["CCR\nSignups"], ["non-CCR Cancellation Funnel"], [""], ["112k"], [""], ["non-CCR\nSignups"], [""], [""], ["49%"], [""], [""], ["Converted"], [""], ["23%"], [""], [""], ["Converted"], [""], ["30%"], [""], [""], ["Trial\nExpired"], ["D"], ["77%"], [""], ["Trial\nExpired"], [""], ["19%"], [""], ["Cancelled\nin Cancel\nFlow"], [""], [""], ["2%\nC"], ["Saved in\nCancel\nFlow"], [""], [""], ["0.3%"], ["Cancelled\nin Cancel\nFlow"], [""], [""], ["0.1%"], ["Saved in\nCancel\nFlow"], [""], ["", "", ""], ["The campaign had positive results for Early Tenure and for Trialers. Performance for ESS & PL w/ 60d+ Tenure was\ninconclusive", "", ""], ["", "", ""], ["HIGHLIGHTS", "", "LOWLIGHTS"], ["● Despite seeing a flat (but directionally positive) impact\non Save Rate for Early Tenure, long-term impact of\nadding these discounts was positive as reflected by the\npositive impact on 92d Retention (+210 retained\ncompanies | +$280k to the Ecosystem Revenue)\n● Save Rate and 92d Retention were also positively\nimpacted for Trialers during the experiment despite\nseeing none of them taking the discount (+107\nretained companies | +$208k Eco. Revenue).", "", "● ESS & PL w/ 60d+ Tenure were not exposed to the discount as\nmuch as expected, which made the experiment inconclusive for\nthis cohort"], ["", "", ""], ["NEXT STEPS & IMPLICATIONS", "", ""], ["● Rollout the discounts for Early Tenured subscribers after 10/31 (date when the ongoing gap closers end)\n● Identify what prevented Trialers from redeeming the discount and rollout TEST to them once is fixed\n● Double down on proactive saves for and winback campaigns for Trialers, as these customers don’t interact much w/ the cancel flow\n● For ESS & PL, perform ROI analysis of Gap Closers to identify if those discounts are better for rollout. If not, fix and retest for ESS & PL w/\n60d+ Tenure", "", ""], ["Global Business Solutio", "ns Group", "43"], ["Results: POSITIVE NEGATIVE\nBIZ IMPACT BIZ IMPACT", "", "Call Outs: A D G"], ["", "FLAT &\nROLL OUT", ""], ["", "", ""], ["", "", "", ""], ["SOURCE OF TRUTH\nELM - 7558\nExpanding Annual for customers with >12M\nTenure Test\nELM Driver: Maya Zultsbeak David\nCRM Analytics: Andre Remy\nELM Workstream: Retention\nDate: 10-22-2024\nEPLMr Qeuisckebasne Rteecorrd: ENLM-a755m8 e\nWorkbook: Link\nBusiness Brief: Link\nSlack Channel: Link", "", "", "SWAG Effort Size\nMini"], ["", "", "", "44\nTemplate v5.1 Updated Oct. 2024"], ["SOURCE OF TRUTH"], ["ELM - 7558\nExpanding Annual for customers with >12M\nTenure Test"], ["ELM Driver: Maya Zultsbeak David\nCRM Analytics: Andre Remy", ""], ["ELM Workstream: Retention\nDate: 10-22-2024\nEPLMr Qeuisckebasne Rteecorrd: ENLM-a755m8 e\nWorkbook: Link", ""], ["Business Brief: Link\nSlack Channel: Link", ""], ["en\nLink", ""], ["", "Link"], ["", "Link"], [""], ["44\nv5.1 Updated Oct. 20"], ["", "", "", "", "", "", "", "", "", ""], ["STILL BAKING\nNew Cancel Flow Di\nOffer discounts to customer segments that have historicall\ndiscount (FTU Subscribers <60D Tenure and Trialers), or h\ndiscount regardless of their price sensitivity.\nSegments (Ess & Plus SKU Medium and High Price Sensitiv\nBusiness Impact: STILL BAKING\nThe campaign was able to improve Save Rate through\nto Early Tenured Customers by 110.3 ITC. This is expe\nadditional saves annually", "", "STILL BAKING", "", "", "PRODUCTS: QBO ● DRIVER: Aditi B ● QB:", "ELM-7175", "● SOT:", "Deck", "● LAUNCH: 01-30-25"], ["", "", "", "", "", "Objective\nGet A) FTU Subscribers <60D Tenure B) Trialers C) Ess & Plus SKU Medium and High Price\nSensitive Customers\nTo Accept a discount instead of canceling their subscription\nBy Incentivizing them with a discount to make them feel supported as valued customers\nHypothesis\nIf we offer a discount to customer segments that have historically not been offered a\ndiscount when initiating cancel, we will increase the save rate of those segments by 105-110\nITC\nResults\nEarly Tenure Discount", "", "", "", ""], ["", "New Cancel Flow Di\nOffer discounts to customer segments that have historicall\ndiscount (FTU Subscribers <60D Tenure and Trialers), or h\ndiscount regardless of their price sensitivity.\nSegments (Ess & Plus SKU Medium and High Price Sensitiv", "New Cancel F", "", "scounts\ny not been offered a\nave had a standard\ne Customers)", "", "", "", "", ""], ["", "", "", "", "", "", "", "", "", ""], ["", "", "", "", "the discounts offered", "", "", "", "", ""], ["", "", "", "", "cted to add 740", "", "", "", "", ""], ["", ""], ["Early Tenure Discount", "", "", "", "", ""], ["KPIs", "TEST", "CONTROL", "Δ", "ITC", "Pr(T>C)"], ["Sample Size", "5,023", "4,919", "", "", ""], ["Save Rate", "8.4%", "7.6%", "0.8%", "110.3", "92.6%"], ["", "", "", "", "", ""], ["Essential & Plus > 60 days", "", "", "", "", ""], ["KPIs", "TEST", "CONTROL", "Δ", "ITC", "Pr(T>C)"], ["Sample Size", "3,387", "3,424", "", "", ""], ["Save Rate", "9.9%", "9.4%", "0.5%", "105.2", "75.2%"], ["", "", "", "", "", ""], ["Trialers", "", "", "", "", ""], ["KPIs", "TEST", "CONTROL", "Δ", "ITC", "Pr(T>C)"], ["Sample Size", "988", "993", "", "", ""], ["Save Rate", "7.5%", "5.3%", "2.2%", "140.3", "97.2%"], ["Global Business Solutio", "ns Group", "162"], ["", "Call Outs: A D G"], ["FLAT &\nROLL OUT", ""], ["", ""], [""], ["POSITIVE BIZ IMPACT"], ["Early Tenure Discount", "", "", "", "", "", "", "", "", ""], ["KPIs", "TEST", "CONTROL", "Δ", "ITC", "Pr(T>C)", "Multi-Screen", "Δ", "ITMS", "Pr(T>C)"], ["Sample Size", "5,023", "4,919", "", "", "", "5,057", "", "", ""], ["Save Rate", "8.4%", "7.6%", "0.8%", "110.3", "92.6%", "15.2%", "-6.8%", "55.1", "0.0%"], ["Saved by CS", "0.3%", "0.1%", "0.2%", "244.8", "97.2%", "0.2%", "0.1%", "137.3", "78.5%"], ["Saved by Upgrade", "0.1%", "0.1%", "0.0%", "122.4", "61.2%", "0.1%", "0.0%", "125.8", "62.9%"], ["Saved by Downgrade", "0.4%", "0.4%", "-0.1%", "83.9", "29.5%", "0.2%", "0.2%", "201.4", "95.9%"], ["Saved by Discount", "0.6%", "0.0%", "0.6%", "", "100.0%", "0.0%", "0.6%", "", ""], ["Unattributed Saves", "6.8%", "6.8%", "0.0%", "100.3", "51.7%", "14.6%", "-7.7%", "46.9", "0.0%"], ["Global Business Solutio", "ns Group", "163"], ["Results: POSITIVE NEGATIVE\nBIZ IMPACT BIZ IMPACT", "", "Call Outs: A D G"], ["", "FLAT &\nROLL OUT", ""], ["", "", ""], [""], ["STILL BAKING"], ["Essential & Plus > 60 days", "", "", "", "", "", "", "", "", ""], ["KPIs", "TEST", "CONTROL", "Δ", "ITC", "Pr(T>C)", "Multi-Screen", "Δ", "ITMS", "Pr(T>C)"], ["Sample Size", "3,387", "3,424", "", "", "", "3,406", "", "", ""], ["Save Rate", "9.9%", "9.4%", "0.5%", "105.2", "75.2%", "30.0%", "-20.1%", "33.0", "0.0%"], ["Saved by CS", "0.1%", "0.4%", "-0.3%", "36.1", "2.2%", "0.4%", "-0.3%", "35.9", "2.1%"], ["Saved by Upgrade", "0.1%", "0.2%", "-0.1%", "50.5", "17.5%", "0.1%", "-0.1%", "60.3", "28.9%"], ["Saved by Downgrade", "0.7%", "0.8%", "-0.1%", "89.9", "35.4%", "1.1%", "-0.3%", "67.0", "6.3%"], ["Saved by Discount", "0.8%", "1.2%", "-0.4%", "65.7", "4.6%", "1.2%", "-0.4%", "63.8", "3.4%"], ["Unattributed Saves", "8.0%", "6.6%", "1.4%", "121.7", "98.9%", "26.8%", "-18.8%", "29.9", "0.0%"], ["Global Business Solutio", "ns Group", "164"], ["Results: POSITIVE NEGATIVE\nBIZ IMPACT BIZ IMPACT", "", "Call Outs: A D G"], ["", "FLAT &\nROLL OUT", ""], ["", "", ""], [""], ["BROKEN & UNMEASURABLE"], ["BROKEN & UNMEASURABLE\nExperiment Customer Experience", "", "", "", "", "", "", "", "", ""], ["Trialers", "", "", "", "", "", "", "", "", ""], ["KPIs", "TEST", "CONTROL", "Δ", "ITC", "Pr(T>C)", "Multi-Screen", "Δ", "ITMS", "Pr(T>C)"], ["Sample Size", "988", "993", "A", "", "", "1,002", "", "", ""], ["Save Rate", "7.5%", "5.3%", "2.2%", "140.3", "97.2%", "17.0%", "-9.5%", "44.1", "0.0%"], ["Saved by CS", "0.1%", "0.0%", "0.1%", "", "75.0%", "0.2%", "-0.1%", "50.7", "31.6%"], ["Saved by Upgrade", "0.0%", "0.2%", "-0.2%", "0.0", "12.3%", "0.0%", "0.0%", "", "50.3%"], ["Saved by Downgrade", "0.6%", "0.0%", "0.6%", "", "99.3%", "0.4%", "0.2%", "152.1", "73.0%"], ["Saved by Discount A", "0.0%", "0.0%", "0.0%", "", "50.1%", "0.0%", "0.0%", "", "50.3%"], ["Unattributed Saves", "6.6%", "4.8%", "1.7%", "136.1", "94.8%", "15.6%", "-9.0%", "42.3", "0.0%"], ["Global Business Solutio", "ns Group", "165"], ["Results: POSITIVE NEGATIVE\nBIZ IMPACT BIZ IMPACT", "", "Call Outs: A D G"], ["", "FLAT &\nROLL OUT", ""], ["", "", ""], ["NEGATIVE Biz Impact"], ["Single Screen increased cancellation rate by 102.2\nITC"], [""], ["HIGHLIGHTS", "", "LOWLIGHTS"], ["● The new design was able to recover some of the CS\nContact volume we lost in the original test.", "", "● Main contributor to the increase in cancellation rate was a\ndrop in Discount Take Rate and a drop in unattributed\nsaves"], ["", "", ""], ["NEXT STEPS & IMPLICATIONS", "", ""], ["● Follow-up with 92d Retention read (ETA: 02/14/2025)\n● Rollout the new cancel flow experience to California Users to comply with state mandate\n● Keep testing new levers on the cancel flow [ELM-7175]\n● By April 2025, all states will be on the new Cancel Flow to comply with Federal mandate", "", ""], ["Intuit Confidential and Pro", "prietary"], ["", "", ""], ["Results -\n31D Wrap report | Initial reads", "", "7"], ["", "", ""], ["", "", ""], ["Current state"], [""], ["Future state"], ["", "Cohort AA", "Cohort BB", "Cohort CC"], ["What they are?", "DIWM eligible", "QRS Payments\neligible", "QRS Payroll\neligible"], ["What is the audience size?", "262.1K", "257.1K", "117.7K"], ["Viewed DIWM IR offers ?", "Yes", "Yes", "Yes"], ["Viewed QRS Payroll IR\noffers?", "Yes", "No", "Yes"], ["Viewed QRS Payments IR\noffers?", "Yes", "Yes", "No"], ["Viewed Non-QRS Payroll\noffers?", "Yes", "Yes", "Yes"], ["Global Business Solution", "s G2ro8up9"], [""], ["INCONCLUSIVE\nTRENDING POSITIVE"]] | V10: Alt Product (slide 35): QBO | Alt TO (slide 35): QBO Customers in | Alt Date (slide 36): 01-30-25 | Alt Product (slide 36): QBO | Alt TO (slide 36): mers | Alt TO (slide 37): mer Experience | Alt BY (slide 37): the new discounts | Alt Date (slide 38): 01-30-25 | Alt Hypothesis (slide 38): If we offer a discount to customer segments that have historically not been offered a discount when initiating cancel, we will increase the save rate of those segments by 105-110 ITC Results Essential & Plus > 60 days KPIs TEST CONTROL Δ ITC Pr(T>C) Sample Size 10,597 10,611 Save Rate 9.7% 9.4% 0.4% 104.0 82.0% Retained 92d (after save) 66.5% 66.0% 0.4% 100.7 43.7% Learnings & Implications A● The campaign manages to improve Save Rate by 104 ITC for ESS + PL w/60d+ Tenure; however, these are not coming from an increase in the discount take rate | Alt Product (slide 38): QBO | Alt TO (slide 38): mers | Alt TO (slide 39): mer Experience | Alt BY (slide 39): an increase in | Alt Date (slide 40): 01-30-25 | Alt Hypothesis (slide 40): If we offer a discount to customer segments that have historically not been offered a discount when initiating cancel, we will increase the save rate of those segments by 105-110 ITC Results Trialers KPIs TEST CONTROL Δ ITC Pr(T>C) Sample Size 2,000 2,041 Save Rate 8.6% 7.2% 1.3% 118.7 92.2% 92d Retention (after Save) 46.3% 42.0% 4.2% 110.0 81.8% Learnings & Implications A● The campaigns managed to improve Save Rate by 118.7 ITC (+27 saves) ●B 92d Retention was also improved by 113.4 ITC (+9 saves) | Alt Product (slide 40): QBO | Alt TO (slide 40): mers | Alt Hypothesis (slide 41): 1: Introducing discounts gave trialers a stop/think Saved by Discount 0.0% 0.0% 0.0% moment, causing them to back down from cancelling A | Alt TO (slide 41): mer Experience | Alt BY (slide 41): CS 0.7% 0.5% 0.2% 129.9 74.5% | Alt TO (slide 42): be charged – 30%, or | Alt BY (slide 42): removing their consent to be charged – 30%, or | Alt status (slide 42): Positive | Alt GET (slide 43): to manually send the wrap | Alt TO (slide 43): the discount as | Alt BY (slide 43): the this cohort | Alt Date (slide 44): 10-22-2024 | Alt TO (slide 44): mers with >12M | Campaign re-appears on slide 162 (gap from slide 44) | Alt Date (slide 162): 01-30-25 | Alt Hypothesis (slide 162): Segments (Ess & Plus SKU Medium and High Price Sensitive Customers) If we offer a discount to customer segments that have historically not been offered a discount when initiating cancel, we will increase the save rate of those segments by 105-110 ITC Results Early Tenure Discount KPIs TEST CONTROL Δ ITC Pr(T>C) Sample Size 5,023 4,919 Save Rate 8.4% 7.6% 0.8% 110.3 92.6% Essential & Plus > 60 days KPIs TEST CONTROL Δ ITC Pr(T>C) Sample Size 3,387 3,424 Save Rate 9.9% 9.4% 0.5% 105.2 75.2% Trialers KPIs TEST CONTROL Δ ITC Pr(T>C) Sample Size 988 993 Save Rate 7.5% 5.3% 2.2% 140.3 97.2% Learnings & Implications A● The discounts tested for Early Tenured customers have managed to increase Save Rate by 110.3 ITC (40 additional saves) ●B Despite a better Save Rate on Trialers and “Essentials & Plus > 60 days”, this | Alt Product (slide 162): QBO | Alt TO (slide 162): mers | Alt TO (slide 163): mer Experience | Alt BY (slide 163): CS 0.3% 0.1% 0.2% 244.8 97.2% 0.2% 0.1% 137.3 78.5% | Alt GET (slide 164): ing issues, we recommend keep this experiment | Alt TO (slide 164): mer Experience | Alt BY (slide 164): CS 0.1% 0.4% -0.3% 36.1 2.2% 0.4% -0.3% 35.9 2.1% | Alt TO (slide 165): mer Experience | Alt BY (slide 165): CS 0.1% 0.0% 0.1% 75.0% 0.2% -0.1% 50.7 31.6% | Campaign re-appears on slide 286 (gap from slide 165) | Alt Date (slide 286): 02/14/2025 | Alt GET (slide 286): to manually send the wrap | Alt TO (slide 286): mers to churn at a higher rate | Alt BY (slide 286): 102.2 | Alt TO (slide 288): ry enables hyper-personalization | Alt TO (slide 289): mer distribution within campaign setup | Alt GET (slide 290): ed for Payroll | Alt TO (slide 290): mers who were targeted for Payroll | Date source: CSV – Current Target Launch Date | Name source: CSV | Business Impact updated from Results Report | Status enriched from Results Report | W10: 34–290 | X10: Copy of FY'25_ CRM Analytics Monthly Experiment_Notebook_AC.pdf
A11: ELM-7558 | B11: Expanding Annual for customers with more than 12M Tenure Test | C11: 01-30-2025 | D11: QuickBooks Online and Advanced subscribers with a high propensity | E11: 3-27-25 | F11: Making them aware that they save 10% by switching to an annual plan. | G11: GET: QuickBooks Online and Advanced subscribers with a high propensity | TO: 3-27-25 | BY: Making them aware that they save 10% by switching to an annual plan. | H11: switch to annual billing page If we surface the discounted annual plan to customers with 12M tenure with a high propensity to churn , we will increase annual plan take rate and retention amongst those customers. Results 92d Retention Cohort Sample Size TEST CON. Δ ITC Pr(T>C) All 757,558 95.4% 95.4% -0.05% 99.95 17% 1y - 2y Tenure 228,920 94.5% 94.8% -0.23% 99.75 0.6% 2 - 4y Tenure (SS + PL + ADV) 189,691 95.3% 95.1% A 0.21% 100.2 100% 2 - 4y Tenure (ESS) 65,172 95.6% 95.7% -0.10% 99.89 25.0% 4y+ Tenure 273,774 96.0% 96.1% -0.05% 99.95 27% Learnings & Implications A● 92d Retention improved only for SS + PL + ADV customers w/2-4 years tenure by 100.2 ITC (196 additional saves) | I11: & Implications A● 92d Retention improved only for SS + PL + ADV customers w/2-4 years tenure by 100.2 ITC (196 additional saves) KPIs TEST CON. Δ ITC Pr(T>C) ●A The campaign managed to add ~5k customers to the Sample Size 378,705 378,853 annual plan 31d Moved to Annual 1.6% 0.3% 1.3% 596.1 100% A 31d QBO Annual Plan 1.5% 0.2% 1.3% 726.4 100% ●B However, the adoption in the annual plan didn’t improve 31d Payroll Annual Plan 0.2% 0.1% 0.1% 264.1 100% 92d Retention; in fact, it’s trending negative. As a result; 92d Retention 95.4% 95.4% -0.05% 99.95 17% 92d Ecosystem Revenue didn’t show any significant B 92d Eco Revenue $316.5 $316.0 50.2% 100.2 74% improvement Global Business Solutions Group 46 A● 92d Retention was negative for customers with 1 - 2 year and 4+ years. ●B Even though the campaign was able to move customer to annual billing frequency for all customers in this experiment, we only see a retention improvement for customers between 2 and 4 years (160 additional saves) Global Business Solutions Group 47 A● Annual plan adoption was positively impacted in all SKUs ●B Essentials was the only SKU that had a negative impact on 92d Retention C● Flat results on 92d Ecosystem Revenue are expected to be reverted on the long term due to a higher retention Global Business Solutions Group 48 Asset Name Emails Sent Reach Open Rate ITB CTR ITB Unsub Rate ITB Email 01 266,190 70.3% 29.1% 90.8 1.3% 140.8 0.1% 96.0 ● Email reached +70% of all customers A Email 02 264,356 69.8% B 27.8% 86.7 0.8% 91.3 0.1% 119.4 assigned to the experiment Email Benchmark* 32% 0.9% 0.09% ● The second email was the least effective B IPD across all engagement metrics Access Point Impressions Reach CTR Benchmark ITB Advanced Shell - Banner 10,754 2.8% 3.1% N/A ● C Despite IPD reach being lower than Banking - Hellobox 68,635 18.1% 0.7% 0.2% 385.72 Email’s, the high IPD CTR was able to drive Invoices - Hellobox 48,263 12.7% 0.5% 1.1% 46.67 more customers to this campaign based QBO Dashboard - Bottom Drawer 115,519 30.5% 2.3% 1.8% 131.52 on the raw number of clicks (8k+ IPD Shell - Banner 169,308 44.7% 3.1% N/A clicks vs 5k+ Email clicks) Global Business Solutions Group 49 | J11: QuickBooks Online | K11: IPD; Email | L11: Trending Positive | Results: 5.1 MEASURE: Complete | M11: Positive Biz Impact | 100.2 ITC-1 | 100.2 ITC-2 | N11: https://docs.google.com/presentation/d/1aox63EiWpgC8VyVoharuLDblWGrHHm23DAYiM9nX_qI/edit#slide=id.g1d9b8a0b231_0_3017 | O11: Retention Rate | P11: 100.2 | Q11: Ecosystem Revenue | R11: 100.2 | S11: Ecosystem Revenue | U11: [["", "", "", "", "", "", "", "", "", ""], ["", "EXPERIMENT RESULTS\nAnnual Plan for >12M cust\nSurfacing the 10% annual discount to custom\ntenure and also have a high propensity to chu\nEmail and IP\nswitch to", "EXPERIMENT RESULTS", "", "", "", "", "", "PRODUCTS: QBO/ADV ● DRIVER: Maya ● QB: ELM-7558 ● SOT: Deck ● DATES: 1-30-25 to 3-27-25", ""], ["", "", "", "", "", "", "", "", "Objective\nGet QuickBooks Online and Advanced subscribers with a high propensity\nto churn and >12M in tenure currently on a monthly plan.\nTo Switch to an annual plan\nBy Making them aware that they save 10% by switching to an annual plan.\nHypothesis\nIf we surface the discounted annual plan to customers with 12M tenure with\na high propensity to churn , we will increase annual plan take rate and\nretention amongst those customers.\nResults", ""], ["", "", "Annual Plan for >", "", "", "omers\ners with >12M in\nrn", "", "", "", ""], ["", "", "", "", "", "", "", "", "", ""], ["", "", "", "", "Email and IP\nswitch to", "Ds linked to in-product\nannual billing page", "", "", "", ""], ["", "", "", "", "", "", "", "", "", ""], ["", "", "", "", "", "", "", "", "", ""], ["", "", "", "", "", "", "", "", "92d Retention\nCohort Sample Size TEST CON. Δ ITC Pr(T>C)\nAll 757,558 95.4% 95.4% -0.05% 99.95 17%\n1y - 2y Tenure 228,920 94.5% 94.8% -0.23% 99.75 0.6%\n2 - 4y Tenure (SS + PL + ADV) 189,691 95.3% 95.1% A 0.21% 100.2 100%\n2 - 4y Tenure (ESS) 65,172 95.6% 95.7% -0.10% 99.89 25.0%\n4y+ Tenure 273,774 96.0% 96.1% -0.05% 99.95 27%\nLearnings & Implications\nA● 92d Retention improved only for SS + PL + ADV customers w/2-4\nyears tenure by 100.2 ITC (196 additional saves)\nGlobal Business Solutions Group 45", ""], ["", "", "", "", "", "", "", "", "", ""], ["", "", "", "", "", "", "", "", "", ""], ["", "", "", "", "", "", "", "", "", ""], ["", "Business Impact: POSITIVE\nBIZ IMPACT\nThe campaign drove higher annual billing adoption, b\nRetention only for 2–4 year customers (SS + PL + ADV).\ncould annually add 520 saves, delivering +$650K in", "", "", "", "ut improved 92d\nTargeting this cohort\nEcosystem Revenue.", "", "", "", ""], ["", "", "", "", "", "", "", "", "", ""], ["", "", "", "", "", "", "", "", "", ""], ["ELM-", "7558"], ["", "", "", "", "", "", ""], ["", "", "92d Retention", "", "", "", ""], ["Cohort", "Sample Size", "TEST", "CON.", "Δ", "ITC", "Pr(T>C)"], ["All", "757,558", "95.4%", "95.4%", "-0.05%", "99.95", "17%"], ["1y - 2y Tenure", "228,920", "94.5%", "94.8%", "-0.23%", "99.75", "0.6%"], ["2 - 4y Tenure (SS + PL + ADV)", "189,691", "95.3%", "95.1%", "A 0.21%", "100.2", "100%"], ["2 - 4y Tenure (ESS)", "65,172", "95.6%", "95.7%", "-0.10%", "99.89", "25.0%"], ["4y+ Tenure", "273,774", "96.0%", "96.1%", "-0.05%", "99.95", "27%"], ["Global Business Solutio", "ns Group", "45"], ["", "Call Outs: A D G"], ["FLAT &\nROLL OUT", ""], ["", ""], [""], ["RESULTS"], ["Overall Results", "", "", "", "", "", ""], ["KPIs", "TEST", "CON.", "Δ", "ITC", "Pr(T>C)", ""], ["Sample Size", "378,705", "378,853", "", "", "", ""], ["31d Moved to Annual", "1.6%", "0.3%", "1.3%", "596.1", "100%", "A"], ["31d QBO Annual Plan", "1.5%", "0.2%", "1.3%", "726.4", "100%", ""], ["31d Payroll Annual Plan", "0.2%", "0.1%", "0.1%", "264.1", "100%", ""], ["92d Retention", "95.4%", "95.4%", "-0.05%", "99.95", "17%", "B"], ["92d Eco Revenue", "$316.5", "$316.0", "50.2%", "100.2", "74%", ""], ["Global Business Solutio", "ns Group", "46"], ["Results: POSITIVE NEGATIVE\nBIZ IMPACT BIZ IMPACT", "", "Call Outs: A D G"], ["", "FLAT &\nROLL OUT", ""], ["", "", ""], [""], ["RESULTS"], ["1 - 2 Years", "", "", "", "", "", ""], ["KPIs", "TEST", "CON.", "Δ", "ITC", "Pr(T>C)", ""], ["Sample Size", "114,462", "114,458", "", "", "", ""], ["31d Moved to Annual", "1.7%", "0.2%", "1.5%", "703.9", "100%", ""], ["31d QBO Annual Plan", "1.6%", "0.1%", "1.5%", "1,092.9", "100%", ""], ["31d Payroll Annual Plan", "0.2%", "0.1%", "0.1%", "205.6", "100%", ""], ["92d Retention", "94.5%", "94.8%", "-0.2%", "99.8", "0.6%", ""], ["92d Eco Revenue", "$298.9", "$298.7", "$0.2", "100.1", "56%", ""], ["3 - 4 Years", "", "", "", "", "", ""], ["KPIs", "TEST", "CON.", "Δ", "ITC", "Pr(T>C)", ""], ["Sample Size", "53,115", "53,586", "", "", "", ""], ["31d Moved to Annual", "1.4%", "0.2%", "1.2%", "622.7", "100%", ""], ["31d QBO Annual Plan", "1.4%", "0.2%", "1.2%", "761.3", "100%", ""], ["31d Payroll Annual Plan", "0.1%", "0.1%", "0.1%", "265.3", "100%", ""], ["92d Retention", "95.5%", "95.5%", "0.1%", "100.1", "77%", ""], ["92d Eco Revenue", "$320.3", "$317.8", "$2.5", "100.8", "88%", ""], ["2 - 3 Years", "", "", "", "", "", ""], ["KPIs", "TEST", "CON.", "Δ", "ITC", "Pr(T>C)", ""], ["Sample Size", "74,344", "73,819", "", "", "", ""], ["31d Moved to Annual", "1.7%", "0.2%", "1.5%", "823.9", "100%", ""], ["31d QBO Annual Plan", "1.6%", "0.2%", "1.4%", "1,001.4", "100%", ""], ["31d Payroll Annual Plan", "0.2%", "0.1%", "0.1%", "359.0", "100%", ""], ["92d Retention", "95.3%", "95.1%", "0.2%", "100.2", "91%", ""], ["92d Eco Revenue", "$305.2", "$302.3", "$3.0", "101.0", "96%", ""], ["4+ Years", "", "", "", "", "", ""], ["KPIs", "TEST", "CON.", "Δ", "ITC", "Pr(T>C)", ""], ["Sample Size", "136,784", "136,990", "", "", "", ""], ["31d Moved to Annual", "1.4%", "0.3%", "1.1%", "441.3", "100%", ""], ["31d QBO Annual Plan", "1.4%", "0.3%", "1.1%", "477.1", "100%", ""], ["31d Payroll Annual Plan", "0.1%", "0.0%", "0.1%", "325.1", "100%", ""], ["92d Retention", "96.0%", "96.1%", "-0.05%", "99.95", "27%", ""], ["92d Eco Revenue", "$335.9", "$337.2", "-$1.3", "99.6", "18%", ""], ["Global Business Solutio", "ns Group", "47"], ["Results: POSITIVE NEGATIVE\nBIZ IMPACT BIZ IMPACT", "", "Call Outs: A D G"], ["", "FLAT &\nROLL OUT", ""], ["", "", ""], [""], ["RESULTS"], ["SS (2 - 4 Years)", "", "", "", "", "", ""], ["KPI", "TEST", "CONTROL", "Δ", "ITC", "Pr(T>C)", ""], ["Sample Size", "58,903", "58,425", "", "", "", ""], ["31d Moved to Annual", "1.9%", "0.2%", "1.8%", "1,127.4", "100.0%", ""], ["92d Retention", "94.9%", "94.8%", "0.1%", "100.1", "84.4%", ""], ["92d Eco Revenue", "$174.8", "$175.3", "-$0.4", "99.7", "34.5%", ""], ["ESS (2 - 4 Years)", "", "", "", "", ""], ["KPI", "TEST", "CONTROL", "Δ", "ITC", "Pr(T>C)"], ["Sample Size", "32,364", "32,808", "", "", ""], ["31d Moved to Annual", "1.4%", "0.2%", "1.1%", "601.5", "100.0%"], ["92d Retention", "95.6%", "95.7%", "-0.1%", "99.9", "25.0%"], ["92d Eco Revenue", "$296.9", "$293.5", "$3.4", "101.2", "94.5%"], ["PL (2 - 4 Years)", "", "", "", "", "", ""], ["KPI", "TEST", "CONTROL", "Δ", "ITC", "Pr(T>C)", ""], ["Sample Size", "27,834", "28,039", "", "", "", ""], ["31d Moved to Annual", "1.1%", "0.3%", "0.9%", "448.3", "100.0%", ""], ["92d Retention", "95.7%", "95.5%", "0.2%", "100.2", "89.7%", ""], ["92d Eco Revenue", "$430.5", "$423.2", "$7.3", "101.7", "99.6%", ""], ["ADV (2 - 4 Years)", "", "", "", "", ""], ["KPI", "TEST", "CONTROL", "Δ", "ITC", "Pr(T>C)"], ["Sample Size", "8,357", "8,133", "", "", ""], ["31d Moved to Annual", "0.9%", "0.3%", "0.6%", "304.7", "100.0%"], ["92d Retention", "96.4%", "95.7%", "0.7%", "100.7", "99.1%"], ["92d Eco Revenue", "$935.7", "$935.7", "-$0.1", "100.0", "50.2%"], ["Global Business Solutio", "ns Group", "48"], ["Results: POSITIVE NEGATIVE\nBIZ IMPACT BIZ IMPACT", "", "Call Outs: A D G"], ["", "FLAT &\nROLL OUT", ""], ["", "", ""], [""], ["RESULTS"], ["TEST Sample Size", "Email", "", "", "", "", "IPD", "", "", ""], ["", "Email Send", "Email Reach", "Email Open", "CTR", "Unsub Rate", "IPD Viewed", "IPD Reach", "CTR", ""], ["378,705", "267,101", "70.5%", "A\n36.3%", "2.0%", "0.2%", "199,431", "52.7%", "4.5%", ""], ["Asset Name", "Email", "", "", "", "", "", "", ""], ["", "Emails Sent", "Reach", "Open Rate", "ITB", "CTR", "ITB", "Unsub Rate", "ITB"], ["Email 01", "266,190", "70.3%", "29.1%", "90.8", "1.3%", "140.8", "0.1%", "96.0"], ["Email 02", "264,356", "69.8%", "B 27.8%", "86.7", "0.8%", "91.3", "0.1%", "119.4"], ["Email Benchmark*", "", "", "32%", "", "0.9%", "", "0.09%", ""], ["Access Point", "IPD", "", "", "", ""], ["", "Impressions", "Reach", "CTR", "Benchmark", "ITB"], ["Advanced Shell - Banner", "10,754", "2.8%", "3.1%", "N/A", ""], ["Banking - Hellobox", "68,635", "18.1%", "0.7%", "0.2%", "385.72"], ["Invoices - Hellobox", "48,263", "12.7%", "0.5%", "1.1%", "46.67"], ["QBO Dashboard - Bottom Drawer", "115,519", "30.5%", "2.3%", "1.8%", "131.52"], ["Shell - Banner", "169,308", "44.7%", "3.1%", "N/A", ""], ["Global Business Solutio", "ns Group", "49"], ["Results: POSITIVE NEGATIVE\nBIZ IMPACT BIZ IMPACT", "", "Call Outs: A D G"], ["", "FLAT &\nROLL OUT", ""], ["", "", ""], ["", "", ""], ["The campaign was able to improved the adoption of annual plan for customers w/1y+ tenure; however, it only\nimproved retention for customers between 2y and 4y tenure", "", ""], ["", "", ""], ["HIGHLIGHTS", "", "LOWLIGHTS"], ["● Campaign moved 5k customers to annual billing\n● Campaign was successful in all fronts for SS, Plus, and\nADV customers with tenure between 2 and 4 years\n● Surfacing annual plan to high churn risk customers\nincreased 92D retention for the 2–4 year tenured cohort\non all plans except Essentials. Rolling out to this cohort is\nexpected to add 520 saves and $650K revenue\nannually", "", "● Campaign did not improve retention for all targeted customers"], ["", "", ""], ["NEXT STEPS & IMPLICATIONS", "", ""], ["● Make this campaign evergreen for SS + PL + ADV customers between 2 and 4 years tenure\n○ Caveat: Current Fusion commercialization plan prevents us from offering the annual plan (will be valid in Nov. 2025)", "", ""], ["Global Business Solutio", "ns Group", "50"], ["Results: POSITIVE NEGATIVE\nBIZ IMPACT BIZ IMPACT", "", "Call Outs: A D G"], ["", "FLAT &\nROLL OUT", ""], ["", "", ""]] | V11: Alt Product (slide 46): Payroll | Alt GET (slide 46): to manually send the wrap | Alt TO (slide 46): add ~5k customers to the | Alt Product (slide 47): Payroll | Alt GET (slide 47): to manually send the wrap | Alt TO (slide 47): Annual 1.7% 0.2% 1.5% 703.9 100% 31d Moved to Annual 1.7% 0.2% 1.5% 823.9 100% | Alt GET (slide 48): to manually send the wrap | Alt TO (slide 48): Annual 1.9% 0.2% 1.8% 1,127.4 100.0% A 31d Moved to Annual 1.4% 0.2% 1.1% 601.5 100.0% A | Alt Product (slide 49): Invoicing | Alt GET (slide 49): to manually send the wrap | Alt TO (slide 49): mers | Alt BY (slide 49): Channel | Alt GET (slide 50): ed customers | Alt TO (slide 50): mers | Date source: CSV – Current Target Launch Date | Name source: CSV | Business Impact updated from Results Report | Status enriched from Results Report | W11: 45–50 | X11: Copy of FY'25_ CRM Analytics Monthly Experiment_Notebook_AC.pdf
A12: ELM-7510 | B12: [FY25 Payments De-risking] Test New >31D Propensity Model | C12: 07-21-2025 | D12: high propensity to attach Non-Merchants (>31D since QBO sign-up) | E12: ##-##-## | F12: showing them that QuickBooks Payments offers an array of payment | G12: GET: high propensity to attach Non-Merchants (>31D since QBO sign-up) | TO: ##-##-## | BY: showing them that QuickBooks Payments offers an array of payment | H12: We will see a positive impact on Payments sign-ups and GNA by targeting high propensity customers with the updated Payments Propensity model. Results Probability KPIs C T ITC Δ (T>C) # companies 330.1K 329.9K Pymts SU 14d 0.60% 0.63% 104 91% 87 A Pymts GNA 14d 0.23% 0.22% 95 81% -37 B Pyrl GNS 14d 0.06% 0.06% 98 -3 C Live SU 14d 0.07% 0.07% 98 -5 Learnings & Implications A● >50% of SU units are from customers who are not exposed to Payments XSLL marketing up to 90d. | I12: & Implications A● >50% of SU units are from customers who are not exposed to Payments XSLL marketing up to 90d. | J12: QuickBooks | K12: IPD | L12: Positive | Results: 5.1 MEASURE: Complete | M12: : NEGATIVE IMPACT ● Low PE invoice creators rate in T led to low GNA rate. Though Payments SU has increased impactfully, low PE invoice creation rate B led to low GNA rate. Also, >50% of the SU impact is from customers who are ● Slight harm to other big QRS recommended products, which C not exposed (Inferred for review) | N12: https://docs.google.com/presentation/d/1EYJoTEmqsCzzXCUYDb2NDnrH8eEhdizAVNA3YM3Hh9E/edit?slide=id.g2efff53d832_0_813#slide=id.g2efff53d832_0_813 | O12: GNS/GNA | P12: 95 | U12: [["", "", "", ""], ["SOURCE OF TRUTH\nELM - 7510\nTest New >31D\nPropensity Model\nELM Driver: Charlotte Wong\nCRM Analytics: Naveen Rajendrapandian\nELM Workstream: Monetization\nDate: 07-21-2025\nELM Quickbase Record: ELM-7510\nWorkbook: Link\nBusiness Brief: Link\nSlack Channel: Link", "", "", "SWAG Effort Size\nM"], ["", "", "", "51\nTemplate v5.2 Updated Jan.. 2025"], ["SOURCE OF TRUTH"], ["ELM - 7510\nTest New >31D"], ["", "SWAG Effort Size", "", ""], ["", "M", "", ""], ["", "", "", ""], ["", "", "51\nv5.2 Updated Jan.. 20", ""], ["Link", ""], ["", "Link"], ["", "Link"], ["", "", "", "", "", "", "", "PRODUCTS: Word ● DRIVER: Name ● QB: ELM-#### ● SOT: Deck ● DATES: ##-##-## to ##-##-##", ""], ["", "", "EXPERIMENT RESULTS", "", "", "D\nts Propensity\nh propensity", "", "", ""], ["", "", "ELM-7510 Test N", "", "", "D\nts Propensity\nh propensity", "", "", ""], ["", "", "", "", "", "", "", "", ""], ["", "", "", "", "", "", "", "", "Learnings & Implications\nA● >50% of SU units are from customers who are not exposed to\nPayments XSLL marketing up to 90d.\n● Low PE invoice creators rate in T led to low GNA rate.\nB\n● Slight harm to other big QRS recommended products, which\nC\ncan be compensated if the incr. Payments SUs are GNAed at\nGlobal Business Solutions Group 52\nbaseline rate (expected: +32 GNA units)."], ["", "", "", "", "", "", "", "", "A● >50% of SU units are from customers who are not exposed to\nPayments XSLL marketing up to 90d.\n● Low PE invoice creators rate in T led to low GNA rate.\nB\n● Slight harm to other big QRS recommended products, which\nC\ncan be compensated if the incr. Payments SUs are GNAed at\nGlobal Business Solutions Group 52"], ["", "Business Impact: NEGATIVE\nIMPACT\nThough Payments SU has increased impactfully, low PE invoice creation rate\nled to low GNA rate. Also, >50% of the SU impact is from customers who are\nnot exposed to Payments offers for at least 90d. We can strategically roll out\non non-marketed customers once in a quarter (expected annual GNAs: 180)", "", "", "", "PE invoice creati", "on rate", "", ""], ["", "", "", "", "", "", "who are\nroll out", "", ""], ["", "", "", "", "", "", "", "", ""], ["", ""], ["", "", "", "", "", "Probability", "", ""], ["KPIs", "C", "T", "", "ITC", "(T>C)", "Δ", ""], ["# companies", "330.1K", "329.9K", "", "", "", "", ""], ["Pymts SU 14d", "0.60%", "0.63%", "", "104", "91%", "87", ""], ["Pymts GNA 14d", "0.23%", "0.22%", "", "95", "81%", "-37", ""], ["Pyrl GNS 14d", "0.06%", "0.06%", "", "98", "", "-3", ""], ["Live SU 14d", "0.07%", "0.07%", "", "98", "", "-5", ""], ["", "", "", "", "", "", "", ""], ["r. Payments SUs are\nGlobal Business Solutio", "GNAed\nns Group", "at\n52"], ["Results: POSITIVE DIR. POSITIVE\nIMPACT IMPACT", "FLAT\nIMPACT", "Call Outs: A D G"]] | V12: Name source: CSV | Status enriched from Results Report | W12: 51–52 | X12: Copy of FY'25_ CRM Analytics Monthly Experiment_Notebook_AC.pdf
A13: ELM-7665 | B13: [FY25 Payments De-risking] AE Funnel Optimization Test | C13: 06-09-2025 | D13: Upto 30d 83.8K 109 39 99 -1 Non-AE 148.6K 111 54 B them every quarter at above Sync-level. | E13: mer who have not seen any Payments Breakdown of customers ever AEed vs. not A● High propensity customers who have not seen | F13: their C2s. We should | G13: GET: Upto 30d 83.8K 109 39 99 -1 Non-AE 148.6K 111 54 B them every quarter at above Sync-level. | TO: mer who have not seen any Payments Breakdown of customers ever AEed vs. not A● High propensity customers who have not seen | BY: their C2s. We should | H13: If we retarget customers who are dropping off at various points in the AE funnel, Then we will drive more PE-invoices sent and more | I13: Analyzing customer who have not seen any Payments Breakdown of customers ever AEed vs. not A● High propensity customers who have not seen XSLL IPD over the past X days Payments XSLL marketing in the past 90d are smaller in volume with highest incremental Non-marketed SIZE SU ITC Δ GNA ITC Δ Non-marketed SIZE SU ITC Δ yield. We can create an EG strategy to target Upto 30d 83.8K 109 39 99 -1 Non-AE 148.6K 111 54 B them every quarter at above Sync-level. Upto 60d 43.6K 116 35 113 10 AE 181.2K 102 31 B● Non-AEs are ~45% of the high propensity Upto 90d 32.9K 129 46 122 13 A Total Treatment 329.9K 104 87 customers and are signing up at a higher rate than AEs. This suggests that we should offer Total Treatment 329.9K 104 87 95 -37 different messaging to AEs like, to send PE invoices (ELM7665), enabling Payments preferences (ELM7665), etc. Control Treatment C● T’s are lagging in creating PE invoices, and getting them paid by their C2s. We should 330.1K 329.9K understand why T is not converting at least at the same rate as Control. Pymts SU 1,990 2,076 0.60% | 0.63% Created PE inv 1,182 1,177 59.4% | 56.7% Pymts GNA 748 59.4% | 56.7% 715 Global Business Solutions Group 53 & Implications ● Like the recent campaigns, GNA rate is trending lower while the sign-up is impactful. | J13: Payments | K13: IPD; Email | L13: Trending Positive | Results: 5.1 MEASURE: Complete | M13: : FLAT & ● Need to understand the individual segments: AE with all the ROLL OUT Though Payments SU has increased impactfully, the GNA rate is trending Payments preferences turned off vs. had at least one lower. Opening up FTU for non-Payments AEs can be rolled out as Payments preferences turned on. (Inferred for review) | N13: https://docs.google.com/presentation/d/1uxWsR0UD5sYEHpNKepQwC4JNtRAKPKAo6Wel9qPgd0s/edit#slide=id.g2efff53d832_0_813 | O13: GNS/GNA | P13: 98 | Q13: Signups | R13: 105 | U13: [[""], ["RESULTS"], ["Marketing gap fill’s impact", "", "", "", "", "", ""], ["Analyzing customer who have not seen any Payments\nXSLL IPD over the past X days", "", "", "", "", "", ""], ["Non-marketed", "SIZE", "", "SU ITC", "Δ", "GNA ITC", "Δ"], ["Upto 30d", "83.8K", "", "109", "39", "99", "-1"], ["Upto 60d", "43.6K", "", "116", "35", "113", "10"], ["Upto 90d", "32", ".9K", "129", "46", "122", "13"], ["Total Treatment", "329.9K", "", "104", "87", "95", "-37"], ["Non-AE vs AE breakdown", "", "", "", "", ""], ["Breakdown of customers ever AEed vs. not", "", "", "", "", ""], ["Non-marketed", "SIZE", "", "SU ITC", "Δ", ""], ["Non-AE", "", "148.6K", "111", "54", "B"], ["AE", "181.2K", "", "102", "31", ""], ["Total Treatment", "329.9K", "", "104", "87", ""], [""], ["Control"], ["330.1K"], [""], ["Treatment"], ["329.9K"], ["", "", "Pymts SU", "", ""], ["", "", "", "", ""], ["", "", "0.60% | 0.63%", "", ""], ["", "", "Created PE inv", "", ""], ["", "", "", "", ""], ["", "", "59.4% | 56.7%", "", ""], ["", "", "", "", ""], ["", "", "Pymts GNA", "", ""], ["748", "", "", "", "715"], ["", "", "59.4% | 56.7%", "", ""], ["", "", "", "", ""], [""], [""], [""], [""], ["Global Business Solutio", "ns Group", "53"], ["Results: POSITIVE NEGATIVE\nBIZ IMPACT BIZ IMPACT", "", "Call Outs: A D G"], ["", "FLAT &\nROLL OUT", ""], ["", "", ""], ["", "", "", "", "", ""], ["Though Payments SU has increased impactfully, low PE invoice creation rate led to low GNA rate. Also, >50% of the\nSU impact is from customers who are not exposed to Payments offers for at least 90d. We can strategically roll out on\nnon-marketed customers once in a quarter (expected annual GNAs: 180)", "", "", "", "", ""], ["HIGHLIGHTS", "", "LOWLIGHTS", "", "", ""], ["● The new Payments v2 model performed\nsignificantly better than the current model and\npost-QRS integration for Payments\n● We have identified that marketing to customers\nafter a long gap is effective\n● We caused insignificant harm to the top the top\neco-system products recommended by QRS\n(Payroll and Live)", "", "● Since we used the existing marketing messages that most\ncustomers are frequently exposed to, there is a potential\nloss in lift\n● In this and a past experiment, there is a signal that our\nmarketing is not effective against AE customers\n● There seems to be a funnel issue where the incremental\nsign-ups are not GNAing at a lower rate", "", "", ""], ["", "", "", "", "", ""], ["NEXT STEPS & IMPLICATIONS", "", "", "", "", ""], ["● Create a new EG to market to non-marketed high propensity customers for all eligible products\n● Understand the low intent to complete FTU and design a follow-up strategy. Reaching to most of the signed up customers\nthrough FTU is also a key", "", "", "", "", ""], ["", "", "", "", "", ""], ["", "", "", "Global Business Solutio", "ns Group", "54"], ["Results: POSITIVE NEGATIVE\nBIZ IMPACT BIZ IMPACT", "", "Call Outs: A D G"], ["", "FLAT &\nROLL OUT", ""], ["", "", ""], ["", "", "", ""], ["SOURCE OF TRUTH\nELM - 7665\nAE Funnel\nOptimization Test\nELM Driver: Silvester Lopez\nCRM Analytics: Naveen Rajendrapandian\nELM Workstream: FTU\nDate: 6-2-2025\nELM Quickbase Record: ELM-7665\nWorkbook: Link\nSlack Channel: Link", "", "", "SWAG Effort Size\nM"], ["", "", "", "55\nTemplate v5.1 Updated Oct. 2024"], ["SOURCE OF TRUTH"], ["ELM - 7665\nAE Funnel"], ["", "SWAG Effort Size", "", ""], ["", "M", "", ""], ["", "", "", ""], ["", "", "55\nv5.1 Updated Oct. 20", ""], ["Link", ""], ["", "Link"], ["EXPERIMENT RESULTS\nAuto-Enabled (AE) Funnel Optim\nRetargeting AE QBO customers to co\nPayments actions when they are on “u\n1. Disabled all payment methods on\n2. Enabled at least one payment me\nsent PE-invoice", "", "", "EXPERIMENT RESULTS", "", "", "", "PRODUCTS: Payments ● DRIVER: Silvester Lopez ● QB:", "ELM-", "7665 ● SOT:", "Deck", "● DATES: 6/9/25 - 8/9/25"], ["", "", "Auto-Enabled (AE) Funnel Optim\nRetargeting AE QBO customers to co\nPayments actions when they are on “u\n1. Disabled all payment methods on\n2. Enabled at least one payment me\nsent PE-invoice", "Auto-Enabled (AE) Fun", "", "", "ization\nmplete key\nnhappy paths”:\ninvoices\nthod; have not", "", "", "", "", ""], ["", "", "", "", "", "", "", "", "", "", "", ""], ["", "", "", "", "", "", "", "", "", "", "", ""], ["", "", "Business Impact: FLAT &\nROLL OUT\nThough Payments SU has increased impactfully, the\nlower. Opening up FTU for non-Payments AEs can b\nEvergreen with an expected ~1,600 incr. Payments\nconverting them at baseline GNA rate (~45%) woul", "", "", "", "GNA rate is trending", "", "", "", "", ""], ["", "", "", "", "", "", "e rolled out as\nsign-ups annually;\nd yield 720 GNA units.", "", "", "", "", ""], ["KPIs", "C", "T", "ITC", "Probability\n(T>C)", "Δ"], ["# companies", "172.6K", "173.1K", "", "", ""], ["Pymts SU 30d", "1.05%", "1.09%", "105", "91%", "82"], ["Pymts GNA 30d", "0.46%", "0.46%", "98", "63%", "-13"], ["Global Business Solutio", "ns Group", "56"], ["", "Call Outs: A D G"], ["FLAT &\nROLL OUT", ""], ["", ""], ["RESULTS\nRetargeting AEs to reconsider Payments pref. is Flat\nThough Payments SU has increased impactfully, the GNA rate is trending lower. Opening up FTU for non-Payments\nAEs can be rolled out as Evergreen with an expected ~1,600 incr. Payments sign-ups annually; converting them at baseline GNA\nrate (~45%) would yield 720 GNA units.\nHIGHLIGHTS LOWLIGHTS\n● Opening up FTU to AE customers proved to drive ● We have got a lower GNA rate indicating an opportunity to\nincremental sign-up impact improve our FTU cycle\n● Personalizing the actions based on customers’ ● We could’ve set the segments in different IXPs to identify\nPayments preference choice helped to lead them the impact driver precisely\nto the correct path quickly ● We might have lost some qualified impr. to higher level\noffers like EG for attach\nNEXT STEPS & IMPLICATIONS\n● Roll out the AEs marketing to EG at Sync-level\n● Understand the low intent to complete FTU and design a follow-up strategy. Reaching to most of the signed up customers\nthrough FTU is also a key\nGlobal Business Solutions Group 57", "", "", ""], ["", "RESULTS\nRetargeting AEs to reconsider Payments pref. is Flat", "", ""], ["", "", ""], ["Though Payments SU has increased impactfully, the GNA rate is trending lower. Opening up FTU for non-Payments\nAEs can be rolled out as Evergreen with an expected ~1,600 incr. Payments sign-ups annually; converting them at baseline GNA\nrate (~45%) would yield 720 GNA units.", "", ""], ["", "", ""], ["HIGHLIGHTS", "", "LOWLIGHTS"], ["● Opening up FTU to AE customers proved to drive\nincremental sign-up impact\n● Personalizing the actions based on customers’\nPayments preference choice helped to lead them\nto the correct path quickly", "", "● We have got a lower GNA rate indicating an opportunity to\nimprove our FTU cycle\n● We could’ve set the segments in different IXPs to identify\nthe impact driver precisely\n● We might have lost some qualified impr. to higher level\noffers like EG for attach"], ["", "", ""], ["NEXT STEPS & IMPLICATIONS", "", ""], ["● Roll out the AEs marketing to EG at Sync-level\n● Understand the low intent to complete FTU and design a follow-up strategy. Reaching to most of the signed up customers\nthrough FTU is also a key", "", ""], ["Global Business Solutio", "ns Group", "57"], ["Results: POSITIVE NEGATIVE\nBIZ IMPACT BIZ IMPACT", "", "Call Outs: A D G"], ["", "FLAT &\nROLL OUT", ""], ["", "", ""]] | V13: Alt GET (slide 54): to manually send the wrap | Alt TO (slide 54): high-propensity customers is Negative | Alt BY (slide 54): QRS sign-ups are not GNAing at a lower rate | Alt Campaign Name (slide 56): ● | Alt Date (slide 56): 6/9/25 | Alt Product (slide 56): QuickBooks | Alt GET (slide 56): ing AE QBO customers to complete key Get QBO customers who have been auto-enabled for Payments | Alt TO (slide 56): Enabled (AE) Funnel Optimization | Alt BY (slide 56): Retargeting them to complete these key actions when they have | Alt GET (slide 57): ing AEs to reconsider Payments pref. is Flat | Alt TO (slide 57): reconsider Payments pref. is Flat | Date source: CSV – Current Target Launch Date | Name source: CSV | Status enriched from Results Report | W13: 53–57 | X13: Copy of FY'25_ CRM Analytics Monthly Experiment_Notebook_AC.pdf
A14: ELM-7188 | B14: MP: FY25 MAR GAP CLOSER: What's New - H2 Edition FY25 | C14: 07-01-2025 | D14: QBO Online Ecosystem subscribers | E14: IOluNtioSn Gs RGOroUuPp 58 | F14: Promoting the new QBO innovation to increase their perceived value of | G14: GET: QBO Online Ecosystem subscribers | TO: IOluNtioSn Gs RGOroUuPp 58 | BY: Promoting the new QBO innovation to increase their perceived value of | H14: new features If customers are made aware of the new innovation page with new features / product releases, it will increase feature adoption & awareness about other offerings thereby increasing retention and attach. Results - B KPIs TEST CON. ITC P(T>C) # Assignments 3,518,061 391,531 Churn (w/31D) 1.015% 1.021% 99.4 66% A ADVANCED upgrades (w/31D) 0.078% 0.073% 106.1 84% A ESS upgrades (w/31D) 0.057% 0.052% 109.2 85% B PLUS upgrades (w/31D) 0.091% 0.092% 99.2 43% Payroll Attach (w/31D) 0.178% 0.175% 101.7 72% Payments Signups (w/31D) 0.541% 0.539% 100.4 55% C Payments GNA (w/31D) 0.469% 0.476% 98.5 27% Ecosystem Revenue /assignment $118.88 $118.56 100.3 91% SAtd Siun o K K p e g c A U U e gl e u p r I s n wda a tw l de s / gin o i ed ie tn k h n r p s = c e t r a l s l ue le gi ld n p v e ek er a v o d n a t d ot n = u A t cl g itn e k n t Learnings & Implications A● Customers notified about new features churned similar as holdout | I14: & Implications A● Customers notified about new features churned similar as holdout DD2366 F3F2EF ● Email open rate is about 27.5% with 94 ITB and CTR is 0.8% with 160 accesspointname offer_viewed offer_clicked CTR ITB FF9331 DBEDEE SBSEG QBO AT AppHomepage (Classic Modal ) 2474833 54370 2.20% ● IPD CTR is about 3.56% CTR 105 ITC as compared to the benchmark SBSEG QBO GT AppHomepage What’s new modal on classic is 2.2% and on Fusion Modal is 2.07% E7DA60 0D333F (Fusion Modal) 480218 9945 2.07% Shell - Notification 342840 4662 1.36% QBO Dashboard - Bottom Drawer 2020478 25846 1.28% 0-0-0 212-215-220 Banking - Hellobox 357084 1752 0.49% 000000 D4D7DC Payments Deposit - Hellobox 30740 116 0.38% 57-58-61 227-229-232 Invoices - Hellobox 280566 754 0.27% 393A3D E3E5E8 Sales - Hellobox 258198 655 0.25% Expenses - Hellobox 260711 620 0.24% 107-108-114 236-238-241 Chart of Accounts - Hellobox 109950 251 0.23% 6B6C72 ECEEF1 SBSEG QBO Hellobox 141-144-150 246-247-249 AppIncomeoverview 121257 215 0.18% 8D9096 F4F5F8 60 Intuit Confidential and Proprietary 186-190-197 255-255-255 BABEC5 FFFFFF | J14: QBO | K14: IPD; Email; Landing Page | L14: Positive (Inferred for review) | Results: 5.1 MEASURE: Complete | M14: Positive Biz Impact | 99.01 ITC-1 | 102.32 ITC-2 | 100.08 ITC-3 | N14: https://docs.google.com/presentation/d/1a8MkKgDftYATJJXbZbqhI18PQ9e8yd5JLlFAdNIlxqY/edit#slide=id.g2efff53d832_0_813 | O14: Churn Rate | P14: 99.01 | Q14: GNS/GNA | R14: 102.32 | S14: Ecosystem Revenue | T14: 100.08 | U14: [["WRAP REPORT", "", ""], ["QBO What’s New", "", ""], ["Link", ""], ["", "Link"], ["", "Link"], ["Template v5.0 Updated Aug 2024\nGLOBAL BGUlSoIbNaEl SBSus SinOeLsUs SToIOluNtioSn Gs RGOroUuPp", "", ""], ["", "", "5"], ["", "GLOBAL BGUlSoIbNaEl SBSus SinOeLsUs SToIOluNtioSn Gs RGOroUuPp", ""], ["", "", ""], ["", "", "", "", "", "", "", "", "", "", "", "PRODUCTS: QBO ● DRIVER: Maya ● QB: ELM-7188 ● SOT: Deck ● DATES: 30/6/25 to 9/30/25", "", ""], ["EXPERIMENT RESULTS\nELM-7188\nWhat’s New 7/1 edition featuring AI Agents as part\nlineup, new Fusion UI, customer hub, Bill Pay now in\nnew features\nB\nA\nSAtdo K e g A U e e pI sn a tw l sgin iie tn k h ns c t rlsue ldp eer v oda d n =u t clitn k\nSiunK pcU glur wdade/o ed r p=e a lle ginv eka ntot Agent\nBusiness Impact:\nSTILL BAKING\nAt 31 days , Customers notified about new features churn\nITC) as holdout , ADV/ESS upgrades are significantly high\nLonger term (92 days) retention impact is still baking.", "", "EXPERIMENT RESULTS", "", "", "", "", "", "", "of the new hero\ncluded and more", "", "", "", ""], ["", "", "", "", "", "", "", "", "", "of the new hero\ncluded and more", "", "", "", ""], ["", "", "", "", "", "", "", "", "", "", "", "", "", ""], ["", "B", "", "", "", "", "", "", "", "", "", "", "", ""], ["", "", "", "", "", "", "", "", "", "", "", "", "", ""], ["", "", "", "", "", "", "", "", "", "", "", "", "", ""], ["", "", "", "A", "", "", "", "", "", "", "", "", "", ""], ["", "", "", "", "", "", "", "", "", "", "", "", "", ""], ["", "", "", "", "", "", "", "", "", "", "", "", "", ""], ["", "", "", "", "", "", "", "", "", "", "", "", "", ""], ["", "", "SAtdo K e g A U e e pI sn a tw l sgin iie tn k h ns c t rlsue ldp eer v oda d n =u t clitn k\nSiunK pcU glur wdade/o ed r p=e a lle ginv eka ntot Agent", "", "", "", "", "", "", "", "", "", "", ""], ["", "", "", "", "", "", "", "", "", "", "", "", "", "Learnings & Implications\nA● Customers notified about new features churned similar as holdout\n● Upgrades to QBO ADVANCED (+160) & ESSENTIALS (+170) are\nB\nsignificantly high\nC● Payroll attach is directionally positive & Payments GNA is significantly\nGlobal Business Solutions Group 59\nlow"], ["", "", "", "", "", "", "", "", "", "", "", "", "", ""], ["", "", "", "", "", "", "", "", "", "", "", "", "", ""], ["", "", "Business Impact:\nSTILL BAKING\nAt 31 days , Customers notified about new features churn\nITC) as holdout , ADV/ESS upgrades are significantly high\nLonger term (92 days) retention impact is still baking.", "", "", "", "", "", "", "", "", "", "", ""], ["", "", "", "", "", "", "", "", "", "ed at a similar rate (99.4\ner (+330 upgrades) ;", "", "", "", ""], ["", "", "", "", "", "", "", "", "", "", "", "", "", ""], ["", "", "", "", "", "", "FLAT\nIMPACT", "", "Call Outs: A D G", "", "", "", "", ""], ["", "", "", "", "", "STILL BAKING", "", "", "", "", "", "", "", ""], ["ELM-7", "188"], ["", "", "", "", ""], ["KPIs", "TEST", "CON.", "ITC", "P(T>C)"], ["# Assignments", "3,518,061", "391,531", "", ""], ["Churn (w/31D)", "1.015%", "1.021%", "99.4", "66%"], ["ADVANCED upgrades (w/31D)", "0.078%", "0.073%", "106.1", "84%"], ["ESS upgrades (w/31D)", "0.057%", "0.052%", "109.2", "85%"], ["PLUS upgrades (w/31D)", "0.091%", "0.092%", "99.2", "43%"], ["Payroll Attach (w/31D)", "0.178%", "0.175%", "101.7", "72%"], ["Payments Signups (w/31D)", "0.541%", "0.539%", "100.4", "55%"], ["Payments GNA (w/31D)", "0.469%", "0.476%", "98.5", "27%"], ["Ecosystem Revenue /assignment", "$118.88", "$118.56", "100.3", "91%"], ["ive & Payments GNA is\nGlobal Business Solutio", "signific\nns Group", "ant\n59"], ["", "", "", "", "", "", "", "", "", "", "", "", "", ""], ["Detailed IPD and Email Performance Summary", "", "", "", "", "", "", "", "", "", "", "", "", ""], ["", "", "", "", "", "", "", "", "", "", "", "", "", ""], ["Email IPD\nCohort Sent Opens % ITB Clicks CTR ITB Imp. Clicks CTR ITB\nTreatment A 1967289 541501 27.53% 94 15729 0.80% 160 2,255,949 80,280 3.56% 119\nEmail Benchmark* 29% 0.5% IPD Benchmark ** 3%\nInsights\n● Email open rate is about 27.5% with 94 ITB and CTR is 0.8% with 160\naccesspointname offer_viewed offer_clicked CTR\nITB\nSBSEG QBO AT AppHomepage\n(Classic Modal ) 2474833 54370 2.20%\n● IPD CTR is about 3.56% CTR 105 ITC as compared to the benchmark\nSBSEG QBO GT AppHomepage\nWhat’s new modal on classic is 2.2% and on Fusion Modal is 2.07%\n(Fusion Modal) 480218 9945 2.07%\nShell - Notification 342840 4662 1.36%\nQBO Dashboard - Bottom Drawer 2020478 25846 1.28%\nBanking - Hellobox 357084 1752 0.49%\nPayments Deposit - Hellobox 30740 116 0.38%\nInvoices - Hellobox 280566 754 0.27%\nSales - Hellobox 258198 655 0.25%\nExpenses - Hellobox 260711 620 0.24%\nChart of Accounts - Hellobox 109950 251 0.23%\nSBSEG QBO Hellobox\nAppIncomeoverview 121257 215 0.18%\n60 Intuit Confidential and Proprietary", "Cohort", "Email", "", "", "", "", "", "", "IPD", "", "", "", ""], ["", "", "Sent", "Opens", "%", "ITB", "Clicks", "CTR", "ITB", "Imp.", "Clicks", "CTR", "ITB", ""], ["", "Treatment A", "1967289", "541501", "27.53%", "94", "15729", "0.80%", "160", "2,255,949", "80,280", "3.56%", "119", ""], ["", "Email Benchmark*", "", "", "29%", "", "", "0.5%", "", "IPD Benchmark **", "", "3%", "", ""], ["Color Key: Stat SigPositive Stat Sig Negativ Flat Directionally Positive Directionally Negative", "", "", "", "", "", "", "", "", "", "", "", "", ""], ["Web Reimagine\ncolor palette"], ["0FD46C"], ["Insights\n● Email open rate is about 27.5% with 94 ITB and CTR is 0.8% with 160\nITB\n● IPD CTR is about 3.56% CTR 105 ITC as compared to the benchmark\nWhat’s new modal on classic is 2.2% and on Fusion Modal is 2.07%", ""], ["accesspointname", "offer_viewed", "offer_clicked", "CTR"], ["SBSEG QBO AT AppHomepage\n(Classic Modal )", "2474833", "54370", "2.20%"], ["SBSEG QBO GT AppHomepage\n(Fusion Modal)", "480218", "9945", "2.07%"], ["Shell - Notification", "342840", "4662", "1.36%"], ["QBO Dashboard - Bottom Drawer", "2020478", "25846", "1.28%"], ["Banking - Hellobox", "357084", "1752", "0.49%"], ["Payments Deposit - Hellobox", "30740", "116", "0.38%"], ["Invoices - Hellobox", "280566", "754", "0.27%"], ["Sales - Hellobox", "258198", "655", "0.25%"], ["Expenses - Hellobox", "260711", "620", "0.24%"], ["Chart of Accounts - Hellobox", "109950", "251", "0.23%"], ["SBSEG QBO Hellobox\nAppIncomeoverview", "121257", "215", "0.18%"], ["FF9331"], ["E7DA60"], ["DBEDEE"], ["0D333F"], ["60", "Intuit Confidential and Proprietary"], ["Stat Sig Negativ", "Flat"], ["", "", "", "", "", ""], [""], ["Landing Page Engagement\nLP Views Clicks CTR"], ["What’s New Landing page 173737 18652 11%\nPlus\nAdvanced\nLP Views / Clicks CTR LP Views / Clicks CTR\nViews 53074 Views 22197\nAccounting Agent 3488 6.57% Accounting Agent 1420 6.40%\nPayments Agent 412 1.86%\nPayments Agent 645 1.22%\nFinance Agent 599 2.70%\nFinance Agent 203 0.38%\nCustomer Agent 181 0.82%\nCustomer Agent 349 0.66%\nProject Management Project Management\nAgent 92 0.17% Agent 216 0.97%\nSS\nEssentials\nLP Views / Clicks CTR LP Views / Clicks CTR\nViews 39670 Views 35102\nAccounting Agent 2041 5.14% Accounting Agent 2495 7.11%\nPayments Agent 118 0.30% Payments Agent 421 1.20% LP Clicks CTR\nFinance Agent 67 0.17% Finance Agent 78 0.22% Fusion in New UI 2338 1.35%\nCustomer Agent 66 0.19% Fusion in Classic UI 2160 1.24%\nCustomer Agent 120 0.30%\nProject Management Project Management Customer Hub 690 0.40%\nAgent 65 0.16% Agent 55 0.16% Bill Pay 750 0.43%\n61 Intuit Confidential and Proprietary"], ["Web Reimagine\ncolor palette"], ["0FD46C"], ["", "", "", "", ""], ["", "", "", "", ""], ["LP", "Views / Clicks", "CTR", "", ""], ["Views", "22197", "", "", ""], ["Accounting Agent", "1420", "6.40%", "", ""], ["Payments Agent", "412", "1.86%", "", ""], ["Finance Agent", "599", "2.70%", "", ""], ["Customer Agent", "181", "0.82%", "", ""], ["", "", "", "", ""], ["Project Management\nAgent", "216", "0.97%", "", ""], ["Essentials", "", "", "", ""], ["LP", "Views", "", "Clicks", "CTR"], ["", "", "", "", ""], ["What’s New Landing page", "173737", "", "18652", "11%"], ["", "", "", "1865", ""], ["", "", "Advanced", "", ""], ["0BA956"], ["0A8543"], ["LP", "Views / Clicks", "CTR"], ["Views", "53074", ""], ["Accounting Agent", "3488", "6.57%"], ["Payments Agent", "645", "1.22%"], ["Finance Agent", "203", "0.38%"], ["Customer Agent", "349", "0.66%"], ["Project Management\nAgent", "92", "0.17%"], ["LP", "Views / Clicks", "CTR"], ["Views", "39670", ""], ["Accounting Agent", "2041", "5.14%"], ["Payments Agent", "118", "0.30%"], ["Finance Agent", "67", "0.17%"], ["Customer Agent", "120", "0.30%"], ["Project Management\nAgent", "65", "0.16%"], ["LP", "Views / Clicks", "CTR", "", "", "", "", "", "", ""], ["Views", "35102", "", "", "", "", "", "", "", ""], ["Accounting Agent", "2495", "7.11%", "", "", "", "", "", "", ""], ["Payments Agent", "421", "1.20%", "", "", "", "", "", "", ""], ["", "", "", "", "", "LP", "Clicks", "", "CTR", ""], ["Finance Agent", "78", "0.22%", "", "", "Fusion in New UI", "2338", "", "1.35%", ""], ["", "", "", "", "", "", "", "", "", ""], ["Customer Agent", "66", "0.19%", "", "", "Fusion in Classic UI", "2160", "", "1.24%", ""], ["Project Management\nAgent", "55", "0.16%", "", "", "Customer Hub", "690", "", "0.40%", ""], ["", "", "", "", "", "Bill Pay", "750", "", "0.43%", ""], ["61 I", "ntuit Confidential and Proprietary"], ["", "", "", "", ""], ["HIGH", "LIGHTS", "", "LOWLIGHTS", ""], ["● Promoting QBO innovations through the What's New section\nincreased awareness of AI agents, and the interruptive\nmodals did not negatively affect customer churn. Instead,\nthey contributed to higher ecosystem revenue by driving\nincremental QBO upgrades.\n● Awareness of new AI agents increased upgrades\nsignificantly QBO Advanced (+160) & Essentials (+170).\n● High engagement on email as well as IPD as compare to\nprevious What’s New campaigns", "", "", "● PSR score is lower for non UCG in July and August as compare to\nUCG group", ""], ["", "", "", "", ""], ["NEXT STEPS & IMPLICATIONS", "", "", "", ""], ["● Longer term impact is still baking", "", "", "", ""], ["Global Business Solutio", "ns Group", "62"], ["Results: POSITIVE NEGATIVE\nBIZ IMPACT BIZ IMPACT", "", "Call Outs: A D G"], ["", "FLAT &\nROLL OUT", ""], ["", "", ""], ["", "", ""], ["FY’25 Content", "", ""], ["", "", ""], ["", "Global Business Solution", ""], ["", "", ""], ["Global Business Solution", "s Group"]] | V14: Alt Date (slide 59): 30/6/25 | Alt Product (slide 59): Bill Pay | Alt TO (slide 59): 9/30/25 | Alt Date (slide 60): 57-58-61 | Alt Product (slide 60): Payments | Alt TO (slide 60): the benchmark | Alt Date (slide 61): 57-58-61 | Alt Product (slide 61): Bill Pay | Alt TO (slide 61): mer Agent 181 0.82% | Alt GET (slide 62): to manually send the wrap | Alt TO (slide 62): increased awareness of AI agents, and the interruptive UCG group | Alt BY (slide 62): driving | Alt status (slide 62): Trending Positive | Date source: CSV – Current Target Launch Date | Name source: CSV | Business Impact updated from Results Report | Status enriched from Results Report | W14: 58–63 | X14: Copy of FY'25_ CRM Analytics Monthly Experiment_Notebook_AC.pdf
A15: ELM-7305 | B15: QBC Multi-Product Strategy | C15: 02-12-2025 | D15: ed Offers - ELM 6227 | E15: PIC TIME | F15: making them aware they can apply for both, advising them that | G15: GET: ed Offers - ELM 6227 | TO: PIC TIME | BY: making them aware they can apply for both, advising them that | H15: Customers will apply at a higher rate for the product they are recommended from the Response Model (Treatment C). Results Treatment Control Treatment A Treatment C (Treatment B) KPIs Evergreens Consolidated Response Treatment A Treatment C 4692 & 6613 MPE Model ITC ITC Sample Size 171,086 169,762 170,381 TL App Submits 3032 2992 2932 99 97 TL Funded 571 551 582 96 102 TL Avg Loan Vol. $48,031 $47,591 $46,191 99 96 LoC App Submits 771 767 800 99 104 LoC Activations 252 254 254 101 101 LoC Avg Loan Vol. $13,699 $13,735 $14,099 100 103 | I15: & Implications A● We can expect incremental loan volume across TL & LoC, Marketing to customers they are eligible to apply for with no cannibalization upon rolling out Treatment C. both Term Loan & Line of Credit using Email, IPD, and a ● Treatment C resulted in lower TL applications submitted B new AI product recommendation model. (upper funnel); however, it was most effective in lower funnel performance (revenue & # loans funded). ● Treatment C had highest lower funnel & upper funnel C performance for LoC. Treatment Control Treatment A Treatment C (Treatment B) KPIs Evergreens Consolidated Response Treatment A Treatment C 4692 & 6613 MPE Model ITC ITC Sample Size 171,086 169,762 170,381 B TL App Submits 3032 2992 2932 99 97 A TL Funded 571 551 582 96 102 TL Avg Loan Vol. $48,031 $47,591 $46,191 99 96 C LoC App Submits 771 767 800 99 104 LoC Activations 252 254 254 101 101 LoC Avg Loan Vol. $13,699 $13,735 $14,099 100 103 & Implications Treatment (T C re o at n m t e r n o t l B) Treatment A Treatment C ●A Treatment C was soft in upper funnel performance. KPIs Evergreens Consolidated Response Treatment A Treatment C 4692 & 6613 MPE Model ITC ITC ● However, this is made up in lower funnel performance, B Sample Size 171,086 169,762 170,381 i.e., loans taken and loans funded. A TL App Submits 3,032 2,992 2,932 99 97 ● Overall, Treatment C resulted in highest revenue. C Submission Rate 1.77% 1.76% 1.72% 99 97 B TL Approved Apps 1,675 1,670 1,679 100 100 Approval rate 55.24% 55.82% 57.26% 101 104 TL Loans Taken 579 556 585 96 101 Loan Take Rate 34.57% 33.29% 34.84% 96 101 TL Loans Funded 571 551 582 96 102 Include project visuals here Loans Funded Rate 98.62% 99.10% 99.49% 100 101 Total Loan Volume $27,425,500 $26,222,500 $26,883,000 96 98 Avg Loan Volume $48,031 $47,591 $46,191 99 96 C Avg. Fico Score 730 729 738 Avg. TL Risk Seg 4.92 4.77 4.78 Global Business Solutions Group 69 A D G B E H C F I & Implications Treatment (T C re o at n m t e r n o t l B) Treatment A Treatment C ●A Overall, Treatment C had strong full-funnel performance KPIs Evergreens Consolidated Response Treatment A Treatment C (App submits → LV → Revenue). 4692 & 6613 MPE Model ITC ITC Sample Size 171,086 169,762 170,381 ●B Treatment C also attracted higher-quality customers, A i.e., higher Fico scores and lower risk scores. LoC App Submits 771 767 800 99 104 Submission Rate 0.45% 0.45% 0.45% 100 104 Apps Approved 539 523 538 97 100 Approval rate 69.91% 68.19% 67.25% 98 96 LoC Activations 252 254 254 101 101 Activation Rate 46.75% 48.57% 47.21% 104 101 Total Loan Volume $3,452,030 $3,488,700 $3,581,043 101 104 Include project visuals here Avg. Loan Volume $13,699 $13,735 $14,099 100 103 Avg. Fico Score 739 714 741 B Avg. TL Risk Seg 4.97 4.88 4.86 Global Business Solutions Group 70 A D G B E H C F I | J15: Bill Pay | K15: IPD; Email | L15: Trending Positive | Results: 5.0 MEASURE: Live - Waiting for Results | M15: Positive Biz Impact | 102 ITC-1 | 101 ITC-2 | 101 ITC-3 | N15: https://docs.google.com/presentation/d/1Q5I7pVxoJDhH-ljxfqGDIBeTPjfGZdJbFuk3B6LMpr8/edit#slide=id.g2efff53d832_0_813 | O15: Ecosystem Revenue | P15: 102 | Q15: Ecosystem Attach | R15: 101 | S15: Ecosystem Attach | T15: 101 | U15: [[""], ["AGENDA"], ["TOPIC", "", "TIME"], ["1.Capital - ELM 7305\nHarsh", "", "10 Min"], ["2.Payroll Cancellation Flow - Targeted Offers - ELM 6227\nManasa", "", "10 Min"], ["3.Bill Pay 4 cell Test\nVijay/Karthik", "", "10 Min"], ["4.Payments T2P\nNaveen", "", "10 Min"], ["5.Account Manager - ELM 7336\nAhmed", "", "10 Min"], ["Global Business Solutio", "ns Group", "64"], ["", "", ""], ["SOURCE OF TRUTH\nELM-7305\nQBC Multi-Product Strategy\nELM Driver: Jason Ditangco\nCRM Analytics: Karthik Renganathan\nELM Workstream: Monetization (Attach & Upgrade)\nDate: 2/12/25\nEPLMr Qeuisckebasne Rteecorrd: ENLM-a730m5 e\nCreative: Emails | IPD Copy | IPD Images\nWorkbook: Link\nBusiness Brief: Link\nSlack Channel: Link", "", "65"], ["SOURCE OF TRUTH", ""], ["ELM-7305\nQBC Multi-Product Strategy", ""], ["ELM Driver: Jason Ditangco\nCRM Analytics: Karthik Renganathan", ""], ["ELM Workstream: Monetization (Attach & Upgrade)\nDate: 2/12/25\nEPLMr Qeuisckebasne Rteecorrd: ENLM-a730m5 e\nCreative: Emails | IPD Copy | IPD Images", ""], ["Workbook: Link\nBusiness Brief: Link\nSlack Channel: Link", ""], ["", ""], ["en\nEmails", "", ""], ["", "Link", ""], ["", "", "ink"], ["", "", "Link"], ["ter N\nIPD Copy |", "ame\nIPD Images"], ["", "", "PRODUCTS: TL & LoC ● DRIVER: Jason ● CRMA: Harsh ● QB: ELM-7305 | ELM-8202 ● LAUNCH:", "5/5/25"], ["RESULTS\nExperiment Customer Experience", "RESULTS", "", ""], ["Experiment Dates\n● Start: 5/5/25\n● End: 6/30/25"], ["Audience Description"], ["Top 50% Propensity\nNon-PQ\nMulti-product eligible"], ["Control\n(Treatment B)"], ["33%\nEvergreens running\nsimultaneously\nELM-6613 & ELM-4692"], ["Treatment A"], ["33%\nConsolidated MPE experience:\njoint TL & LoC messaging"], ["Treatment C"], ["33%\nMarketing based on Response\nModel product recommendation"], ["", "", "", ""], ["", "", "", ""], ["", "", "", ""], ["", "", "", ""], ["", ""], ["", ""], ["Global Business Solutio", "ns Group", "66"], ["Results: POSITIVE NEGATIVE\nBIZ IMPACT BIZ IMPACT", "", "Call Outs: A D G"], ["", "FLAT &\nROLL OUT", ""], ["", "", ""], ["EXPERIMENT RESULTS\nELM-7305 Non-P\nMarketing to customers they are eligible\nboth Term Loan & Line of Credit using E\nnew AI product recommendation model\nBusiness Impact: STPILOL SBIATIKVIENG\nBIZ IMPACT\n[Treatment C] Response model targeted marketing r\nincrease in expected revenue across TL (102 ITC) &\ncannibalization between products.", "", "", "", "", "", "", "", "", "", "Q MPE\nto apply for\nmail, IPD, and a\n.", "", "", "PRODUCTS: TL & LoC ● DRIVER: Jason ● CRMA: Harsh ● QB: ELM-7305 | ELM-8202 ● LAUNCH: 5/5/25", "", "", "", "", "", "", "", "", ""], ["", "", "EXPERIMENT RESULTS", "", "", "", "", "", "", "", "", "", "", "", "", "", "", "", "", "", "", "", ""], ["", "", "", "", "", "", "", "", "", "", "Q MPE\nto apply for\nmail, IPD, and a\n.", "", "", "", "", "Objective\nGet Non-PQ QBO customers eligible for both TL & LoC\nTo apply for TL, LoC, or both\nBy making them aware they can apply for both, advising them that\nthe funds can be used as a safety net or to invest in their business,\nand informing them that the application process is quick and easy\nHypothesis\nCustomers will apply at a higher rate for the product they are\nrecommended from the Response Model (Treatment C).\nResults", "", "", "", "", "", "", ""], ["", "", "", "", "", "", "", "", "", "", "", "", "", "", "", "", "", "", "", "", "", "", ""], ["", "", "", "", "", "", "", "", "", "", "", "", "", "", "", "", "", "", "", "", "", "", ""], ["", "", "", "", "", "", "", "", "", "", "", "", "", "", "Treatment", "", "", "", "", "", "", "", ""], ["", "", "", "", "", "", "", "", "", "", "", "", "", "", "", "", "", "Control\n(Treatment B)", "Treatment A", "Treatment C", "", "", ""], ["", "", "", "", "", "", "", "", "", "", "", "", "", "", "KPIs", "", "", "Evergreens\n4692 & 6613", "Consolidated\nMPE", "Response\nModel", "Treatment A\nITC", "Treatment C\nITC", ""], ["", "", "", "", "", "", "", "", "", "", "", "", "", "", "Sample Size", "", "", "171,086", "169,762", "170,381", "", "", ""], ["", "", "", "", "", "", "", "", "", "", "", "", "", "", "TL App Submits", "", "", "3032", "2992", "2932", "99", "97", ""], ["", "", "", "", "", "", "", "", "", "", "", "", "", "", "TL Funded", "", "", "571", "551", "582", "96", "102", ""], ["", "", "", "", "", "", "", "", "", "", "", "", "", "", "TL Avg Loan Vol.", "", "", "$48,031", "$47,591", "$46,191", "99", "96", ""], ["", "", "", "", "", "", "", "", "", "", "", "", "", "", "LoC App Submits", "", "", "771", "767", "800", "99", "104", ""], ["", "", "", "", "", "", "", "", "", "", "", "", "", "LoC Activations 252 254 254 101 101\nLoC Avg Loan Vol. $13,699 $13,735 $14,099 100 103", "", "", "", "", "", "", "", "", ""], ["", "", "", "", "", "", "", "", "", "", "", "", "", "", "LoC Activations", "", "", "252", "254", "254", "101", "101", ""], ["", "", "", "", "", "", "", "", "", "", "", "", "", "", "LoC Avg Loan Vol.", "", "", "$13,699", "$13,735", "$14,099", "100", "103", ""], ["", "", "", "", "", "", "", "", "", "", "", "", "", "", "", "", "", "", "", "", "", "", ""], ["", "Business Impact: STPILOL SBIATIKVIENG\nBIZ IMPACT\n[Treatment C] Response model targeted marketing r\nincrease in expected revenue across TL (102 ITC) &\ncannibalization between products.", "", "", "", "", "", "", "", "", "", "", "", "", "", "", "", "", "", "", "", "", ""], ["", "", "", "", "", "", "", "", "", "", "esulted in stat sig\nLoC (101 ITC) with n", "", "o", "Global Business Solutions Group", "", "", "", "", "", "", "", "", ""], ["", "", "", "", "", "", "", "", "", "Call Outs: A D G", "", "", "", "", "", "", "", "", "", "", "", "", ""], ["", "", "", "", "", "FLAT &\nROLL OUT", "", "", "", "", "", "", "", "", "", "", "", "", "", "", "", "", ""], ["", "", "", "", "", "", "", "", "", "", "", "", "", "", "", "", "", "", "", "", "", "", ""], [""], ["ELM-7305"], [""], ["ELM-8202"], ["EXPERIMENT RESULTS\nELM-7305 Non-P\nMarketing to customers they are eligible\nboth Term Loan & Line of Credit using E\nnew AI product recommendation model\nBusiness Impact: STPILOL SBIATIKVIENG\nBIZ IMPACT\nResponse model targeted marketing resulted in stat\nexpected revenue across TL (102 ITC) & LoC (101 I\ncannibalization between products.", "", "", "", "", "", "", "", "", "", "Q MPE\nto apply for\nmail, IPD, and a\n.", "", "", "PRODUCTS: TL & LoC ● DRIVER: Jason ● CRMA: Harsh ● QB: ELM-7305 | ELM-8202 ● LAUNCH: 5/5/25", "", "", "", "", "", "", "", ""], ["", "", "EXPERIMENT RESULTS", "", "", "", "", "", "", "", "", "", "", "", "", "", "", "", "", "", "", ""], ["", "", "", "", "", "", "", "", "", "", "Q MPE\nto apply for\nmail, IPD, and a\n.", "", "", "", "", "", "", "", "", "", "", ""], ["", "", "", "", "", "", "", "", "", "", "", "", "", "", "", "", "", "", "", "", "", ""], ["", "", "", "", "", "", "", "", "", "", "", "", "", "", "", "", "", "", "", "", "", ""], ["", "", "", "", "", "", "", "", "", "", "", "", "", "", "Treatment", "", "Control\n(Treatment B)", "Treatment A", "Treatment C", "", "", ""], ["", "", "", "", "", "", "", "", "", "", "", "", "", "", "KPIs", "", "Evergreens\n4692 & 6613", "Consolidated\nMPE", "Response\nModel", "Treatment A\nITC", "Treatment C\nITC", ""], ["", "", "", "", "", "", "", "", "", "", "", "", "", "", "Sample Size", "", "171,086", "169,762", "170,381", "", "", ""], ["", "", "", "", "", "", "", "", "", "", "", "", "", "", "TL App Submits", "", "3032", "2992", "2932", "99", "97", ""], ["", "", "", "", "", "", "", "", "", "", "", "", "", "", "TL Funded", "", "571", "551", "582", "96", "102", ""], ["", "", "", "", "", "", "", "", "", "", "", "", "", "", "TL Avg Loan Vol.", "", "$48,031", "$47,591", "$46,191", "99", "96", ""], ["", "", "", "", "", "", "", "", "", "", "", "", "", "", "LoC App Submits", "", "771", "767", "800", "99", "104", ""], ["", "", "", "", "", "", "", "", "", "", "", "", "", "LoC Activations 252 254 254 101 101\nLoC Avg Loan Vol. $13,699 $13,735 $14,099 100 103", "", "", "", "", "", "", "", ""], ["", "", "", "", "", "", "", "", "", "", "", "", "", "", "LoC Activations", "", "252", "254", "254", "101", "101", ""], ["", "", "", "", "", "", "", "", "", "", "", "", "", "", "LoC Avg Loan Vol.", "", "$13,699", "$13,735", "$14,099", "100", "103", ""], ["", "", "", "", "", "", "", "", "", "", "", "", "", "", "", "", "", "", "", "", "", ""], ["", "Business Impact: STPILOL SBIATIKVIENG\nBIZ IMPACT\nResponse model targeted marketing resulted in stat\nexpected revenue across TL (102 ITC) & LoC (101 I\ncannibalization between products.", "", "", "", "", "", "", "", "", "", "", "", "", "", "", "", "", "", "", "", ""], ["", "", "", "", "", "", "", "", "", "", "sig increase in\nTC) with no", "", "", "Global Business Solutions Group", "", "", "", "", "", "", "", ""], ["", "", "", "", "", "", "", "", "", "Call Outs: A D G", "", "", "", "", "", "", "", "", "", "", "", ""], ["", "", "", "", "", "FLAT &\nROLL OUT", "", "", "", "", "", "", "", "", "", "", "", "", "", "", "", ""], ["", "", "", "", "", "", "", "", "", "", "", "", "", "", "", "", "", "", "", "", "", ""], [""], ["ELM-7305"], [""], ["ELM-8202"], ["EXPERIMENT RESULTS Term Loan\nTreatment Control Treatment A Treatment C\n(Treatment B)\nKPIs Evergreens Consolidated Response\n4692 & 6613 MPE Model\nSample Size 171,086 169,762 170,381\nTL App Submits 3,032 2,992 2,932\nSubmission Rate 1.77% 1.76% 1.72%\nTL Approved Apps 1,675 1,670 1,679\nApproval rate 55.24% 55.82% 57.26%\nTL Loans Taken 579 556 585\nLoan Take Rate 34.57% 33.29% 34.84%\nTL Loans Funded 571 551 582\nInclude project visuals here\nLoans Funded Rate 98.62% 99.10% 99.49%\nTotal Loan Volume $27,425,500 $26,222,500 $26,883,000\nAvg Loan Volume $48,031 $47,591 $46,191\nAvg. Fico Score 730 729 738\nAvg. TL Risk Seg 4.92 4.77 4.78", "EXPERIMENT RESULTS Term Loan", "", "", "", "", "", "", "", "", ""], ["", "Treatment", "", "", "Control\n(Treatment B)", "Treatment A", "Treatment C", "", "", "", ""], ["", "KPIs", "", "", "Evergreens\n4692 & 6613", "Consolidated\nMPE", "Response\nModel", "Treatment A\nITC", "Treatment C\nITC", "", ""], ["", "Sample Size", "", "", "171,086", "169,762", "170,381", "", "", "", ""], ["", "TL App Submits", "", "", "3,032", "2,992", "2,932", "99", "97", "", ""], ["", "S", "ubmission Rate", "", "1.77%", "1.76%", "1.72%", "99", "", "", "97"], ["", "T", "L Approved Apps", "", "1,675", "1,670", "1,679", "100", "1", "", "00"], ["", "A", "pproval rate", "", "55.24%", "55.82%", "57.26%", "101", "1", "", "04"], ["", "T", "L Loans Taken", "", "579", "556", "585", "96", "1", "", "01"], ["", "L", "oan Take Rate", "", "", "", "", "", "1", "", "01"], ["", "", "", "Take Rate", "34.57%", "33.29%", "34.84%", "96", "", "", ""], ["", "T", "L Lo", "ans Funded", "571", "551", "582", "96", "", "1", "02"], ["", "L", "oans", "Funded Rate", "Include p\n98.62%", "roject visu\n99.10%", "als here\n99.49%", "100", "", "1", "01"], ["", "T", "otal Loan Volume", "Loan Volume", "$27,425,500", "$26,222,500", "$26,883,000", "96", "", "", "98"], ["", "", "", "", "", "", "", "", "", "", ""], ["", "A", "vg Loan Volume", "", "$48,031", "$47,591", "$46,191", "99", "", "", "96"], ["", "", "", "", "", "", "", "", "", "", ""], ["", "", "", "", "", "", "", "", "", "", ""], ["", "A", "vg. Fico Score", "", "730", "729", "738", "", "", "", ""], ["", "", "", "", "", "", "", "", "", "", ""], ["", "A", "vg. TL Risk Seg", "", "4.92", "4.77", "4.78", "", "", "", ""], ["", "", "", "", "", "", "", "", "", "", ""], ["", "", "", "", "", "", "", "", "", "", ""], ["", "", "", "", "", "", "", "", "", "", ""], ["Global Business Solutio", "ns Group", "69"], ["EXPERIMENT RESULTS Line of Credit\nTreatment Control Treatment A Treatment C\n(Treatment B)\nKPIs Evergreens Consolidated Response\n4692 & 6613 MPE Model\nSample Size 171,086 169,762 170,381\nLoC App Submits 771 767 800\nSubmission Rate 0.45% 0.45% 0.45%\nApps Approved 539 523 538\nApproval rate 69.91% 68.19% 67.25%\nLoC Activations 252 254 254\nActivation Rate 46.75% 48.57% 47.21%\nTotal Loan Volume $3,452,030 $3,488,700 $3,581,043\nInclude project visuals here\nAvg. Loan Volume $13,699 $13,735 $14,099\nAvg. Fico Score 739 714 741\nAvg. TL Risk Seg 4.97 4.88 4.86", "EXPERIMENT RESULTS Line of Credit", "", "", "", "", "", "", "", "", ""], ["", "Treatment", "", "", "Control\n(Treatment B)", "Treatment A", "Treatment C", "", "", "", ""], ["", "KPIs", "", "", "Evergreens\n4692 & 6613", "Consolidated\nMPE", "Response\nModel", "Treatment A\nITC", "Treatment C\nITC", "", ""], ["", "Sample Size", "", "", "171,086", "169,762", "170,381", "", "", "", ""], ["", "LoC App Submits", "", "", "771", "767", "800", "99", "104", "", ""], ["", "S", "ubmission Rate", "", "0.45%", "0.45%", "0.45%", "100", "1", "", "04"], ["", "A", "pps Approved", "", "539", "523", "538", "97", "1", "", "00"], ["", "A", "pproval rate", "", "69.91%", "68.19%", "67.25%", "98", "", "", "96"], ["", "L", "oC Activations", "", "252", "254", "254", "101", "1", "", "01"], ["", "A", "ctivation Rate", "", "", "", "", "", "1", "", "01"], ["", "", "", "tion Rate", "46.75%", "48.57%", "47.21%", "104", "", "", ""], ["", "T", "otal", "Loan Volume", "$3,452,030", "$3,488,700", "$3,581,043", "101", "", "1", "04"], ["", "A", "vg. L", "oan Volume", "Include p\n$13,699", "roject visu\n$13,735", "als here\n$14,099", "100", "", "1", "03"], ["", "", "", "", "", "", "", "", "", "", ""], ["", "", "", "", "", "", "", "", "", "", ""], ["", "A", "vg. Fico Score", "", "739", "714", "741", "B", "", "", ""], ["", "", "", "", "", "", "", "", "", "", ""], ["", "A", "vg. TL Risk Seg", "", "4.97", "4.88", "4.86", "", "", "", ""], ["", "", "", "", "", "", "", "", "", "", ""], ["", "", "", "", "", "", "", "", "", "", ""], ["", "", "", "", "", "", "", "", "", "", ""], ["Global Business Solutio", "ns Group", "70"], [""], ["RESULTS"], [""], ["Multi-product marketing powered by both the Propensity model and the Response model resulted in incremental\nrevenue (101 ITC) and no cannibalization between products."], ["HIGHLIGHTS", "", "LOWLIGHTS"], ["● Healthy engagement and conversion metrics with\nthe Response Model group indicates effectiveness\nof the model and marketing personalization.\n● LoC metrics with Response Model were higher\nacross the entirety of the funnel\n● Cannibalization is not present between products\nacross the funnel.", "", "● Although both treatments showed lower upper funnel\nperformance for TL, it was made up in upper funnel\nperformance, i.e., revenue.\n● Treatment A (Consolidated MPE without Response Model)\nperformed lower across the board, likely due to choice\nparadox."], ["", "", ""], ["NEXT STEPS & IMPLICATIONS", "", ""], ["● Rollout Treatment C (Response Model) as Evergreen marketing.\n● For future multi-product campaigns, it’s likely better to present one product to a customer at a time.", "", ""], ["Global Business Solutio", "ns Group", "7"], ["Results: POSITIVE NEGATIVE\nBIZ IMPACT BIZ IMPACT", "", "Call Outs: A D G"], ["", "FLAT &\nROLL OUT", ""], ["", "", ""], ["WRAP REPORT", "", ""], ["", "", ""], ["Launch Targeted Offe\nexperiment on Payroll\nFlow", "r\nCancel", ""], ["ELM Driver: Name Here\nCRM Analytics: Name Here\nELM Workstream: Name Here\nDate: ##-##-####\nELM Quickbase Record: ELM-####\nWorkbook: Link\nBusiness Brief: Link\nSlack Channel: Link", "", ""], ["Link", ""], ["", "Link"], ["", "Link"], ["", "Template v5.1 Updated Oct. 2024\nGLOBAL BGUlSoIbNaEl SBSus SinOeLsUs SToIOluNtioSn Gs RGOroUuPp", "", ""], ["", "", "", "7"], ["", "", "GLOBAL BGUlSoIbNaEl SBSus SinOeLsUs SToIOluNtioSn Gs RGOroUuPp", ""], ["", "", "", ""], [""], ["AGENDA"], ["TOPIC", "", "TIME"], ["01.QBO FY’25 Customer Growth - Gap Closer\nAndre", "", "10 Min"], ["02.QBO Upgrade Funnel optimization\nKarthik", "", "10 Min"], ["03.Capital - ELM 7305\nHarsh", "", "20 Min"], ["04.Build Habits\nAneesh", "", "10 Min"], ["05.DIWM FTU Trial Optimization\nAneesh", "", "10 Min"], ["Global Business Solutio", "ns Group", "95"]] | V15: Alt Date (slide 66): 5/5/25 | Alt TO (slide 66): mer Experience | Alt Date (slide 67): 5/5/25 | Alt Product (slide 67): QBO | Alt GET (slide 67): Non-PQ QBO customers eligible for both TL & LoC | Alt TO (slide 67): mers eligible for both TL & LoC | Alt Date (slide 68): 5/5/25 | Alt GET (slide 68): ed marketing resulted in stat sig increase in | Alt TO (slide 68): customers they are eligible to apply for with no cannibalization upon rolling out Treatment C. | Alt Date (slide 69): 5/5/25 | Alt TO (slide 69): tal Loan Volume $27,425,500 $26,222,500 $26,883,000 96 98 | Alt Date (slide 70): 5/5/25 | Alt TO (slide 70): mers, | Alt GET (slide 71): to manually send the wrap | Alt TO (slide 71): choice | Alt BY (slide 71): both the Propensity model and the Response model resulted in incremental | Alt Product (slide 72): Payroll | Alt TO (slide 72): IOluNtioSn Gs RGOroUuPp 72 | Campaign re-appears on slide 95 (gap from slide 72) | Alt Product (slide 95): Capital | Date source: CSV – Current Target Launch Date | Name source: CSV | Business Impact updated from Results Report | Status enriched from Results Report | W15: 64–95 | X15: Copy of FY'25_ CRM Analytics Monthly Experiment_Notebook_AC.pdf
A16: ELM-6227 | B16: Launch Targeted Offer experiment on Payroll Cancel Flow | C16: 05-12-2025 | D16: ed Offer Launch Get Attached & Standalone Payroll customers who click on ‘Cancel | E16: 06/30/25 | F16: Reinforcing benefits of Payroll and offering them a discount to make them | G16: GET: ed Offer Launch Get Attached & Standalone Payroll customers who click on ‘Cancel | TO: 06/30/25 | BY: Reinforcing benefits of Payroll and offering them a discount to make them | H16: [P0 Input Goal Priority] Drive saves for Payroll through Reimagined Payroll Cancel flow by launching the first set of Targeted Offers for Payroll cancels. Current evergreen experience for the Payroll Cancel Flow (no targeted offers) launched on 4/1 (ELM-8011). We are now testing targeted offers on top of that experience in a 2-cell experiment: Control: NO Targeted Offers Treatment: (40%, 50%, 60%) off for 3 month offers (using Payroll Price Sensitivity model) Duration: 6-7 weeks | I16: & Implications Payroll Cancel Flow without Targeted Offers Payroll Cancel Flow with Targeted Offer ● A Regardless of their price sensitivity, overall cancel confirmation rate reduced by 2% and saves rate increased by 9% in treatment cell with TO A● IPDs across all groups had higher than benchmark engagement Global Business Solutions Group 77 and launch test with new design ● Move away from offering lower than EDLP discounts to customers who are price sensitive ● Explore and iterate ways to improve saves rate amongst low price sensitive customers other than pricing levers Global Business Solutions Group 78 | J16: Payroll | K16: IPD | L16: Positive (Inferred for review) | Results: 5.1 MEASURE: Complete | M16: Positive Biz Impact | 98 ITC-1 | N16: https://docs.google.com/presentation/d/1J8AGhqimekh03qFyVJE3vEH1xTEfSOxHS7Y1ewGomZg/edit#slide=id.g2efff53d832_0_813 | O16: Cancel Rate | P16: 98 | U16: [["", "", "", "", "", "", "", "", "", "PRODUCTS: Payroll ● DRIVER: Samir K. Ahmed ● QB: ELM-6227 ● SOT: Deck ● DATES: 05/23/25 to 06/30/25", ""], ["Experiment Results\nELM-6227 Payroll Cancel Fl\nTargeted Offer Launch\nTesting targeted offer discounts in the single-scree\nfor customers intending to cancel their Payroll subs\nPromotion Structure:\n● Payroll Attach: 40%, 50%, 60% off for 3 months\n(managed by Payroll Price Sensitivity model)\n● Catch-all audiences: 50% off for 3 months\n(customers who could not be placed by the Payroll price sensitivity\n● Payroll Standalone: 50% off for 3 months\nControl\nInclude project visuals here\nPayroll Cancel Flow without Targeted Offers Payroll Ca\nBusiness Impact: POSITIVE\nBIZ IMPACT\nTargeted offers in the Payroll Cancel flow resulted in 12% hig\nrate. Of the 3 tested offers, the 50% and 60%/3 mos offers dr\nincrementality. Estimated incremental saves of ~65 Payroll u", "Experiment Results", "", "", "", "", "", "ow -\nn Payroll Cancel Flow\ncription.\nmodel)", "", "", ""], ["", "ELM-6227 Payroll C", "", "", "", "", "", "ow -", "", "", ""], ["", "", "", "", "", "", "", "", "", "", ""], ["", "", "Testing targeted offer discounts in the single-scree\nfor customers intending to cancel their Payroll subs\nPromotion Structure:\n● Payroll Attach: 40%, 50%, 60% off for 3 months\n(managed by Payroll Price Sensitivity model)\n● Catch-all audiences: 50% off for 3 months", "", "", "", "", "", "", "", ""], ["", "", "(customers who could not be placed by the Payroll price sensitivity\n● Payroll Standalone: 50% off for 3 months", "", "", "", "", "model)", "", "", ""], ["", "", "Control\nInclude project visuals here\nPayroll Cancel Flow without Targeted Offers Payroll Ca\niness Impact: POSITIVE\nBIZ IMPACT", "", "", "", "", "", "", "", ""], ["", "", "", "", "", "", "", "Treatment", "", "", ""], ["", "", "", "", "", "", "", "", "", "", ""], ["", "", "", "Include project vis", "", "ua", "ls here", "", "", "", ""], ["", "", "", "", "", "", "", "", "", "", ""], ["", "", "", "", "", "", "", "", "", "", "Learnings & Implications\n● A Regardless of their price sensitivity, overall cancel confirmation rate reduced by 2%\nand saves rate increased by 9% in treatment cell with TO\n●B ~40% of all customers saved in the treatment cancel flow experience took a TO\nGlobal Business Solutions Group 73"], ["", "", "", "", "", "", "Payroll Ca", "ncel Flow with Targeted", "Offer", "", ""], ["", "", "", "", "", "", "", "", "", "", "●B ~40% of all customers saved in the treatment cancel flow experience took a TO\nGlobal Business Solutions Group 73"], ["", "", "eted offers in the Payroll Cancel flow resulted in 12% hig\nOf the 3 tested offers, the 50% and 60%/3 mos offers dr", "", "", "", "", "her incremental sa\nove the most", "", "", ""], ["", "", "", "", "", "", "", "", "", "", ""], ["Objective\nGet Attached & Standalone Payroll customers who click on ‘Cancel\nSubscription’ for their Payroll subscription\nTo Accept a discount instead of canceling their subscription\nBy Reinforcing benefits of Payroll and offering them a discount to make them\nfeel supported as valued customers\nResults (5/23 - 6/30)\nProbability\nKPIs - Regardless of sensitivity CON. TEST Δ ITC\n(T>C)\nCancel Starts 1.0K 2.0K"], ["Cancel Confirmation rate 83.7% 81.7% -2.0% 98 91.1%\nAA\nNet Saves Rate 16.3% 18.3% 2.0% 112 84.1%\nSaves by TO 0.0% 7.50% 7.5% N/A\nDowngrade rate 1.1% 0.50% -0.6% 44\nUpgrade rate 0.1% 0.25% 0.1% 241\nSaved by CS+ others 15.0% 10.1% -5.0% 67\n*Net Saves rate = customers who did not cancel (includes taking the TO, downgrades, upgrades)\nLearnings & Implications\n● A Regardless of their price sensitivity, overall cancel confirmation rate reduced by 2%\nand saves rate increased by 9% in treatment cell with TO\n●B ~40% of all customers saved in the treatment cancel flow experience took a TO\nGlobal Business Solutions Group 73"], ["KPIs - Regardless of sensitivity", "CON.", "TEST", "Δ", "ITC", "Probability\n(T>C)"], ["Cancel Starts", "1.0K", "2.0K", "", "", ""], ["Cancel Confirmation rate", "83.7%", "81.7%", "-2.0%", "98\nA", "91.1%"], ["Net Saves Rate", "16.3%", "18.3%", "2.0%", "A\n112", "84.1%"], ["Saves by TO", "0.0%", "7.50%", "7.5%", "N/A", ""], ["Downgrade rate", "1.1%", "0.50%", "-0.6%", "44", ""], ["Upgrade rate", "0.1%", "0.25%", "0.1%", "241", ""], ["Saved by CS+ others", "15.0%", "10.1%", "-5.0%", "67", ""], ["*Net Saves rate = customers who did not cancel (includes taking the TO, downgrades, upgrades)", "", "", "", "", ""], ["", "Control"], ["", "Include project vis"], ["", "Payroll Cancel Flow without Targeted Offers"], ["Global Business Solutio", "ns Group", "73"], ["POSITIVE\nKPI’s by price sensitivity BIZ IMPACT", "", "", "", "", "", "", "", "", "", ""], ["KPIs - High Price sensitivity\n(60%)", "", "CON.", "", "TEST", "", "Δ", "", "ITC", "", "Probability\n(T>C)"], ["Cancel Starts", "", "287", "", "542", "", "", "", "", "", ""], ["Cancel Confirmation rate", "", "86.1%", "", "83.8%", "", "-2.3%", "", "97", "", "80.3%"], ["Net Saves Rate", "", "13.9%", "", "16.2%", "", "2.3%", "", "116", "", "81.8%"], ["Saves by TO", "", "0.0%", "", "5.4%", "", "5.4%", "", "N/A", "", ""], ["Saves by downgrade", "", "0.3%", "", "0.4%", "", "0.0%", "", "106", "", ""], ["Saves by upgrade", "", "0.0%", "", "0.2%", "", "0.2%", "", "N/A", "", ""], ["Saves by CS+other", "", "13.6%", "", "10.3%", "", "-3.3%", "", "76", "", ""], ["", "", "", "", "", "", "", "", "", "", ""], ["", "KPIs - Low Price sensitivity (40%)", "", "CON.", "", "TEST", "", "Δ", "", "ITC", "Probability\n(T>C)"], ["", "Cancel Starts", "", "120", "", "199", "", "", "", "", ""], ["", "Cancel Confirmation rate", "", "76.7%", "", "76.4%", "", "-0.3%", "", "100", "51.7%"], ["", "Net Saves Rate", "", "23.3%", "", "23.6%", "", "0.3%", "", "101", "51.2%"], ["", "Saves by TO", "", "0.0%", "", "4.5%", "", "4.5%", "", "N/A", ""], ["", "Saves by downgrade", "", "1.7%", "", "1.5%", "", "-0.2%", "", "90", ""], ["", "Saves by upgrade", "", "0.8%", "", "1.0%", "", "0.2%", "", "N/A", ""], ["", "Saves by CS+ other", "", "20.8%", "", "16.6%", "", "-4.3%", "", "80", ""], ["KPIs - Medium Price sensitivity (50%)", "CON.", "TEST", "Δ", "ITC", "Probability\n(T>C)"], ["Cancel Starts", "261", "490", "", "", ""], ["Cancel Confirmation rate", "82.4%", "82.7%", "0.3%", "100", "54.7%"], ["Net Saves Rate", "17.6%", "17.3%", "-0.3%", "98", "43.1%"], ["Saves by TO", "0.0%", "6.3%", "6.3%", "N/A", ""], ["Saves by downgrade", "0.8%", "0.4%", "-0.4%", "53", ""], ["Saves by upgrade", "0.0%", "0.2%", "0.2%", "N/A", ""], ["Saves by CS+other", "16.9%", "10.4%", "-6.5%", "62", ""], ["High Price Sensitivity Group\n● Saves Rate: Demonstrated a positive incremental lift at 118 ITC.\n● Cancellations: Net cancellations decreased by 3%.\n● Confidence Level: High, supported by robust sample size and statistical significance.\nMedium and Low Price Sensitivity Groups\n● Performance: Trends for both cancellation and net saves rate were largely flat\n● Confidence Level: Moderate, due to smaller sample sizes, which limits directional\ncertainty\n● As expected, customers with low price sensitivity had the lowest share (17%) of total\nsaves from targeted offers. The % of total saves generated from the med and high price\nsensitivity groups was at least 30% each."], [""], ["KPIs - Catch all (50%; No price sensitivity o/p)", "CON.", "TEST", "Δ", "ITC", "Probability\n(T>C)"], ["Cancel Starts", "1.1K", "1.7K", "", "", ""], ["Cancel Confirmation rate", "83.4%", "79.8%", "-3.7%", "96", "96.2%"], ["Net Saves Rate", "16.6%", "20.2%", "3.7%", "122", "93.2%"], ["Saves by TO", "0.0%", "6.4%", "6.4%", "N/A", ""], ["Saves by downgrade", "0.9%", "0.5%", "-0.4%", "52", ""], ["Saves by upgrade", "0.2%", "0.1%", "-0.1%", "N/A", ""], ["Saves by CS+other", "15.5%", "13.3%", "-2.2%", "86", ""], ["KPIs - Standalone (50%)", "CON.", "TEST", "Δ", "ITC", "Probability\n(T>C)"], ["Cancel Starts", "275", "265", "", "", ""], ["Cancel Confirmation rate", "85.45%", "84.53%", "-0.9%", "99", "62.1%"], ["Net Saves Rate", "14.5%", "15.5%", "0.9%", "106", "47.9%"], ["Saves by TO", "0%", "5%", "5.3%", "N/A", ""], ["Saves by downgrade", "1.5%", "0.4%", "-1.1%", "26", ""], ["Saves by upgrade", "0.0%", "0.0%", "0.0%", "N/A", ""], ["Saves by CS+other", "13.1%", "9.8%", "-3.3%", "75", ""], ["POSITIVE\nKPI’s by SKU BIZ IMPACT", "", "", "", "", ""], ["", "KPIs - PREMIUM", "CON.", "TEST", "Δ", "ITC"], ["", "Cancel Starts", "148", "394", "", ""], ["", "Cancel Confirmation rate", "87.8%", "82.5%", "-5.4%", "94"], ["", "Net Saves Rate", "12.2%", "17.5%", "5.4%", "144"], ["", "Saves by TO", "0.0%", "7.4%", "7.4%", "N/A"], ["", "Saves by downgrade", "2.0%", "1.0%", "-1.0%", "50"], ["", "Saves by upgrade", "0.0%", "0.3%", "0.3%", "N/A"], ["", "Saves by CS+other", "10.1%", "8.9%", "-1.3%", "88"], ["KPIs - CORE", "CON.", "TEST", "Δ", "ITC"], ["Cancel Starts", "420", "932", "", ""], ["Cancel Confirmation rate", "82.1%", "82.2%", "0.0%", "100"], ["Net Saves Rate", "17.9%", "17.8%", "0.0%", "100"], ["Saves by TO", "0.0%", "11.3%", "11.3%", "N/A"], ["Saves by downgrade", "0.2%", "0.1%", "-0.1%", "45"], ["Saves by upgrade", "0.2%", "0.3%", "0.1%", "N/A"], ["Saves by CS+other", "17.4%", "6.1%", "-11.3%", "35"], ["KPIs - ELITE", "CON.", "TEST", "Δ", "ITC", ""], ["Cancel Starts", "70", "144", "", "", ""], ["Cancel Confirmation rate", "90.0%", "81.3%", "-8.8%", "90", ""], ["Net Saves Rate", "10.0%", "18.8%", "8.8%", "188", ""], ["Saves by TO", "0.0%", "6.3%", "6.3%", "N/A", ""], ["Saves by downgrade", "0.8%", "0.4%", "-0.4%", "53", ""], ["Saves by upgrade", "0.0%", "0.2%", "0.2%", "N/A", ""], ["Saves by CS+other", "9.2%", "11.8%", "2.6%", "128", ""], ["POSITI", "", ""], ["", "POSITI", "VE"], ["RESULTS", "BIZ IMPA", "CT"], ["CHANNEL ENGAGEMENT", "", "", "", ""], ["Cohort", "IPD", "", "", ""], ["", "Imp.", "Clicks", "CTR", "ITB"], ["Catch all", "1,293", "69", "5.34%", "243"], ["Medium Sensitivity", "583", "24", "4.12%", "187"], ["High Sensitivity", "678", "30", "4.42%", "201"], ["Low Sensitivity", "248", "13", "5.24%", "238"], ["Standalone", "335", "13", "3.88%", "176"], ["", "IPD Benchmark **", "", "2.20%", ""], ["Global Business Solutio", "ns Group", "77"], ["Results: POSITIVE NEGATIVE\nBIZ IMPACT BIZ IMPACT", "", "Call Outs: A D G"], ["", "FLAT &\nROLL OUT", ""], ["", "", ""], ["RESULTS POSITI\nBIZ IMPA", ""], ["", "VE\nCT"], ["saves", "", "", ""], ["", "", "", ""], ["", "HIGHLIGHTS", "", "LOWLIGHTS"], ["", "● Overall increase in saves rate with high confidence\n● Discount tiers that were equal to or higher than\nEDLP seems to work better than other discount\ntiers\n● TO led to incremental saves amongst customers\nwho were not captured by the price sensitivity\nmodel (catch all) as well", "", "● Leakages of TO shown to customers in control cell which\nreduced volume of assignments in control by 30%\n● Coverage of TO amongst all assignments was not 100% as\nexpected\n● Catch all bucket had much higher than expected volume of\ncustomers\n● The campaign had to be wrapped up faster than expected\nwhich resulted in lower than estimated sample sizes"], ["", "", "", ""], ["", "NEXT STEPS & IMPLICATIONS", "", ""], ["", "● Explore ways to roll this out in absence of a winback campaign for Payroll\n● Iterate over the learnings and launch test with new design\n● Move away from offering lower than EDLP discounts to customers who are price sensitive\n● Explore and iterate ways to improve saves rate amongst low price sensitive customers other than pricing levers", "", ""], ["Global Business Solutio", "ns Group", "78"], ["Results: POSITIVE NEGATIVE\nBIZ IMPACT BIZ IMPACT", "", "Call Outs: A D G"], ["", "FLAT &\nROLL OUT", ""], ["", "", ""]] | V16: Alt GET (slide 74): ed offers. The % of total saves generated from the med and high price | Alt TO (slide 74): 0.0% 5.4% 5.4% N/A Saves by TO 0.0% 6.3% 6.3% N/A | Alt BY (slide 74): price sensitivity BIZ IMPACT | Alt GET (slide 75): ed for the offers | Alt TO (slide 75): 0.0% 6.4% 6.4% N/A Saves by TO 0% 5% 5.3% N/A | Alt BY (slide 75): price sensitivity BIZ IMPACT | Alt TO (slide 76): 0.0% 11.3% 11.3% N/A Saves by TO 0.0% 7.4% 7.4% N/A | Alt BY (slide 76): SKU BIZ IMPACT | Alt status (slide 77): Trending Positive | Alt GET (slide 78): ed offers on cancellation flow resulted in incremental | Alt TO (slide 78): shown to customers in control cell which | Alt BY (slide 78): 30% | Alt status (slide 78): Trending Positive | Date source: CSV – Current Target Launch Date | Name source: CSV | Hypothesis filled from CSV Project Description CSV (Inferred for review) | Business Impact updated from Results Report | Status enriched from Results Report | W16: 73–78 | X16: Copy of FY'25_ CRM Analytics Monthly Experiment_Notebook_AC.pdf
A17: ELM-8276 | B17: Fusion Lineup: Bill Pay Basic Activation Test | C17: 07-01-2025 | D17: QBO customers who are not subscribed to Bill Pay | E17: mer goes directly to TRON Similar to current state but with Activate CTA for | F17: informing them that Bill Pay Basic is now included in their subscriptions | G17: GET: QBO customers who are not subscribed to Bill Pay | TO: mer goes directly to TRON Similar to current state but with Activate CTA for | BY: informing them that Bill Pay Basic is now included in their subscriptions | H17: If we send customers to activate their Bill Pay Basic subscription to a landing page vs. directly to TRON to activate; we will drive a greater business impact as measured by the number of sign-ups (GNS) activations (GNA). <30 Day Results GNA Probability Bucket GNS Rate GNS ITC. GNA ITC Rate (T>C) Multi-Sku Activate 6.9% 99 2.9% 96 % BP Page Activate 6.9% 98 3.0% 97 % Direct-To-Tron 8.0% 114 3.2% 105 Control 7.0% - 3.1% - Key Takeaways 1 Sending customers directly to TRON significantly improves top of funnel [GNS - 114 ITC , +90], downstream conversion is weaker 2 There is only 72% conversion from approved to GNS for Tron while Control | I17: 1 Sending customers directly to TRON significantly improves top of funnel [GNS - 114 ITC , +90], downstream conversion is weaker 2 There is only 72% conversion from approved to GNS for Tron while Control | J17: Bill Pay | K17: Landing Page | L17: Positive | Results: 5.1 MEASURE: Complete | M17: Negative Biz Impact | 116 ITC-1 | 110 ITC-2 | N17: https://docs.google.com/presentation/d/1ned7ZQvaqcfXvZj7Bq_lePfhbimqJZadZcs10IN2H0g/edit?usp=sharing | O17: GNS/GNA | P17: 116 | Q17: GNS/GNA | R17: 110 | S17: GNS/GNA | U17: [["", "", "", ""], ["SOURCE OF TRUTH\nELM - 8276\nBill Pay Basic Activation Test\n(QBO New Line-Up)\nELM Driver: Melissa Rattrovo, Chelsea Bauer\nCRM Analytics: Karthik Renganathan, Vijay Yeddu\nELM Workstream: Monetization\nDate: 07-25-2025\nELM Quickbase Record: ELM-8276\nWorkbook: Link ⏐ FIGMA", "", "", "SWAG Effort Size\nM"], ["", "", "", "79\nTemplate v5.2 Updated Jan.. 2025"], ["SOURCE OF TRUTH", ""], ["ELM - 8276\nBill Pay Basic Activation Test", ""], ["", "SWAG Effort Size", "", ""], ["", "M", "", ""], ["", "", "", ""], ["", "", "79\nv5.2 Updated Jan.. 20", ""], ["Bill Pay Activation Test Experience - 4 cell test\n[FIGMA]\nTreatment A Treatment C Control - Cell D\nCustomer goes directly to TRON Similar to current state but with Activate CTA for\nCurrent state Bill Pay Sign-Up Pg, evergreen\nBasic and pink call out of included in current QB\nexperience\nplan\nAll sku’s → choose plan\nTreatment B\nsoft landing page, only references Bill Pay Basic with Activate CTA.\nGlobal Business Solutions Group", "", "", "", "", ""], ["", "", "", "", "", ""], ["", "", "", "", "", ""], ["", "", "", "", "", ""], ["", "", "", "", "", ""], ["", "", "Global Business Solutions Group", "", "", ""], ["", ""], ["", ""], ["", "", "", "", "", ""], ["EARLY EXPERIMENT RESULTS <30 DAY\nBill Pay Basic Activation\n(QBO New Line-Up)\nTesting 3 new customer journeys vs. curren\nexperience to activate Bill Pay Basic which i\nthe QBO subscription.\nBusiness Impact:\nSTILL BAKING", "", "EARLY EXPERIMENT RESULTS <30 DAY", "Test\nt Bill Pay sign up\ns now included in", "", "PRODUCTS: Bill Pay ● DRIVERS: Melissa/Chelsea ● CRMA: Vijay ● QB: ELM-8276 ● DATES: 07-01-25 to 11-01-25"], ["", "", "", "", "", "Objective\nGet QBO customers who are not subscribed to Bill Pay\nTo activate and use Bill Pay Basic / paid SKU\nBy informing them that Bill Pay Basic is now included in their subscriptions\nbut have other paid SKUs available to meet their business needs.\nHypothesis\nIf we send customers to activate their Bill Pay Basic subscription to a landing\npage vs. directly to TRON to activate; we will drive a greater business impact\nas measured by the number of sign-ups (GNS) activations (GNA).\n<30 Day Results\nGNA Probability\nBucket GNS Rate GNS ITC. GNA ITC\nRate (T>C)\nMulti-Sku Activate 6.9% 99 2.9% 96 %\nBP Page Activate 6.9% 98 3.0% 97 %\nDirect-To-Tron 8.0% 114 3.2% 105\nControl 7.0% - 3.1% -\nKey Takeaways\n1 Sending customers directly to TRON significantly improves top of funnel\n[GNS - 114 ITC , +90], downstream conversion is weaker\n2 There is only 72% conversion from approved to GNS for Tron while Control\nconversion is at 90% similar to other two buckets\n3 The other two buckets did not show significant uplift in conversion rates\ncompared to the control, hence flat impact. Global Business Solutions Group 81"], ["", "", "", "Test\nt Bill Pay sign up\ns now included in", "", ""], ["", "", "Bill Pay Basic Activation\n(QBO New Line-Up)\nTesting 3 new customer journeys vs. curren\nexperience to activate Bill Pay Basic which i\nthe QBO subscription.", "", "", ""], ["", "", "", "", "", ""], ["", "", "", "", "", ""], ["", "", "", "", "", "1\n2"], ["", "", "", "", "", ""], ["", "", "", "", "", ""], ["", "Business Impact:\nSTILL BAKING", "", "", "", ""], ["", "", "", "", "", ""], ["", "", "", "", "", ""], ["Objective\nGet QBO customers who are not subscribed to Bill Pay\nTo activate and use Bill Pay Basic / paid SKU\nBy informing them that Bill Pay Basic is now included in their subscriptions\nbut have other paid SKUs available to meet their business needs.\nHypothesis\nIf we send customers to activate their Bill Pay Basic subscription to a landing\npage vs. directly to TRON to activate; we will drive a greater business impact\nas measured by the number of sign-ups (GNS) activations (GNA).\n<30 Day Results", "", "", "", "", "", ""], ["", "Bucket", "GNS Rate", "GNS ITC.", "GNA\nRate", "GNA ITC", "Probability\n(T>C)"], ["", "Multi-Sku Activate", "6.9%", "99", "2.9%", "96", "%"], ["", "BP Page Activate", "6.9%", "98", "3.0%", "97", "%"], ["", "Direct-To-Tron", "8.0%", "114", "3.2%", "105", ""], ["", "Control", "7.0%", "-", "3.1%", "-", ""], ["ct. Global Business Solutio", "ns Group", "81"], ["", "", "Call Outs: A D G"], ["", "FLAT\nIMPACT", ""], ["STILL BAKING", "", ""], ["", "", "", ""], ["SOURCE OF TRUTH\nELM - 7785\nTap to Pay Launch\nELM Driver: Charlotte Wong\nCRM Analytics: Naveen Rajendrapandian\nELM Workstream: Monetization\nDate: 04-10-2025\nEPLMr Qeuisckebasne Rteecorrd: ENLM-a778m5 e\nWorkbook: Merchants & Non-Merchants\nBusiness Brief: Link\nSlack Channel: Link", "", "", "SWAG Effort Size\nL"], ["", "", "", "82\nTemplate v5.0 Updated Aug 2024"], ["SOURCE OF TRUTH"], ["ELM - 7785\nTap to Pay Launch"], ["ELM Driver: Charlotte Wong\nCRM Analytics: Naveen Rajendrapandian", ""], ["ELM Workstream: Monetization\nDate: 04-10-2025\nEPLMr Qeuisckebasne Rteecorrd: ENLM-a778m5 e\nWorkbook: Merchants & Non-Merchants", ""], ["Business Brief: Link\nSlack Channel: Link", ""], ["ELM-7785"], ["Name\nNon-Merchants"], [""], ["82\nv5.0 Updated Aug 20"]] | V17: Alt Date (slide 81): 07-01-25 | Alt TO (slide 81): 11-01-25 | Alt Date (slide 82): 04-10-2025 | Alt TO (slide 82): Pay Launch | Date source: CSV – Current Target Launch Date | Name source: CSV | Business Impact updated from Results Report | Status enriched from Results Report | W17: 79–82 | X17: Copy of FY'25_ CRM Analytics Monthly Experiment_Notebook_AC.pdf
A18: ELM-7785 | B18: Tap to Pay Launch | C18: 03-25-2025 | D18: Non-Merchants with QuickBooks Mobile | E18: Pay Launch: | F18: demonstrating the value that T2P offers in helping them | G18: GET: Non-Merchants with QuickBooks Mobile | TO: Pay Launch: | BY: demonstrating the value that T2P offers in helping them | H18: Tap to Pay solves one of our customers’ biggest pain points (waiting to get paid); if we tell Non-Merchants about this new in-person payment feature in QBM we will increase GNA and T2P activation. Results Bayesian Annual KPIs CONT. TEST ITC (>0 impact) incr. units # companies 247K 246K Pymts SU 30d 0.72% 0.73% 102 A 71% Pymts GNA 30d 0.26% 0.26% 99 T2P enablements 30d 0.12% 0.13% 112 B 91% 630 T2P usage 30d 0.004% 0.011% 281 340 Learnings & Implications A● The impact of 2% incr. in Payments SU is not stat sig, but per | I18: & Implications A● The impact of 2% incr. in Payments SU is not stat sig, but per & Implications A● No significant CV impact even with increased T2P | J18: QuickBooks | K18: IPD; Push; Email; Landing Page | L18: Positive (Inferred for review) | Results: 5.1 MEASURE: Complete | M18: Flat | 99 ITC-1 | 101 ITC-2 | 101 ITC-3 | N18: https://docs.google.com/presentation/d/1z0644C_MAtQY_j_kbzUGo1VdvmycEDD06CyvNwmWi3g/edit#slide=id.g3097b480f52_0_0 | O18: GNS/GNA | P18: 99 | Q18: Charge Volume | R18: 101 | S18: Charge Volume | T18: 101 | U18: [["", "", "", "", "", "", "", "", "", "", "", "", "", "", ""], ["EXPERIMENT RESULTS\nELM-7785 Tap to Pay Laun\nNon-Merchants\nIPD, Email, Push, and in-product landing\ncampaign targeting Non-Merchants sup\nlaunch of Tap to Pay for the QuickBooks\nBusiness Impact: FLAT\nIMPACT\nTargeting Non-Merchants with the T2P feature did\nattaches or enablement, but early sign-up signals\ninto existing marketing.", "", "EXPERIMENT RESULTS", "", "", "", "", "", "", "ch:\npage\nporting the\nMobile app", "", "", "", "", "PRODUCTS: QBO Payments ● DRIVER: Charlotte Wong ● QB: ELM-7785 ● SOT: Deck ●\nLAUNCH: 04-10-25"], ["", "", "", "", "", "", "", "", "", "ch:\npage\nporting the\nMobile app", "", "", "", "", ""], ["", "", "", "", "", "", "", "", "", "", "", "", "", "", ""], ["", "", "", "", "", "", "", "", "", "", "", "", "", "", ""], ["", "", "", "", "", "", "", "", "", "", "", "", "", "", ""], ["", "", "", "", "", "", "", "", "", "", "", "", "", "", ""], ["", "", "", "", "", "", "", "", "", "", "", "", "", "", ""], ["", "", "", "", "", "", "", "", "", "", "", "", "", "", ""], ["", "", "", "", "", "", "", "", "", "", "", "", "", "", ""], ["", "", "", "", "", "", "", "", "", "", "", "", "", "", ""], ["", "", "", "", "", "", "", "", "", "", "", "", "", "", ""], ["", "Business Impact: FLAT\nIMPACT\nTargeting Non-Merchants with the T2P feature did\nattaches or enablement, but early sign-up signals\ninto existing marketing.", "", "", "", "", "", "", "", "", "", "", "", "", ""], ["", "", "Targeting Non-Merchants with the T2P feature did", "", "", "", "", "", "", "", "", "", "", "", ""], ["", "", "", "", "", "", "", "", "", "n’t drive signific", "", "", "ant", "", ""], ["", "", "attaches or enablement, but early sign-up signals", "", "", "", "", "", "", "suggest we can", "", "", "fold it", "", ""], ["", "", "nto existing marketing.", "", "", "", "", "", "", "", "", "", "", "", ""], ["", "", "", "", "Bayesian", "Annual"], ["KPIs", "CONT.", "TEST", "ITC", "(>0 impact)", "incr. units"], ["# companies", "247K", "246K", "", "", ""], ["Pymts SU 30d", "0.72%", "0.73%", "102", "A 71%", ""], ["Pymts GNA 30d", "0.26%", "0.26%", "99", "", ""], ["T2P enablements 30d", "0.12%", "0.13%", "112", "B 91%", "630"], ["T2P usage 30d", "0.004%", "0.011%", "281", "", "340"], ["", "", "", "", "", ""], ["was helpful.\nGlobal Business Solutio", "ns Group", "83"], ["", "", "Call Outs: A D G"], ["", "FLAT\nIMPACT", ""], ["STILL BAKING", "", ""], ["", "", "", "", "", "", "", "", "", "", "", "", ""], ["", "", "", "", "", "", "", "", "", "", "", "PRODUCTS: QBO Payments ● DRIVER: Charlotte Wong ● QB: ELM-7785 ● SOT: Deck ●\nLAUNCH: 03-25-25\nObjective\nGet (1) Merchants with QBM or GoPayment apps; and (2)\nMerchants without QBM\nTo use Tap to Pay\nBy demonstrating the value that T2P offers in helping them get\npaid faster and easier\nHypothesis\nTap to Pay solves one of our customers’ biggest pain points (waiting\nto get paid); if we tell Merchants about this new in-person payment\nfeature in QBM and GP we will increase CV and T2P activation.\nResults\nBayesian Annual\nKPIs CONT. TEST ITC\n(>0 impact) incr. units\n# companies 586K 587K\nPymts active use 30d 49.5% 49.5% 100\nA\nAvg. CV 30d $6,273 $6,332 101 Cont Samp\nT2P enablements 30d 1.26% 1.45% 115 21K\nT2P usage 30d 0.30% 0.34% 116 5K\nLearnings & Implications\nA● No significant CV impact even with increased T2P\nenablement due to low adoption rate in general. Do a follow\non T2P usage and share of CV.\nGlobal Business Solutions Group 84", ""], ["EXPERIMENT RESULTS\nELM-7785 Tap to Pay Launch\nMerchants\nIPD, Email, Push, and in-product landing\ntargeting Merchants supporting the laun\nfor the QuickBooks Mobile and GoPaym\nBusiness Impact: FLAT\nIMPACT\nMarketing to existing merchants could significantly bo\ndriving an estimated 21K incremental units per year, th\non CV remains flat. We can integrate this into our existi", "", "EXPERIMENT RESULTS", "", "", "", "", "", ":\npage campaign\nch of Tap to Pay\nent apps", "", "", "", ""], ["", "", "ELM-7785 Tap to Pa", "", "", "", "", "", "", "", "", "", ""], ["", "", "", "", "", "", "", "", "", "", "", "", ""], ["", "", "", "", "", "", "", "", "", "", "", "", ""], ["", "", "", "", "", "", "", "", "", "", "", "", ""], ["", "", "", "", "", "", "", "", "", "", "", "", ""], ["", "", "", "", "", "", "", "", "", "", "", "", ""], ["", "", "", "", "", "", "", "", "", "", "", "", ""], ["", "", "", "", "", "", "", "", "", "", "", "", ""], ["", "", "", "", "", "", "", "", "", "", "", "", "Learnings & Implications\nA● No significant CV impact even with increased T2P\nenablement due to low adoption rate in general. Do a follow\non T2P usage and share of CV."], ["", "", "", "", "", "", "", "", "", "", "", "", "A● No significant CV impact even with increased T2P\nenablement due to low adoption rate in general. Do a follow\non T2P usage and share of CV."], ["", "", "", "", "", "", "", "", "", "", "", "", ""], ["", "Business Impact: FLAT\nIMPACT\nMarketing to existing merchants could significantly bo\ndriving an estimated 21K incremental units per year, th\non CV remains flat. We can integrate this into our existi", "", "", "", "", "", "", "", "", "", "", ""], ["", "", "Marketing to existing merchants could significantly bo", "", "", "", "", "", "", "", "", "", ""], ["", "", "", "", "", "", "", "", "ost T2P enableme", "nt,", "", "", ""], ["", "", "driving an estimated 21K incremental units per year, th", "", "", "", "", "", "ough the overall i", "mpact", "", "", ""], ["", "", "on CV remains flat", ". We can integrate this into our existi", "", "", "", "", "ng marketing.", "", "", "", ""], ["NCH: 03-25-25"], ["Objective\nGet (1) Merchants with QBM or GoPayment apps; and (2)\nMerchants without QBM\nTo use Tap to Pay\nBy demonstrating the value that T2P offers in helping them get\npaid faster and easier\nHypothesis\nTap to Pay solves one of our customers’ biggest pain points (waiting\nto get paid); if we tell Merchants about this new in-person payment\nfeature in QBM and GP we will increase CV and T2P activation.\nResults"], ["", "", "", "", "", "", "", ""], ["KPIs", "CONT.", "TEST", "", "ITC", "Bayesian\n(>0 impact)", "", "Annual\nincr. units"], ["# companies", "586K", "587K", "", "", "", "", ""], ["Pymts active use 30d", "49.5%", "49.5%", "", "100", "", "", ""], ["Avg. CV 30d", "$6,273", "$6,332", "", "101", "A", "Cont Samp", ""], ["T2P enablements 30d", "1.26%", "1.45%", "", "115", "", "", "21K"], ["T2P usage 30d", "0.30%", "0.34%", "", "116", "", "", "5K"], ["", "", "", "", "", "", "", ""], ["Global Business Solutio", "ns Group", "84"], ["", "Call Outs: A D G"], ["FLAT\nIMPACT", ""], [""], ["RESULTS"], [""], ["While impact on GNA and CV was flat, we did see positive impact on T2P enablement, suggesting that incorporating Tap to Pay\nmessaging into existing marketing for both Merchants and Non-Merchants (vs. rolling out the entire standalone Tap to Pay\nlaunch campaign as evergreen) may be beneficial. Communications required by our Apple contract have also been considered\nas part of the recommended next steps in the next slide."], ["HIGHLIGHTS", "", "LOWLIGHTS", "", "", "", ""], ["● Non-Merchants: (1) per Bayesian, T2P messaging\nhas 71% chance to have (+) impact on Payments\nsign-ups; (2) T2P enablements were 112 ITC\n● Merchants: T2P enablements were 115 ITC", "", "● Non-Merchants: impact to Payments GNA 30D was flat\n● Merchants: impact to CV 30D and Payments Active Use\n30D were both flat", "", "", "", ""], ["", "", "", "", "", "", ""], ["Global Business Solutions Group 8", "", "", "", "", "", ""], ["", "", "", "Global Business Solutio", "ns Group", "8", "5"], ["", ""], ["Results: POSITIVE NEGATIVE\nBIZ IMPACT BIZ IMPACT", "", "Call Outs: A D G"], ["", "FLAT &\nROLL OUT", ""], ["", "", ""], [""], ["RESULTS"], ["", "", "", "", ""], ["", "Based on the campaign’s flat results, here is what we will and will not do for Tap to Pay (experiments and evergreens).", "", "", ""], ["", "", "", "", ""], ["", "", "CHANNEL", "AUDIENCE", ""], ["ACTION", "", "", "", ""], ["NEW TEST: Highlight Tap to Pay as a mobile benefit (one amongst several)\nin QBM SS FTU", "", "Email", "0-31D QBM SS customers", "COMPLETED: ELM-7770 experiment will be live in Q1"], ["NEW TEST: Highlight Tap to Pay as a Payments benefit (one amongst\nseveral) in Payments nurture campaign", "", "Email, IPD, push", "0-90D post-GNA Merchants", "IN PROGRESS: ELM-5776 experiment will be live in Q1"], ["NEW EVERGREEN: Rollout standalone Tap to Pay GoPayment pushes", "", "Push", "GoPayment customers", "TBD: Change order to turn on in H1"], ["NEW EVERGREEN: Rollout standalone ELM-7785 Tap to Pay emails and\npushes to eligible customers", "", "Email, Push", ">180D QBM Merchants &\nNon-Merchants", "TBD: Change order to turn on in H1"], ["NEW EVERGREEN: Help PD incorporate existing Tap to Pay landing page\ninto the QBO navigation", "", "In-product LP", "QBO Merchants,\nNon-Merchants", "TBD: This is an ask for PD to incorporate; most likely work\nwith FODE team"], ["EXISTING EVERGREEN: Update existing Merchant/Non-Merchant OICMS\npages with Tap to Pay messaging (vs. card reader message)", "", "OICMS", "QBO Merchants,\nNon-Merchants", "TBD: Change order to turn on in H1"], ["NO ACTION", "", "", "", ""], ["NEW EVERGREEN: Rollout stand alone ELM-7785 Tap to Pay IPDs as\nevergreen", "", "IPD", "Merchants, Non-Merchants", "N/A: Cannibalization with existing Payments evergreen IPD\ncampaigns"], ["NEW TEST: Ad hoc campaigns for new Apple features and capabilities", "", "All", "All eligible customers", "N/A: As part of Apple contract requirements these can be\ndone through either Whats New or an Approve It For Me\npush notification (which is driven by GTM)"], ["EXISTING EVERGREEN: Highlight Tap to Pay as a Payments benefit (one\namongst several) in Payments FTU", "", "Email, IPD, push", "0-31D pre-GNA Merchants", "DEPRIORITIZED: If this gets prioritized in FY26 then TTP\nmessaging will be included"], ["", "", "", "", ""], ["NEW TEST: Highlight Tap to Pay as a mobile benefit (one amongst several)\nin QBM SP FTU optimization", "", "Email, push", "0-31D QBM SP customers", "DEPRIORITIZED: If this gets prioritized in FY26 then TTP\nGlobal Business Solutions Group 86\nmessaging will be included"], ["this gets prioritized in FY\nGlobal Business Solutio\nncluded", "26 then T\nns Group", "TP\n86"], ["FLAT &\nROLL OUT"], [""], [""], ["RESULTS"], ["Non-Merchants", "", "", "", "", "", "", "", "", "", "", "", "", ""], ["This campaign something something something business impact", "", "", "", "", "", "", "", "", "", "", "", "", ""], ["Cohort", "Email", "", "", "", "", "", "", "", "IPD", "", "", "", "Push"], ["", "Sent", "%", "Opens", "%", "ITB", "CTR", "ITB", "Unsub", "Impr.", "%", "CTR", "ITB", ""], ["Treatment", "60.2K", "24.4%", "18.1K", "30.1%", "100", "0.4%", "13", "0", "113.3K", "45.9%", "0.5%", "21", ""], ["Email Benchmark*", "", "", "", "30%", "", "3%", "", "", "IPD\nBenchm\nark **", "", "2.6%", "", ""], ["ITB* Describe the benchmark", "", "", "", "", "", "", "", "", "IPB** Describe the benchmark", "", "", "", ""], ["Merchants", "", "", "", "", "", "", "", "", "", "", "", "", ""], ["This campaign something something something business impact", "", "", "", "", "", "", "", "", "", "", "", "", ""], ["Cohort", "Email", "", "", "", "", "", "", "", "IPD", "", "", "", "Push"], ["", "Sent", "%", "Opens", "%", "ITB", "CTR", "ITB", "Unsub", "Impr.", "%", "CTR", "ITB", ""], ["Treatment", "310.8K", "52.9%", "128.5K", "41.4%", "138", "1.2%", "41", "0", "339.4K", "57.8%", "2.1%", "163", ""], ["Email Benchmark*", "", "", "", "30%", "", "3%", "", "", "IPD\nBenchm\nark **", "", "1.3%", "", ""], ["ITB* Describe the benchmark", "", "", "", "", "", "", "", "", "IPB** Describe the benchmark", "", "", "", ""], ["Global Business Solutio", "ns Group", "87"], ["Results: POSITIVE NEGATIVE\nBIZ IMPACT BIZ IMPACT", "", "Call Outs: A D G"], ["", "FLAT &\nROLL OUT", ""], ["", "", ""]] | V18: Alt Date (slide 84): 03-25-25 | Alt Hypothesis (slide 84): Tap to Pay solves one of our customers’ biggest pain points (waiting to get paid); if we tell Merchants about this new in-person payment feature in QBM and GP we will increase CV and T2P activation. Results Bayesian Annual KPIs CONT. TEST ITC (>0 impact) incr. units # companies 586K 587K Pymts active use 30d 49.5% 49.5% 100 A Avg. CV 30d $6,273 $6,332 101 Cont Samp T2P enablements 30d 1.26% 1.45% 115 21K T2P usage 30d 0.30% 0.34% 116 5K Learnings & Implications A● No significant CV impact even with increased T2P | Alt GET (slide 84): (1) Merchants with QBM or GoPayment apps; and (2) | Alt BY (slide 84): demonstrating the value that T2P offers in helping them get | Alt Campaign Name (slide 85): was Flat Impact | Alt Product (slide 85): Payments | Alt GET (slide 85): to manually send the wrap | Alt BY (slide 85): our Apple contract have also been considered | Alt status (slide 85): Trending Positive | Alt Campaign Name (slide 86): was Flat Impact | Alt Hypothesis (slide 86): If this gets prioritized in FY26 then TTP | Alt Product (slide 86): Payments | Alt GET (slide 86): s prioritized in FY26 then TTP | Alt TO (slide 86): Pay (experiments and evergreens). | Alt BY (slide 86): GTM) | Alt status (slide 86): Trending Positive | Alt status (slide 87): Trending Positive | Date source: CSV – Current Target Launch Date | Name source: CSV | Business Impact updated from Results Report | Status enriched from Results Report | W18: 83–87 | X18: Copy of FY'25_ CRM Analytics Monthly Experiment_Notebook_AC.pdf
